{
  "type": "Feature",
  "properties": {
    "gn:admin1_code":"10",
    "gn:asciiname":"Alto de Fulon",
    "gn:country_code":"CU",
    "gn:dem":115,
    "gn:feature_class":"P",
    "gn:feature_code":"PPL",
    "gn:name":"Alto de Ful\u00f3n",
    "gn:population":0,
    "gn:timezone":"America/Havana",
    "iso:country":"CU",
    "name:spa_x_preferred":[
        "Alto de Ful\u00f3n"
    ],
    "wof:name":"Alto de Fulon",
    "wof:placetype":"locality"
},
  "geometry": {"coordinates":[-74.2454,20.30543],"type":"Point"}
}