{
  "type": "Feature",
  "properties": {
    "gn:admin1_code":"MA",
    "gn:asciiname":"Pica Pica",
    "gn:country_code":"CU",
    "gn:dem":74,
    "gn:feature_class":"P",
    "gn:feature_code":"PPLL",
    "gn:name":"Pica Pica",
    "gn:population":0,
    "gn:timezone":"America/Havana",
    "iso:country":"CU",
    "name:und_x_variant":[
        "Pico Pico",
        "Pica Pica"
    ],
    "wof:name":"Pica Pica",
    "wof:placetype":"locality"
},
  "geometry": {"coordinates":[-82.40000000000001,22.88333],"type":"Point"}
}