{
  "type": "Feature",
  "properties": {
    "gn:admin1_code":"03",
    "gn:asciiname":"San Manuel",
    "gn:country_code":"CU",
    "gn:dem":69,
    "gn:feature_class":"P",
    "gn:feature_code":"PPLL",
    "gn:name":"San Manuel",
    "gn:population":0,
    "gn:timezone":"America/Havana",
    "iso:country":"CU",
    "wof:name":"San Manuel",
    "wof:placetype":"locality"
},
  "geometry": {"coordinates":[-80.68778,22.59472],"type":"Point"}
}