{
  "type": "Feature",
  "properties": {
    "gn:admin1_code":"10",
    "gn:asciiname":"Boca de Quibijan",
    "gn:country_code":"CU",
    "gn:dem":36,
    "gn:feature_class":"P",
    "gn:feature_code":"PPLL",
    "gn:name":"Boca de Quibij\u00e1n",
    "gn:population":0,
    "gn:timezone":"America/Havana",
    "iso:country":"CU",
    "wof:name":"Boca de Quibijan",
    "wof:placetype":"locality"
},
  "geometry": {"coordinates":[-74.63944000000002,20.35528],"type":"Point"}
}