{
  "type": "Feature",
  "properties": {
    "iso:country":"CU",
    "name:deu_x_preferred":[
        "Nal\u00f3n"
    ],
    "qs:gn_pop":0,
    "qs:name":"Nal\u00f3n",
    "qs:name_adm0":"Cuba",
    "qs:name_adm1":"Ciudad de la Habana",
    "qs:photos":73,
    "qs:photos_1k":15,
    "qs:photos_9k":1,
    "qs:photos_9r":2,
    "qs:photos_all":73,
    "qs:photos_sr":2,
    "qs:placetype":"Town",
    "qs:pop_sr":"0",
    "qs:woe_adm0":23424793,
    "wd:wordcount":25,
    "wof:name":"Nal\u00f3n",
    "wof:placetype":"locality"
},
  "geometry": {"coordinates":[-82.331542,23.10247],"type":"Point"}
}