{
  "type": "Feature",
  "properties": {
    "gn:admin1_code":"MA",
    "gn:asciiname":"Fundamento",
    "gn:country_code":"CU",
    "gn:dem":123,
    "gn:feature_class":"P",
    "gn:feature_code":"PPL",
    "gn:name":"Fundamento",
    "gn:population":0,
    "gn:timezone":"America/Havana",
    "iso:country":"CU",
    "wof:name":"Fundamento",
    "wof:placetype":"locality"
},
  "geometry": {"coordinates":[-82.14556,23.01833],"type":"Point"}
}