{
  "type": "Feature",
  "properties": {
    "gn:admin1_code":"01",
    "gn:asciiname":"Villamil",
    "gn:cc2":"CU",
    "gn:country_code":"CU",
    "gn:dem":55,
    "gn:feature_class":"P",
    "gn:feature_code":"PPLL",
    "gn:name":"Villamil",
    "gn:population":0,
    "gn:timezone":"America/Havana",
    "iso:country":"CU",
    "name:ceb_x_preferred":[
        "Villamil"
    ],
    "name:deu_x_preferred":[
        "Villamil"
    ],
    "name:fra_x_preferred":[
        "Villamil"
    ],
    "name:spa_x_preferred":[
        "Villamil"
    ],
    "name:swe_x_preferred":[
        "Villamil"
    ],
    "name:und_x_variant":[
        "Las Gu\u00e1simas",
        "Villamil"
    ],
    "wof:name":"Villamil",
    "wof:placetype":"locality"
},
  "geometry": {"coordinates":[-83.81667,22.31667],"type":"Point"}
}