{
  "type": "Feature",
  "properties": {
    "gn:admin1_code":"12",
    "gn:asciiname":"Ronda",
    "gn:country_code":"CU",
    "gn:dem":12,
    "gn:feature_class":"P",
    "gn:feature_code":"PPL",
    "gn:name":"Ronda",
    "gn:population":0,
    "gn:timezone":"America/Havana",
    "iso:country":"CU",
    "name:ara_x_preferred":[
        "\u0631\u0646\u062f\u0629"
    ],
    "name:arg_x_preferred":[
        "Ronda"
    ],
    "name:ast_x_preferred":[
        "Ronda"
    ],
    "name:azb_x_preferred":[
        "\u0631\u0648\u0646\u062f\u0627"
    ],
    "name:bcl_x_preferred":[
        "Ronda"
    ],
    "name:cat_x_preferred":[
        "Ronda"
    ],
    "name:ces_x_preferred":[
        "Ronda"
    ],
    "name:dan_x_preferred":[
        "Ronda"
    ],
    "name:deu_x_preferred":[
        "Ronda"
    ],
    "name:ell_x_preferred":[
        "\u03a1\u03cc\u03bd\u03c4\u03b1"
    ],
    "name:epo_x_preferred":[
        "Arundo"
    ],
    "name:eus_x_preferred":[
        "Ronda"
    ],
    "name:fas_x_preferred":[
        "\u0631\u0648\u0646\u062f\u0627"
    ],
    "name:fin_x_preferred":[
        "Ronda"
    ],
    "name:fra_x_preferred":[
        "Ronda"
    ],
    "name:glg_x_preferred":[
        "Ronda"
    ],
    "name:hat_x_preferred":[
        "Ronda"
    ],
    "name:heb_x_preferred":[
        "\u05e8\u05d5\u05e0\u05d3\u05d4"
    ],
    "name:hun_x_preferred":[
        "Ronda"
    ],
    "name:hye_x_preferred":[
        "\u054c\u0578\u0576\u0564\u0561"
    ],
    "name:ind_x_preferred":[
        "Ronda"
    ],
    "name:ita_x_preferred":[
        "Ronda"
    ],
    "name:jpn_x_preferred":[
        "\u30ed\u30f3\u30c0"
    ],
    "name:kaz_x_preferred":[
        "\u0420\u043e\u043d\u0434\u0430"
    ],
    "name:kon_x_preferred":[
        "Ronda"
    ],
    "name:kor_x_preferred":[
        "\ub860\ub2e4"
    ],
    "name:lat_x_preferred":[
        "Arunda"
    ],
    "name:lav_x_preferred":[
        "Ronda"
    ],
    "name:mlg_x_preferred":[
        "Ronda"
    ],
    "name:msa_x_preferred":[
        "Ronda"
    ],
    "name:nld_x_preferred":[
        "Ronda"
    ],
    "name:nor_x_preferred":[
        "Ronda"
    ],
    "name:oci_x_preferred":[
        "Ronda"
    ],
    "name:pol_x_preferred":[
        "Ronda"
    ],
    "name:por_x_preferred":[
        "Ronda"
    ],
    "name:ron_x_preferred":[
        "Ronda"
    ],
    "name:rus_x_preferred":[
        "\u0420\u043e\u043d\u0434\u0430"
    ],
    "name:slv_x_preferred":[
        "Ronda"
    ],
    "name:spa_x_preferred":[
        "Ronda"
    ],
    "name:sqi_x_preferred":[
        "Ronda"
    ],
    "name:srp_x_preferred":[
        "\u0420\u043e\u043d\u0434\u0430"
    ],
    "name:swe_x_preferred":[
        "Ronda"
    ],
    "name:szl_x_preferred":[
        "Ronda"
    ],
    "name:tur_x_preferred":[
        "Ronda"
    ],
    "name:ukr_x_preferred":[
        "\u0420\u043e\u043d\u0434\u0430"
    ],
    "name:uzb_x_preferred":[
        "Ronda"
    ],
    "name:vie_x_preferred":[
        "Ronda"
    ],
    "name:vls_x_preferred":[
        "Ronda"
    ],
    "name:war_x_preferred":[
        "Ronda"
    ],
    "name:zho_x_preferred":[
        "\u9f99\u8fbe"
    ],
    "wof:name":"Ronda",
    "wof:placetype":"locality"
},
  "geometry": {"coordinates":[-75.77585999999999,21.10033],"type":"Point"}
}