{
  "type": "Feature",
  "properties": {
    "gn:admin1_code":"12",
    "gn:asciiname":"Ronda",
    "gn:country_code":"CU",
    "gn:dem":12,
    "gn:feature_class":"P",
    "gn:feature_code":"PPL",
    "gn:name":"Ronda",
    "gn:population":0,
    "gn:timezone":"America/Havana",
    "iso:country":"CU",
    "name:spa_x_preferred":[
        "Ronda"
    ],
    "wof:name":"Ronda",
    "wof:placetype":"locality"
},
  "geometry": {"coordinates":[-75.77585999999999,21.10033],"type":"Point"}
}