{
  "type": "Feature",
  "properties": {
    "gn:admin1_code":"09",
    "gn:asciiname":"San Juan Dos",
    "gn:country_code":"CU",
    "gn:dem":70,
    "gn:feature_class":"P",
    "gn:feature_code":"PPL",
    "gn:name":"San Juan Dos",
    "gn:population":0,
    "gn:timezone":"America/Havana",
    "iso:country":"CU",
    "name:spa_x_preferred":[
        "San Juan Dos"
    ],
    "wof:name":"San Juan Dos",
    "wof:placetype":"locality"
},
  "geometry": {"coordinates":[-76.90016,20.18021],"type":"Point"}
}