{
  "type": "Feature",
  "properties": {
    "gn:admin1_code":"AR",
    "gn:asciiname":"Palomino Viejo",
    "gn:country_code":"CU",
    "gn:dem":53,
    "gn:feature_class":"P",
    "gn:feature_code":"PPLL",
    "gn:name":"Palomino Viejo",
    "gn:population":0,
    "gn:timezone":"America/Havana",
    "iso:country":"CU",
    "name:und_x_variant":[
        "Palomino",
        "Palomino Viejo"
    ],
    "wof:name":"Palomino Viejo",
    "wof:placetype":"locality"
},
  "geometry": {"coordinates":[-82.58444,23.00611],"type":"Point"}
}