{
  "type": "Feature",
  "properties": {
    "gn:country":"CU",
    "gn:fcode":"PPL",
    "gn:pop":16548,
    "iso:country":"CU",
    "name:ast_x_preferred":[
        "Guane"
    ],
    "name:cat_x_preferred":[
        "Guane"
    ],
    "name:cym_x_preferred":[
        "Guane"
    ],
    "name:deu_x_preferred":[
        "Guane"
    ],
    "name:eng_x_preferred":[
        "Guane"
    ],
    "name:fra_x_preferred":[
        "Guane"
    ],
    "name:gle_x_preferred":[
        "Guane"
    ],
    "name:hat_x_preferred":[
        "Guane"
    ],
    "name:ita_x_preferred":[
        "Guane"
    ],
    "name:jpn_x_preferred":[
        "\u30b0\u30a2\u30cd"
    ],
    "name:kat_x_preferred":[
        "\u10d2\u10e3\u10d0\u10dc\u10d4"
    ],
    "name:nld_x_preferred":[
        "Guane"
    ],
    "name:por_x_preferred":[
        "Guane"
    ],
    "name:rus_x_preferred":[
        "\u0413\u0443\u0430\u043d\u0435"
    ],
    "name:spa_x_preferred":[
        "Guane"
    ],
    "name:swe_x_preferred":[
        "Municipio de Guane"
    ],
    "name:vie_x_preferred":[
        "Guane"
    ],
    "name:zho_x_preferred":[
        "\u74dc\u5167"
    ],
    "qs:name":"Guane",
    "qs:photos_9r":0,
    "qs:photos_sr":0,
    "qs:pop_sr":"6",
    "wd:wordcount":260,
    "wof:name":"Guane",
    "wof:placetype":"locality",
    "wof:population":16548
},
  "geometry": {"coordinates":[-84.08750000000001,22.2025],"type":"Point"}
}