{
  "type": "Feature",
  "properties": {
    "gn:admin1_code":"AR",
    "gn:asciiname":"Las Tres Palmas",
    "gn:country_code":"CU",
    "gn:dem":38,
    "gn:feature_class":"P",
    "gn:feature_code":"PPLL",
    "gn:name":"Las Tres Palmas",
    "gn:population":0,
    "gn:timezone":"America/Havana",
    "iso:country":"CU",
    "wof:name":"Las Tres Palmas",
    "wof:placetype":"locality"
},
  "geometry": {"coordinates":[-83.26666999999998,22.88333],"type":"Point"}
}