{
  "type": "Feature",
  "properties": {
    "gn:admin1_code":"09",
    "gn:asciiname":"Los Haticos",
    "gn:cc2":"CU",
    "gn:country_code":"CU",
    "gn:dem":43,
    "gn:feature_class":"P",
    "gn:feature_code":"PPLL",
    "gn:name":"Los Haticos",
    "gn:population":0,
    "gn:timezone":"America/Havana",
    "iso:country":"CU",
    "name:spa_x_preferred":[
        "Los Haticos"
    ],
    "name:und_x_variant":[
        "Haticos",
        "Los Haticos"
    ],
    "wof:name":"Los Haticos",
    "wof:placetype":"locality"
},
  "geometry": {"coordinates":[-76.51666999999998,20.56667],"type":"Point"}
}