{
  "type": "Feature",
  "properties": {
    "gn:admin1_code":"08",
    "gn:asciiname":"La Bomba Vieja",
    "gn:country_code":"CU",
    "gn:dem":22,
    "gn:feature_class":"P",
    "gn:feature_code":"PPLL",
    "gn:name":"La Bomba Vieja",
    "gn:population":0,
    "gn:timezone":"America/Havana",
    "iso:country":"CU",
    "name:spa_x_preferred":[
        "La Bomba Vieja"
    ],
    "wof:name":"La Bomba Vieja",
    "wof:placetype":"locality"
},
  "geometry": {"coordinates":[-80.37572,21.99603],"type":"Point"}
}