{
  "type": "Feature",
  "properties": {
    "gn:admin1_code":"MA",
    "gn:asciiname":"La Varia",
    "gn:country_code":"CU",
    "gn:dem":100,
    "gn:feature_class":"P",
    "gn:feature_code":"PPLL",
    "gn:name":"La Var\u00eda",
    "gn:population":0,
    "gn:timezone":"America/Havana",
    "iso:country":"CU",
    "wof:name":"La Varia",
    "wof:placetype":"locality"
},
  "geometry": {"coordinates":[-81.96666999999999,22.91667],"type":"Point"}
}