{
  "type": "Feature",
  "properties": {
    "gn:admin1_code":"12",
    "gn:asciiname":"Rio Seco Diez y Siete",
    "gn:country_code":"CU",
    "gn:dem":61,
    "gn:feature_class":"P",
    "gn:feature_code":"PPL",
    "gn:name":"R\u00edo Seco Diez y Siete",
    "gn:population":0,
    "gn:timezone":"America/Havana",
    "iso:country":"CU",
    "name:spa_x_preferred":[
        "R\u00edo Seco Diez y Siete"
    ],
    "name:und_x_variant":[
        "R\u00edo Seco N\u00famero 17",
        "R\u00edo Seco N\u00famero Diecisiete"
    ],
    "wof:name":"Rio Seco Diez y Siete",
    "wof:placetype":"locality"
},
  "geometry": {"coordinates":[-75.70818,21.09659],"type":"Point"}
}