{
  "type": "Feature",
  "properties": {
    "gn:admin1_code":"07",
    "gn:asciiname":"Crucero Pitajones",
    "gn:country_code":"CU",
    "gn:dem":16,
    "gn:feature_class":"P",
    "gn:feature_code":"PPLL",
    "gn:name":"Crucero Pitajones",
    "gn:population":0,
    "gn:timezone":"America/Havana",
    "iso:country":"CU",
    "name:spa_x_preferred":[
        "Crucero Pitajones"
    ],
    "name:und_x_variant":[
        "Pitajones",
        "Krusero-Pitakhones"
    ],
    "wof:name":"Crucero Pitajones",
    "wof:placetype":"locality"
},
  "geometry": {"coordinates":[-78.81572,21.71193],"type":"Point"}
}