{
  "type": "Feature",
  "properties": {
    "gn:admin1_code":"13",
    "gn:asciiname":"Guanito",
    "gn:country_code":"CU",
    "gn:dem":15,
    "gn:feature_class":"P",
    "gn:feature_code":"PPL",
    "gn:name":"Guanito",
    "gn:population":0,
    "gn:timezone":"America/Havana",
    "iso:country":"CU",
    "name:spa_x_preferred":[
        "Guanito"
    ],
    "wof:name":"Guanito",
    "wof:placetype":"locality"
},
  "geometry": {"coordinates":[-76.79982,21.23841],"type":"Point"}
}