{
  "type": "Feature",
  "properties": {
    "gn:admin1_code":"12",
    "gn:asciiname":"Castellano Dos",
    "gn:country_code":"CU",
    "gn:dem":42,
    "gn:feature_class":"P",
    "gn:feature_code":"PPL",
    "gn:name":"Castellano Dos",
    "gn:population":0,
    "gn:timezone":"America/Havana",
    "iso:country":"CU",
    "name:und_x_variant":[
        "Castellanos Numero 2",
        "Castellanos",
        "Castellano Dos"
    ],
    "wof:name":"Castellano Dos",
    "wof:placetype":"locality"
},
  "geometry": {"coordinates":[-75.80728000000001,20.64959],"type":"Point"}
}