{
  "type": "Feature",
  "properties": {
    "gn:admin1_code":"05",
    "gn:asciiname":"La Deseada",
    "gn:country_code":"CU",
    "gn:dem":55,
    "gn:feature_class":"P",
    "gn:feature_code":"PPL",
    "gn:name":"La Deseada",
    "gn:population":0,
    "gn:timezone":"America/Havana",
    "iso:country":"CU",
    "name:spa_x_preferred":[
        "La Deseada"
    ],
    "wof:name":"La Deseada",
    "wof:placetype":"locality"
},
  "geometry": {"coordinates":[-77.94015,21.02408],"type":"Point"}
}