{
  "type": "Feature",
  "properties": {
    "gn:admin1_code":"09",
    "gn:asciiname":"Derecho de Caridad",
    "gn:country_code":"CU",
    "gn:dem":382,
    "gn:feature_class":"P",
    "gn:feature_code":"PPL",
    "gn:name":"Derecho de Caridad",
    "gn:population":0,
    "gn:timezone":"America/Havana",
    "iso:country":"CU",
    "name:spa_x_preferred":[
        "Derecho de Caridad"
    ],
    "wof:name":"Derecho de Caridad",
    "wof:placetype":"locality"
},
  "geometry": {"coordinates":[-77.11582,19.987],"type":"Point"}
}