{
  "type": "Feature",
  "properties": {
    "gn:admin1_code":"14",
    "gn:asciiname":"Limones Cantero",
    "gn:country_code":"CU",
    "gn:dem":222,
    "gn:feature_class":"P",
    "gn:feature_code":"PPL",
    "gn:name":"Limones Cantero",
    "gn:population":0,
    "gn:timezone":"America/Havana",
    "iso:country":"CU",
    "name:und_x_variant":[
        "Limones",
        "Limones Cantero"
    ],
    "wof:name":"Limones Cantero",
    "wof:placetype":"locality"
},
  "geometry": {"coordinates":[-79.87545,21.93992],"type":"Point"}
}