{
  "type": "Feature",
  "properties": {
    "gn:admin1_code":"08",
    "gn:asciiname":"El Salobre",
    "gn:country_code":"CU",
    "gn:dem":31,
    "gn:feature_class":"P",
    "gn:feature_code":"PPLL",
    "gn:name":"El Salobre",
    "gn:population":0,
    "gn:timezone":"America/Havana",
    "iso:country":"CU",
    "wof:name":"El Salobre",
    "wof:placetype":"locality"
},
  "geometry": {"coordinates":[-80.62028000000002,22.18417],"type":"Point"}
}