{
  "type": "Feature",
  "properties": {
    "gn:admin1_code":"05",
    "gn:asciiname":"Los Quemaditos",
    "gn:country_code":"CU",
    "gn:dem":43,
    "gn:feature_class":"P",
    "gn:feature_code":"PPLL",
    "gn:name":"Los Quemaditos",
    "gn:population":0,
    "gn:timezone":"America/Havana",
    "iso:country":"CU",
    "name:spa_x_preferred":[
        "Los Quemaditos"
    ],
    "name:und_x_variant":[
        "Quemadito"
    ],
    "wof:name":"Los Quemaditos",
    "wof:placetype":"locality"
},
  "geometry": {"coordinates":[-78.02779,21.7483],"type":"Point"}
}