{
  "type": "Feature",
  "properties": {
    "gn:admin1_code":"08",
    "gn:asciiname":"Ramon Balboa",
    "gn:country_code":"CU",
    "gn:dem":86,
    "gn:feature_class":"P",
    "gn:feature_code":"PPL",
    "gn:name":"Ram\u00f3n Balboa",
    "gn:population":0,
    "gn:timezone":"America/Havana",
    "iso:country":"CU",
    "name:spa_x_preferred":[
        "Ram\u00f3n Balboa"
    ],
    "wof:name":"Ramon Balboa",
    "wof:placetype":"locality"
},
  "geometry": {"coordinates":[-80.30724000000002,22.35155],"type":"Point"}
}