{
  "type": "Feature",
  "properties": {
    "gn:admin1_code":"14",
    "gn:asciiname":"Guanal Alto",
    "gn:country_code":"CU",
    "gn:dem":41,
    "gn:feature_class":"P",
    "gn:feature_code":"PPL",
    "gn:name":"Guanal Alto",
    "gn:population":0,
    "gn:timezone":"America/Havana",
    "iso:country":"CU",
    "name:spa_x_preferred":[
        "Mart\u00edn L\u00f3pez"
    ],
    "name:spa_x_variant":[
        "Guanal Alto"
    ],
    "wof:name":"Guanal Alto",
    "wof:placetype":"locality"
},
  "geometry": {"coordinates":[-79.23846,21.77643],"type":"Point"}
}