{
  "type": "Feature",
  "properties": {
    "gn:admin1_code":"01",
    "gn:asciiname":"Zamacois",
    "gn:cc2":"CU",
    "gn:country_code":"CU",
    "gn:dem":31,
    "gn:feature_class":"P",
    "gn:feature_code":"PPLL",
    "gn:name":"Zamacois",
    "gn:population":0,
    "gn:timezone":"America/Havana",
    "iso:country":"CU",
    "name:und_x_variant":[
        "San Macoy",
        "Zamacois"
    ],
    "wof:name":"Zamacois",
    "wof:placetype":"locality"
},
  "geometry": {"coordinates":[-83.73333000000002,22.33333],"type":"Point"}
}