{
  "type": "Feature",
  "properties": {
    "gn:admin1_code":"13",
    "gn:asciiname":"La Cana",
    "gn:country_code":"CU",
    "gn:dem":50,
    "gn:feature_class":"P",
    "gn:feature_code":"PPLL",
    "gn:name":"La Ca\u00f1a",
    "gn:population":0,
    "gn:timezone":"America/Havana",
    "iso:country":"CU",
    "wof:name":"La Cana",
    "wof:placetype":"locality"
},
  "geometry": {"coordinates":[-77.21666999999999,20.91667],"type":"Point"}
}