{
  "type": "Feature",
  "properties": {
    "gn:admin1_code":"12",
    "gn:asciiname":"Colonia Peralta",
    "gn:country_code":"CU",
    "gn:dem":72,
    "gn:feature_class":"P",
    "gn:feature_code":"PPLL",
    "gn:name":"Colonia Peralta",
    "gn:population":0,
    "gn:timezone":"America/Havana",
    "iso:country":"CU",
    "wof:name":"Colonia Peralta",
    "wof:placetype":"locality"
},
  "geometry": {"coordinates":[-76.2975,20.71917],"type":"Point"}
}