{
  "type": "Feature",
  "properties": {
    "gn:admin1_code":"03",
    "gn:asciiname":"San Ignacio",
    "gn:country_code":"CU",
    "gn:dem":29,
    "gn:feature_class":"P",
    "gn:feature_code":"PPLL",
    "gn:name":"San Ignacio",
    "gn:population":0,
    "gn:timezone":"America/Havana",
    "iso:country":"CU",
    "name:ceb_x_preferred":[
        "San Ignacio"
    ],
    "name:deu_x_preferred":[
        "San Ignacio"
    ],
    "name:epo_x_preferred":[
        "San Ignacio"
    ],
    "name:fra_x_preferred":[
        "San Ignacio"
    ],
    "name:heb_x_preferred":[
        "\u05e1\u05df \u05d0\u05d9\u05d2\u05e0\u05e1\u05d9\u05d5"
    ],
    "name:ita_x_preferred":[
        "San Ignacio"
    ],
    "name:kat_x_preferred":[
        "\u10e1\u10d0\u10dc-\u10d8\u10d2\u10dc\u10d0\u10e1\u10d8\u10dd"
    ],
    "name:kor_x_preferred":[
        "\uc0b0\uc774\uadf8\ub098\uc2dc\uc624"
    ],
    "name:nld_x_preferred":[
        "San Ignacio"
    ],
    "name:pol_x_preferred":[
        "San Ignacio"
    ],
    "name:por_x_preferred":[
        "San Ignacio"
    ],
    "name:ron_x_preferred":[
        "San Ignacio"
    ],
    "name:rus_x_preferred":[
        "\u0421\u0430\u043d-\u0418\u0433\u043d\u0430\u0441\u0438\u043e"
    ],
    "name:sco_x_preferred":[
        "San Ignacio"
    ],
    "name:spa_x_preferred":[
        "San Ignacio"
    ],
    "name:swe_x_preferred":[
        "San Ignacio"
    ],
    "name:war_x_preferred":[
        "San Ignacio"
    ],
    "wof:name":"San Ignacio",
    "wof:placetype":"locality"
},
  "geometry": {"coordinates":[-81.13333,22.65],"type":"Point"}
}