{
  "type": "Feature",
  "properties": {
    "gn:admin1_code":"12",
    "gn:asciiname":"San Juan de las Puercas",
    "gn:country_code":"CU",
    "gn:dem":196,
    "gn:feature_class":"P",
    "gn:feature_code":"PPLL",
    "gn:name":"San Juan de las Puercas",
    "gn:population":0,
    "gn:timezone":"America/Havana",
    "iso:country":"CU",
    "wof:name":"San Juan de las Puercas",
    "wof:placetype":"locality"
},
  "geometry": {"coordinates":[-76.04111,20.86944],"type":"Point"}
}