{
  "type": "Feature",
  "properties": {
    "gn:admin1_code":"01",
    "gn:asciiname":"La Conchita",
    "gn:country_code":"CU",
    "gn:dem":1,
    "gn:feature_class":"P",
    "gn:feature_code":"PPLL",
    "gn:name":"La Conchita",
    "gn:population":0,
    "gn:timezone":"America/Havana",
    "iso:country":"CU",
    "wof:name":"La Conchita",
    "wof:placetype":"locality"
},
  "geometry": {"coordinates":[-83.91667,22.16667],"type":"Point"}
}