{
  "type": "Feature",
  "properties": {
    "gn:admin1_code":"09",
    "gn:asciiname":"Cubena",
    "gn:country_code":"CU",
    "gn:dem":18,
    "gn:feature_class":"P",
    "gn:feature_code":"PPL",
    "gn:name":"Cube\u00f1a",
    "gn:population":0,
    "gn:timezone":"America/Havana",
    "iso:country":"CU",
    "name:spa_x_preferred":[
        "Cube\u00f1a"
    ],
    "wof:name":"Cubena",
    "wof:placetype":"locality"
},
  "geometry": {"coordinates":[-77.33381999999997,20.15861],"type":"Point"}
}