{
  "type": "Feature",
  "properties": {
    "gn:admin1_code":"16",
    "gn:asciiname":"Picuarto",
    "gn:country_code":"CU",
    "gn:dem":184,
    "gn:feature_class":"P",
    "gn:feature_code":"PPL",
    "gn:name":"Picuarto",
    "gn:population":0,
    "gn:timezone":"America/Havana",
    "iso:country":"CU",
    "wof:name":"Picuarto",
    "wof:placetype":"locality"
},
  "geometry": {"coordinates":[-79.98333000000002,22.23333],"type":"Point"}
}