{
  "type": "Feature",
  "properties": {
    "gn:admin1_code":"05",
    "gn:asciiname":"Los Dolores",
    "gn:country_code":"CU",
    "gn:dem":118,
    "gn:feature_class":"P",
    "gn:feature_code":"PPL",
    "gn:name":"Los Dolores",
    "gn:population":0,
    "gn:timezone":"America/Havana",
    "iso:country":"CU",
    "name:spa_x_preferred":[
        "Los Dolores"
    ],
    "wof:name":"Los Dolores",
    "wof:placetype":"locality"
},
  "geometry": {"coordinates":[-77.74784,21.04661],"type":"Point"}
}