{
  "type": "Feature",
  "properties": {
    "gn:admin1_code":"AR",
    "gn:asciiname":"Coblet",
    "gn:country_code":"CU",
    "gn:dem":69,
    "gn:feature_class":"P",
    "gn:feature_code":"PPL",
    "gn:name":"Coblet",
    "gn:population":0,
    "gn:timezone":"America/Havana",
    "iso:country":"CU",
    "wof:name":"Coblet",
    "wof:placetype":"locality"
},
  "geometry": {"coordinates":[-82.91389000000002,22.80472],"type":"Point"}
}