{
  "type": "Feature",
  "properties": {
    "gn:admin1_code":"12",
    "gn:asciiname":"La Caridad",
    "gn:country_code":"CU",
    "gn:dem":90,
    "gn:feature_class":"P",
    "gn:feature_code":"PPL",
    "gn:name":"La Caridad",
    "gn:population":0,
    "gn:timezone":"America/Havana",
    "iso:country":"CU",
    "name:und_x_variant":[
        "El Sitio de la Caridad",
        "La Caridad del Sitio",
        "La Caridad"
    ],
    "wof:name":"La Caridad",
    "wof:placetype":"locality"
},
  "geometry": {"coordinates":[-76.19325000000001,20.71909],"type":"Point"}
}