{
  "type": "Feature",
  "properties": {
    "gn:admin1_code":"12",
    "gn:asciiname":"La Caridad",
    "gn:country_code":"CU",
    "gn:dem":90,
    "gn:feature_class":"P",
    "gn:feature_code":"PPL",
    "gn:name":"La Caridad",
    "gn:population":0,
    "gn:timezone":"America/Havana",
    "iso:country":"CU",
    "name:ast_x_preferred":[
        "A Carid\u00e1"
    ],
    "name:deu_x_preferred":[
        "La Caridad"
    ],
    "name:spa_x_preferred":[
        "La Caridad"
    ],
    "name:und_x_variant":[
        "El Sitio de la Caridad",
        "La Caridad del Sitio",
        "La Caridad"
    ],
    "name:urd_x_preferred":[
        "\u0644\u0627 \u06a9\u0627\u0631\u06cc\u0688\u0627\u0688"
    ],
    "wof:name":"La Caridad",
    "wof:placetype":"locality"
},
  "geometry": {"coordinates":[-76.19325000000001,20.71909],"type":"Point"}
}