{
  "type": "Feature",
  "properties": {
    "gn:admin1_code":"16",
    "gn:asciiname":"Carratala",
    "gn:country_code":"CU",
    "gn:dem":4,
    "gn:feature_class":"P",
    "gn:feature_code":"PPL",
    "gn:name":"Carratal\u00e1",
    "gn:population":0,
    "gn:timezone":"America/Havana",
    "iso:country":"CU",
    "name:spa_x_preferred":[
        "Carratal\u00e1"
    ],
    "wof:name":"Carratala",
    "wof:placetype":"locality"
},
  "geometry": {"coordinates":[-79.72824,22.71775],"type":"Point"}
}