{
  "type": "Feature",
  "properties": {
    "gn:admin1_code":"MA",
    "gn:asciiname":"Playa del Caimito",
    "gn:country_code":"CU",
    "gn:dem":7,
    "gn:feature_class":"P",
    "gn:feature_code":"PPL",
    "gn:name":"Playa del Caimito",
    "gn:population":0,
    "gn:timezone":"America/Havana",
    "iso:country":"CU",
    "name:spa_x_preferred":[
        "Playa del Caimito"
    ],
    "name:und_x_variant":[
        "Playa de Caimito",
        "Playa Caimito"
    ],
    "wof:name":"Playa del Caimito",
    "wof:placetype":"locality"
},
  "geometry": {"coordinates":[-81.87685999999999,22.67974],"type":"Point"}
}