{
  "type": "Feature",
  "properties": {
    "gn:gn_country":"CU",
    "gn:gn_fcode":"PPLX",
    "gn:gn_pop":0,
    "iso:country":"CU",
    "name:spa_x_preferred":[
        "Reparto Veguita de Galo"
    ],
    "name:unk_x_variant":[
        "Reparto Veguita de Galo"
    ],
    "qs_pg:aaroncc":"CU",
    "qs_pg:gn_country":"CU",
    "qs_pg:gn_fcode":"PPLX",
    "qs_pg:gn_pop":0,
    "qs_pg:name":"Reparto Veguita de Galo",
    "qs_pg:name_adm0":"Cuba",
    "qs_pg:name_adm1":"Santiago de Cuba",
    "qs_pg:photos":691,
    "qs_pg:photos_1k":140,
    "qs_pg:photos_9k":3,
    "qs_pg:photos_9r":5,
    "qs_pg:photos_all":691,
    "qs_pg:photos_sr":8,
    "qs_pg:pop_sr":0,
    "qs_pg:qs_pg_placetype":"neighbourhood",
    "qs_pg:qs_pg_placetype_gp":"Suburb",
    "qs_pg:woe_adm0":23424793,
    "woe:adm0_id":23424793,
    "woe:name_adm0":"Cuba",
    "woe:name_adm1":"Santiago de Cuba",
    "woe:placetype":"Suburb",
    "wof:name":"Reparto Veguita de Galo",
    "wof:placetype":"neighbourhood"
},
  "geometry": {"coordinates":[-75.81667,20.01667],"type":"Point"}
}