{
  "type": "Feature",
  "properties": {
    "gn:admin1_code":"16",
    "gn:asciiname":"Fidencia",
    "gn:country_code":"CU",
    "gn:dem":156,
    "gn:feature_class":"P",
    "gn:feature_code":"PPLL",
    "gn:name":"Fidencia",
    "gn:population":0,
    "gn:timezone":"America/Havana",
    "iso:country":"CU",
    "wof:name":"Fidencia",
    "wof:placetype":"locality"
},
  "geometry": {"coordinates":[-79.65000000000001,22.35],"type":"Point"}
}