{
  "type": "Feature",
  "properties": {
    "gn:admin1_code":"16",
    "gn:asciiname":"La Fe",
    "gn:country_code":"CU",
    "gn:dem":225,
    "gn:feature_class":"P",
    "gn:feature_code":"PPLL",
    "gn:name":"La F\u00e9",
    "gn:population":0,
    "gn:timezone":"America/Havana",
    "iso:country":"CU",
    "name:spa_x_preferred":[
        "La F\u00e9"
    ],
    "name:spa_x_variant":[
        "La Fe"
    ],
    "name:srp_x_preferred":[
        "\u041b\u0430 \u0424\u0435"
    ],
    "wof:name":"La Fe",
    "wof:placetype":"locality"
},
  "geometry": {"coordinates":[-79.37347,22.28586],"type":"Point"}
}