{
  "type": "Feature",
  "properties": {
    "gn:admin1_code":"05",
    "gn:asciiname":"Fela Tres",
    "gn:country_code":"CU",
    "gn:dem":60,
    "gn:feature_class":"P",
    "gn:feature_code":"PPL",
    "gn:name":"Fela Tres",
    "gn:population":0,
    "gn:timezone":"America/Havana",
    "iso:country":"CU",
    "name:spa_x_preferred":[
        "Fela Tres"
    ],
    "wof:name":"Fela Tres",
    "wof:placetype":"locality"
},
  "geometry": {"coordinates":[-78.1528,21.22744],"type":"Point"}
}