{
  "type": "Feature",
  "properties": {
    "gn:admin1_code":"16",
    "gn:asciiname":"Jiquial",
    "gn:cc2":"CU",
    "gn:country_code":"CU",
    "gn:dem":8,
    "gn:feature_class":"P",
    "gn:feature_code":"PPLL",
    "gn:name":"Jiquial",
    "gn:population":0,
    "gn:timezone":"America/Havana",
    "iso:country":"CU",
    "name:und_x_variant":[
        "Jigual",
        "Jiquial"
    ],
    "wof:name":"Jiquial",
    "wof:placetype":"locality"
},
  "geometry": {"coordinates":[-79.59999999999999,22.56667],"type":"Point"}
}