{
  "type": "Feature",
  "properties": {
    "gn:admin1_code":"AR",
    "gn:asciiname":"Guayabal",
    "gn:country_code":"CU",
    "gn:dem":110,
    "gn:feature_class":"P",
    "gn:feature_code":"PPL",
    "gn:name":"Guayabal",
    "gn:population":0,
    "gn:timezone":"America/Havana",
    "iso:country":"CU",
    "name:ceb_x_preferred":[
        "Guayabal"
    ],
    "name:deu_x_preferred":[
        "Guayabal"
    ],
    "name:fra_x_preferred":[
        "Guayabal"
    ],
    "name:ita_x_preferred":[
        "Guayabal"
    ],
    "name:nld_x_preferred":[
        "Guayabal"
    ],
    "name:por_x_preferred":[
        "Guayabal"
    ],
    "name:sco_x_preferred":[
        "Guayabal"
    ],
    "name:spa_x_preferred":[
        "Guayabal"
    ],
    "name:swe_x_preferred":[
        "Guayabal"
    ],
    "name:und_x_variant":[
        "El Guayabal",
        "Guayabal"
    ],
    "wof:name":"Guayabal",
    "wof:placetype":"locality"
},
  "geometry": {"coordinates":[-82.61833,22.92361],"type":"Point"}
}