{
  "type": "Feature",
  "properties": {
    "gn:admin1_code":"05",
    "gn:asciiname":"La Zoila",
    "gn:country_code":"CU",
    "gn:dem":116,
    "gn:feature_class":"P",
    "gn:feature_code":"PPL",
    "gn:name":"La Zoila",
    "gn:population":0,
    "gn:timezone":"America/Havana",
    "iso:country":"CU",
    "name:spa_x_preferred":[
        "La Zoila"
    ],
    "wof:name":"La Zoila",
    "wof:placetype":"locality"
},
  "geometry": {"coordinates":[-77.84198000000001,21.17323],"type":"Point"}
}