{
  "type": "Feature",
  "properties": {
    "gn:admin1_code":"12",
    "gn:asciiname":"Almirante",
    "gn:country_code":"CU",
    "gn:dem":86,
    "gn:feature_class":"P",
    "gn:feature_code":"PPL",
    "gn:name":"Almirante",
    "gn:population":0,
    "gn:timezone":"America/Havana",
    "iso:country":"CU",
    "name:cat_x_preferred":[
        "Almirante"
    ],
    "name:deu_x_preferred":[
        "Almirante"
    ],
    "name:fra_x_preferred":[
        "Almirante"
    ],
    "name:glg_x_preferred":[
        "Almirante"
    ],
    "name:ita_x_preferred":[
        "Almirante"
    ],
    "name:por_x_preferred":[
        "Almirante"
    ],
    "name:und_x_variant":[
        "El Almirante",
        "Almirante"
    ],
    "wof:name":"Almirante",
    "wof:placetype":"locality"
},
  "geometry": {"coordinates":[-76.19633,20.94279],"type":"Point"}
}