{
  "type": "Feature",
  "properties": {
    "gn:admin1_code":"MA",
    "gn:asciiname":"Aguirre",
    "gn:country_code":"CU",
    "gn:dem":103,
    "gn:feature_class":"P",
    "gn:feature_code":"PPLL",
    "gn:name":"Aguirre",
    "gn:population":0,
    "gn:timezone":"America/Havana",
    "iso:country":"CU",
    "name:cat_x_preferred":[
        "Aguirre"
    ],
    "name:ceb_x_preferred":[
        "Aguirre"
    ],
    "name:deu_x_preferred":[
        "Aguirre"
    ],
    "name:fas_x_preferred":[
        "\u0622\u06af\u06cc\u0631\u0647"
    ],
    "name:fra_x_preferred":[
        "Aguirre"
    ],
    "name:hrv_x_preferred":[
        "Aguirre"
    ],
    "name:ita_x_preferred":[
        "Aguirre"
    ],
    "name:jpn_x_preferred":[
        "\u30a2\u30ae\u30fc\u30ec"
    ],
    "name:kor_x_preferred":[
        "\uc544\uae30\ub808"
    ],
    "name:nds_x_preferred":[
        "Aguirre"
    ],
    "name:nld_x_preferred":[
        "Aguirre"
    ],
    "name:pol_x_preferred":[
        "Aguirre"
    ],
    "name:por_x_preferred":[
        "Aguirre"
    ],
    "name:rus_x_preferred":[
        "\u0410\u0433\u0438\u0440\u0440\u0435"
    ],
    "name:slk_x_preferred":[
        "Aguirre"
    ],
    "name:slv_x_preferred":[
        "Aguirre"
    ],
    "name:spa_x_preferred":[
        "Aguirre"
    ],
    "name:swe_x_preferred":[
        "Aguirre"
    ],
    "name:ukr_x_preferred":[
        "\u0410\u0433\u0456\u0440\u0440\u0435"
    ],
    "name:zho_x_preferred":[
        "\u963f\u5409\u96f7"
    ],
    "wof:name":"Aguirre",
    "wof:placetype":"locality"
},
  "geometry": {"coordinates":[-81.97161,22.96602],"type":"Point"}
}