{
  "type": "Feature",
  "properties": {
    "gn:admin1_code":"MA",
    "gn:asciiname":"Aguirre",
    "gn:country_code":"CU",
    "gn:dem":103,
    "gn:feature_class":"P",
    "gn:feature_code":"PPLL",
    "gn:name":"Aguirre",
    "gn:population":0,
    "gn:timezone":"America/Havana",
    "iso:country":"CU",
    "name:spa_x_preferred":[
        "Aguirre"
    ],
    "wof:name":"Aguirre",
    "wof:placetype":"locality"
},
  "geometry": {"coordinates":[-81.97161,22.96602],"type":"Point"}
}