{
  "type": "Feature",
  "properties": {
    "gn:admin1_code":"05",
    "gn:asciiname":"Tienda de Guaicanamar",
    "gn:country_code":"CU",
    "gn:dem":45,
    "gn:feature_class":"P",
    "gn:feature_code":"PPLL",
    "gn:name":"Tienda de Guaicanamar",
    "gn:population":0,
    "gn:timezone":"America/Havana",
    "iso:country":"CU",
    "wof:name":"Tienda de Guaicanamar",
    "wof:placetype":"locality"
},
  "geometry": {"coordinates":[-77.91667,20.98333],"type":"Point"}
}