{
  "type": "Feature",
  "properties": {
    "gn:admin1_code":"08",
    "gn:asciiname":"Belmonte",
    "gn:country_code":"CU",
    "gn:dem":9,
    "gn:feature_class":"P",
    "gn:feature_code":"PPLL",
    "gn:name":"Belmonte",
    "gn:population":0,
    "gn:timezone":"America/Havana",
    "iso:country":"CU",
    "name:spa_x_preferred":[
        "Belmonte"
    ],
    "wof:name":"Belmonte",
    "wof:placetype":"locality"
},
  "geometry": {"coordinates":[-80.36338000000001,22.12155],"type":"Point"}
}