{
  "type": "Feature",
  "properties": {
    "gn:admin1_code":"07",
    "gn:asciiname":"La Constancia",
    "gn:country_code":"CU",
    "gn:dem":8,
    "gn:feature_class":"P",
    "gn:feature_code":"PPLL",
    "gn:name":"La Constancia",
    "gn:population":0,
    "gn:timezone":"America/Havana",
    "iso:country":"CU",
    "wof:name":"La Constancia",
    "wof:placetype":"locality"
},
  "geometry": {"coordinates":[-78.83333,22.33333],"type":"Point"}
}