{
  "type": "Feature",
  "properties": {
    "gn:admin1_code":"03",
    "gn:asciiname":"Guerrero",
    "gn:country_code":"CU",
    "gn:dem":118,
    "gn:feature_class":"P",
    "gn:feature_code":"PPLL",
    "gn:name":"Guerrero",
    "gn:population":0,
    "gn:timezone":"America/Havana",
    "iso:country":"CU",
    "name:spa_x_preferred":[
        "Guerrero"
    ],
    "wof:name":"Guerrero",
    "wof:placetype":"locality"
},
  "geometry": {"coordinates":[-81.32285999999998,22.8808],"type":"Point"}
}