{
  "type": "Feature",
  "properties": {
    "gn:admin1_code":"10",
    "gn:asciiname":"Guaibano Abajo",
    "gn:country_code":"CU",
    "gn:dem":162,
    "gn:feature_class":"P",
    "gn:feature_code":"PPLL",
    "gn:name":"Guaibano Abajo",
    "gn:population":0,
    "gn:timezone":"America/Havana",
    "iso:country":"CU",
    "wof:name":"Guaibano Abajo",
    "wof:placetype":"locality"
},
  "geometry": {"coordinates":[-74.82666999999999,20.14278],"type":"Point"}
}