{
  "type": "Feature",
  "properties": {
    "gn:admin1_code":"05",
    "gn:asciiname":"Anton",
    "gn:country_code":"CU",
    "gn:dem":60,
    "gn:feature_class":"P",
    "gn:feature_code":"PPL",
    "gn:name":"Ant\u00f3n",
    "gn:population":0,
    "gn:timezone":"America/Havana",
    "iso:country":"CU",
    "name:aze_x_preferred":[
        "Anton"
    ],
    "name:bul_x_preferred":[
        "\u0410\u043d\u0442\u043e\u043d"
    ],
    "name:ceb_x_preferred":[
        "Anton"
    ],
    "name:ces_x_preferred":[
        "Anton"
    ],
    "name:deu_x_preferred":[
        "Anton"
    ],
    "name:ell_x_preferred":[
        "\u0391\u03bd\u03c4\u03cc\u03bd"
    ],
    "name:est_x_preferred":[
        "Anton"
    ],
    "name:fra_x_preferred":[
        "Anton"
    ],
    "name:heb_x_preferred":[
        "\u05d0\u05e0\u05d8\u05d5\u05df"
    ],
    "name:hye_x_preferred":[
        "\u0531\u0576\u057f\u0578\u0576"
    ],
    "name:ita_x_preferred":[
        "Anton"
    ],
    "name:jpn_x_preferred":[
        "\u30a2\u30f3\u30c8\u30f3"
    ],
    "name:nld_x_preferred":[
        "Anton"
    ],
    "name:nor_x_preferred":[
        "Anton"
    ],
    "name:pol_x_preferred":[
        "Anton"
    ],
    "name:ron_x_preferred":[
        "Anton"
    ],
    "name:rus_x_preferred":[
        "\u0410\u043d\u0442\u043e\u043d"
    ],
    "name:spa_x_preferred":[
        "Ant\u00f3n"
    ],
    "name:srp_x_preferred":[
        "\u0410\u043d\u0442\u043e\u043d"
    ],
    "name:swe_x_preferred":[
        "Anton"
    ],
    "name:tam_x_preferred":[
        "\u0b85\u0ba9\u0bcd\u0b9f\u0ba9\u0bcd"
    ],
    "name:ukr_x_preferred":[
        "\u0410\u043d\u0442\u043e\u043d"
    ],
    "wof:name":"Anton",
    "wof:placetype":"locality"
},
  "geometry": {"coordinates":[-78.11551,21.15502],"type":"Point"}
}