{
  "type": "Feature",
  "properties": {
    "gn:admin1_code":"05",
    "gn:asciiname":"Anton",
    "gn:country_code":"CU",
    "gn:dem":60,
    "gn:feature_class":"P",
    "gn:feature_code":"PPL",
    "gn:name":"Ant\u00f3n",
    "gn:population":0,
    "gn:timezone":"America/Havana",
    "iso:country":"CU",
    "name:spa_x_preferred":[
        "Ant\u00f3n"
    ],
    "wof:name":"Anton",
    "wof:placetype":"locality"
},
  "geometry": {"coordinates":[-78.11551,21.15502],"type":"Point"}
}