{
  "type": "Feature",
  "properties": {
    "gn:admin1_code":"01",
    "gn:asciiname":"El Jibaro",
    "gn:country_code":"CU",
    "gn:dem":66,
    "gn:feature_class":"P",
    "gn:feature_code":"PPLL",
    "gn:name":"El J\u00edbaro",
    "gn:population":0,
    "gn:timezone":"America/Havana",
    "iso:country":"CU",
    "wof:name":"El Jibaro",
    "wof:placetype":"locality"
},
  "geometry": {"coordinates":[-83.63389000000002,22.46833],"type":"Point"}
}