{
  "type": "Feature",
  "properties": {
    "gn:admin1_code":"14",
    "gn:asciiname":"Guinia de Soto",
    "gn:country_code":"CU",
    "gn:dem":38,
    "gn:feature_class":"P",
    "gn:feature_code":"PPL",
    "gn:name":"G\u00fcinia de Soto",
    "gn:population":0,
    "gn:timezone":"America/Havana",
    "iso:country":"CU",
    "name:spa_x_preferred":[
        "G\u00fcinia de Soto"
    ],
    "wof:name":"Guinia de Soto",
    "wof:placetype":"locality"
},
  "geometry": {"coordinates":[-79.81474,21.92592],"type":"Point"}
}