{
  "type": "Feature",
  "properties": {
    "gn:admin1_code":"13",
    "gn:asciiname":"Coloma Cuatro",
    "gn:country_code":"CU",
    "gn:dem":12,
    "gn:feature_class":"P",
    "gn:feature_code":"PPL",
    "gn:name":"Coloma Cuatro",
    "gn:population":0,
    "gn:timezone":"America/Havana",
    "iso:country":"CU",
    "name:spa_x_preferred":[
        "Coloma Cuatro"
    ],
    "wof:name":"Coloma Cuatro",
    "wof:placetype":"locality"
},
  "geometry": {"coordinates":[-76.76018000000001,21.22519],"type":"Point"}
}