{
  "type": "Feature",
  "properties": {
    "gn:admin1_code":"12",
    "gn:asciiname":"Los Haticos",
    "gn:country_code":"CU",
    "gn:dem":10,
    "gn:feature_class":"P",
    "gn:feature_code":"PPL",
    "gn:name":"Los Haticos",
    "gn:population":0,
    "gn:timezone":"America/Havana",
    "iso:country":"CU",
    "name:spa_x_preferred":[
        "Los Haticos"
    ],
    "name:und_x_variant":[
        "Haticos"
    ],
    "wof:name":"Los Haticos",
    "wof:placetype":"locality"
},
  "geometry": {"coordinates":[-75.67636999999998,21.07011],"type":"Point"}
}