{
  "type": "Feature",
  "properties": {
    "gn:admin1_code":"08",
    "gn:asciiname":"La Reunion",
    "gn:country_code":"CU",
    "gn:dem":41,
    "gn:feature_class":"P",
    "gn:feature_code":"PPLL",
    "gn:name":"La Reuni\u00f3n",
    "gn:population":0,
    "gn:timezone":"America/Havana",
    "iso:country":"CU",
    "name:ceb_x_preferred":[
        "La Reunion"
    ],
    "name:fra_x_preferred":[
        "La R\u00e9union"
    ],
    "name:nld_x_preferred":[
        "La R\u00e9union"
    ],
    "name:srp_x_preferred":[
        "\u041b\u0430 \u0420\u0435\u0443\u043d\u0438\u043e\u043d"
    ],
    "name:swe_x_preferred":[
        "La Reunion"
    ],
    "wof:name":"La Reunion",
    "wof:placetype":"locality"
},
  "geometry": {"coordinates":[-80.59999999999999,22.43333],"type":"Point"}
}