{
  "type": "Feature",
  "properties": {
    "gn:admin1_code":"16",
    "gn:asciiname":"Las Delicias",
    "gn:country_code":"CU",
    "gn:dem":74,
    "gn:feature_class":"P",
    "gn:feature_code":"PPL",
    "gn:name":"Las Delicias",
    "gn:population":0,
    "gn:timezone":"America/Havana",
    "iso:country":"CU",
    "name:spa_x_preferred":[
        "Las Delicias"
    ],
    "wof:name":"Las Delicias",
    "wof:placetype":"locality"
},
  "geometry": {"coordinates":[-80.33752,22.57704],"type":"Point"}
}