{
  "type": "Feature",
  "properties": {
    "gn:admin1_code":"05",
    "gn:asciiname":"Cuatro Companeros",
    "gn:country_code":"CU",
    "gn:dem":22,
    "gn:feature_class":"P",
    "gn:feature_code":"PPL",
    "gn:name":"Cuatro Compa\u00f1eros",
    "gn:population":0,
    "gn:timezone":"America/Havana",
    "iso:country":"CU",
    "name:spa_x_preferred":[
        "Cuatro Compa\u00f1eros"
    ],
    "wof:name":"Cuatro Companeros",
    "wof:placetype":"locality"
},
  "geometry": {"coordinates":[-78.05998000000002,20.97582],"type":"Point"}
}