{
  "type": "Feature",
  "properties": {
    "gn:admin1_code":"05",
    "gn:asciiname":"Siboney",
    "gn:country_code":"CU",
    "gn:dem":105,
    "gn:feature_class":"P",
    "gn:feature_code":"PPL",
    "gn:name":"Siboney",
    "gn:population":0,
    "gn:timezone":"America/Havana",
    "iso:country":"CU",
    "name:bre_x_preferred":[
        "Siboney"
    ],
    "name:deu_x_preferred":[
        "Siboney"
    ],
    "name:fra_x_preferred":[
        "Siboney"
    ],
    "name:hun_x_preferred":[
        "Siboney"
    ],
    "name:spa_x_preferred":[
        "Siboney"
    ],
    "name:und_x_variant":[
        "Marchena"
    ],
    "wof:name":"Siboney",
    "wof:placetype":"locality"
},
  "geometry": {"coordinates":[-77.6722,21.24531],"type":"Point"}
}