{
  "type": "Feature",
  "properties": {
    "gn:admin1_code":"09",
    "gn:asciiname":"Maguar",
    "gn:country_code":"CU",
    "gn:dem":153,
    "gn:feature_class":"P",
    "gn:feature_code":"PPL",
    "gn:name":"Maguar",
    "gn:population":0,
    "gn:timezone":"America/Havana",
    "iso:country":"CU",
    "name:spa_x_preferred":[
        "Maguar"
    ],
    "wof:name":"Maguar",
    "wof:placetype":"locality"
},
  "geometry": {"coordinates":[-76.67723000000002,20.20098],"type":"Point"}
}