{
  "type": "Feature",
  "properties": {
    "gn:admin1_code":"10",
    "gn:asciiname":"Hector Infante",
    "gn:country_code":"CU",
    "gn:dem":94,
    "gn:feature_class":"P",
    "gn:feature_code":"PPL",
    "gn:name":"Hector Infante",
    "gn:population":0,
    "gn:timezone":"America/Havana",
    "iso:country":"CU",
    "name:und_x_variant":[
        "Romel\u00ede",
        "Hector Infante"
    ],
    "wof:name":"Hector Infante",
    "wof:placetype":"locality"
},
  "geometry": {"coordinates":[-75.09203000000002,20.17373],"type":"Point"}
}