{
  "type": "Feature",
  "properties": {
    "gn:admin1_code":"12",
    "gn:asciiname":"Gustavo",
    "gn:country_code":"CU",
    "gn:dem":131,
    "gn:feature_class":"P",
    "gn:feature_code":"PPLL",
    "gn:name":"Gustavo",
    "gn:population":0,
    "gn:timezone":"America/Havana",
    "iso:country":"CU",
    "name:bre_x_preferred":[
        "Gustavo"
    ],
    "name:deu_x_preferred":[
        "Gustavo"
    ],
    "name:epo_x_preferred":[
        "Gustavo"
    ],
    "name:ita_x_preferred":[
        "Gustavo"
    ],
    "name:jpn_x_preferred":[
        "\u30b0\u30b9\u30bf\u30dc"
    ],
    "name:por_x_preferred":[
        "Gustavo"
    ],
    "name:spa_x_preferred":[
        "Gustavo"
    ],
    "name:ukr_x_preferred":[
        "\u0413\u0443\u0441\u0442\u0430\u0432\u043e"
    ],
    "wof:name":"Gustavo",
    "wof:placetype":"locality"
},
  "geometry": {"coordinates":[-76.28583,20.94444],"type":"Point"}
}