{
  "type": "Feature",
  "properties": {
    "gn:admin1_code":"12",
    "gn:asciiname":"Gustavo",
    "gn:country_code":"CU",
    "gn:dem":131,
    "gn:feature_class":"P",
    "gn:feature_code":"PPLL",
    "gn:name":"Gustavo",
    "gn:population":0,
    "gn:timezone":"America/Havana",
    "iso:country":"CU",
    "wof:name":"Gustavo",
    "wof:placetype":"locality"
},
  "geometry": {"coordinates":[-76.28583,20.94444],"type":"Point"}
}