{
  "type": "Feature",
  "properties": {
    "gn:admin1_code":"16",
    "gn:asciiname":"Navarro",
    "gn:country_code":"CU",
    "gn:dem":18,
    "gn:feature_class":"P",
    "gn:feature_code":"PPL",
    "gn:name":"Navarro",
    "gn:population":0,
    "gn:timezone":"America/Havana",
    "iso:country":"CU",
    "name:spa_x_preferred":[
        "Navarro"
    ],
    "wof:name":"Navarro",
    "wof:placetype":"locality"
},
  "geometry": {"coordinates":[-79.77083,22.64797],"type":"Point"}
}