{
  "type": "Feature",
  "properties": {
    "gn:admin1_code":"10",
    "gn:asciiname":"La Cidra",
    "gn:country_code":"CU",
    "gn:dem":53,
    "gn:feature_class":"P",
    "gn:feature_code":"PPLL",
    "gn:name":"La Cidra",
    "gn:population":0,
    "gn:timezone":"America/Havana",
    "iso:country":"CU",
    "wof:name":"La Cidra",
    "wof:placetype":"locality"
},
  "geometry": {"coordinates":[-74.43333,20.23333],"type":"Point"}
}