{
  "type": "Feature",
  "properties": {
    "gn:admin1_code":"MA",
    "gn:asciiname":"La Teresa",
    "gn:country_code":"CU",
    "gn:dem":43,
    "gn:feature_class":"P",
    "gn:feature_code":"PPLL",
    "gn:name":"La Teresa",
    "gn:population":0,
    "gn:timezone":"America/Havana",
    "iso:country":"CU",
    "wof:name":"La Teresa",
    "wof:placetype":"locality"
},
  "geometry": {"coordinates":[-82.05,22.81667],"type":"Point"}
}