{
  "type": "Feature",
  "properties": {
    "gn:admin1_code":"10",
    "gn:asciiname":"La Cuaba",
    "gn:cc2":"CU",
    "gn:country_code":"CU",
    "gn:dem":52,
    "gn:feature_class":"P",
    "gn:feature_code":"PPL",
    "gn:name":"La Cuaba",
    "gn:population":0,
    "gn:timezone":"America/Havana",
    "iso:country":"CU",
    "name:und_x_variant":[
        "Cuaba",
        "La Cuaba"
    ],
    "wof:name":"La Cuaba",
    "wof:placetype":"locality"
},
  "geometry": {"coordinates":[-75.09472,20.135],"type":"Point"}
}