{
  "type": "Feature",
  "properties": {
    "gn:admin1_code":"01",
    "gn:asciiname":"Punta de Santa Clara",
    "gn:cc2":"CU",
    "gn:country_code":"CU",
    "gn:dem":32,
    "gn:feature_class":"P",
    "gn:feature_code":"PPLL",
    "gn:name":"Punta de Santa Clara",
    "gn:population":0,
    "gn:timezone":"America/Havana",
    "iso:country":"CU",
    "name:und_x_variant":[
        "Santa Clara",
        "Punta Santa Clara",
        "Punto Santa Clara",
        "Punta de Santa Clara"
    ],
    "wof:name":"Punta de Santa Clara",
    "wof:placetype":"locality"
},
  "geometry": {"coordinates":[-83.43333,22.46667],"type":"Point"}
}