{
  "type": "Feature",
  "properties": {
    "gn:admin1_code":"13",
    "gn:asciiname":"Gia Dos",
    "gn:country_code":"CU",
    "gn:dem":19,
    "gn:feature_class":"P",
    "gn:feature_code":"PPL",
    "gn:name":"G\u00eda Dos",
    "gn:population":0,
    "gn:timezone":"America/Havana",
    "iso:country":"CU",
    "name:spa_x_preferred":[
        "G\u00eda Dos"
    ],
    "name:und_x_variant":[
        "La G\u00eda"
    ],
    "wof:name":"Gia Dos",
    "wof:placetype":"locality"
},
  "geometry": {"coordinates":[-76.78306000000001,21.215],"type":"Point"}
}