{
  "type": "Feature",
  "properties": {
    "gn:admin1_code":"03",
    "gn:asciiname":"Cocodrilos",
    "gn:cc2":"CU",
    "gn:country_code":"CU",
    "gn:dem":10,
    "gn:feature_class":"P",
    "gn:feature_code":"PPL",
    "gn:name":"Cocodrilos",
    "gn:population":0,
    "gn:timezone":"America/Havana",
    "iso:country":"CU",
    "name:und_x_variant":[
        "Cocodrilo",
        "Cocodrilos"
    ],
    "wof:name":"Cocodrilos",
    "wof:placetype":"locality"
},
  "geometry": {"coordinates":[-81.55972,22.63778],"type":"Point"}
}