{
  "type": "Feature",
  "properties": {
    "gn:admin1_code":"10",
    "gn:asciiname":"El Acueducto",
    "gn:country_code":"CU",
    "gn:dem":34,
    "gn:feature_class":"P",
    "gn:feature_code":"PPL",
    "gn:name":"El Acueducto",
    "gn:population":0,
    "gn:timezone":"America/Havana",
    "iso:country":"CU",
    "name:rus_x_preferred":[
        "El\u2019-Akuedukto"
    ],
    "name:und_x_variant":[
        "El Jig\u00fce",
        "El Jiq\u00fcw",
        "El Acueducto"
    ],
    "wof:name":"El Acueducto",
    "wof:placetype":"locality"
},
  "geometry": {"coordinates":[-75.03331,20.01303],"type":"Point"}
}