{
  "type": "Feature",
  "properties": {
    "gn:admin1_code":"16",
    "gn:asciiname":"San Cristobal",
    "gn:country_code":"CU",
    "gn:dem":178,
    "gn:feature_class":"P",
    "gn:feature_code":"PPLL",
    "gn:name":"San Crist\u00f3bal",
    "gn:population":0,
    "gn:timezone":"America/Havana",
    "iso:country":"CU",
    "name:fas_x_preferred":[
        "\u0633\u0627\u0646 \u06a9\u0631\u06cc\u0633\u062a\u0648\u0628\u0627\u0644"
    ],
    "name:heb_x_preferred":[
        "\u05d0\u05d9\u05d9 \u05e1\u05df \u05db\u05e8\u05d9\u05e1\u05d8\u05d5\u05d1\u05dc"
    ],
    "name:hun_x_preferred":[
        "San Cristobal"
    ],
    "name:spa_x_preferred":[
        "San Crist\u00f3bal"
    ],
    "name:und_x_variant":[
        "Corojo",
        "Corojo de San Crist\u00f3bal"
    ],
    "wof:name":"San Cristobal",
    "wof:placetype":"locality"
},
  "geometry": {"coordinates":[-79.57349000000001,22.24841],"type":"Point"}
}