{
  "type": "Feature",
  "properties": {
    "gn:admin1_code":"AR",
    "gn:asciiname":"Amistad",
    "gn:country_code":"CU",
    "gn:dem":23,
    "gn:feature_class":"P",
    "gn:feature_code":"PPLL",
    "gn:name":"Amistad",
    "gn:population":0,
    "gn:timezone":"America/Havana",
    "iso:country":"CU",
    "name:bul_x_preferred":[
        "\u0410\u043c\u0438\u0441\u0442\u0430\u0434"
    ],
    "name:ces_x_preferred":[
        "Amistad"
    ],
    "name:deu_x_preferred":[
        "Amistad"
    ],
    "name:fas_x_preferred":[
        "\u0622\u0645\u06cc\u0633\u062a\u0627\u062f"
    ],
    "name:heb_x_preferred":[
        "\u05d0\u05de\u05d9\u05e1\u05d8\u05d0\u05d3"
    ],
    "name:ita_x_preferred":[
        "Amistad"
    ],
    "name:nld_x_preferred":[
        "Amistad"
    ],
    "name:nor_x_preferred":[
        "Amistad"
    ],
    "name:rus_x_preferred":[
        "\u0410\u043c\u0438\u0441\u0442\u0430\u0434"
    ],
    "name:slk_x_preferred":[
        "Amistad"
    ],
    "name:spa_x_preferred":[
        "Amistad"
    ],
    "name:srp_x_preferred":[
        "\u0410\u043c\u0438\u0441\u0442\u0430\u0434"
    ],
    "name:tur_x_preferred":[
        "Amistad"
    ],
    "wof:name":"Amistad",
    "wof:placetype":"locality"
},
  "geometry": {"coordinates":[-82.5775,22.82278],"type":"Point"}
}