{
  "type": "Feature",
  "properties": {
    "gn:admin1_code":"14",
    "gn:asciiname":"Los Telles",
    "gn:country_code":"CU",
    "gn:dem":225,
    "gn:feature_class":"P",
    "gn:feature_code":"PPL",
    "gn:name":"Los Telles",
    "gn:population":0,
    "gn:timezone":"America/Havana",
    "iso:country":"CU",
    "name:spa_x_preferred":[
        "Los Telles"
    ],
    "name:und_x_variant":[
        "Las Llanabas",
        "Llanadas",
        "Las Llanadas"
    ],
    "wof:name":"Los Telles",
    "wof:placetype":"locality"
},
  "geometry": {"coordinates":[-79.10593,22.21034],"type":"Point"}
}