{
  "type": "Feature",
  "properties": {
    "gn:admin1_code":"05",
    "gn:asciiname":"Rio Lazaro",
    "gn:country_code":"CU",
    "gn:dem":44,
    "gn:feature_class":"P",
    "gn:feature_code":"PPLL",
    "gn:name":"R\u00edo L\u00e1zaro",
    "gn:population":0,
    "gn:timezone":"America/Havana",
    "iso:country":"CU",
    "name:spa_x_preferred":[
        "R\u00edo L\u00e1zaro"
    ],
    "name:und_x_variant":[
        "L\u00e1zaro"
    ],
    "wof:name":"Rio Lazaro",
    "wof:placetype":"locality"
},
  "geometry": {"coordinates":[-78.30583,21.80167],"type":"Point"}
}