{
  "type": "Feature",
  "properties": {
    "gn:admin1_code":"MA",
    "gn:asciiname":"Caraballo",
    "gn:country_code":"CU",
    "gn:dem":27,
    "gn:feature_class":"P",
    "gn:feature_code":"PPLL",
    "gn:name":"Caraballo",
    "gn:population":0,
    "gn:timezone":"America/Havana",
    "iso:country":"CU",
    "name:spa_x_preferred":[
        "Caraballo"
    ],
    "wof:name":"Caraballo",
    "wof:placetype":"locality"
},
  "geometry": {"coordinates":[-82.05826,22.79256],"type":"Point"}
}