{
  "type": "Feature",
  "properties": {
    "gn:admin1_code":"14",
    "gn:asciiname":"Nacimiento de los Dos Rios",
    "gn:cc2":"CU",
    "gn:country_code":"CU",
    "gn:dem":253,
    "gn:feature_class":"P",
    "gn:feature_code":"PPLL",
    "gn:name":"Nacimiento de los Dos R\u00edos",
    "gn:population":0,
    "gn:timezone":"America/Havana",
    "iso:country":"CU",
    "name:und_x_variant":[
        "Nacimiento",
        "Nacimento de los Dos R\u00edos",
        "Nacimiento de los Dos R\u00edos"
    ],
    "wof:name":"Nacimiento de los Dos Rios",
    "wof:placetype":"locality"
},
  "geometry": {"coordinates":[-79.22972,22.23556],"type":"Point"}
}