{
  "type": "Feature",
  "properties": {
    "gn:admin1_code":"AR",
    "gn:asciiname":"Nuestra Senora de Regla",
    "gn:country_code":"CU",
    "gn:dem":28,
    "gn:feature_class":"P",
    "gn:feature_code":"PPLL",
    "gn:name":"Nuestra Se\u00f1ora de Regla",
    "gn:population":0,
    "gn:timezone":"America/Havana",
    "iso:country":"CU",
    "wof:name":"Nuestra Senora de Regla",
    "wof:placetype":"locality"
},
  "geometry": {"coordinates":[-82.58333,22.81667],"type":"Point"}
}