{
  "type": "Feature",
  "properties": {
    "gn:admin1_code":"AR",
    "gn:asciiname":"Las Pozas",
    "gn:country_code":"CU",
    "gn:dem":34,
    "gn:feature_class":"P",
    "gn:feature_code":"PPL",
    "gn:name":"Las Pozas",
    "gn:population":0,
    "gn:timezone":"America/Havana",
    "iso:country":"CU",
    "name:spa_x_preferred":[
        "Las Pozas"
    ],
    "wof:name":"Las Pozas",
    "wof:placetype":"locality"
},
  "geometry": {"coordinates":[-83.29638,22.8702],"type":"Point"}
}