{
  "type": "Feature",
  "properties": {
    "gn:admin1_code":"15",
    "gn:asciiname":"Manacas",
    "gn:country_code":"CU",
    "gn:dem":259,
    "gn:feature_class":"P",
    "gn:feature_code":"PPL",
    "gn:name":"Manacas",
    "gn:population":0,
    "gn:timezone":"America/Havana",
    "iso:country":"CU",
    "name:und_x_variant":[
        "Manaca",
        "Manacas"
    ],
    "wof:name":"Manacas",
    "wof:placetype":"locality"
},
  "geometry": {"coordinates":[-76.13370999999999,20.14976],"type":"Point"}
}