{
  "type": "Feature",
  "properties": {
    "gn:admin1_code":"13",
    "gn:asciiname":"Tesoro",
    "gn:country_code":"CU",
    "gn:dem":63,
    "gn:feature_class":"P",
    "gn:feature_code":"PPLL",
    "gn:name":"Tesoro",
    "gn:population":0,
    "gn:timezone":"America/Havana",
    "iso:country":"CU",
    "wof:name":"Tesoro",
    "wof:placetype":"locality"
},
  "geometry": {"coordinates":[-77.63333,20.86667000000001],"type":"Point"}
}