{
  "type": "Feature",
  "properties": {
    "gn:admin1_code":"15",
    "gn:asciiname":"El Sitio",
    "gn:cc2":"CU",
    "gn:country_code":"CU",
    "gn:dem":66,
    "gn:feature_class":"P",
    "gn:feature_code":"PPLL",
    "gn:name":"El Sitio",
    "gn:population":0,
    "gn:timezone":"America/Havana",
    "iso:country":"CU",
    "name:und_x_variant":[
        "El Sitio del Doutor R. Arango",
        "El Sitio"
    ],
    "wof:name":"El Sitio",
    "wof:placetype":"locality"
},
  "geometry": {"coordinates":[-75.8325,19.97306],"type":"Point"}
}