{
  "type": "Feature",
  "properties": {
    "gn:admin1_code":"16",
    "gn:asciiname":"Republica",
    "gn:country_code":"CU",
    "gn:dem":80,
    "gn:feature_class":"P",
    "gn:feature_code":"PPL",
    "gn:name":"Rep\u00fablica",
    "gn:population":0,
    "gn:timezone":"America/Havana",
    "iso:country":"CU",
    "name:spa_x_preferred":[
        "Rep\u00fablica"
    ],
    "wof:name":"Republica",
    "wof:placetype":"locality"
},
  "geometry": {"coordinates":[-80.38686,22.7721],"type":"Point"}
}