{
  "type": "Feature",
  "properties": {
    "gn:admin1_code":"10",
    "gn:asciiname":"El Mije",
    "gn:country_code":"CU",
    "gn:dem":227,
    "gn:feature_class":"P",
    "gn:feature_code":"PPL",
    "gn:name":"El Mije",
    "gn:population":0,
    "gn:timezone":"America/Havana",
    "iso:country":"CU",
    "name:spa_x_preferred":[
        "El Mije"
    ],
    "wof:name":"El Mije",
    "wof:placetype":"locality"
},
  "geometry": {"coordinates":[-74.86175,20.14178],"type":"Point"}
}