{
  "type": "Feature",
  "properties": {
    "gn:admin1_code":"10",
    "gn:asciiname":"El Posango",
    "gn:country_code":"CU",
    "gn:dem":67,
    "gn:feature_class":"P",
    "gn:feature_code":"PPL",
    "gn:name":"El Posango",
    "gn:population":0,
    "gn:timezone":"America/Havana",
    "iso:country":"CU",
    "name:spa_x_preferred":[
        "El Posango"
    ],
    "wof:name":"El Posango",
    "wof:placetype":"locality"
},
  "geometry": {"coordinates":[-74.68008,20.09809],"type":"Point"}
}