{
  "type": "Feature",
  "properties": {
    "gn:admin1_code":"05",
    "gn:asciiname":"La Nenita",
    "gn:country_code":"CU",
    "gn:dem":54,
    "gn:feature_class":"P",
    "gn:feature_code":"PPLL",
    "gn:name":"La Nenita",
    "gn:population":0,
    "gn:timezone":"America/Havana",
    "iso:country":"CU",
    "wof:name":"La Nenita",
    "wof:placetype":"locality"
},
  "geometry": {"coordinates":[-78.27611,21.50583],"type":"Point"}
}