{
  "type": "Feature",
  "properties": {
    "gn:admin1_code":"03",
    "gn:asciiname":"Bella Union",
    "gn:country_code":"CU",
    "gn:dem":77,
    "gn:feature_class":"P",
    "gn:feature_code":"PPLL",
    "gn:name":"Bella Uni\u00f3n",
    "gn:population":0,
    "gn:timezone":"America/Havana",
    "iso:country":"CU",
    "name:ces_x_preferred":[
        "Bella Union"
    ],
    "name:deu_x_preferred":[
        "Bella Union"
    ],
    "name:fin_x_preferred":[
        "Bella Union"
    ],
    "name:fra_x_preferred":[
        "Bella Union"
    ],
    "name:glg_x_preferred":[
        "Bella Union"
    ],
    "name:ita_x_preferred":[
        "Bella Union Records"
    ],
    "name:jpn_x_preferred":[
        "\u30d9\u30e9\u30fb\u30e6\u30cb\u30aa\u30f3"
    ],
    "name:por_x_preferred":[
        "Bella Union"
    ],
    "name:swe_x_preferred":[
        "Bella Union"
    ],
    "wof:name":"Bella Union",
    "wof:placetype":"locality"
},
  "geometry": {"coordinates":[-80.68861,22.73],"type":"Point"}
}