{
  "type": "Feature",
  "properties": {
    "gn:admin1_code":"10",
    "gn:asciiname":"Guaso",
    "gn:country_code":"CU",
    "gn:dem":115,
    "gn:feature_class":"P",
    "gn:feature_code":"PPL",
    "gn:name":"Guaso",
    "gn:population":0,
    "gn:timezone":"America/Havana",
    "iso:country":"CU",
    "name:spa_x_preferred":[
        "Guaso"
    ],
    "wof:name":"Guaso",
    "wof:placetype":"locality"
},
  "geometry": {"coordinates":[-75.16833000000003,20.23167],"type":"Point"}
}