{
  "type": "Feature",
  "properties": {
    "gn:admin1_code":"03",
    "gn:asciiname":"Curamaguey",
    "gn:country_code":"CU",
    "gn:dem":41,
    "gn:feature_class":"P",
    "gn:feature_code":"PPLL",
    "gn:name":"Curamag\u00fcey",
    "gn:population":0,
    "gn:timezone":"America/Havana",
    "iso:country":"CU",
    "name:spa_x_preferred":[
        "Curamag\u00fcey"
    ],
    "name:und_x_variant":[
        "Cura Mag\u00fcey"
    ],
    "wof:name":"Curamaguey",
    "wof:placetype":"locality"
},
  "geometry": {"coordinates":[-80.91405999999998,22.63418],"type":"Point"}
}