{
  "type": "Feature",
  "properties": {
    "gn:admin1_code":"08",
    "gn:asciiname":"Natalia",
    "gn:country_code":"CU",
    "gn:dem":14,
    "gn:feature_class":"P",
    "gn:feature_code":"PPLL",
    "gn:name":"Natalia",
    "gn:population":0,
    "gn:timezone":"America/Havana",
    "iso:country":"CU",
    "name:ceb_x_preferred":[
        "Natalia"
    ],
    "name:deu_x_preferred":[
        "Natalia"
    ],
    "name:est_x_preferred":[
        "Natalia"
    ],
    "name:fin_x_preferred":[
        "Natalia"
    ],
    "name:fra_x_preferred":[
        "Natalia"
    ],
    "name:ind_x_preferred":[
        "Natalia"
    ],
    "name:ita_x_preferred":[
        "Natalia"
    ],
    "name:jpn_x_preferred":[
        "\u30ca\u30bf\u30ea\u30a2"
    ],
    "name:kor_x_preferred":[
        "\ub098\ud0c8\ub9ac\uc544"
    ],
    "name:nld_x_preferred":[
        "Natalia"
    ],
    "name:pol_x_preferred":[
        "Natalia"
    ],
    "name:spa_x_preferred":[
        "Natalia"
    ],
    "name:tur_x_preferred":[
        "Natalia"
    ],
    "name:vie_x_preferred":[
        "Natalie"
    ],
    "wof:name":"Natalia",
    "wof:placetype":"locality"
},
  "geometry": {"coordinates":[-80.58333,22.11667000000001],"type":"Point"}
}