{
  "type": "Feature",
  "properties": {
    "gn:admin1_code":"10",
    "gn:asciiname":"Corralillo",
    "gn:country_code":"CU",
    "gn:dem":161,
    "gn:feature_class":"P",
    "gn:feature_code":"PPL",
    "gn:name":"Corralillo",
    "gn:population":0,
    "gn:timezone":"America/Havana",
    "iso:country":"CU",
    "name:fra_x_preferred":[
        "Corralillo"
    ],
    "name:ita_x_preferred":[
        "Corralillo"
    ],
    "name:kat_x_preferred":[
        "\u10d9\u10dd\u10e0\u10d0\u10da\u10d8\u10da\u10d8\u10dd"
    ],
    "name:pol_x_preferred":[
        "Corralillo"
    ],
    "name:por_x_preferred":[
        "Corralillo"
    ],
    "name:sco_x_preferred":[
        "Corralillo"
    ],
    "name:spa_x_preferred":[
        "Corralillo"
    ],
    "name:vie_x_preferred":[
        "Corralillo"
    ],
    "name:zho_x_preferred":[
        "\u79d1\u62c9\u5229\u7565"
    ],
    "wof:name":"Corralillo",
    "wof:placetype":"locality"
},
  "geometry": {"coordinates":[-75.4464,20.2167],"type":"Point"}
}