{
  "type": "Feature",
  "properties": {
    "gn:admin1_code":"14",
    "gn:asciiname":"Magua",
    "gn:country_code":"CU",
    "gn:dem":52,
    "gn:feature_class":"P",
    "gn:feature_code":"PPL",
    "gn:name":"Magua",
    "gn:population":0,
    "gn:timezone":"America/Havana",
    "iso:country":"CU",
    "name:pol_x_preferred":[
        "Chytry Lis"
    ],
    "name:ukr_x_preferred":[
        "\u041c\u0430\u0433\u0443\u0430"
    ],
    "wof:name":"Magua",
    "wof:placetype":"locality"
},
  "geometry": {"coordinates":[-79.91167,21.84778],"type":"Point"}
}