{
  "type": "Feature",
  "properties": {
    "gn:admin1_code":"03",
    "gn:asciiname":"El Puntal",
    "gn:country_code":"CU",
    "gn:dem":31,
    "gn:feature_class":"P",
    "gn:feature_code":"PPLL",
    "gn:name":"El Puntal",
    "gn:population":0,
    "gn:timezone":"America/Havana",
    "iso:country":"CU",
    "wof:name":"El Puntal",
    "wof:placetype":"locality"
},
  "geometry": {"coordinates":[-80.98333000000002,22.81667],"type":"Point"}
}