{
  "type": "Feature",
  "properties": {
    "gn:admin1_code":"14",
    "gn:asciiname":"San Carlos del Quemado",
    "gn:country_code":"CU",
    "gn:dem":68,
    "gn:feature_class":"P",
    "gn:feature_code":"PPLL",
    "gn:name":"San Carlos del Quemado",
    "gn:population":0,
    "gn:timezone":"America/Havana",
    "iso:country":"CU",
    "wof:name":"San Carlos del Quemado",
    "wof:placetype":"locality"
},
  "geometry": {"coordinates":[-79.76666999999998,21.85],"type":"Point"}
}