{
  "type": "Feature",
  "properties": {
    "gn:admin1_code":"10",
    "gn:asciiname":"Palenque",
    "gn:country_code":"CU",
    "gn:dem":221,
    "gn:feature_class":"P",
    "gn:feature_code":"PPL",
    "gn:name":"Palenque",
    "gn:population":0,
    "gn:timezone":"America/Havana",
    "iso:country":"CU",
    "name:spa_x_preferred":[
        "Palenque"
    ],
    "wof:name":"Palenque",
    "wof:placetype":"locality"
},
  "geometry": {"coordinates":[-75.44963,19.98032000000001],"type":"Point"}
}