{
  "type": "Feature",
  "properties": {
    "gn:admin1_code":"16",
    "gn:asciiname":"El Carril",
    "gn:country_code":"CU",
    "gn:dem":112,
    "gn:feature_class":"P",
    "gn:feature_code":"PPLL",
    "gn:name":"El Carril",
    "gn:population":0,
    "gn:timezone":"America/Havana",
    "iso:country":"CU",
    "name:spa_x_preferred":[
        "El Carril"
    ],
    "name:und_x_variant":[
        "Carrii",
        "Carril"
    ],
    "wof:name":"El Carril",
    "wof:placetype":"locality"
},
  "geometry": {"coordinates":[-80.12263,22.29677],"type":"Point"}
}