{
  "type": "Feature",
  "properties": {
    "gn:admin1_code":"03",
    "gn:asciiname":"Ategorrieta",
    "gn:country_code":"CU",
    "gn:dem":30,
    "gn:feature_class":"P",
    "gn:feature_code":"PPL",
    "gn:name":"Ategorrieta",
    "gn:population":0,
    "gn:timezone":"America/Havana",
    "iso:country":"CU",
    "name:spa_x_preferred":[
        "Ategorrieta"
    ],
    "name:und_x_variant":[
        "Etagorrieta"
    ],
    "wof:name":"Ategorrieta",
    "wof:placetype":"locality"
},
  "geometry": {"coordinates":[-80.95125,22.93935],"type":"Point"}
}