{
  "type": "Feature",
  "properties": {
    "gn:admin1_code":"13",
    "gn:asciiname":"Puerto Carupano",
    "gn:country_code":"CU",
    "gn:dem":6,
    "gn:feature_class":"P",
    "gn:feature_code":"PPL",
    "gn:name":"Puerto Car\u00fapano",
    "gn:population":0,
    "gn:timezone":"America/Havana",
    "iso:country":"CU",
    "name:spa_x_preferred":[
        "Puerto Car\u00fapano"
    ],
    "wof:name":"Puerto Carupano",
    "wof:placetype":"locality"
},
  "geometry": {"coordinates":[-76.54026999999998,21.22684],"type":"Point"}
}