{
  "type": "Feature",
  "properties": {
    "gn:admin1_code":"16",
    "gn:asciiname":"La Margarita",
    "gn:country_code":"CU",
    "gn:dem":80,
    "gn:feature_class":"P",
    "gn:feature_code":"PPLL",
    "gn:name":"La Margarita",
    "gn:population":0,
    "gn:timezone":"America/Havana",
    "iso:country":"CU",
    "name:spa_x_preferred":[
        "La Margarita"
    ],
    "wof:name":"La Margarita",
    "wof:placetype":"locality"
},
  "geometry": {"coordinates":[-80.42638000000002,22.65869],"type":"Point"}
}