{
  "type": "Feature",
  "properties": {
    "gn:admin1_code":"05",
    "gn:asciiname":"El Guao",
    "gn:country_code":"CU",
    "gn:dem":50,
    "gn:feature_class":"P",
    "gn:feature_code":"PPLL",
    "gn:name":"El Guao",
    "gn:population":0,
    "gn:timezone":"America/Havana",
    "iso:country":"CU",
    "name:spa_x_preferred":[
        "El Guao"
    ],
    "wof:name":"El Guao",
    "wof:placetype":"locality"
},
  "geometry": {"coordinates":[-77.29049000000001,21.24316],"type":"Point"}
}