{
  "type": "Feature",
  "properties": {
    "gn:admin1_code":"13",
    "gn:asciiname":"Bazarales",
    "gn:country_code":"CU",
    "gn:dem":96,
    "gn:feature_class":"P",
    "gn:feature_code":"PPLL",
    "gn:name":"Bazarales",
    "gn:population":0,
    "gn:timezone":"America/Havana",
    "iso:country":"CU",
    "wof:name":"Bazarales",
    "wof:placetype":"locality"
},
  "geometry": {"coordinates":[-76.79083,21.06722],"type":"Point"}
}