{
  "type": "Feature",
  "properties": {
    "gn:admin1_code":"03",
    "gn:asciiname":"Garcia Capote",
    "gn:country_code":"CU",
    "gn:dem":57,
    "gn:feature_class":"P",
    "gn:feature_code":"PPL",
    "gn:name":"Garc\u00eda Capote",
    "gn:population":0,
    "gn:timezone":"America/Havana",
    "iso:country":"CU",
    "name:spa_x_preferred":[
        "Garc\u00eda Capote"
    ],
    "wof:name":"Garcia Capote",
    "wof:placetype":"locality"
},
  "geometry": {"coordinates":[-80.96590999999999,22.74793],"type":"Point"}
}