{
  "type": "Feature",
  "properties": {
    "gn:admin1_code":"07",
    "gn:asciiname":"Tres Ceibas",
    "gn:country_code":"CU",
    "gn:dem":36,
    "gn:feature_class":"P",
    "gn:feature_code":"PPLL",
    "gn:name":"Tres Ceibas",
    "gn:population":0,
    "gn:timezone":"America/Havana",
    "iso:country":"CU",
    "wof:name":"Tres Ceibas",
    "wof:placetype":"locality"
},
  "geometry": {"coordinates":[-79.03667,21.76194],"type":"Point"}
}