{
  "type": "Feature",
  "properties": {
    "gn:admin1_code":"03",
    "gn:asciiname":"Cuartel",
    "gn:cc2":"CU",
    "gn:country_code":"CU",
    "gn:dem":9,
    "gn:feature_class":"P",
    "gn:feature_code":"PPLL",
    "gn:name":"Cuartel",
    "gn:population":0,
    "gn:timezone":"America/Havana",
    "iso:country":"CU",
    "name:und_x_variant":[
        "Chucho Cuartel",
        "Cuartel"
    ],
    "wof:name":"Cuartel",
    "wof:placetype":"locality"
},
  "geometry": {"coordinates":[-81.31667,22.63333],"type":"Point"}
}