{
  "type": "Feature",
  "properties": {
    "gn:admin1_code":"15",
    "gn:asciiname":"Ramon de las Yaguas",
    "gn:cc2":"CU",
    "gn:country_code":"CU",
    "gn:dem":267,
    "gn:feature_class":"P",
    "gn:feature_code":"PPL",
    "gn:name":"Ram\u00f3n de las Yaguas",
    "gn:population":0,
    "gn:timezone":"America/Havana",
    "iso:country":"CU",
    "name:und_x_variant":[
        "Ram\u00f3n de las Yeguas",
        "Ram\u00f3n de las Yagua",
        "Ram\u00f3n de las Yaguas"
    ],
    "wof:name":"Ramon de las Yaguas",
    "wof:placetype":"locality"
},
  "geometry": {"coordinates":[-75.46666999999999,20.03333],"type":"Point"}
}