{
  "type": "Feature",
  "properties": {
    "gn:admin1_code":"15",
    "gn:asciiname":"El Treinta y Sieta",
    "gn:country_code":"CU",
    "gn:dem":148,
    "gn:feature_class":"P",
    "gn:feature_code":"PPL",
    "gn:name":"El Treinta y Sieta",
    "gn:population":0,
    "gn:timezone":"America/Havana",
    "iso:country":"CU",
    "name:spa_x_preferred":[
        "El Treinta y Sieta"
    ],
    "wof:name":"El Treinta y Sieta",
    "wof:placetype":"locality"
},
  "geometry": {"coordinates":[-75.85876999999998,20.35682000000001],"type":"Point"}
}