{
  "type": "Feature",
  "properties": {
    "gn:admin1_code":"02",
    "gn:asciiname":"Rancho Pekita",
    "gn:cc2":"CU",
    "gn:country_code":"CU",
    "gn:dem":37,
    "gn:feature_class":"P",
    "gn:feature_code":"PPL",
    "gn:name":"Rancho Pekita",
    "gn:population":0,
    "gn:timezone":"America/Havana",
    "iso:country":"CU",
    "name:und_x_variant":[
        "Buenavista",
        "Rancho Pekita"
    ],
    "wof:name":"Rancho Pekita",
    "wof:placetype":"locality"
},
  "geometry": {"coordinates":[-82.26666999999998,23.15],"type":"Point"}
}