{
  "type": "Feature",
  "properties": {
    "gn:admin1_code":"08",
    "gn:asciiname":"La Martina",
    "gn:country_code":"CU",
    "gn:dem":134,
    "gn:feature_class":"P",
    "gn:feature_code":"PPLL",
    "gn:name":"La Martina",
    "gn:population":0,
    "gn:timezone":"America/Havana",
    "iso:country":"CU",
    "name:spa_x_preferred":[
        "La Martina"
    ],
    "wof:name":"La Martina",
    "wof:placetype":"locality"
},
  "geometry": {"coordinates":[-80.15397,22.32633],"type":"Point"}
}