{
  "type": "Feature",
  "properties": {
    "gn:admin1_code":"03",
    "gn:asciiname":"San Antonio de Valera",
    "gn:country_code":"CU",
    "gn:dem":78,
    "gn:feature_class":"P",
    "gn:feature_code":"PPLL",
    "gn:name":"San Antonio de Valera",
    "gn:population":0,
    "gn:timezone":"America/Havana",
    "iso:country":"CU",
    "wof:name":"San Antonio de Valera",
    "wof:placetype":"locality"
},
  "geometry": {"coordinates":[-81.60944000000001,22.83833],"type":"Point"}
}