{
  "type": "Feature",
  "properties": {
    "gn:admin1_code":"10",
    "gn:asciiname":"El Rincon",
    "gn:cc2":"CU",
    "gn:country_code":"CU",
    "gn:dem":57,
    "gn:feature_class":"P",
    "gn:feature_code":"PPL",
    "gn:name":"El Rinc\u00f3n",
    "gn:population":0,
    "gn:timezone":"America/Havana",
    "iso:country":"CU",
    "name:rus_x_preferred":[
        "El\u2019-Rinkon"
    ],
    "name:und_x_variant":[
        "El Rinc\u00f3n"
    ],
    "wof:name":"El Rincon",
    "wof:placetype":"locality"
},
  "geometry": {"coordinates":[-75.32639,20.09694],"type":"Point"}
}