{
  "type": "Feature",
  "properties": {
    "gn:admin1_code":"12",
    "gn:asciiname":"Yabazon Abajo",
    "gn:country_code":"CU",
    "gn:dem":34,
    "gn:feature_class":"P",
    "gn:feature_code":"PPL",
    "gn:name":"Yabaz\u00f3n Abajo",
    "gn:population":0,
    "gn:timezone":"America/Havana",
    "iso:country":"CU",
    "name:und_x_variant":[
        "Yabaz\u00f3n",
        "Yabason",
        "Yabaz\u00f3n Abajo"
    ],
    "wof:name":"Yabazon Abajo",
    "wof:placetype":"locality"
},
  "geometry": {"coordinates":[-76.18241999999999,21.02851],"type":"Point"}
}