{
  "type": "Feature",
  "properties": {
    "gn:admin1_code":"MA",
    "gn:asciiname":"Rio Blanco",
    "gn:country_code":"CU",
    "gn:dem":125,
    "gn:feature_class":"P",
    "gn:feature_code":"PPL",
    "gn:name":"R\u00edo Blanco",
    "gn:population":0,
    "gn:timezone":"America/Havana",
    "iso:country":"CU",
    "name:spa_x_preferred":[
        "R\u00edo Blanco"
    ],
    "wof:name":"Rio Blanco",
    "wof:placetype":"locality"
},
  "geometry": {"coordinates":[-82.22845,22.88704],"type":"Point"}
}