{
  "type": "Feature",
  "properties": {
    "gn:admin1_code":"05",
    "gn:asciiname":"La Veinte y Una",
    "gn:country_code":"CU",
    "gn:dem":80,
    "gn:feature_class":"P",
    "gn:feature_code":"PPL",
    "gn:name":"La Veinte y Una",
    "gn:population":0,
    "gn:timezone":"America/Havana",
    "iso:country":"CU",
    "name:spa_x_preferred":[
        "La Veinte y Una"
    ],
    "wof:name":"La Veinte y Una",
    "wof:placetype":"locality"
},
  "geometry": {"coordinates":[-77.50248000000001,20.9969],"type":"Point"}
}