{
  "type": "Feature",
  "properties": {
    "gn:admin1_code":"05",
    "gn:asciiname":"La Grabriela",
    "gn:country_code":"CU",
    "gn:dem":38,
    "gn:feature_class":"P",
    "gn:feature_code":"PPL",
    "gn:name":"La Grabriela",
    "gn:population":0,
    "gn:timezone":"America/Havana",
    "iso:country":"CU",
    "name:spa_x_preferred":[
        "La Grabriela"
    ],
    "name:und_x_variant":[
        "Gabriela",
        "La Gabriela"
    ],
    "wof:name":"La Grabriela",
    "wof:placetype":"locality"
},
  "geometry": {"coordinates":[-77.58023,21.64674],"type":"Point"}
}