{
  "type": "Feature",
  "properties": {
    "gn:admin1_code":"MA",
    "gn:asciiname":"Puerto Escondido",
    "gn:country_code":"CU",
    "gn:dem":18,
    "gn:feature_class":"P",
    "gn:feature_code":"PPLL",
    "gn:name":"Puerto Escondido",
    "gn:population":0,
    "gn:timezone":"America/Havana",
    "iso:country":"CU",
    "wof:name":"Puerto Escondido",
    "wof:placetype":"locality"
},
  "geometry": {"coordinates":[-81.72417,23.13917],"type":"Point"}
}