{
  "type": "Feature",
  "properties": {
    "gn:admin1_code":"03",
    "gn:asciiname":"Noda",
    "gn:country_code":"CU",
    "gn:dem":40,
    "gn:feature_class":"P",
    "gn:feature_code":"PPLL",
    "gn:name":"Noda",
    "gn:population":0,
    "gn:timezone":"America/Havana",
    "iso:country":"CU",
    "name:ceb_x_preferred":[
        "Noda"
    ],
    "name:deu_x_preferred":[
        "Noda"
    ],
    "name:fra_x_preferred":[
        "Noda"
    ],
    "name:lav_x_preferred":[
        "Noda"
    ],
    "name:mlg_x_preferred":[
        "Noda"
    ],
    "name:nld_x_preferred":[
        "Noda"
    ],
    "name:pol_x_preferred":[
        "Noda"
    ],
    "name:por_x_preferred":[
        "Noda"
    ],
    "name:spa_x_preferred":[
        "Noda"
    ],
    "name:swe_x_preferred":[
        "Noda"
    ],
    "wof:name":"Noda",
    "wof:placetype":"locality"
},
  "geometry": {"coordinates":[-80.76666999999998,22.53333],"type":"Point"}
}