{
  "type": "Feature",
  "properties": {
    "gn:admin1_code":"12",
    "gn:asciiname":"Buenaventura",
    "gn:country_code":"CU",
    "gn:dem":96,
    "gn:feature_class":"P",
    "gn:feature_code":"PPL",
    "gn:name":"Buenaventura",
    "gn:population":0,
    "gn:timezone":"America/Havana",
    "iso:country":"CU",
    "name:spa_x_preferred":[
        "Buenaventura"
    ],
    "wof:name":"Buenaventura",
    "wof:placetype":"locality"
},
  "geometry": {"coordinates":[-76.6395,20.86352],"type":"Point"}
}