{
  "type": "Feature",
  "properties": {
    "gn:admin1_code":"15",
    "gn:asciiname":"Vega Grande",
    "gn:country_code":"CU",
    "gn:dem":144,
    "gn:feature_class":"P",
    "gn:feature_code":"PPLL",
    "gn:name":"Vega Grande",
    "gn:population":0,
    "gn:timezone":"America/Havana",
    "iso:country":"CU",
    "wof:name":"Vega Grande",
    "wof:placetype":"locality"
},
  "geometry": {"coordinates":[-75.99639000000001,20.19944],"type":"Point"}
}