{
  "type": "Feature",
  "properties": {
    "gn:admin1_code":"13",
    "gn:asciiname":"Tana",
    "gn:country_code":"CU",
    "gn:dem":27,
    "gn:feature_class":"P",
    "gn:feature_code":"PPL",
    "gn:name":"Tana",
    "gn:population":0,
    "gn:timezone":"America/Havana",
    "iso:country":"CU",
    "name:spa_x_preferred":[
        "Tana"
    ],
    "wof:name":"Tana",
    "wof:placetype":"locality"
},
  "geometry": {"coordinates":[-77.44926,20.81075],"type":"Point"}
}