{
  "type": "Feature",
  "properties": {
    "gn:admin1_code":"14",
    "gn:asciiname":"La Yaya",
    "gn:country_code":"CU",
    "gn:dem":195,
    "gn:feature_class":"P",
    "gn:feature_code":"PPLL",
    "gn:name":"La Yaya",
    "gn:population":0,
    "gn:timezone":"America/Havana",
    "iso:country":"CU",
    "name:und_x_variant":[
        "Vicente Rodriguez",
        "La Yaya"
    ],
    "wof:name":"La Yaya",
    "wof:placetype":"locality"
},
  "geometry": {"coordinates":[-79.63679999999999,22.12813],"type":"Point"}
}