{
  "type": "Feature",
  "properties": {
    "gn:admin1_code":"10",
    "gn:asciiname":"Pilones",
    "gn:country_code":"CU",
    "gn:dem":237,
    "gn:feature_class":"P",
    "gn:feature_code":"PPL",
    "gn:name":"Pilones",
    "gn:population":0,
    "gn:timezone":"America/Havana",
    "iso:country":"CU",
    "name:spa_x_preferred":[
        "Pilones"
    ],
    "wof:name":"Pilones",
    "wof:placetype":"locality"
},
  "geometry": {"coordinates":[-74.85531999999998,20.12293],"type":"Point"}
}