{
  "type": "Feature",
  "properties": {
    "gn:admin1_code":"14",
    "gn:asciiname":"Limones",
    "gn:country_code":"CU",
    "gn:dem":66,
    "gn:feature_class":"P",
    "gn:feature_code":"PPLL",
    "gn:name":"Limones",
    "gn:population":0,
    "gn:timezone":"America/Havana",
    "iso:country":"CU",
    "name:ceb_x_preferred":[
        "Limones"
    ],
    "name:srp_x_preferred":[
        "\u041b\u0438\u043c\u043e\u043d\u0435\u0441"
    ],
    "name:swe_x_preferred":[
        "Limones"
    ],
    "wof:name":"Limones",
    "wof:placetype":"locality"
},
  "geometry": {"coordinates":[-79.08889000000001,21.85417],"type":"Point"}
}