{
  "type": "Feature",
  "properties": {
    "gn:admin1_code":"07",
    "gn:asciiname":"La Tinaja",
    "gn:country_code":"CU",
    "gn:dem":33,
    "gn:feature_class":"P",
    "gn:feature_code":"PPL",
    "gn:name":"La Tinaja",
    "gn:population":0,
    "gn:timezone":"America/Havana",
    "iso:country":"CU",
    "wof:name":"La Tinaja",
    "wof:placetype":"locality"
},
  "geometry": {"coordinates":[-79.11083000000001,21.76083],"type":"Point"}
}