{
  "type": "Feature",
  "properties": {
    "gn:admin1_code":"03",
    "gn:asciiname":"Mendez Capote",
    "gn:country_code":"CU",
    "gn:dem":36,
    "gn:feature_class":"P",
    "gn:feature_code":"PPL",
    "gn:name":"M\u00e9ndez Capote",
    "gn:population":0,
    "gn:timezone":"America/Havana",
    "iso:country":"CU",
    "name:spa_x_preferred":[
        "M\u00e9ndez Capote"
    ],
    "name:und_x_variant":[
        "Lagunillas"
    ],
    "wof:name":"Mendez Capote",
    "wof:placetype":"locality"
},
  "geometry": {"coordinates":[-81.20999999999999,22.95094],"type":"Point"}
}