{
  "type": "Feature",
  "properties": {
    "gn:admin1_code":"05",
    "gn:asciiname":"Cuatro Caminos",
    "gn:country_code":"CU",
    "gn:dem":59,
    "gn:feature_class":"P",
    "gn:feature_code":"PPLL",
    "gn:name":"Cuatro Caminos",
    "gn:population":0,
    "gn:timezone":"America/Havana",
    "iso:country":"CU",
    "wof:name":"Cuatro Caminos",
    "wof:placetype":"locality"
},
  "geometry": {"coordinates":[-78.18556,21.40778],"type":"Point"}
}