{
  "type": "Feature",
  "properties": {
    "gn:admin1_code":"05",
    "gn:asciiname":"Los Dolores",
    "gn:country_code":"CU",
    "gn:dem":44,
    "gn:feature_class":"P",
    "gn:feature_code":"PPLL",
    "gn:name":"Los Dolores",
    "gn:population":0,
    "gn:timezone":"America/Havana",
    "iso:country":"CU",
    "name:spa_x_preferred":[
        "Los Dolores"
    ],
    "wof:name":"Los Dolores",
    "wof:placetype":"locality"
},
  "geometry": {"coordinates":[-78.11865999999998,21.82971],"type":"Point"}
}