{
  "type": "Feature",
  "properties": {
    "gn:admin1_code":"MA",
    "gn:asciiname":"Bello Indio",
    "gn:country_code":"CU",
    "gn:dem":6,
    "gn:feature_class":"P",
    "gn:feature_code":"PPL",
    "gn:name":"Bello Indio",
    "gn:population":0,
    "gn:timezone":"America/Havana",
    "iso:country":"CU",
    "name:spa_x_preferred":[
        "Bello Indio"
    ],
    "wof:name":"Bello Indio",
    "wof:placetype":"locality"
},
  "geometry": {"coordinates":[-82.03805,22.69759],"type":"Point"}
}