{
  "type": "Feature",
  "properties": {
    "gn:admin1_code":"12",
    "gn:asciiname":"Los Platanos",
    "gn:country_code":"CU",
    "gn:dem":203,
    "gn:feature_class":"P",
    "gn:feature_code":"PPL",
    "gn:name":"Los Pl\u00e1tanos",
    "gn:population":0,
    "gn:timezone":"America/Havana",
    "iso:country":"CU",
    "name:spa_x_preferred":[
        "Los Pl\u00e1tanos"
    ],
    "wof:name":"Los Platanos",
    "wof:placetype":"locality"
},
  "geometry": {"coordinates":[-75.37304,20.61876],"type":"Point"}
}