{
  "type": "Feature",
  "properties": {
    "gn:admin1_code":"01",
    "gn:asciiname":"Palomar",
    "gn:country_code":"CU",
    "gn:dem":36,
    "gn:feature_class":"P",
    "gn:feature_code":"PPLL",
    "gn:name":"Palomar",
    "gn:population":0,
    "gn:timezone":"America/Havana",
    "iso:country":"CU",
    "name:bre_x_preferred":[
        "Palomar"
    ],
    "name:cat_x_preferred":[
        "Palomar"
    ],
    "name:ceb_x_preferred":[
        "Palomar"
    ],
    "name:deu_x_preferred":[
        "Palomar"
    ],
    "name:fas_x_preferred":[
        "\u067e\u0627\u0644\u0648\u0645\u0627\u0631"
    ],
    "name:fra_x_preferred":[
        "Palomar"
    ],
    "name:ita_x_preferred":[
        "Palomar"
    ],
    "name:pol_x_preferred":[
        "Palomar"
    ],
    "name:por_x_preferred":[
        "Palomar"
    ],
    "name:spa_x_preferred":[
        "Palomar"
    ],
    "name:srp_x_preferred":[
        "\u041f\u0430\u043b\u043e\u043c\u0430\u0440"
    ],
    "name:swe_x_preferred":[
        "Palomar"
    ],
    "wof:name":"Palomar",
    "wof:placetype":"locality"
},
  "geometry": {"coordinates":[-83.65000000000001,22.35],"type":"Point"}
}