{
  "type": "Feature",
  "properties": {
    "gn:admin1_code":"08",
    "gn:asciiname":"Cabada",
    "gn:country_code":"CU",
    "gn:dem":117,
    "gn:feature_class":"P",
    "gn:feature_code":"PPLL",
    "gn:name":"Cabada",
    "gn:population":0,
    "gn:timezone":"America/Havana",
    "iso:country":"CU",
    "wof:name":"Cabada",
    "wof:placetype":"locality"
},
  "geometry": {"coordinates":[-80.18333,22.21667],"type":"Point"}
}