{
  "type": "Feature",
  "properties": {
    "gn:admin1_code":"15",
    "gn:asciiname":"El Iris",
    "gn:country_code":"CU",
    "gn:dem":458,
    "gn:feature_class":"P",
    "gn:feature_code":"PPL",
    "gn:name":"El Iris",
    "gn:population":0,
    "gn:timezone":"America/Havana",
    "iso:country":"CU",
    "name:spa_x_preferred":[
        "El Iris"
    ],
    "name:und_x_variant":[
        "Iris",
        "El Iris"
    ],
    "wof:name":"El Iris",
    "wof:placetype":"locality"
},
  "geometry": {"coordinates":[-75.66319,20.36838],"type":"Point"}
}