{
  "type": "Feature",
  "properties": {
    "gn:admin1_code":"08",
    "gn:asciiname":"Barrio Nuevo",
    "gn:country_code":"CU",
    "gn:dem":45,
    "gn:feature_class":"P",
    "gn:feature_code":"PPLL",
    "gn:name":"Barrio Nuevo",
    "gn:population":0,
    "gn:timezone":"America/Havana",
    "iso:country":"CU",
    "wof:name":"Barrio Nuevo",
    "wof:placetype":"locality"
},
  "geometry": {"coordinates":[-80.71666999999999,22.43333],"type":"Point"}
}