{
  "type": "Feature",
  "properties": {
    "gn:admin1_code":"08",
    "gn:asciiname":"Las Cajas",
    "gn:country_code":"CU",
    "gn:dem":48,
    "gn:feature_class":"P",
    "gn:feature_code":"PPL",
    "gn:name":"Las Cajas",
    "gn:population":0,
    "gn:timezone":"America/Havana",
    "iso:country":"CU",
    "name:spa_x_preferred":[
        "Las Cajas"
    ],
    "wof:name":"Las Cajas",
    "wof:placetype":"locality"
},
  "geometry": {"coordinates":[-80.77745,22.45385],"type":"Point"}
}