{
  "type": "Feature",
  "properties": {
    "gn:admin1_code":"12",
    "gn:asciiname":"El Jobal",
    "gn:country_code":"CU",
    "gn:dem":29,
    "gn:feature_class":"P",
    "gn:feature_code":"PPL",
    "gn:name":"El Jobal",
    "gn:population":0,
    "gn:timezone":"America/Havana",
    "iso:country":"CU",
    "name:und_x_variant":[
        "Jobal",
        "El Jobal"
    ],
    "wof:name":"El Jobal",
    "wof:placetype":"locality"
},
  "geometry": {"coordinates":[-76.22239999999999,21.12995],"type":"Point"}
}