{
  "type": "Feature",
  "properties": {
    "gn:admin1_code":"07",
    "gn:asciiname":"La Francia",
    "gn:country_code":"CU",
    "gn:dem":33,
    "gn:feature_class":"P",
    "gn:feature_code":"PPLL",
    "gn:name":"La Francia",
    "gn:population":0,
    "gn:timezone":"America/Havana",
    "iso:country":"CU",
    "wof:name":"La Francia",
    "wof:placetype":"locality"
},
  "geometry": {"coordinates":[-78.49694000000002,21.82694],"type":"Point"}
}