{
  "type": "Feature",
  "properties": {
    "iso:country":"CU",
    "name:ast_x_preferred":[
        "Benito Jer\u00f3nimo Feijoo"
    ],
    "name:cat_x_preferred":[
        "Benito Jer\u00f3nimo Feijoo"
    ],
    "name:ces_x_preferred":[
        "Benito Jer\u00f3nimo Feijoo"
    ],
    "name:deu_x_preferred":[
        "Benito Jer\u00f3nimo Feijoo"
    ],
    "name:epo_x_preferred":[
        "Benito Jer\u00f3nimo Feijoo"
    ],
    "name:eus_x_preferred":[
        "Benito Jer\u00f3nimo Feij\u00f3o"
    ],
    "name:fra_x_preferred":[
        "Benito Jer\u00f3nimo Feijoo"
    ],
    "name:glg_x_preferred":[
        "Benito Xer\u00f3nimo Feijoo e Montenegro"
    ],
    "name:ita_x_preferred":[
        "Benito Feijoo"
    ],
    "name:spa_x_preferred":[
        "Benito Jer\u00f3nimo Feijoo"
    ],
    "name:spa_x_variant":[
        "Fray Benito"
    ],
    "qs:gn_country":"CU",
    "qs:gn_fcode":"PPL",
    "qs:gn_pop":0,
    "qs:name":"Fray Benito",
    "qs:name_adm0":"Cuba",
    "qs:name_adm1":"Holguin",
    "qs:photos":40,
    "qs:photos_1k":8,
    "qs:photos_9k":1,
    "qs:photos_9r":2,
    "qs:photos_all":40,
    "qs:photos_sr":2,
    "qs:placetype":"Town",
    "qs:pop_sr":"0",
    "qs:woe_adm0":23424793,
    "wof:name":"Fray Benito",
    "wof:placetype":"locality"
},
  "geometry": {"coordinates":[-76.05694,21.03861],"type":"Point"}
}