{
  "type": "Feature",
  "properties": {
    "gn:admin1_code":"09",
    "gn:asciiname":"Guabeje",
    "gn:country_code":"CU",
    "gn:dem":59,
    "gn:feature_class":"P",
    "gn:feature_code":"PPLL",
    "gn:name":"Guabeje",
    "gn:population":0,
    "gn:timezone":"America/Havana",
    "iso:country":"CU",
    "wof:name":"Guabeje",
    "wof:placetype":"locality"
},
  "geometry": {"coordinates":[-77.08333,20.11667000000001],"type":"Point"}
}