{
  "type": "Feature",
  "properties": {
    "gn:admin1_code":"03",
    "gn:asciiname":"San Rafael",
    "gn:country_code":"CU",
    "gn:dem":24,
    "gn:feature_class":"P",
    "gn:feature_code":"PPLL",
    "gn:name":"San Rafael",
    "gn:population":0,
    "gn:timezone":"America/Havana",
    "iso:country":"CU",
    "wof:name":"San Rafael",
    "wof:placetype":"locality"
},
  "geometry": {"coordinates":[-81.08333,22.55],"type":"Point"}
}