{
  "type": "Feature",
  "properties": {
    "gn:admin1_code":"07",
    "gn:asciiname":"Las Pojas",
    "gn:country_code":"CU",
    "gn:dem":105,
    "gn:feature_class":"P",
    "gn:feature_code":"PPL",
    "gn:name":"Las Pojas",
    "gn:population":0,
    "gn:timezone":"America/Havana",
    "iso:country":"CU",
    "name:spa_x_preferred":[
        "Las Pojas"
    ],
    "name:und_x_variant":[
        "Las Pajas"
    ],
    "wof:name":"Las Pojas",
    "wof:placetype":"locality"
},
  "geometry": {"coordinates":[-78.93626,22.10401],"type":"Point"}
}