{
  "type": "Feature",
  "properties": {
    "gn:admin1_code":"14",
    "gn:asciiname":"Hernandez",
    "gn:country_code":"CU",
    "gn:dem":61,
    "gn:feature_class":"P",
    "gn:feature_code":"PPLL",
    "gn:name":"Hern\u00e1ndez",
    "gn:population":0,
    "gn:timezone":"America/Havana",
    "iso:country":"CU",
    "wof:name":"Hernandez",
    "wof:placetype":"locality"
},
  "geometry": {"coordinates":[-79.38333,21.98333],"type":"Point"}
}