{
  "type": "Feature",
  "properties": {
    "gn:admin1_code":"03",
    "gn:asciiname":"Santa Susana",
    "gn:cc2":"CU",
    "gn:country_code":"CU",
    "gn:dem":28,
    "gn:feature_class":"P",
    "gn:feature_code":"PPL",
    "gn:name":"Santa Susana",
    "gn:population":0,
    "gn:timezone":"America/Havana",
    "iso:country":"CU",
    "name:ceb_x_preferred":[
        "Santa Susana"
    ],
    "name:glg_x_preferred":[
        "Santa Susana"
    ],
    "name:pol_x_preferred":[
        "Santa Susana"
    ],
    "name:por_x_preferred":[
        "Santa Susana"
    ],
    "name:sco_x_preferred":[
        "Santa Susana"
    ],
    "name:spa_x_preferred":[
        "Santa Susana"
    ],
    "name:srp_x_preferred":[
        "\u0421\u0430\u043d\u0442\u0430 \u0421\u0443\u0441\u0430\u043d\u0430"
    ],
    "name:swe_x_preferred":[
        "Santa Susana"
    ],
    "name:und_x_variant":[
        "Santa Susana Batey",
        "Santa Susana"
    ],
    "wof:name":"Santa Susana",
    "wof:placetype":"locality"
},
  "geometry": {"coordinates":[-81.03194000000001,22.71528],"type":"Point"}
}