{
  "type": "Feature",
  "properties": {
    "gn:admin1_code":"03",
    "gn:asciiname":"Guamuticas",
    "gn:cc2":"CU",
    "gn:country_code":"CU",
    "gn:dem":52,
    "gn:feature_class":"P",
    "gn:feature_code":"PPL",
    "gn:name":"Guamuticas",
    "gn:population":0,
    "gn:timezone":"America/Havana",
    "iso:country":"CU",
    "name:und_x_variant":[
        "Batey Guamuticas",
        "Guamuticas"
    ],
    "wof:name":"Guamuticas",
    "wof:placetype":"locality"
},
  "geometry": {"coordinates":[-80.96666999999999,22.78333],"type":"Point"}
}