{
  "type": "Feature",
  "properties": {
    "gn:admin1_code":"10",
    "gn:asciiname":"La Foli",
    "gn:country_code":"CU",
    "gn:dem":724,
    "gn:feature_class":"P",
    "gn:feature_code":"PPLL",
    "gn:name":"La Fol\u00ed",
    "gn:population":0,
    "gn:timezone":"America/Havana",
    "iso:country":"CU",
    "wof:name":"La Foli",
    "wof:placetype":"locality"
},
  "geometry": {"coordinates":[-75.15000000000001,20.35],"type":"Point"}
}