{
  "type": "Feature",
  "properties": {
    "gn:admin1_code":"03",
    "gn:asciiname":"San Agustin",
    "gn:country_code":"CU",
    "gn:dem":44,
    "gn:feature_class":"P",
    "gn:feature_code":"PPLL",
    "gn:name":"San Agust\u00edn",
    "gn:population":0,
    "gn:timezone":"America/Havana",
    "iso:country":"CU",
    "wof:name":"San Agustin",
    "wof:placetype":"locality"
},
  "geometry": {"coordinates":[-81.69444,23.00111],"type":"Point"}
}