{
  "type": "Feature",
  "properties": {
    "gn:admin1_code":"07",
    "gn:asciiname":"Palmas",
    "gn:country_code":"CU",
    "gn:dem":83,
    "gn:feature_class":"P",
    "gn:feature_code":"PPL",
    "gn:name":"Palmas",
    "gn:population":0,
    "gn:timezone":"America/Havana",
    "iso:country":"CU",
    "name:spa_x_preferred":[
        "Palmas"
    ],
    "name:und_x_variant":[
        "Palma"
    ],
    "wof:name":"Palmas",
    "wof:placetype":"locality"
},
  "geometry": {"coordinates":[-78.95563,22.13964],"type":"Point"}
}