{
  "type": "Feature",
  "properties": {
    "gn:admin1_code":"07",
    "gn:asciiname":"Palmas",
    "gn:country_code":"CU",
    "gn:dem":83,
    "gn:feature_class":"P",
    "gn:feature_code":"PPL",
    "gn:name":"Palmas",
    "gn:population":0,
    "gn:timezone":"America/Havana",
    "iso:country":"CU",
    "name:ben_x_preferred":[
        "\u09aa\u09be\u09ae\u09be\u09b8"
    ],
    "name:cat_x_preferred":[
        "Palmas"
    ],
    "name:ceb_x_preferred":[
        "Palmas"
    ],
    "name:deu_x_preferred":[
        "Palmas"
    ],
    "name:ell_x_preferred":[
        "\u03a0\u03ac\u03bb\u03bc\u03b1\u03c2"
    ],
    "name:fra_x_preferred":[
        "Palmas"
    ],
    "name:heb_x_preferred":[
        "\u05e4\u05d0\u05dc\u05de\u05d0\u05e1"
    ],
    "name:hin_x_preferred":[
        "\u092a\u0932\u094d\u092e\u093e\u0938"
    ],
    "name:ind_x_preferred":[
        "Palmas"
    ],
    "name:ita_x_preferred":[
        "Palmas"
    ],
    "name:kor_x_preferred":[
        "\ud314\ub9c8\uc2a4"
    ],
    "name:nld_x_preferred":[
        "Palmas"
    ],
    "name:nor_x_preferred":[
        "Palmas"
    ],
    "name:pol_x_preferred":[
        "Palmas"
    ],
    "name:por_x_preferred":[
        "Palmas"
    ],
    "name:sco_x_preferred":[
        "Palmas"
    ],
    "name:slk_x_preferred":[
        "Palmas"
    ],
    "name:spa_x_preferred":[
        "Palmas"
    ],
    "name:srp_x_preferred":[
        "\u041f\u0430\u043b\u043c\u0430\u0441"
    ],
    "name:swe_x_preferred":[
        "Palmas"
    ],
    "name:szl_x_preferred":[
        "Palmas"
    ],
    "name:tur_x_preferred":[
        "Palmas"
    ],
    "name:ukr_x_preferred":[
        "\u041f\u0430\u043b\u044c\u043c\u0430\u0441"
    ],
    "name:und_x_variant":[
        "Palma"
    ],
    "name:urd_x_preferred":[
        "\u067e\u0627\u0644\u0645\u0627\u0633"
    ],
    "name:vie_x_preferred":[
        "Palmas"
    ],
    "name:vol_x_preferred":[
        "Palmas"
    ],
    "name:war_x_preferred":[
        "Palmas"
    ],
    "name:zho_x_preferred":[
        "\u5e15\u5c14\u9a6c\u65af"
    ],
    "wof:name":"Palmas",
    "wof:placetype":"locality"
},
  "geometry": {"coordinates":[-78.95563,22.13964],"type":"Point"}
}