{
  "type": "Feature",
  "properties": {
    "gn:admin1_code":"05",
    "gn:asciiname":"Playa de Florida",
    "gn:country_code":"CU",
    "gn:dem":-9999,
    "gn:feature_class":"P",
    "gn:feature_code":"PPL",
    "gn:name":"Playa de Florida",
    "gn:population":0,
    "gn:timezone":"America/Havana",
    "iso:country":"CU",
    "name:spa_x_preferred":[
        "Playa de Florida"
    ],
    "name:und_x_variant":[
        "Playa Santa Mar\u00eda"
    ],
    "wof:name":"Playa de Florida",
    "wof:placetype":"locality"
},
  "geometry": {"coordinates":[-78.56870000000001,21.40796],"type":"Point"}
}