{
  "type": "Feature",
  "properties": {
    "gn:admin1_code":"16",
    "gn:asciiname":"Guinia de Miranda",
    "gn:country_code":"CU",
    "gn:dem":124,
    "gn:feature_class":"P",
    "gn:feature_code":"PPL",
    "gn:name":"G\u00fcin\u00eda de Miranda",
    "gn:population":0,
    "gn:timezone":"America/Havana",
    "iso:country":"CU",
    "name:und_x_variant":[
        "General Lino-P\u00e9rez",
        "G\u00fcin\u00eda de Miranda"
    ],
    "wof:name":"Guinia de Miranda",
    "wof:placetype":"locality"
},
  "geometry": {"coordinates":[-79.86384,22.0471],"type":"Point"}
}