{
  "type": "Feature",
  "properties": {
    "gn:admin1_code":"AR",
    "gn:asciiname":"La Zona",
    "gn:country_code":"CU",
    "gn:dem":6,
    "gn:feature_class":"P",
    "gn:feature_code":"PPLL",
    "gn:name":"La Zona",
    "gn:population":0,
    "gn:timezone":"America/Havana",
    "iso:country":"CU",
    "name:und_x_variant":[
        "Batey Zona",
        "La Zona"
    ],
    "wof:name":"La Zona",
    "wof:placetype":"locality"
},
  "geometry": {"coordinates":[-83.15000000000001,22.96667],"type":"Point"}
}