{
  "type": "Feature",
  "properties": {
    "gn:admin1_code":"15",
    "gn:asciiname":"Mirador",
    "gn:country_code":"CU",
    "gn:dem":363,
    "gn:feature_class":"P",
    "gn:feature_code":"PPLL",
    "gn:name":"Mirador",
    "gn:population":0,
    "gn:timezone":"America/Havana",
    "iso:country":"CU",
    "name:ceb_x_preferred":[
        "Mirador"
    ],
    "name:deu_x_preferred":[
        "Mirador"
    ],
    "name:fra_x_preferred":[
        "Mirador"
    ],
    "name:ita_x_preferred":[
        "Mirador"
    ],
    "name:nld_x_preferred":[
        "Mirador"
    ],
    "name:nor_x_preferred":[
        "Mirador"
    ],
    "name:por_x_preferred":[
        "Mirador"
    ],
    "name:rus_x_preferred":[
        "\u041c\u0438\u0440\u0430\u0434\u043e\u0440"
    ],
    "name:spa_x_preferred":[
        "Mirador"
    ],
    "name:srp_x_preferred":[
        "\u041c\u0438\u0440\u0430\u0434\u043e\u0440"
    ],
    "name:swe_x_preferred":[
        "Mirador"
    ],
    "name:vie_x_preferred":[
        "Mirador"
    ],
    "name:vol_x_preferred":[
        "Mirador"
    ],
    "wof:name":"Mirador",
    "wof:placetype":"locality"
},
  "geometry": {"coordinates":[-75.80500000000001,20.09861],"type":"Point"}
}