{
  "type": "Feature",
  "properties": {
    "gn:admin1_code":"15",
    "gn:asciiname":"Mirador",
    "gn:country_code":"CU",
    "gn:dem":363,
    "gn:feature_class":"P",
    "gn:feature_code":"PPLL",
    "gn:name":"Mirador",
    "gn:population":0,
    "gn:timezone":"America/Havana",
    "iso:country":"CU",
    "wof:name":"Mirador",
    "wof:placetype":"locality"
},
  "geometry": {"coordinates":[-75.80500000000001,20.09861],"type":"Point"}
}