{
  "type": "Feature",
  "properties": {
    "gn:admin1_code":"16",
    "gn:asciiname":"El Paraiso",
    "gn:country_code":"CU",
    "gn:dem":136,
    "gn:feature_class":"P",
    "gn:feature_code":"PPLL",
    "gn:name":"El Para\u00edso",
    "gn:population":0,
    "gn:timezone":"America/Havana",
    "iso:country":"CU",
    "name:spa_x_preferred":[
        "El Para\u00edso"
    ],
    "wof:name":"El Paraiso",
    "wof:placetype":"locality"
},
  "geometry": {"coordinates":[-79.53499000000002,22.3909],"type":"Point"}
}