{
  "type": "Feature",
  "properties": {
    "gn:admin1_code":"12",
    "gn:asciiname":"Baguanos Viejo",
    "gn:country_code":"CU",
    "gn:dem":98,
    "gn:feature_class":"P",
    "gn:feature_code":"PPL",
    "gn:name":"B\u00e1guanos Viejo",
    "gn:population":0,
    "gn:timezone":"America/Havana",
    "iso:country":"CU",
    "name:spa_x_preferred":[
        "B\u00e1guanos Viejo"
    ],
    "wof:name":"Baguanos Viejo",
    "wof:placetype":"locality"
},
  "geometry": {"coordinates":[-76.04706999999998,20.76294],"type":"Point"}
}