{
  "type": "Feature",
  "properties": {
    "gn:admin1_code":"16",
    "gn:asciiname":"Ciudad Pesquera Caibarien",
    "gn:country_code":"CU",
    "gn:dem":1,
    "gn:feature_class":"P",
    "gn:feature_code":"PPL",
    "gn:name":"Ciudad Pesquera Caibari\u00e9n",
    "gn:population":0,
    "gn:timezone":"America/Havana",
    "iso:country":"CU",
    "name:spa_x_preferred":[
        "Ciudad Pesquera Caibari\u00e9n"
    ],
    "wof:name":"Ciudad Pesquera Caibarien",
    "wof:placetype":"locality"
},
  "geometry": {"coordinates":[-79.4526,22.51916],"type":"Point"}
}