{
  "type": "Feature",
  "properties": {
    "gn:admin1_code":"07",
    "gn:asciiname":"Sofia",
    "gn:country_code":"CU",
    "gn:dem":17,
    "gn:feature_class":"P",
    "gn:feature_code":"PPL",
    "gn:name":"Sof\u00eda",
    "gn:population":0,
    "gn:timezone":"America/Havana",
    "iso:country":"CU",
    "name:spa_x_preferred":[
        "Sof\u00eda"
    ],
    "wof:name":"Sofia",
    "wof:placetype":"locality"
},
  "geometry": {"coordinates":[-78.39138,21.99718],"type":"Point"}
}