{
  "type": "Feature",
  "properties": {
    "gn:admin1_code":"12",
    "gn:asciiname":"Cuatro Caminos",
    "gn:country_code":"CU",
    "gn:dem":15,
    "gn:feature_class":"P",
    "gn:feature_code":"PPL",
    "gn:name":"Cuatro Caminos",
    "gn:population":0,
    "gn:timezone":"America/Havana",
    "iso:country":"CU",
    "name:spa_x_preferred":[
        "Cuatro Caminos"
    ],
    "wof:name":"Cuatro Caminos",
    "wof:placetype":"locality"
},
  "geometry": {"coordinates":[-76.05684000000002,21.06879],"type":"Point"}
}