{
  "type": "Feature",
  "properties": {
    "gn:admin1_code":"13",
    "gn:asciiname":"Las Tunas",
    "gn:country_code":"CU",
    "gn:dem":55,
    "gn:feature_class":"P",
    "gn:feature_code":"PPLL",
    "gn:name":"Las Tunas",
    "gn:population":0,
    "gn:timezone":"America/Havana",
    "iso:country":"CU",
    "name:ceb_x_preferred":[
        "Las Tunas"
    ],
    "name:deu_x_preferred":[
        "Las Tunas"
    ],
    "name:nld_x_preferred":[
        "Las Tunas"
    ],
    "name:pol_x_preferred":[
        "Las Tunas"
    ],
    "name:por_x_preferred":[
        "Las Tunas"
    ],
    "name:sco_x_preferred":[
        "Las Tunas"
    ],
    "name:spa_x_preferred":[
        "Las Tunas"
    ],
    "name:srp_x_preferred":[
        "\u041b\u0430\u0441 \u0422\u0443\u043d\u0430\u0441"
    ],
    "name:swe_x_preferred":[
        "Las Tunas"
    ],
    "name:tur_x_preferred":[
        "Las Tunas"
    ],
    "wof:name":"Las Tunas",
    "wof:placetype":"locality"
},
  "geometry": {"coordinates":[-77.52472,20.93444],"type":"Point"}
}