{
  "type": "Feature",
  "properties": {
    "gn:admin1_code":"05",
    "gn:asciiname":"Las Mojas Dos",
    "gn:country_code":"CU",
    "gn:dem":27,
    "gn:feature_class":"P",
    "gn:feature_code":"PPLL",
    "gn:name":"Las Mojas Dos",
    "gn:population":0,
    "gn:timezone":"America/Havana",
    "iso:country":"CU",
    "name:spa_x_preferred":[
        "Las Mojas Dos"
    ],
    "name:und_x_variant":[
        "Las Monjas Dos"
    ],
    "wof:name":"Las Mojas Dos",
    "wof:placetype":"locality"
},
  "geometry": {"coordinates":[-78.26742,21.22733],"type":"Point"}
}