{
  "type": "Feature",
  "properties": {
    "gn:admin1_code":"15",
    "gn:asciiname":"Corral del Rio",
    "gn:country_code":"CU",
    "gn:dem":70,
    "gn:feature_class":"P",
    "gn:feature_code":"PPL",
    "gn:name":"Corral del R\u00edo",
    "gn:population":0,
    "gn:timezone":"America/Havana",
    "iso:country":"CU",
    "wof:name":"Corral del Rio",
    "wof:placetype":"locality"
},
  "geometry": {"coordinates":[-76.75414000000001,19.94964],"type":"Point"}
}