{
  "type": "Feature",
  "properties": {
    "gn:admin1_code":"AR",
    "gn:asciiname":"El Maranon",
    "gn:country_code":"CU",
    "gn:dem":53,
    "gn:feature_class":"P",
    "gn:feature_code":"PPL",
    "gn:name":"El Mara\u00f1\u00f3n",
    "gn:population":0,
    "gn:timezone":"America/Havana",
    "iso:country":"CU",
    "name:spa_x_preferred":[
        "El Mara\u00f1\u00f3n"
    ],
    "wof:name":"El Maranon",
    "wof:placetype":"locality"
},
  "geometry": {"coordinates":[-82.55084000000002,23.0164],"type":"Point"}
}