{
  "type": "Feature",
  "properties": {
    "gn:admin1_code":"13",
    "gn:asciiname":"Yarigua",
    "gn:country_code":"CU",
    "gn:dem":112,
    "gn:feature_class":"P",
    "gn:feature_code":"PPL",
    "gn:name":"Yarigu\u00e1",
    "gn:population":0,
    "gn:timezone":"America/Havana",
    "iso:country":"CU",
    "name:spa_x_preferred":[
        "Yarigu\u00e1"
    ],
    "wof:name":"Yarigua",
    "wof:placetype":"locality"
},
  "geometry": {"coordinates":[-77.04346,21.01363],"type":"Point"}
}