{
  "type": "Feature",
  "properties": {
    "gn:admin1_code":"12",
    "gn:asciiname":"Candelaria Munilla",
    "gn:country_code":"CU",
    "gn:dem":51,
    "gn:feature_class":"P",
    "gn:feature_code":"PPL",
    "gn:name":"Candelaria Munilla",
    "gn:population":0,
    "gn:timezone":"America/Havana",
    "iso:country":"CU",
    "name:und_x_variant":[
        "Candelaria",
        "Candelaria Munilla"
    ],
    "wof:name":"Candelaria Munilla",
    "wof:placetype":"locality"
},
  "geometry": {"coordinates":[-76.23801999999998,21.05852],"type":"Point"}
}