{
  "type": "Feature",
  "properties": {
    "iso:country":"CU",
    "name:unk_x_variant":[
        "Guajay"
    ],
    "qs:gn_country":"CU",
    "qs:gn_fcode":"PPL",
    "qs:gn_pop":0,
    "qs:name":"Wajay",
    "qs:name_adm0":"Cuba",
    "qs:name_adm1":"Ciudad de la Habana",
    "qs:photos":49,
    "qs:photos_1k":10,
    "qs:photos_9k":1,
    "qs:photos_9r":2,
    "qs:photos_all":49,
    "qs:photos_sr":2,
    "qs:placetype":"Town",
    "qs:pop_sr":"0",
    "qs:woe_adm0":23424793,
    "wd:wordcount":26,
    "wof:name":"Wajay",
    "wof:placetype":"locality"
},
  "geometry": {"coordinates":[-82.42278,23.00333],"type":"Point"}
}