{
  "type": "Feature",
  "properties": {
    "gn:admin1_code":"MA",
    "gn:asciiname":"Playa Jibacoa",
    "gn:country_code":"CU",
    "gn:dem":7,
    "gn:feature_class":"P",
    "gn:feature_code":"PPL",
    "gn:name":"Playa Jibacoa",
    "gn:population":0,
    "gn:timezone":"America/Havana",
    "iso:country":"CU",
    "name:und_x_variant":[
        "Jibacoa",
        "Playa de Jibacoa",
        "Rutiner",
        "Playa Jibacoa"
    ],
    "wof:name":"Playa Jibacoa",
    "wof:placetype":"locality"
},
  "geometry": {"coordinates":[-81.8501,23.14889],"type":"Point"}
}