{
  "type": "Feature",
  "properties": {
    "gn:admin1_code":"10",
    "gn:asciiname":"La Caldera",
    "gn:country_code":"CU",
    "gn:dem":496,
    "gn:feature_class":"P",
    "gn:feature_code":"PPLL",
    "gn:name":"La Caldera",
    "gn:population":0,
    "gn:timezone":"America/Havana",
    "iso:country":"CU",
    "name:ceb_x_preferred":[
        "La Caldera"
    ],
    "name:deu_x_preferred":[
        "La Caldera"
    ],
    "name:fra_x_preferred":[
        "La Caldera"
    ],
    "name:nld_x_preferred":[
        "La Caldera"
    ],
    "name:por_x_preferred":[
        "La Caldera"
    ],
    "name:spa_x_preferred":[
        "La Caldera"
    ],
    "name:swe_x_preferred":[
        "La Caldera"
    ],
    "name:urd_x_preferred":[
        "\u0644\u0627 \u06a9\u0627\u0644\u0688\u06cc\u0631\u0627"
    ],
    "name:zho_x_preferred":[
        "\u62c9\u5361\u723e\u5fb7\u62c9"
    ],
    "wof:name":"La Caldera",
    "wof:placetype":"locality"
},
  "geometry": {"coordinates":[-74.85722,20.28972000000001],"type":"Point"}
}