{
  "type": "Feature",
  "properties": {
    "gn:admin1_code":"03",
    "gn:asciiname":"Quemado Grande",
    "gn:country_code":"CU",
    "gn:dem":13,
    "gn:feature_class":"P",
    "gn:feature_code":"PPLL",
    "gn:name":"Quemado Grande",
    "gn:population":0,
    "gn:timezone":"America/Havana",
    "iso:country":"CU",
    "name:und_x_variant":[
        "Batey Quemado Grande",
        "Quemado Grande"
    ],
    "wof:name":"Quemado Grande",
    "wof:placetype":"locality"
},
  "geometry": {"coordinates":[-81.06910000000001,22.49131],"type":"Point"}
}