{
  "type": "Feature",
  "properties": {
    "gn:admin1_code":"13",
    "gn:asciiname":"Playa Habanero",
    "gn:country_code":"CU",
    "gn:dem":4,
    "gn:feature_class":"P",
    "gn:feature_code":"PPL",
    "gn:name":"Playa Habanero",
    "gn:population":0,
    "gn:timezone":"America/Havana",
    "iso:country":"CU",
    "name:spa_x_preferred":[
        "Playa Habanero"
    ],
    "wof:name":"Playa Habanero",
    "wof:placetype":"locality"
},
  "geometry": {"coordinates":[-77.40545,20.69993],"type":"Point"}
}