{
  "type": "Feature",
  "properties": {
    "gn:admin1_code":"14",
    "gn:asciiname":"Los Charcazos",
    "gn:country_code":"CU",
    "gn:dem":103,
    "gn:feature_class":"P",
    "gn:feature_code":"PPLL",
    "gn:name":"Los Charcazos",
    "gn:population":0,
    "gn:timezone":"America/Havana",
    "iso:country":"CU",
    "wof:name":"Los Charcazos",
    "wof:placetype":"locality"
},
  "geometry": {"coordinates":[-79.18333,22.01667],"type":"Point"}
}