{
  "type": "Feature",
  "properties": {
    "gn:admin1_code":"07",
    "gn:asciiname":"La Jocuma",
    "gn:country_code":"CU",
    "gn:dem":89,
    "gn:feature_class":"P",
    "gn:feature_code":"PPL",
    "gn:name":"La Jocuma",
    "gn:population":0,
    "gn:timezone":"America/Havana",
    "iso:country":"CU",
    "name:spa_x_preferred":[
        "La Jocuma"
    ],
    "wof:name":"La Jocuma",
    "wof:placetype":"locality"
},
  "geometry": {"coordinates":[-78.98938000000003,21.89118],"type":"Point"}
}