{
  "type": "Feature",
  "properties": {
    "gn:admin1_code":"07",
    "gn:asciiname":"Sierra Alta",
    "gn:country_code":"CU",
    "gn:dem":48,
    "gn:feature_class":"P",
    "gn:feature_code":"PPLL",
    "gn:name":"Sierra Alta",
    "gn:population":0,
    "gn:timezone":"America/Havana",
    "iso:country":"CU",
    "wof:name":"Sierra Alta",
    "wof:placetype":"locality"
},
  "geometry": {"coordinates":[-78.45528,21.71806],"type":"Point"}
}