{
  "type": "Feature",
  "properties": {
    "gn:admin1_code":"09",
    "gn:asciiname":"Nogueiro",
    "gn:country_code":"CU",
    "gn:dem":10,
    "gn:feature_class":"P",
    "gn:feature_code":"PPLL",
    "gn:name":"Nogue\u00edro",
    "gn:population":0,
    "gn:timezone":"America/Havana",
    "iso:country":"CU",
    "name:spa_x_preferred":[
        "Nogue\u00edro"
    ],
    "wof:name":"Nogueiro",
    "wof:placetype":"locality"
},
  "geometry": {"coordinates":[-77.21026999999999,20.20101],"type":"Point"}
}