{
  "type": "Feature",
  "properties": {
    "gn:admin1_code":"01",
    "gn:asciiname":"Fortuna",
    "gn:country_code":"CU",
    "gn:dem":32,
    "gn:feature_class":"P",
    "gn:feature_code":"PPL",
    "gn:name":"Fortuna",
    "gn:population":0,
    "gn:timezone":"America/Havana",
    "iso:country":"CU",
    "name:spa_x_preferred":[
        "Fortuna"
    ],
    "wof:name":"Fortuna",
    "wof:placetype":"locality"
},
  "geometry": {"coordinates":[-83.79701,22.30236],"type":"Point"}
}