{
  "type": "Feature",
  "properties": {
    "gn:admin1_code":"15",
    "gn:asciiname":"Bebe",
    "gn:country_code":"CU",
    "gn:dem":301,
    "gn:feature_class":"P",
    "gn:feature_code":"PPLL",
    "gn:name":"Beb\u00e9",
    "gn:population":0,
    "gn:timezone":"America/Havana",
    "iso:country":"CU",
    "wof:name":"Bebe",
    "wof:placetype":"locality"
},
  "geometry": {"coordinates":[-75.73333000000002,20.28333],"type":"Point"}
}