{
  "type": "Feature",
  "properties": {
    "gn:admin1_code":"08",
    "gn:asciiname":"Potrerillo",
    "gn:country_code":"CU",
    "gn:dem":86,
    "gn:feature_class":"P",
    "gn:feature_code":"PPL",
    "gn:name":"Potrerillo",
    "gn:population":0,
    "gn:timezone":"America/Havana",
    "iso:country":"CU",
    "name:spa_x_preferred":[
        "Potrerillo"
    ],
    "wof:name":"Potrerillo",
    "wof:placetype":"locality"
},
  "geometry": {"coordinates":[-80.14440999999999,22.26747],"type":"Point"}
}