{
  "type": "Feature",
  "properties": {
    "gn:admin1_code":"10",
    "gn:asciiname":"Nibujon",
    "gn:country_code":"CU",
    "gn:dem":12,
    "gn:feature_class":"P",
    "gn:feature_code":"PPL",
    "gn:name":"Nibuj\u00f3n",
    "gn:population":0,
    "gn:timezone":"America/Havana",
    "iso:country":"CU",
    "name:spa_x_preferred":[
        "Nibuj\u00f3n"
    ],
    "wof:name":"Nibujon",
    "wof:placetype":"locality"
},
  "geometry": {"coordinates":[-74.64988000000002,20.50372],"type":"Point"}
}