{
  "type": "Feature",
  "properties": {
    "gn:admin1_code":"01",
    "gn:asciiname":"Los Cayos",
    "gn:country_code":"CU",
    "gn:dem":5,
    "gn:feature_class":"P",
    "gn:feature_code":"PPL",
    "gn:name":"Los Cayos",
    "gn:population":0,
    "gn:timezone":"America/Havana",
    "iso:country":"CU",
    "name:und_x_variant":[
        "Cayos",
        "Los Cayos"
    ],
    "wof:name":"Los Cayos",
    "wof:placetype":"locality"
},
  "geometry": {"coordinates":[-84.07319,21.96276],"type":"Point"}
}