{
  "type": "Feature",
  "properties": {
    "gn:admin1_code":"02",
    "gn:asciiname":"Cojimar",
    "gn:country_code":"CU",
    "gn:dem":17,
    "gn:feature_class":"P",
    "gn:feature_code":"PPL",
    "gn:name":"Coj\u00edmar",
    "gn:population":0,
    "gn:timezone":"America/Havana",
    "iso:country":"CU",
    "name:und_x_variant":[
        "Coj\u00edmar"
    ],
    "wof:name":"Cojimar",
    "wof:placetype":"locality"
},
  "geometry": {"coordinates":[-82.3001,23.16368],"type":"Point"}
}