{
  "type": "Feature",
  "properties": {
    "gn:admin1_code":"13",
    "gn:asciiname":"Aguilar",
    "gn:country_code":"CU",
    "gn:dem":34,
    "gn:feature_class":"P",
    "gn:feature_code":"PPLL",
    "gn:name":"Aguilar",
    "gn:population":0,
    "gn:timezone":"America/Havana",
    "iso:country":"CU",
    "name:arg_x_preferred":[
        "Aguilar"
    ],
    "name:cat_x_preferred":[
        "Aguilar"
    ],
    "name:ceb_x_preferred":[
        "Aguilar"
    ],
    "name:ces_x_preferred":[
        "Aguilar"
    ],
    "name:deu_x_preferred":[
        "Aguilar"
    ],
    "name:fra_x_preferred":[
        "Aguilar"
    ],
    "name:heb_x_preferred":[
        "\u05d0\u05d2\u05d9\u05dc\u05e8"
    ],
    "name:ita_x_preferred":[
        "Aguilar"
    ],
    "name:jpn_x_preferred":[
        "\u30a2\u30ae\u30e9\u30fc\u30eb"
    ],
    "name:nds_x_preferred":[
        "Aguilar"
    ],
    "name:nld_x_preferred":[
        "Aguilar"
    ],
    "name:rus_x_preferred":[
        "\u0410\u0433\u0438\u043b\u0430\u0440"
    ],
    "name:sco_x_preferred":[
        "Aguilar"
    ],
    "name:slv_x_preferred":[
        "Aguilar"
    ],
    "name:spa_x_preferred":[
        "Aguilar"
    ],
    "name:swe_x_preferred":[
        "Aguilar"
    ],
    "name:ukr_x_preferred":[
        "\u0410\u0433\u0456\u043b\u0430\u0440"
    ],
    "name:war_x_preferred":[
        "Aguilar"
    ],
    "wof:name":"Aguilar",
    "wof:placetype":"locality"
},
  "geometry": {"coordinates":[-77.05056,21.22722000000001],"type":"Point"}
}