{
  "type": "Feature",
  "properties": {
    "gn:admin1_code":"AR",
    "gn:asciiname":"Abreu",
    "gn:country_code":"CU",
    "gn:dem":4,
    "gn:feature_class":"P",
    "gn:feature_code":"PPLL",
    "gn:name":"Abreu",
    "gn:population":0,
    "gn:timezone":"America/Havana",
    "iso:country":"CU",
    "name:cat_x_preferred":[
        "Abreu"
    ],
    "name:ceb_x_preferred":[
        "Abreu"
    ],
    "name:deu_x_preferred":[
        "Abreu"
    ],
    "name:fin_x_preferred":[
        "Abreu"
    ],
    "name:fra_x_preferred":[
        "Abreu"
    ],
    "name:ita_x_preferred":[
        "Abreu"
    ],
    "name:jpn_x_preferred":[
        "\u30a2\u30d6\u30ec\u30a4\u30e6"
    ],
    "name:nld_x_preferred":[
        "Abreu"
    ],
    "name:rus_x_preferred":[
        "\u0410\u0431\u0440\u0435\u0443"
    ],
    "name:slv_x_preferred":[
        "Abreu"
    ],
    "name:spa_x_preferred":[
        "Abreu"
    ],
    "name:swe_x_preferred":[
        "Abreu"
    ],
    "wof:name":"Abreu",
    "wof:placetype":"locality"
},
  "geometry": {"coordinates":[-82.58333,22.75],"type":"Point"}
}