{
  "type": "Feature",
  "properties": {
    "gn:admin1_code":"10",
    "gn:asciiname":"Playa Sabanalamar",
    "gn:country_code":"CU",
    "gn:dem":9,
    "gn:feature_class":"P",
    "gn:feature_code":"PPL",
    "gn:name":"Playa Sabanalamar",
    "gn:population":0,
    "gn:timezone":"America/Havana",
    "iso:country":"CU",
    "name:spa_x_preferred":[
        "Playa Sabanalamar"
    ],
    "wof:name":"Playa Sabanalamar",
    "wof:placetype":"locality"
},
  "geometry": {"coordinates":[-74.80161,20.0455],"type":"Point"}
}