{
  "type": "Feature",
  "properties": {
    "gn:admin1_code":"13",
    "gn:asciiname":"San Julian",
    "gn:country_code":"CU",
    "gn:dem":104,
    "gn:feature_class":"P",
    "gn:feature_code":"PPL",
    "gn:name":"San Juli\u00e1n",
    "gn:population":0,
    "gn:timezone":"America/Havana",
    "iso:country":"CU",
    "name:spa_x_preferred":[
        "San Juli\u00e1n"
    ],
    "wof:name":"San Julian",
    "wof:placetype":"locality"
},
  "geometry": {"coordinates":[-76.56919000000001,21.0065],"type":"Point"}
}