{
  "type": "Feature",
  "properties": {
    "gn:admin1_code":"10",
    "gn:asciiname":"El Cupey",
    "gn:country_code":"CU",
    "gn:dem":376,
    "gn:feature_class":"P",
    "gn:feature_code":"PPL",
    "gn:name":"El Cupey",
    "gn:population":0,
    "gn:timezone":"America/Havana",
    "iso:country":"CU",
    "name:spa_x_preferred":[
        "El Cupey"
    ],
    "wof:name":"El Cupey",
    "wof:placetype":"locality"
},
  "geometry": {"coordinates":[-74.25019,20.19087],"type":"Point"}
}