{
  "type": "Feature",
  "properties": {
    "gn:admin1_code":"MA",
    "gn:asciiname":"El Compromiso",
    "gn:country_code":"CU",
    "gn:dem":55,
    "gn:feature_class":"P",
    "gn:feature_code":"PPLL",
    "gn:name":"El Compromiso",
    "gn:population":0,
    "gn:timezone":"America/Havana",
    "iso:country":"CU",
    "wof:name":"El Compromiso",
    "wof:placetype":"locality"
},
  "geometry": {"coordinates":[-82.36667,22.83333],"type":"Point"}
}