{
  "type": "Feature",
  "properties": {
    "gn:admin1_code":"16",
    "gn:asciiname":"La Matilde",
    "gn:country_code":"CU",
    "gn:dem":100,
    "gn:feature_class":"P",
    "gn:feature_code":"PPLL",
    "gn:name":"La Matilde",
    "gn:population":0,
    "gn:timezone":"America/Havana",
    "iso:country":"CU",
    "name:und_x_variant":[
        "Matilde",
        "La Matilde"
    ],
    "wof:name":"La Matilde",
    "wof:placetype":"locality"
},
  "geometry": {"coordinates":[-79.73325,22.484],"type":"Point"}
}