{
  "type": "Feature",
  "properties": {
    "gn:admin1_code":"09",
    "gn:asciiname":"Caney Abajo",
    "gn:cc2":"CU",
    "gn:country_code":"CU",
    "gn:dem":26,
    "gn:feature_class":"P",
    "gn:feature_code":"PPL",
    "gn:name":"Caney Abajo",
    "gn:population":0,
    "gn:timezone":"America/Havana",
    "iso:country":"CU",
    "name:und_x_variant":[
        "Caney",
        "Caney Abajo"
    ],
    "wof:name":"Caney Abajo",
    "wof:placetype":"locality"
},
  "geometry": {"coordinates":[-77.34999999999999,20.13333],"type":"Point"}
}