{
  "type": "Feature",
  "properties": {
    "gn:admin1_code":"15",
    "gn:asciiname":"La Matilde",
    "gn:country_code":"CU",
    "gn:dem":232,
    "gn:feature_class":"P",
    "gn:feature_code":"PPL",
    "gn:name":"La Matilde",
    "gn:population":0,
    "gn:timezone":"America/Havana",
    "iso:country":"CU",
    "name:spa_x_preferred":[
        "La Matilde"
    ],
    "name:und_x_variant":[
        "Matilde"
    ],
    "wof:name":"La Matilde",
    "wof:placetype":"locality"
},
  "geometry": {"coordinates":[-76.10092,20.09913],"type":"Point"}
}