{
  "type": "Feature",
  "properties": {
    "gn:admin1_code":"01",
    "gn:asciiname":"El Gache",
    "gn:cc2":"CU",
    "gn:country_code":"CU",
    "gn:dem":36,
    "gn:feature_class":"P",
    "gn:feature_code":"PPLL",
    "gn:name":"El Gache",
    "gn:population":0,
    "gn:timezone":"America/Havana",
    "iso:country":"CU",
    "name:und_x_variant":[
        "Mar\u00eda Victoria",
        "El Gacho",
        "El Gache"
    ],
    "wof:name":"El Gache",
    "wof:placetype":"locality"
},
  "geometry": {"coordinates":[-83.84999999999999,22.26667],"type":"Point"}
}