{
  "type": "Feature",
  "properties": {
    "gn:admin1_code":"08",
    "gn:asciiname":"Vista Alegre",
    "gn:country_code":"CU",
    "gn:dem":62,
    "gn:feature_class":"P",
    "gn:feature_code":"PPLL",
    "gn:name":"Vista Alegre",
    "gn:population":0,
    "gn:timezone":"America/Havana",
    "iso:country":"CU",
    "name:und_x_variant":[
        "Vista Alagre",
        "Vista Alegre"
    ],
    "wof:name":"Vista Alegre",
    "wof:placetype":"locality"
},
  "geometry": {"coordinates":[-80.35682,22.25545],"type":"Point"}
}