{
  "type": "Feature",
  "properties": {
    "gn:admin1_code":"12",
    "gn:asciiname":"Dominguez",
    "gn:country_code":"CU",
    "gn:dem":112,
    "gn:feature_class":"P",
    "gn:feature_code":"PPLL",
    "gn:name":"Dom\u00ednguez",
    "gn:population":0,
    "gn:timezone":"America/Havana",
    "iso:country":"CU",
    "name:spa_x_preferred":[
        "Dom\u00ednguez"
    ],
    "wof:name":"Dominguez",
    "wof:placetype":"locality"
},
  "geometry": {"coordinates":[-76.52332,20.91025],"type":"Point"}
}