{
  "type": "Feature",
  "properties": {
    "gn:admin1_code":"05",
    "gn:asciiname":"Triunfo",
    "gn:country_code":"CU",
    "gn:dem":22,
    "gn:feature_class":"P",
    "gn:feature_code":"PPLL",
    "gn:name":"Triunfo",
    "gn:population":0,
    "gn:timezone":"America/Havana",
    "iso:country":"CU",
    "name:spa_x_preferred":[
        "Triunfo"
    ],
    "wof:name":"Triunfo",
    "wof:placetype":"locality"
},
  "geometry": {"coordinates":[-78.20614,21.93453],"type":"Point"}
}