{
  "type": "Feature",
  "properties": {
    "gn:admin1_code":"15",
    "gn:asciiname":"Cuatro Caminos",
    "gn:country_code":"CU",
    "gn:dem":226,
    "gn:feature_class":"P",
    "gn:feature_code":"PPL",
    "gn:name":"Cuatro Caminos",
    "gn:population":0,
    "gn:timezone":"America/Havana",
    "iso:country":"CU",
    "name:spa_x_preferred":[
        "Cuatro caminos"
    ],
    "name:und_x_variant":[
        "Poblado cuatro Caminos",
        "Cuatro Caminos"
    ],
    "wof:name":"Cuatro Caminos",
    "wof:placetype":"locality"
},
  "geometry": {"coordinates":[-75.58605,20.13166],"type":"Point"}
}