{
  "type": "Feature",
  "properties": {
    "gn:admin1_code":"AR",
    "gn:asciiname":"Norona",
    "gn:country_code":"CU",
    "gn:dem":115,
    "gn:feature_class":"P",
    "gn:feature_code":"PPL",
    "gn:name":"Noro\u00f1a",
    "gn:population":0,
    "gn:timezone":"America/Havana",
    "iso:country":"CU",
    "name:und_x_variant":[
        "Batey Noro\u00f1a",
        "Noro\u00f1a"
    ],
    "wof:name":"Norona",
    "wof:placetype":"locality"
},
  "geometry": {"coordinates":[-82.69795999999999,22.95578],"type":"Point"}
}