{
  "type": "Feature",
  "properties": {
    "gn:admin1_code":"10",
    "gn:asciiname":"Jaragua",
    "gn:country_code":"CU",
    "gn:dem":14,
    "gn:feature_class":"P",
    "gn:feature_code":"PPL",
    "gn:name":"Jaragua",
    "gn:population":0,
    "gn:timezone":"America/Havana",
    "iso:country":"CU",
    "name:spa_x_preferred":[
        "Jaragua"
    ],
    "wof:name":"Jaragua",
    "wof:placetype":"locality"
},
  "geometry": {"coordinates":[-74.70361,20.53624],"type":"Point"}
}