{
  "type": "Feature",
  "properties": {
    "gn:admin1_code":"03",
    "gn:asciiname":"Cidra",
    "gn:country_code":"CU",
    "gn:dem":110,
    "gn:feature_class":"P",
    "gn:feature_code":"PPL",
    "gn:name":"Cidra",
    "gn:population":0,
    "gn:timezone":"America/Havana",
    "iso:country":"CU",
    "name:und_x_variant":[
        "Santa Ana",
        "La Cidra",
        "Cidra"
    ],
    "wof:name":"Cidra",
    "wof:placetype":"locality"
},
  "geometry": {"coordinates":[-81.54057,22.92154],"type":"Point"}
}