{
  "type": "Feature",
  "properties": {
    "gn:admin1_code":"14",
    "gn:asciiname":"Pascasio",
    "gn:country_code":"CU",
    "gn:dem":31,
    "gn:feature_class":"P",
    "gn:feature_code":"PPLL",
    "gn:name":"Pascasio",
    "gn:population":0,
    "gn:timezone":"America/Havana",
    "iso:country":"CU",
    "name:spa_x_preferred":[
        "Pascasto"
    ],
    "name:spa_x_variant":[
        "Pascasio"
    ],
    "wof:name":"Pascasio",
    "wof:placetype":"locality"
},
  "geometry": {"coordinates":[-79.48425,21.75334],"type":"Point"}
}