{
  "type": "Feature",
  "properties": {
    "gn:admin1_code":"AR",
    "gn:asciiname":"Ceiba Gorda",
    "gn:country_code":"CU",
    "gn:dem":95,
    "gn:feature_class":"P",
    "gn:feature_code":"PPLL",
    "gn:name":"Ceiba Gorda",
    "gn:population":0,
    "gn:timezone":"America/Havana",
    "iso:country":"CU",
    "name:spa_x_preferred":[
        "Ceiba Gorda"
    ],
    "wof:name":"Ceiba Gorda",
    "wof:placetype":"locality"
},
  "geometry": {"coordinates":[-83.15739000000001,22.70659],"type":"Point"}
}