{
  "type": "Feature",
  "properties": {
    "gn:admin1_code":"05",
    "gn:asciiname":"El Porvenir",
    "gn:country_code":"CU",
    "gn:dem":73,
    "gn:feature_class":"P",
    "gn:feature_code":"PPL",
    "gn:name":"El Porvenir",
    "gn:population":0,
    "gn:timezone":"America/Havana",
    "iso:country":"CU",
    "name:spa_x_preferred":[
        "El Porvenir"
    ],
    "wof:name":"El Porvenir",
    "wof:placetype":"locality"
},
  "geometry": {"coordinates":[-77.6088,21.03925],"type":"Point"}
}