{
  "type": "Feature",
  "properties": {
    "gn:admin1_code":"15",
    "gn:asciiname":"Las Chivas",
    "gn:country_code":"CU",
    "gn:dem":206,
    "gn:feature_class":"P",
    "gn:feature_code":"PPLL",
    "gn:name":"Las Chivas",
    "gn:population":0,
    "gn:timezone":"America/Havana",
    "iso:country":"CU",
    "name:und_x_variant":[
        "La Chivas",
        "Las Chivos",
        "Las Chivas"
    ],
    "wof:name":"Las Chivas",
    "wof:placetype":"locality"
},
  "geometry": {"coordinates":[-75.91580999999999,20.1507],"type":"Point"}
}