{
  "type": "Feature",
  "properties": {
    "gn:admin1_code":"16",
    "gn:asciiname":"Taguayabon",
    "gn:country_code":"CU",
    "gn:dem":75,
    "gn:feature_class":"P",
    "gn:feature_code":"PPL",
    "gn:name":"Taguayab\u00f3n",
    "gn:population":0,
    "gn:timezone":"America/Havana",
    "iso:country":"CU",
    "name:und_x_variant":[
        "Jaguayabon",
        "Taguayab\u00f3n"
    ],
    "wof:name":"Taguayabon",
    "wof:placetype":"locality"
},
  "geometry": {"coordinates":[-79.65188000000001,22.48028],"type":"Point"}
}