{
  "type": "Feature",
  "properties": {
    "gn:admin1_code":"12",
    "gn:asciiname":"Corua Numero Ocho",
    "gn:cc2":"CU",
    "gn:country_code":"CU",
    "gn:dem":12,
    "gn:feature_class":"P",
    "gn:feature_code":"PPLL",
    "gn:name":"Cor\u00faa N\u00famero Ocho",
    "gn:population":0,
    "gn:timezone":"America/Havana",
    "iso:country":"CU",
    "name:und_x_variant":[
        "Corua N\u00famero 8",
        "Cor\u00faa N\u00famero Ocho"
    ],
    "wof:name":"Corua Numero Ocho",
    "wof:placetype":"locality"
},
  "geometry": {"coordinates":[-75.56667,20.68333],"type":"Point"}
}