{
  "type": "Feature",
  "properties": {
    "gn:admin1_code":"05",
    "gn:asciiname":"Crucero Las Margaritas",
    "gn:country_code":"CU",
    "gn:dem":71,
    "gn:feature_class":"P",
    "gn:feature_code":"PPL",
    "gn:name":"Crucero Las Margaritas",
    "gn:population":0,
    "gn:timezone":"America/Havana",
    "iso:country":"CU",
    "name:spa_x_preferred":[
        "Crucero Las Margaritas"
    ],
    "wof:name":"Crucero Las Margaritas",
    "wof:placetype":"locality"
},
  "geometry": {"coordinates":[-78.18599,21.51062],"type":"Point"}
}