{
  "type": "Feature",
  "properties": {
    "gn:admin1_code":"13",
    "gn:asciiname":"Playa Las Bocas",
    "gn:country_code":"CU",
    "gn:dem":7,
    "gn:feature_class":"P",
    "gn:feature_code":"PPL",
    "gn:name":"Playa Las Bocas",
    "gn:population":0,
    "gn:timezone":"America/Havana",
    "iso:country":"CU",
    "name:spa_x_preferred":[
        "Playa Las Bocas"
    ],
    "wof:name":"Playa Las Bocas",
    "wof:placetype":"locality"
},
  "geometry": {"coordinates":[-76.53391999999999,21.26059],"type":"Point"}
}