{
  "type": "Feature",
  "properties": {
    "gn:admin1_code":"05",
    "gn:asciiname":"Las Delicias del Palmarito",
    "gn:country_code":"CU",
    "gn:dem":89,
    "gn:feature_class":"P",
    "gn:feature_code":"PPLL",
    "gn:name":"Las Delicias del Palmarito",
    "gn:population":0,
    "gn:timezone":"America/Havana",
    "iso:country":"CU",
    "wof:name":"Las Delicias del Palmarito",
    "wof:placetype":"locality"
},
  "geometry": {"coordinates":[-77.93333,21.33333],"type":"Point"}
}