{
  "type": "Feature",
  "properties": {
    "gn:admin1_code":"15",
    "gn:asciiname":"Sitio Campo",
    "gn:country_code":"CU",
    "gn:dem":229,
    "gn:feature_class":"P",
    "gn:feature_code":"PPL",
    "gn:name":"Sitio Campo",
    "gn:population":0,
    "gn:timezone":"America/Havana",
    "iso:country":"CU",
    "name:spa_x_preferred":[
        "Sitio Campo"
    ],
    "wof:name":"Sitio Campo",
    "wof:placetype":"locality"
},
  "geometry": {"coordinates":[-75.53690999999998,20.23985],"type":"Point"}
}