{
  "type": "Feature",
  "properties": {
    "gn:admin1_code":"14",
    "gn:asciiname":"Diez Caballerias",
    "gn:country_code":"CU",
    "gn:dem":120,
    "gn:feature_class":"P",
    "gn:feature_code":"PPLL",
    "gn:name":"Diez Caballer\u00edas",
    "gn:population":0,
    "gn:timezone":"America/Havana",
    "iso:country":"CU",
    "wof:name":"Diez Caballerias",
    "wof:placetype":"locality"
},
  "geometry": {"coordinates":[-79.09999999999999,21.95],"type":"Point"}
}