{
  "type": "Feature",
  "properties": {
    "gn:admin1_code":"15",
    "gn:asciiname":"Las Lagunas",
    "gn:country_code":"CU",
    "gn:dem":24,
    "gn:feature_class":"P",
    "gn:feature_code":"PPLL",
    "gn:name":"Las Lagunas",
    "gn:population":0,
    "gn:timezone":"America/Havana",
    "iso:country":"CU",
    "name:ceb_x_preferred":[
        "Las Lagunas"
    ],
    "name:spa_x_preferred":[
        "Las Lagunas"
    ],
    "name:srp_x_preferred":[
        "\u041b\u0430\u0441 \u041b\u0430\u0433\u0443\u043d\u0430\u0441"
    ],
    "name:swe_x_preferred":[
        "Las Lagunas"
    ],
    "wof:name":"Las Lagunas",
    "wof:placetype":"locality"
},
  "geometry": {"coordinates":[-75.79424,19.99135],"type":"Point"}
}