{
  "type": "Feature",
  "properties": {
    "gn:admin1_code":"16",
    "gn:asciiname":"Virgen de Regla",
    "gn:country_code":"CU",
    "gn:dem":112,
    "gn:feature_class":"P",
    "gn:feature_code":"PPLL",
    "gn:name":"Virgen de Regla",
    "gn:population":0,
    "gn:timezone":"America/Havana",
    "iso:country":"CU",
    "wof:name":"Virgen de Regla",
    "wof:placetype":"locality"
},
  "geometry": {"coordinates":[-79.78333000000001,22.35],"type":"Point"}
}