{
  "type": "Feature",
  "properties": {
    "gn:admin1_code":"03",
    "gn:asciiname":"Sobrado",
    "gn:country_code":"CU",
    "gn:dem":67,
    "gn:feature_class":"P",
    "gn:feature_code":"PPLL",
    "gn:name":"Sobrado",
    "gn:population":0,
    "gn:timezone":"America/Havana",
    "iso:country":"CU",
    "wof:name":"Sobrado",
    "wof:placetype":"locality"
},
  "geometry": {"coordinates":[-80.67721999999998,22.70806],"type":"Point"}
}