{
  "type": "Feature",
  "properties": {
    "gn:admin1_code":"08",
    "gn:asciiname":"Venero de San Jose",
    "gn:country_code":"CU",
    "gn:dem":53,
    "gn:feature_class":"P",
    "gn:feature_code":"PPLL",
    "gn:name":"Venero de San Jos\u00e9",
    "gn:population":0,
    "gn:timezone":"America/Havana",
    "iso:country":"CU",
    "wof:name":"Venero de San Jose",
    "wof:placetype":"locality"
},
  "geometry": {"coordinates":[-80.71666999999999,22.41667],"type":"Point"}
}