{
  "type": "Feature",
  "properties": {
    "gn:admin1_code":"15",
    "gn:asciiname":"Sarah Veinte",
    "gn:country_code":"CU",
    "gn:dem":151,
    "gn:feature_class":"P",
    "gn:feature_code":"PPL",
    "gn:name":"Sarah Veinte",
    "gn:population":0,
    "gn:timezone":"America/Havana",
    "iso:country":"CU",
    "name:spa_x_preferred":[
        "Sarah Veinte"
    ],
    "wof:name":"Sarah Veinte",
    "wof:placetype":"locality"
},
  "geometry": {"coordinates":[-76.05774,20.34549],"type":"Point"}
}