{
  "type": "Feature",
  "properties": {
    "gn:admin1_code":"01",
    "gn:asciiname":"Tejar",
    "gn:country_code":"CU",
    "gn:dem":46,
    "gn:feature_class":"P",
    "gn:feature_code":"PPLL",
    "gn:name":"Tejar",
    "gn:population":0,
    "gn:timezone":"America/Havana",
    "iso:country":"CU",
    "wof:name":"Tejar",
    "wof:placetype":"locality"
},
  "geometry": {"coordinates":[-83.61667,22.45],"type":"Point"}
}