{
  "type": "Feature",
  "properties": {
    "iso:country":"CU",
    "name:spa_x_preferred":[
        "Banao"
    ],
    "qs:gn_country":"CU",
    "qs:gn_fcode":"PPL",
    "qs:gn_pop":0,
    "qs:name":"Banao",
    "qs:name_adm0":"Cuba",
    "qs:name_adm1":"Sancti Spiritus",
    "qs:photos":22,
    "qs:photos_1k":4,
    "qs:photos_9k":1,
    "qs:photos_9r":1,
    "qs:photos_all":22,
    "qs:photos_sr":1,
    "qs:placetype":"Town",
    "qs:pop_sr":"0",
    "qs:woe_adm0":23424793,
    "wof:name":"Banao",
    "wof:placetype":"locality"
},
  "geometry": {"coordinates":[-79.56861000000001,21.82861],"type":"Point"}
}