{
  "type": "Feature",
  "properties": {
    "gn:admin1_code":"08",
    "gn:asciiname":"El Junco",
    "gn:country_code":"CU",
    "gn:dem":8,
    "gn:feature_class":"P",
    "gn:feature_code":"PPLL",
    "gn:name":"El Junco",
    "gn:population":0,
    "gn:timezone":"America/Havana",
    "iso:country":"CU",
    "name:spa_x_preferred":[
        "El Junco"
    ],
    "wof:name":"El Junco",
    "wof:placetype":"locality"
},
  "geometry": {"coordinates":[-80.65626999999998,22.14297],"type":"Point"}
}