{
  "type": "Feature",
  "properties": {
    "gn:admin1_code":"14",
    "gn:asciiname":"Juan Torres",
    "gn:country_code":"CU",
    "gn:dem":19,
    "gn:feature_class":"P",
    "gn:feature_code":"PPL",
    "gn:name":"Juan Torres",
    "gn:population":0,
    "gn:timezone":"America/Havana",
    "iso:country":"CU",
    "name:spa_x_preferred":[
        "Juan Torres"
    ],
    "wof:name":"Juan Torres",
    "wof:placetype":"locality"
},
  "geometry": {"coordinates":[-79.30285000000001,21.71619],"type":"Point"}
}