{
  "type": "Feature",
  "properties": {
    "gn:admin1_code":"09",
    "gn:asciiname":"Alto del Aguacate",
    "gn:country_code":"CU",
    "gn:dem":167,
    "gn:feature_class":"P",
    "gn:feature_code":"PPL",
    "gn:name":"Alto del Aguacate",
    "gn:population":0,
    "gn:timezone":"America/Havana",
    "iso:country":"CU",
    "name:spa_x_preferred":[
        "Alto del Aguacate"
    ],
    "wof:name":"Alto del Aguacate",
    "wof:placetype":"locality"
},
  "geometry": {"coordinates":[-77.39865,19.99124],"type":"Point"}
}