{
  "type": "Feature",
  "properties": {
    "iso:country":"CU",
    "name:eng_x_variant":[
        "MUSA"
    ],
    "name:fas_x_preferred":[
        "\u0641\u0631\u0648\u062f\u06af\u0627\u0647 \u0633\u0646 \u0622\u0646\u062a\u0648\u0646\u06cc\u0648 \u062f \u0644\u0648\u0633 \u0628\u0627\u0646\u06cc\u0648\u0633"
    ],
    "name:msa_x_preferred":[
        "Lapangan Terbang San Antonio De Los Banos"
    ],
    "name:tgk_x_preferred":[
        "\u0424\u0443\u0440\u0443\u0434\u0433\u043e\u04b3\u0438 \u0441\u0438\u043d \u043e\u043d\u0442\u0443\u043d\u0435\u044e \u0434 \u043b\u04ef\u0441 \u0431\u043e\u043d\u044e\u0441"
    ],
    "oa:elevation_ft":"164",
    "oa:type":"small_airport",
    "wd:wordcount":744,
    "woe:hierarchy":{
        "country_id":23424793,
        "planet_id":1,
        "state_id":2345115
    },
    "wof:name":"San Antonio de Los Banos Airport",
    "wof:placetype":"campus"
},
  "geometry": {"coordinates":[-82.509444,22.871667],"type":"Point"}
}