{
  "type": "Feature",
  "properties": {
    "gn:admin1_code":"05",
    "gn:asciiname":"La Rosalia",
    "gn:country_code":"CU",
    "gn:dem":17,
    "gn:feature_class":"P",
    "gn:feature_code":"PPLL",
    "gn:name":"La Rosal\u00eda",
    "gn:population":0,
    "gn:timezone":"America/Havana",
    "iso:country":"CU",
    "wof:name":"La Rosalia",
    "wof:placetype":"locality"
},
  "geometry": {"coordinates":[-77.97306,20.79583],"type":"Point"}
}