{
  "type": "Feature",
  "properties": {
    "gn:admin1_code":"05",
    "gn:asciiname":"Sierra Maestra",
    "gn:country_code":"CU",
    "gn:dem":11,
    "gn:feature_class":"P",
    "gn:feature_code":"PPL",
    "gn:name":"Sierra Maestra",
    "gn:population":0,
    "gn:timezone":"America/Havana",
    "iso:country":"CU",
    "name:spa_x_preferred":[
        "Sierra Maestra"
    ],
    "wof:name":"Sierra Maestra",
    "wof:placetype":"locality"
},
  "geometry": {"coordinates":[-78.21861,20.94636],"type":"Point"}
}