{
  "type": "Feature",
  "properties": {
    "gn:admin1_code":"03",
    "gn:asciiname":"Bacallao",
    "gn:country_code":"CU",
    "gn:dem":55,
    "gn:feature_class":"P",
    "gn:feature_code":"PPLL",
    "gn:name":"Bacallao",
    "gn:population":0,
    "gn:timezone":"America/Havana",
    "iso:country":"CU",
    "wof:name":"Bacallao",
    "wof:placetype":"locality"
},
  "geometry": {"coordinates":[-80.71666999999999,22.76667],"type":"Point"}
}