{
  "type": "Feature",
  "properties": {
    "gn:admin1_code":"09",
    "gn:asciiname":"Pestan",
    "gn:country_code":"CU",
    "gn:dem":51,
    "gn:feature_class":"P",
    "gn:feature_code":"PPL",
    "gn:name":"Pest\u00e1n",
    "gn:population":0,
    "gn:timezone":"America/Havana",
    "iso:country":"CU",
    "name:spa_x_preferred":[
        "Pest\u00e1n"
    ],
    "wof:name":"Pestan",
    "wof:placetype":"locality"
},
  "geometry": {"coordinates":[-76.45094,20.55353],"type":"Point"}
}