{
  "type": "Feature",
  "properties": {
    "gn:admin1_code":"05",
    "gn:asciiname":"Cascorro",
    "gn:country_code":"CU",
    "gn:dem":91,
    "gn:feature_class":"P",
    "gn:feature_code":"PPL",
    "gn:name":"Cascorro",
    "gn:population":0,
    "gn:timezone":"America/Havana",
    "iso:country":"CU",
    "name:und_x_variant":[
        "Poblado Cascorro",
        "Cascorro"
    ],
    "wof:name":"Cascorro",
    "wof:placetype":"locality"
},
  "geometry": {"coordinates":[-77.45366,21.19423],"type":"Point"}
}