{
  "type": "Feature",
  "properties": {
    "gn:admin1_code":"14",
    "gn:asciiname":"Yamagua",
    "gn:country_code":"CU",
    "gn:dem":135,
    "gn:feature_class":"P",
    "gn:feature_code":"PPL",
    "gn:name":"Yamagua",
    "gn:population":0,
    "gn:timezone":"America/Havana",
    "iso:country":"CU",
    "name:und_x_variant":[
        "La Yamagua"
    ],
    "wof:name":"Yamagua",
    "wof:placetype":"locality"
},
  "geometry": {"coordinates":[-79.56376999999998,22.04427],"type":"Point"}
}