{
  "type": "Feature",
  "properties": {
    "gn:admin1_code":"16",
    "gn:asciiname":"Yaniz",
    "gn:country_code":"CU",
    "gn:dem":5,
    "gn:feature_class":"P",
    "gn:feature_code":"PPLL",
    "gn:name":"Y\u00e1niz",
    "gn:population":0,
    "gn:timezone":"America/Havana",
    "iso:country":"CU",
    "wof:name":"Yaniz",
    "wof:placetype":"locality"
},
  "geometry": {"coordinates":[-79.98333000000002,22.83333],"type":"Point"}
}