{
  "type": "Feature",
  "properties": {
    "gn:admin1_code":"05",
    "gn:asciiname":"La Tumba",
    "gn:country_code":"CU",
    "gn:dem":33,
    "gn:feature_class":"P",
    "gn:feature_code":"PPLL",
    "gn:name":"La Tumba",
    "gn:population":0,
    "gn:timezone":"America/Havana",
    "iso:country":"CU",
    "name:spa_x_preferred":[
        "La Tumba"
    ],
    "name:spa_x_variant":[
        "La tumba"
    ],
    "wof:name":"La Tumba",
    "wof:placetype":"locality"
},
  "geometry": {"coordinates":[-77.65876999999998,21.60079],"type":"Point"}
}