{
  "type": "Feature",
  "properties": {
    "gn:admin1_code":"14",
    "gn:asciiname":"Dagamal",
    "gn:country_code":"CU",
    "gn:dem":151,
    "gn:feature_class":"P",
    "gn:feature_code":"PPLL",
    "gn:name":"Dagamal",
    "gn:population":0,
    "gn:timezone":"America/Havana",
    "iso:country":"CU",
    "name:spa_x_preferred":[
        "Dagamal"
    ],
    "wof:name":"Dagamal",
    "wof:placetype":"locality"
},
  "geometry": {"coordinates":[-79.12745,22.06513],"type":"Point"}
}