{
  "type": "Feature",
  "properties": {
    "gn:admin1_code":"12",
    "gn:asciiname":"Dagamito Dos",
    "gn:country_code":"CU",
    "gn:dem":110,
    "gn:feature_class":"P",
    "gn:feature_code":"PPL",
    "gn:name":"Dagamito Dos",
    "gn:population":0,
    "gn:timezone":"America/Havana",
    "iso:country":"CU",
    "name:spa_x_preferred":[
        "Dagamito Dos"
    ],
    "wof:name":"Dagamito Dos",
    "wof:placetype":"locality"
},
  "geometry": {"coordinates":[-76.65834,20.84665],"type":"Point"}
}