{
  "type": "Feature",
  "properties": {
    "gn:admin1_code":"16",
    "gn:asciiname":"Jiquiabo",
    "gn:country_code":"CU",
    "gn:dem":65,
    "gn:feature_class":"P",
    "gn:feature_code":"PPL",
    "gn:name":"Jiquiabo",
    "gn:population":0,
    "gn:timezone":"America/Havana",
    "iso:country":"CU",
    "name:spa_x_preferred":[
        "San Isidro"
    ],
    "name:und_x_variant":[
        "Poblado Jiquiabo",
        "Jiquiabo"
    ],
    "wof:name":"Jiquiabo",
    "wof:placetype":"locality"
},
  "geometry": {"coordinates":[-80.39676,22.68975],"type":"Point"}
}