{
  "type": "Feature",
  "properties": {
    "gn:admin1_code":"05",
    "gn:asciiname":"Guano Alto",
    "gn:country_code":"CU",
    "gn:dem":52,
    "gn:feature_class":"P",
    "gn:feature_code":"PPL",
    "gn:name":"Guano Alto",
    "gn:population":0,
    "gn:timezone":"America/Havana",
    "iso:country":"CU",
    "name:und_x_variant":[
        "La Palma de Guanoalto",
        "Guano Alto"
    ],
    "wof:name":"Guano Alto",
    "wof:placetype":"locality"
},
  "geometry": {"coordinates":[-78.15654000000001,21.10564],"type":"Point"}
}