{
  "type": "Feature",
  "properties": {
    "gn:admin1_code":"05",
    "gn:asciiname":"La Oriental",
    "gn:country_code":"CU",
    "gn:dem":25,
    "gn:feature_class":"P",
    "gn:feature_code":"PPL",
    "gn:name":"La Oriental",
    "gn:population":0,
    "gn:timezone":"America/Havana",
    "iso:country":"CU",
    "name:spa_x_preferred":[
        "La Oriental"
    ],
    "wof:name":"La Oriental",
    "wof:placetype":"locality"
},
  "geometry": {"coordinates":[-77.36969000000001,21.39859],"type":"Point"}
}