{
  "type": "Feature",
  "properties": {
    "gn:admin1_code":"03",
    "gn:asciiname":"Maria Teresa",
    "gn:country_code":"CU",
    "gn:dem":69,
    "gn:feature_class":"P",
    "gn:feature_code":"PPLL",
    "gn:name":"Mar\u00eda Teresa",
    "gn:population":0,
    "gn:timezone":"America/Havana",
    "iso:country":"CU",
    "name:spa_x_preferred":[
        "Mar\u00eda Teresa"
    ],
    "wof:name":"Maria Teresa",
    "wof:placetype":"locality"
},
  "geometry": {"coordinates":[-80.61199000000001,22.73067],"type":"Point"}
}