{
  "type": "Feature",
  "properties": {
    "gn:admin1_code":"15",
    "gn:asciiname":"Quemadito",
    "gn:country_code":"CU",
    "gn:dem":100,
    "gn:feature_class":"P",
    "gn:feature_code":"PPL",
    "gn:name":"Quemadito",
    "gn:population":0,
    "gn:timezone":"America/Havana",
    "iso:country":"CU",
    "name:spa_x_preferred":[
        "Quemadito"
    ],
    "wof:name":"Quemadito",
    "wof:placetype":"locality"
},
  "geometry": {"coordinates":[-75.94601999999998,20.37137],"type":"Point"}
}