{
  "type": "Feature",
  "properties": {
    "gn:admin1_code":"01",
    "gn:asciiname":"Reforma",
    "gn:country_code":"CU",
    "gn:dem":65,
    "gn:feature_class":"P",
    "gn:feature_code":"PPLL",
    "gn:name":"Reforma",
    "gn:population":0,
    "gn:timezone":"America/Havana",
    "iso:country":"CU",
    "name:cat_x_preferred":[
        "Reforma"
    ],
    "name:eus_x_preferred":[
        "Diario Reforma"
    ],
    "name:nld_x_preferred":[
        "Reforma"
    ],
    "name:nor_x_preferred":[
        "Reforma"
    ],
    "name:que_x_preferred":[
        "Reforma"
    ],
    "name:spa_x_preferred":[
        "Reforma"
    ],
    "wof:name":"Reforma",
    "wof:placetype":"locality"
},
  "geometry": {"coordinates":[-83.60444,22.54333],"type":"Point"}
}