{
  "type": "Feature",
  "properties": {
    "gn:admin1_code":"05",
    "gn:asciiname":"Maria Lola",
    "gn:country_code":"CU",
    "gn:dem":66,
    "gn:feature_class":"P",
    "gn:feature_code":"PPL",
    "gn:name":"Mar\u00eda Lola",
    "gn:population":0,
    "gn:timezone":"America/Havana",
    "iso:country":"CU",
    "name:spa_x_preferred":[
        "Mar\u00eda Lola"
    ],
    "wof:name":"Maria Lola",
    "wof:placetype":"locality"
},
  "geometry": {"coordinates":[-78.27051,21.76339],"type":"Point"}
}