{
  "type": "Feature",
  "properties": {
    "gn:admin1_code":"15",
    "gn:asciiname":"Los Anoncillos",
    "gn:country_code":"CU",
    "gn:dem":112,
    "gn:feature_class":"P",
    "gn:feature_code":"PPL",
    "gn:name":"Los Anoncillos",
    "gn:population":0,
    "gn:timezone":"America/Havana",
    "iso:country":"CU",
    "name:spa_x_preferred":[
        "Los Anoncillos"
    ],
    "wof:name":"Los Anoncillos",
    "wof:placetype":"locality"
},
  "geometry": {"coordinates":[-75.99365999999998,20.34653],"type":"Point"}
}