{
  "type": "Feature",
  "properties": {
    "gn:admin1_code":"16",
    "gn:asciiname":"Maboa",
    "gn:country_code":"CU",
    "gn:dem":85,
    "gn:feature_class":"P",
    "gn:feature_code":"PPL",
    "gn:name":"Maboa",
    "gn:population":0,
    "gn:timezone":"America/Havana",
    "iso:country":"CU",
    "name:und_x_variant":[
        "La Maboa"
    ],
    "wof:name":"Maboa",
    "wof:placetype":"locality"
},
  "geometry": {"coordinates":[-80.45026,22.68292000000001],"type":"Point"}
}