{
  "type": "Feature",
  "properties": {
    "gn:admin1_code":"MA",
    "gn:asciiname":"El Seborucal",
    "gn:country_code":"CU",
    "gn:dem":82,
    "gn:feature_class":"P",
    "gn:feature_code":"PPLL",
    "gn:name":"El Seborucal",
    "gn:population":0,
    "gn:timezone":"America/Havana",
    "iso:country":"CU",
    "wof:name":"El Seborucal",
    "wof:placetype":"locality"
},
  "geometry": {"coordinates":[-81.72111,23.00333],"type":"Point"}
}