{
  "type": "Feature",
  "properties": {
    "gn:admin1_code":"16",
    "gn:asciiname":"La Caridad",
    "gn:country_code":"CU",
    "gn:dem":102,
    "gn:feature_class":"P",
    "gn:feature_code":"PPLL",
    "gn:name":"La Caridad",
    "gn:population":0,
    "gn:timezone":"America/Havana",
    "iso:country":"CU",
    "wof:name":"La Caridad",
    "wof:placetype":"locality"
},
  "geometry": {"coordinates":[-79.95,22.51667],"type":"Point"}
}