{
  "type": "Feature",
  "properties": {
    "gn:admin1_code":"09",
    "gn:asciiname":"Cana Amarga",
    "gn:country_code":"CU",
    "gn:dem":206,
    "gn:feature_class":"P",
    "gn:feature_code":"PPL",
    "gn:name":"Ca\u00f1a Amarga",
    "gn:population":0,
    "gn:timezone":"America/Havana",
    "iso:country":"CU",
    "name:spa_x_preferred":[
        "Ca\u00f1a Amarga"
    ],
    "wof:name":"Cana Amarga",
    "wof:placetype":"locality"
},
  "geometry": {"coordinates":[-77.50882,19.91663],"type":"Point"}
}