{
  "type": "Feature",
  "properties": {
    "gn:admin1_code":"07",
    "gn:asciiname":"Potrero Abajo",
    "gn:country_code":"CU",
    "gn:dem":4,
    "gn:feature_class":"P",
    "gn:feature_code":"PPLL",
    "gn:name":"Potrero Abajo",
    "gn:population":0,
    "gn:timezone":"America/Havana",
    "iso:country":"CU",
    "name:und_x_variant":[
        "Potrero Abajo de Dos Hermanas"
    ],
    "wof:name":"Potrero Abajo",
    "wof:placetype":"locality"
},
  "geometry": {"coordinates":[-78.84635,21.66076],"type":"Point"}
}