{
  "type": "Feature",
  "properties": {
    "gn:admin1_code":"04",
    "gn:asciiname":"Presidio Modelo",
    "gn:country_code":"CU",
    "gn:dem":16,
    "gn:feature_class":"P",
    "gn:feature_code":"PPLL",
    "gn:name":"Presidio Modelo",
    "gn:population":0,
    "gn:timezone":"America/Havana",
    "iso:country":"CU",
    "wof:name":"Presidio Modelo",
    "wof:placetype":"locality"
},
  "geometry": {"coordinates":[-82.76666999999998,21.88333],"type":"Point"}
}