{
  "type": "Feature",
  "properties": {
    "gn:admin1_code":"04",
    "gn:asciiname":"Presidio Modelo",
    "gn:country_code":"CU",
    "gn:dem":16,
    "gn:feature_class":"P",
    "gn:feature_code":"PPLL",
    "gn:name":"Presidio Modelo",
    "gn:population":0,
    "gn:timezone":"America/Havana",
    "iso:country":"CU",
    "name:deu_x_preferred":[
        "Presidio Modelo"
    ],
    "name:fin_x_preferred":[
        "Presidio Modelo"
    ],
    "name:fra_x_preferred":[
        "Presidio Modelo"
    ],
    "name:ind_x_preferred":[
        "Presidio Modelo"
    ],
    "name:nor_x_preferred":[
        "Presidio Modelo"
    ],
    "name:por_x_preferred":[
        "Pres\u00eddio Modelo"
    ],
    "name:rus_x_preferred":[
        "\u041f\u0440\u0435\u0441\u0438\u0434\u0438\u043e \u041c\u043e\u0434\u0435\u043b\u043e"
    ],
    "name:spa_x_preferred":[
        "Presidio Modelo"
    ],
    "name:swe_x_preferred":[
        "Presidio Modelo"
    ],
    "wof:name":"Presidio Modelo",
    "wof:placetype":"locality"
},
  "geometry": {"coordinates":[-82.76666999999998,21.88333],"type":"Point"}
}