{
  "type": "Feature",
  "properties": {
    "gn:admin1_code":"12",
    "gn:asciiname":"Dumois Cinco",
    "gn:country_code":"CU",
    "gn:dem":10,
    "gn:feature_class":"P",
    "gn:feature_code":"PPL",
    "gn:name":"Dumois Cinco",
    "gn:population":0,
    "gn:timezone":"America/Havana",
    "iso:country":"CU",
    "name:spa_x_preferred":[
        "Dumois Cinco"
    ],
    "wof:name":"Dumois Cinco",
    "wof:placetype":"locality"
},
  "geometry": {"coordinates":[-75.80671,20.76215],"type":"Point"}
}