{
  "type": "Feature",
  "properties": {
    "gn:admin1_code":"01",
    "gn:asciiname":"Pasada de Marin",
    "gn:country_code":"CU",
    "gn:dem":9,
    "gn:feature_class":"P",
    "gn:feature_code":"PPLL",
    "gn:name":"Pasada de Mar\u00edn",
    "gn:population":0,
    "gn:timezone":"America/Havana",
    "iso:country":"CU",
    "name:und_x_variant":[
        "Pasada de Mar\u00edn",
        "Paso Marin",
        "Pasa de Mar\u00edn"
    ],
    "wof:name":"Pasada de Marin",
    "wof:placetype":"locality"
},
  "geometry": {"coordinates":[-84.03702,21.9606],"type":"Point"}
}