{
  "type": "Feature",
  "properties": {
    "gn:admin1_code":"10",
    "gn:asciiname":"Hacienda Gran Tierra",
    "gn:country_code":"CU",
    "gn:dem":387,
    "gn:feature_class":"P",
    "gn:feature_code":"PPLL",
    "gn:name":"Hacienda Gran Tierra",
    "gn:population":0,
    "gn:timezone":"America/Havana",
    "iso:country":"CU",
    "wof:name":"Hacienda Gran Tierra",
    "wof:placetype":"locality"
},
  "geometry": {"coordinates":[-74.21666999999999,20.18333],"type":"Point"}
}