{
  "type": "Feature",
  "properties": {
    "gn:admin1_code":"15",
    "gn:asciiname":"Ya Veremos",
    "gn:country_code":"CU",
    "gn:dem":181,
    "gn:feature_class":"P",
    "gn:feature_code":"PPL",
    "gn:name":"Ya Veremos",
    "gn:population":0,
    "gn:timezone":"America/Havana",
    "iso:country":"CU",
    "name:spa_x_preferred":[
        "Ya Veremos"
    ],
    "wof:name":"Ya Veremos",
    "wof:placetype":"locality"
},
  "geometry": {"coordinates":[-76.08989,20.37574],"type":"Point"}
}