{
  "type": "Feature",
  "properties": {
    "gn:admin1_code":"01",
    "gn:asciiname":"Aracelia",
    "gn:country_code":"CU",
    "gn:dem":73,
    "gn:feature_class":"P",
    "gn:feature_code":"PPLL",
    "gn:name":"Aracelia",
    "gn:population":0,
    "gn:timezone":"America/Havana",
    "iso:country":"CU",
    "wof:name":"Aracelia",
    "wof:placetype":"locality"
},
  "geometry": {"coordinates":[-83.59999999999999,22.53333],"type":"Point"}
}