{
  "type": "Feature",
  "properties": {
    "gn:admin1_code":"14",
    "gn:asciiname":"Sabanilla",
    "gn:country_code":"CU",
    "gn:dem":79,
    "gn:feature_class":"P",
    "gn:feature_code":"PPLL",
    "gn:name":"Sabanilla",
    "gn:population":0,
    "gn:timezone":"America/Havana",
    "iso:country":"CU",
    "name:ceb_x_preferred":[
        "Sabanilla"
    ],
    "name:deu_x_preferred":[
        "Municipio Sabanilla"
    ],
    "name:epo_x_preferred":[
        "Sabanilla"
    ],
    "name:eus_x_preferred":[
        "Sabanilla"
    ],
    "name:fra_x_preferred":[
        "Sabanilla"
    ],
    "name:por_x_preferred":[
        "Sabanilla"
    ],
    "name:rus_x_preferred":[
        "\u0421\u0430\u0431\u0430\u043d\u0438\u043b\u044c\u044f"
    ],
    "name:sco_x_preferred":[
        "Sabanilla"
    ],
    "name:spa_x_preferred":[
        "Sabanilla"
    ],
    "name:srp_x_preferred":[
        "\u041e\u043f\u0448\u0442\u0438\u043d\u0430 \u0421\u0430\u0431\u0430\u043d\u0438\u0459\u0430"
    ],
    "name:swe_x_preferred":[
        "Sabanilla"
    ],
    "name:urd_x_preferred":[
        "\u0633\u0628\u0646\u0644\u06c1"
    ],
    "name:vie_x_preferred":[
        "Sabanilla"
    ],
    "wof:name":"Sabanilla",
    "wof:placetype":"locality"
},
  "geometry": {"coordinates":[-79.91667,21.81667],"type":"Point"}
}