{
  "type": "Feature",
  "properties": {
    "gn:admin1_code":"03",
    "gn:asciiname":"Santiago Alvarez",
    "gn:country_code":"CU",
    "gn:dem":78,
    "gn:feature_class":"P",
    "gn:feature_code":"PPLL",
    "gn:name":"Santiago Alv\u00e1rez",
    "gn:population":0,
    "gn:timezone":"America/Havana",
    "iso:country":"CU",
    "wof:name":"Santiago Alvarez",
    "wof:placetype":"locality"
},
  "geometry": {"coordinates":[-80.61166999999998,22.73639],"type":"Point"}
}