{
  "type": "Feature",
  "properties": {
    "gn:admin1_code":"15",
    "gn:asciiname":"Guamaro",
    "gn:country_code":"CU",
    "gn:dem":293,
    "gn:feature_class":"P",
    "gn:feature_code":"PPLL",
    "gn:name":"Guamaro",
    "gn:population":0,
    "gn:timezone":"America/Havana",
    "iso:country":"CU",
    "name:spa_x_preferred":[
        "Guamaro"
    ],
    "wof:name":"Guamaro",
    "wof:placetype":"locality"
},
  "geometry": {"coordinates":[-75.96826,20.00369],"type":"Point"}
}