{
  "type": "Feature",
  "properties": {
    "gn:admin1_code":"10",
    "gn:asciiname":"Cayo Guin",
    "gn:country_code":"CU",
    "gn:dem":13,
    "gn:feature_class":"P",
    "gn:feature_code":"PPL",
    "gn:name":"Cayo G\u00fc\u00edn",
    "gn:population":0,
    "gn:timezone":"America/Havana",
    "iso:country":"CU",
    "name:und_x_variant":[
        "Cayo Juin",
        "Cayo G\u00fc\u00edn"
    ],
    "wof:name":"Cayo Guin",
    "wof:placetype":"locality"
},
  "geometry": {"coordinates":[-74.56442,20.43333],"type":"Point"}
}