{
  "type": "Feature",
  "properties": {
    "gn:admin1_code":"09",
    "gn:asciiname":"Puente de Guillen",
    "gn:country_code":"CU",
    "gn:dem":13,
    "gn:feature_class":"P",
    "gn:feature_code":"PPL",
    "gn:name":"Puente de Guill\u00e9n",
    "gn:population":0,
    "gn:timezone":"America/Havana",
    "iso:country":"CU",
    "name:spa_x_preferred":[
        "Puente de Guill\u00e9n"
    ],
    "wof:name":"Puente de Guillen",
    "wof:placetype":"locality"
},
  "geometry": {"coordinates":[-76.99809,20.70212],"type":"Point"}
}