{
  "type": "Feature",
  "properties": {
    "gn:admin1_code":"09",
    "gn:asciiname":"Gonzalez",
    "gn:cc2":"CU",
    "gn:country_code":"CU",
    "gn:dem":46,
    "gn:feature_class":"P",
    "gn:feature_code":"PPLL",
    "gn:name":"Gonz\u00e1lez",
    "gn:population":0,
    "gn:timezone":"America/Havana",
    "iso:country":"CU",
    "name:und_x_variant":[
        "Limoncito",
        "Gonz\u00e1lez"
    ],
    "wof:name":"Gonzalez",
    "wof:placetype":"locality"
},
  "geometry": {"coordinates":[-76.50083000000002,20.63889],"type":"Point"}
}