{
  "type": "Feature",
  "properties": {
    "gn:admin1_code":"AR",
    "gn:asciiname":"Corojalito Arriba",
    "gn:country_code":"CU",
    "gn:dem":23,
    "gn:feature_class":"P",
    "gn:feature_code":"PPL",
    "gn:name":"Corojalito Arriba",
    "gn:population":0,
    "gn:timezone":"America/Havana",
    "iso:country":"CU",
    "name:spa_x_preferred":[
        "Corojalito Arriba"
    ],
    "name:und_x_variant":[
        "El Corojalito"
    ],
    "wof:name":"Corojalito Arriba",
    "wof:placetype":"locality"
},
  "geometry": {"coordinates":[-83.19185,22.9723],"type":"Point"}
}