{
  "type": "Feature",
  "properties": {
    "gn:admin1_code":"16",
    "gn:asciiname":"Higinia",
    "gn:country_code":"CU",
    "gn:dem":177,
    "gn:feature_class":"P",
    "gn:feature_code":"PPLL",
    "gn:name":"Higinia",
    "gn:population":0,
    "gn:timezone":"America/Havana",
    "iso:country":"CU",
    "name:spa_x_preferred":[
        "Higinia"
    ],
    "wof:name":"Higinia",
    "wof:placetype":"locality"
},
  "geometry": {"coordinates":[-79.73383000000003,22.2525],"type":"Point"}
}