{
  "type": "Feature",
  "properties": {
    "gn:admin1_code":"01",
    "gn:asciiname":"La Rosa",
    "gn:country_code":"CU",
    "gn:dem":15,
    "gn:feature_class":"P",
    "gn:feature_code":"PPLL",
    "gn:name":"La Rosa",
    "gn:population":0,
    "gn:timezone":"America/Havana",
    "iso:country":"CU",
    "name:spa_x_preferred":[
        "La Rosa"
    ],
    "wof:name":"La Rosa",
    "wof:placetype":"locality"
},
  "geometry": {"coordinates":[-83.49911999999998,22.29733],"type":"Point"}
}