{
  "type": "Feature",
  "properties": {
    "gn:admin1_code":"09",
    "gn:asciiname":"Las Lajitas",
    "gn:country_code":"CU",
    "gn:dem":128,
    "gn:feature_class":"P",
    "gn:feature_code":"PPL",
    "gn:name":"Las Lajitas",
    "gn:population":0,
    "gn:timezone":"America/Havana",
    "iso:country":"CU",
    "name:ceb_x_preferred":[
        "Las Lajitas"
    ],
    "name:por_x_preferred":[
        "Las Lajitas"
    ],
    "name:spa_x_preferred":[
        "Las Lajitas"
    ],
    "name:und_x_variant":[
        "La Lajita",
        "Lajitas"
    ],
    "name:urd_x_preferred":[
        "\u0644\u0627\u0633 \u0644\u0627\u062c\u06cc\u0679\u0627\u0633"
    ],
    "wof:name":"Las Lajitas",
    "wof:placetype":"locality"
},
  "geometry": {"coordinates":[-77.40210999999999,20.01759],"type":"Point"}
}