{
  "type": "Feature",
  "properties": {
    "gn:admin1_code":"15",
    "gn:asciiname":"Abajo",
    "gn:country_code":"CU",
    "gn:dem":138,
    "gn:feature_class":"P",
    "gn:feature_code":"PPLL",
    "gn:name":"Abajo",
    "gn:population":0,
    "gn:timezone":"America/Havana",
    "iso:country":"CU",
    "wof:name":"Abajo",
    "wof:placetype":"locality"
},
  "geometry": {"coordinates":[-75.48999999999999,20.16167],"type":"Point"}
}