{
  "type": "Feature",
  "properties": {
    "gn:admin1_code":"15",
    "gn:admin2_code":"3406",
    "gn:asciiname":"Dos Moya",
    "gn:country_code":"CU",
    "gn:dem":14,
    "gn:feature_class":"P",
    "gn:feature_code":"PPL",
    "gn:name":"Dos Moya",
    "gn:population":0,
    "gn:timezone":"America/Havana",
    "iso:country":"CU",
    "wof:name":"Dos Moya",
    "wof:placetype":"locality"
},
  "geometry": {"coordinates":[-75.70413000000001,19.97069],"type":"Point"}
}