{
  "type": "Feature",
  "properties": {
    "gn:admin1_code":"01",
    "gn:asciiname":"Sandino",
    "gn:country_code":"CU",
    "gn:dem":14,
    "gn:feature_class":"P",
    "gn:feature_code":"PPL",
    "gn:name":"Sandino",
    "gn:population":0,
    "gn:timezone":"America/Havana",
    "iso:country":"CU",
    "name:ceb_x_preferred":[
        "Sandino"
    ],
    "name:deu_x_preferred":[
        "Sandino"
    ],
    "name:fra_x_preferred":[
        "Sandino"
    ],
    "name:ita_x_preferred":[
        "Sandino"
    ],
    "name:kat_x_preferred":[
        "\u10e1\u10d0\u10dc\u10d3\u10d8\u10dc\u10dd"
    ],
    "name:nld_x_preferred":[
        "Sandino"
    ],
    "name:por_x_preferred":[
        "Sandino"
    ],
    "name:spa_x_preferred":[
        "Sandino"
    ],
    "name:swe_x_preferred":[
        "Sandino"
    ],
    "name:und_x_variant":[
        "Ciudad Sandino",
        "Sandino"
    ],
    "name:vie_x_preferred":[
        "Sandino"
    ],
    "name:zho_x_preferred":[
        "\u6851\u8fea\u8afe"
    ],
    "wof:name":"Sandino",
    "wof:placetype":"locality"
},
  "geometry": {"coordinates":[-84.20769,22.08069],"type":"Point"}
}