{
  "type": "Feature",
  "properties": {
    "gn:admin1_code":"13",
    "gn:asciiname":"Claudio",
    "gn:country_code":"CU",
    "gn:dem":23,
    "gn:feature_class":"P",
    "gn:feature_code":"PPL",
    "gn:name":"Claudio",
    "gn:population":0,
    "gn:timezone":"America/Havana",
    "iso:country":"CU",
    "name:bre_x_preferred":[
        "Claudio"
    ],
    "name:deu_x_preferred":[
        "Claudio"
    ],
    "name:ita_x_preferred":[
        "Claudio"
    ],
    "name:jpn_x_preferred":[
        "\u30af\u30e9\u30a6\u30c7\u30a3\u30aa"
    ],
    "name:kor_x_preferred":[
        "\ud074\ub77c\uc6b0\ub514\uc624"
    ],
    "name:spa_x_preferred":[
        "Claudio"
    ],
    "name:swe_x_preferred":[
        "Claudio"
    ],
    "name:tgl_x_preferred":[
        "Claudio"
    ],
    "wof:name":"Claudio",
    "wof:placetype":"locality"
},
  "geometry": {"coordinates":[-76.91064,21.21243],"type":"Point"}
}