{
  "type": "Feature",
  "properties": {
    "gn:admin1_code":"16",
    "gn:asciiname":"El Mosquito",
    "gn:country_code":"CU",
    "gn:dem":43,
    "gn:feature_class":"P",
    "gn:feature_code":"PPLL",
    "gn:name":"El Mosquito",
    "gn:population":0,
    "gn:timezone":"America/Havana",
    "iso:country":"CU",
    "name:spa_x_preferred":[
        "El Mosquito"
    ],
    "wof:name":"El Mosquito",
    "wof:placetype":"locality"
},
  "geometry": {"coordinates":[-79.83325000000001,22.60265],"type":"Point"}
}