{
  "type": "Feature",
  "properties": {
    "gn:admin1_code":"MA",
    "gn:asciiname":"Angelita",
    "gn:country_code":"CU",
    "gn:dem":102,
    "gn:feature_class":"P",
    "gn:feature_code":"PPLL",
    "gn:name":"Angelita",
    "gn:population":0,
    "gn:timezone":"America/Havana",
    "iso:country":"CU",
    "wof:name":"Angelita",
    "wof:placetype":"locality"
},
  "geometry": {"coordinates":[-81.92860999999998,22.87389],"type":"Point"}
}