{
  "type": "Feature",
  "properties": {
    "gn:admin1_code":"13",
    "gn:asciiname":"Dos Hermanas",
    "gn:country_code":"CU",
    "gn:dem":49,
    "gn:feature_class":"P",
    "gn:feature_code":"PPLL",
    "gn:name":"Dos Hermanas",
    "gn:population":0,
    "gn:timezone":"America/Havana",
    "iso:country":"CU",
    "wof:name":"Dos Hermanas",
    "wof:placetype":"locality"
},
  "geometry": {"coordinates":[-77.18333,20.88333],"type":"Point"}
}