{
  "type": "Feature",
  "properties": {
    "gn:admin1_code":"01",
    "gn:asciiname":"La Guardia",
    "gn:country_code":"CU",
    "gn:dem":17,
    "gn:feature_class":"P",
    "gn:feature_code":"PPLL",
    "gn:name":"La Guardia",
    "gn:population":0,
    "gn:timezone":"America/Havana",
    "iso:country":"CU",
    "name:ceb_x_preferred":[
        "La Guardia"
    ],
    "name:deu_x_preferred":[
        "La Guardia"
    ],
    "name:epo_x_preferred":[
        "La Guardia"
    ],
    "name:fra_x_preferred":[
        "La Guardia"
    ],
    "name:heb_x_preferred":[
        "\u05dc\u05d4 \u05d2\u05d5\u05d0\u05e8\u05d3\u05d9\u05d4"
    ],
    "name:hun_x_preferred":[
        "La Guardia"
    ],
    "name:ita_x_preferred":[
        "La Guardia"
    ],
    "name:kor_x_preferred":[
        "\ub77c\uac00\ub514\uc544"
    ],
    "name:nld_x_preferred":[
        "La Guardia"
    ],
    "name:rus_x_preferred":[
        "\u041b\u0430-\u0413\u0443\u0430\u0440\u0434\u0438\u044f"
    ],
    "name:sco_x_preferred":[
        "La Guardia"
    ],
    "name:spa_x_preferred":[
        "La Guardia"
    ],
    "name:srp_x_preferred":[
        "La Guardia"
    ],
    "name:swe_x_preferred":[
        "La Guardia"
    ],
    "wof:name":"La Guardia",
    "wof:placetype":"locality"
},
  "geometry": {"coordinates":[-83.84999999999999,22.25],"type":"Point"}
}