{
  "type": "Feature",
  "properties": {
    "gn:admin1_code":"10",
    "gn:asciiname":"La Guanabana",
    "gn:country_code":"CU",
    "gn:dem":173,
    "gn:feature_class":"P",
    "gn:feature_code":"PPL",
    "gn:name":"La Guan\u00e1bana",
    "gn:population":0,
    "gn:timezone":"America/Havana",
    "iso:country":"CU",
    "name:spa_x_preferred":[
        "La Guan\u00e1bana"
    ],
    "wof:name":"La Guanabana",
    "wof:placetype":"locality"
},
  "geometry": {"coordinates":[-75.40566,19.96374],"type":"Point"}
}