{
  "type": "Feature",
  "properties": {
    "gn:admin1_code":"10",
    "gn:asciiname":"La Perrera",
    "gn:country_code":"CU",
    "gn:dem":618,
    "gn:feature_class":"P",
    "gn:feature_code":"PPL",
    "gn:name":"La Perrera",
    "gn:population":0,
    "gn:timezone":"America/Havana",
    "iso:country":"CU",
    "name:spa_x_preferred":[
        "La Perrera"
    ],
    "wof:name":"La Perrera",
    "wof:placetype":"locality"
},
  "geometry": {"coordinates":[-74.7407,20.14561],"type":"Point"}
}