{
  "type": "Feature",
  "properties": {
    "gn:admin1_code":"16",
    "gn:asciiname":"Las Glorias",
    "gn:country_code":"CU",
    "gn:dem":182,
    "gn:feature_class":"P",
    "gn:feature_code":"PPLL",
    "gn:name":"Las Glorias",
    "gn:population":0,
    "gn:timezone":"America/Havana",
    "iso:country":"CU",
    "name:spa_x_preferred":[
        "Las Glorias"
    ],
    "wof:name":"Las Glorias",
    "wof:placetype":"locality"
},
  "geometry": {"coordinates":[-79.94928,22.31401],"type":"Point"}
}