{
  "type": "Feature",
  "properties": {
    "gn:admin1_code":"09",
    "gn:asciiname":"Monteria",
    "gn:cc2":"CU",
    "gn:country_code":"CU",
    "gn:dem":378,
    "gn:feature_class":"P",
    "gn:feature_code":"PPLL",
    "gn:name":"Monter\u00eda",
    "gn:population":0,
    "gn:timezone":"America/Havana",
    "iso:country":"CU",
    "name:und_x_variant":[
        "La Manteria",
        "Montoria",
        "Monter\u00eda"
    ],
    "wof:name":"Monteria",
    "wof:placetype":"locality"
},
  "geometry": {"coordinates":[-77.05,20.03333],"type":"Point"}
}