{
  "type": "Feature",
  "properties": {
    "gn:admin1_code":"03",
    "gn:asciiname":"El Vinculo",
    "gn:country_code":"CU",
    "gn:dem":7,
    "gn:feature_class":"P",
    "gn:feature_code":"PPLL",
    "gn:name":"El V\u00ednculo",
    "gn:population":0,
    "gn:timezone":"America/Havana",
    "iso:country":"CU",
    "name:spa_x_preferred":[
        "El V\u00ednculo"
    ],
    "wof:name":"El Vinculo",
    "wof:placetype":"locality"
},
  "geometry": {"coordinates":[-81.49847,22.38616],"type":"Point"}
}