{
  "type": "Feature",
  "properties": {
    "gn:admin1_code":"12",
    "gn:asciiname":"La Ligera",
    "gn:country_code":"CU",
    "gn:dem":23,
    "gn:feature_class":"P",
    "gn:feature_code":"PPL",
    "gn:name":"La Ligera",
    "gn:population":0,
    "gn:timezone":"America/Havana",
    "iso:country":"CU",
    "name:und_x_variant":[
        "La Lijera"
    ],
    "wof:name":"La Ligera",
    "wof:placetype":"locality"
},
  "geometry": {"coordinates":[-76.13345,21.05719],"type":"Point"}
}