{
  "type": "Feature",
  "properties": {
    "gn:admin1_code":"14",
    "gn:asciiname":"Alto Cedro",
    "gn:country_code":"CU",
    "gn:dem":214,
    "gn:feature_class":"P",
    "gn:feature_code":"PPLL",
    "gn:name":"Alto Cedro",
    "gn:population":0,
    "gn:timezone":"America/Havana",
    "iso:country":"CU",
    "wof:name":"Alto Cedro",
    "wof:placetype":"locality"
},
  "geometry": {"coordinates":[-79.03333000000001,22.03333],"type":"Point"}
}