{
  "type": "Feature",
  "properties": {
    "gn:admin1_code":"03",
    "gn:asciiname":"Los Jardines",
    "gn:country_code":"CU",
    "gn:dem":11,
    "gn:feature_class":"P",
    "gn:feature_code":"PPL",
    "gn:name":"Los Jardines",
    "gn:population":0,
    "gn:timezone":"America/Havana",
    "iso:country":"CU",
    "name:spa_x_preferred":[
        "Los Jardines"
    ],
    "wof:name":"Los Jardines",
    "wof:placetype":"locality"
},
  "geometry": {"coordinates":[-81.27313000000002,22.61949],"type":"Point"}
}