{
  "type": "Feature",
  "properties": {
    "gn:admin1_code":"04",
    "gn:asciiname":"Las Nuevas",
    "gn:country_code":"CU",
    "gn:dem":17,
    "gn:feature_class":"P",
    "gn:feature_code":"PPL",
    "gn:name":"Las Nuevas",
    "gn:population":0,
    "gn:timezone":"America/Havana",
    "iso:country":"CU",
    "name:spa_x_preferred":[
        "Las Nuevas"
    ],
    "name:und_x_variant":[
        "La Nueva"
    ],
    "wof:name":"Las Nuevas",
    "wof:placetype":"locality"
},
  "geometry": {"coordinates":[-82.91063,21.82941],"type":"Point"}
}