{
  "type": "Feature",
  "properties": {
    "gn:admin1_code":"AR",
    "gn:asciiname":"Rancho Cabo",
    "gn:country_code":"CU",
    "gn:dem":280,
    "gn:feature_class":"P",
    "gn:feature_code":"PPLL",
    "gn:name":"Rancho Cabo",
    "gn:population":0,
    "gn:timezone":"America/Havana",
    "iso:country":"CU",
    "name:spa_x_preferred":[
        "Rancho Cabo"
    ],
    "name:und_x_variant":[
        "Rancho Cobo"
    ],
    "wof:name":"Rancho Cabo",
    "wof:placetype":"locality"
},
  "geometry": {"coordinates":[-83.10750999999998,22.86377],"type":"Point"}
}