{
  "type": "Feature",
  "properties": {
    "gn:admin1_code":"13",
    "gn:asciiname":"El Diez",
    "gn:country_code":"CU",
    "gn:dem":49,
    "gn:feature_class":"P",
    "gn:feature_code":"PPL",
    "gn:name":"El Diez",
    "gn:population":0,
    "gn:timezone":"America/Havana",
    "iso:country":"CU",
    "name:spa_x_preferred":[
        "El Diez"
    ],
    "wof:name":"El Diez",
    "wof:placetype":"locality"
},
  "geometry": {"coordinates":[-77.53998,20.9096],"type":"Point"}
}