{
  "type": "Feature",
  "properties": {
    "gn:admin1_code":"AR",
    "gn:asciiname":"Macasta",
    "gn:country_code":"CU",
    "gn:dem":61,
    "gn:feature_class":"P",
    "gn:feature_code":"PPL",
    "gn:name":"Macasta",
    "gn:population":0,
    "gn:timezone":"America/Havana",
    "iso:country":"CU",
    "name:spa_x_preferred":[
        "Macasta"
    ],
    "name:und_x_variant":[
        "Macosta",
        "Macast\u00e1"
    ],
    "wof:name":"Macasta",
    "wof:placetype":"locality"
},
  "geometry": {"coordinates":[-82.5167,23.00379],"type":"Point"}
}