{
  "type": "Feature",
  "properties": {
    "gn:admin1_code":"01",
    "gn:asciiname":"Capote",
    "gn:country_code":"CU",
    "gn:dem":75,
    "gn:feature_class":"P",
    "gn:feature_code":"PPLL",
    "gn:name":"Capote",
    "gn:population":0,
    "gn:timezone":"America/Havana",
    "iso:country":"CU",
    "wof:name":"Capote",
    "wof:placetype":"locality"
},
  "geometry": {"coordinates":[-83.28305999999998,22.63639],"type":"Point"}
}