{
  "type": "Feature",
  "properties": {
    "gn:admin1_code":"14",
    "gn:asciiname":"El Corojo",
    "gn:country_code":"CU",
    "gn:dem":18,
    "gn:feature_class":"P",
    "gn:feature_code":"PPLL",
    "gn:name":"El Corojo",
    "gn:population":0,
    "gn:timezone":"America/Havana",
    "iso:country":"CU",
    "name:spa_x_preferred":[
        "El Corojo"
    ],
    "name:und_x_variant":[
        "Corojo"
    ],
    "wof:name":"El Corojo",
    "wof:placetype":"locality"
},
  "geometry": {"coordinates":[-79.57505999999999,21.71185],"type":"Point"}
}