{
  "type": "Feature",
  "properties": {
    "gn:admin1_code":"MA",
    "gn:asciiname":"Santisima Trinidad",
    "gn:country_code":"CU",
    "gn:dem":117,
    "gn:feature_class":"P",
    "gn:feature_code":"PPLL",
    "gn:name":"Sant\u00edsima Trinidad",
    "gn:population":0,
    "gn:timezone":"America/Havana",
    "iso:country":"CU",
    "wof:name":"Santisima Trinidad",
    "wof:placetype":"locality"
},
  "geometry": {"coordinates":[-81.93333,22.93333],"type":"Point"}
}