{
  "type": "Feature",
  "properties": {
    "gn:admin1_code":"12",
    "gn:asciiname":"Previo",
    "gn:country_code":"CU",
    "gn:dem":367,
    "gn:feature_class":"P",
    "gn:feature_code":"PPL",
    "gn:name":"Previo",
    "gn:population":0,
    "gn:timezone":"America/Havana",
    "iso:country":"CU",
    "name:spa_x_preferred":[
        "Previo"
    ],
    "name:und_x_variant":[
        "El Predio"
    ],
    "wof:name":"Previo",
    "wof:placetype":"locality"
},
  "geometry": {"coordinates":[-75.21073,20.47947000000001],"type":"Point"}
}