{
  "type": "Feature",
  "properties": {
    "gn:admin1_code":"AR",
    "gn:asciiname":"Vargas",
    "gn:country_code":"CU",
    "gn:dem":45,
    "gn:feature_class":"P",
    "gn:feature_code":"PPLL",
    "gn:name":"Vargas",
    "gn:population":0,
    "gn:timezone":"America/Havana",
    "iso:country":"CU",
    "wof:name":"Vargas",
    "wof:placetype":"locality"
},
  "geometry": {"coordinates":[-82.58333,22.85],"type":"Point"}
}