{
  "type": "Feature",
  "properties": {
    "gn:admin1_code":"01",
    "gn:asciiname":"Los Cayuelos",
    "gn:country_code":"CU",
    "gn:dem":11,
    "gn:feature_class":"P",
    "gn:feature_code":"PPL",
    "gn:name":"Los Cayuelos",
    "gn:population":0,
    "gn:timezone":"America/Havana",
    "iso:country":"CU",
    "name:spa_x_preferred":[
        "Los Cayuelos"
    ],
    "wof:name":"Los Cayuelos",
    "wof:placetype":"locality"
},
  "geometry": {"coordinates":[-84.92390999999998,21.84769],"type":"Point"}
}