{
  "type": "Feature",
  "properties": {
    "gn:admin1_code":"16",
    "gn:asciiname":"Jose Rene Riquelme",
    "gn:country_code":"CU",
    "gn:dem":98,
    "gn:feature_class":"P",
    "gn:feature_code":"PPL",
    "gn:name":"Jos\u00e9 Ren\u00e9 Riquelme",
    "gn:population":0,
    "gn:timezone":"America/Havana",
    "iso:country":"CU",
    "name:spa_x_preferred":[
        "Jos\u00e9 R. Riquelme"
    ],
    "name:spa_x_variant":[
        "Jos\u00e9 Ren\u00e9 Riquelme"
    ],
    "wof:name":"Jose Rene Riquelme",
    "wof:placetype":"locality"
},
  "geometry": {"coordinates":[-80.33379000000002,22.82859],"type":"Point"}
}