{
  "type": "Feature",
  "properties": {
    "gn:admin1_code":"MA",
    "gn:asciiname":"Plazaola",
    "gn:country_code":"CU",
    "gn:dem":31,
    "gn:feature_class":"P",
    "gn:feature_code":"PPLL",
    "gn:name":"Plazaola",
    "gn:population":0,
    "gn:timezone":"America/Havana",
    "iso:country":"CU",
    "name:spa_x_preferred":[
        "Plazaola"
    ],
    "wof:name":"Plazaola",
    "wof:placetype":"locality"
},
  "geometry": {"coordinates":[-82.22134,22.78317],"type":"Point"}
}