{
  "type": "Feature",
  "properties": {
    "gn:admin1_code":"15",
    "gn:asciiname":"Bolanos",
    "gn:country_code":"CU",
    "gn:dem":328,
    "gn:feature_class":"P",
    "gn:feature_code":"PPLL",
    "gn:name":"Bolanos",
    "gn:population":0,
    "gn:timezone":"America/Havana",
    "iso:country":"CU",
    "name:spa_x_preferred":[
        "Bolanos"
    ],
    "wof:name":"Bolanos",
    "wof:placetype":"locality"
},
  "geometry": {"coordinates":[-75.62069,20.27684],"type":"Point"}
}