{
  "type": "Feature",
  "properties": {
    "gn:admin1_code":"10",
    "gn:asciiname":"La Dolorita",
    "gn:country_code":"CU",
    "gn:dem":199,
    "gn:feature_class":"P",
    "gn:feature_code":"PPL",
    "gn:name":"La Dolorita",
    "gn:population":0,
    "gn:timezone":"America/Havana",
    "iso:country":"CU",
    "name:spa_x_preferred":[
        "La Dolorita"
    ],
    "wof:name":"La Dolorita",
    "wof:placetype":"locality"
},
  "geometry": {"coordinates":[-74.26031,20.28561],"type":"Point"}
}