{
  "type": "Feature",
  "properties": {
    "gn:admin1_code":"16",
    "gn:asciiname":"Flor de Cuba",
    "gn:country_code":"CU",
    "gn:dem":26,
    "gn:feature_class":"P",
    "gn:feature_code":"PPLL",
    "gn:name":"Flor de Cuba",
    "gn:population":0,
    "gn:timezone":"America/Havana",
    "iso:country":"CU",
    "name:spa_x_preferred":[
        "Flor de Cuba"
    ],
    "wof:name":"Flor de Cuba",
    "wof:placetype":"locality"
},
  "geometry": {"coordinates":[-80.22674000000001,22.84247],"type":"Point"}
}