{
  "type": "Feature",
  "properties": {
    "gn:admin1_code":"03",
    "gn:asciiname":"La Vega",
    "gn:cc2":"CU",
    "gn:country_code":"CU",
    "gn:dem":47,
    "gn:feature_class":"P",
    "gn:feature_code":"PPLL",
    "gn:name":"La Vega",
    "gn:population":0,
    "gn:timezone":"America/Havana",
    "iso:country":"CU",
    "name:und_x_variant":[
        "Las Vegas",
        "La Vega"
    ],
    "wof:name":"La Vega",
    "wof:placetype":"locality"
},
  "geometry": {"coordinates":[-80.91417,22.59667],"type":"Point"}
}