{
  "type": "Feature",
  "properties": {
    "gn:admin1_code":"08",
    "gn:asciiname":"Gutierrez",
    "gn:country_code":"CU",
    "gn:dem":64,
    "gn:feature_class":"P",
    "gn:feature_code":"PPLL",
    "gn:name":"Guti\u00e9rrez",
    "gn:population":0,
    "gn:timezone":"America/Havana",
    "iso:country":"CU",
    "name:spa_x_preferred":[
        "Guti\u00e9rrez"
    ],
    "wof:name":"Gutierrez",
    "wof:placetype":"locality"
},
  "geometry": {"coordinates":[-80.54204,22.47705],"type":"Point"}
}