{
  "type": "Feature",
  "properties": {
    "gn:admin1_code":"15",
    "gn:asciiname":"Dos Caminos",
    "gn:country_code":"CU",
    "gn:dem":192,
    "gn:feature_class":"P",
    "gn:feature_code":"PPL",
    "gn:name":"Dos Caminos",
    "gn:population":0,
    "gn:timezone":"America/Havana",
    "iso:country":"CU",
    "name:und_x_variant":[
        "Dos Camino",
        "Dos Caminos"
    ],
    "wof:name":"Dos Caminos",
    "wof:placetype":"locality"
},
  "geometry": {"coordinates":[-75.78910999999999,20.18348],"type":"Point"}
}