{
  "type": "Feature",
  "properties": {
    "gn:admin1_code":"16",
    "gn:asciiname":"San Enrique",
    "gn:country_code":"CU",
    "gn:dem":113,
    "gn:feature_class":"P",
    "gn:feature_code":"PPL",
    "gn:name":"San Enrique",
    "gn:population":0,
    "gn:timezone":"America/Havana",
    "iso:country":"CU",
    "name:spa_x_preferred":[
        "San Enrique"
    ],
    "wof:name":"San Enrique",
    "wof:placetype":"locality"
},
  "geometry": {"coordinates":[-80.40143,22.89848],"type":"Point"}
}