{
  "type": "Feature",
  "properties": {
    "gn:admin1_code":"16",
    "gn:asciiname":"Francisco Perez",
    "gn:country_code":"CU",
    "gn:dem":165,
    "gn:feature_class":"P",
    "gn:feature_code":"PPL",
    "gn:name":"Francisco P\u00e9rez",
    "gn:population":0,
    "gn:timezone":"America/Havana",
    "iso:country":"CU",
    "name:spa_x_preferred":[
        "Francisco P\u00e9rez"
    ],
    "wof:name":"Francisco Perez",
    "wof:placetype":"locality"
},
  "geometry": {"coordinates":[-79.59747,22.35532000000001],"type":"Point"}
}