{
  "type": "Feature",
  "properties": {
    "gn:admin1_code":"05",
    "gn:asciiname":"Los Guasimales",
    "gn:country_code":"CU",
    "gn:dem":55,
    "gn:feature_class":"P",
    "gn:feature_code":"PPLL",
    "gn:name":"Los Guasimales",
    "gn:population":0,
    "gn:timezone":"America/Havana",
    "iso:country":"CU",
    "name:spa_x_preferred":[
        "Los Guasimales"
    ],
    "wof:name":"Los Guasimales",
    "wof:placetype":"locality"
},
  "geometry": {"coordinates":[-78.38252,21.69016],"type":"Point"}
}