{
  "type": "Feature",
  "properties": {
    "gn:admin1_code":"14",
    "gn:asciiname":"Carboney",
    "gn:country_code":"CU",
    "gn:dem":133,
    "gn:feature_class":"P",
    "gn:feature_code":"PPL",
    "gn:name":"Carboney",
    "gn:population":0,
    "gn:timezone":"America/Havana",
    "iso:country":"CU",
    "name:spa_x_preferred":[
        "Calboney"
    ],
    "name:spa_x_variant":[
        "Carboney"
    ],
    "wof:name":"Carboney",
    "wof:placetype":"locality"
},
  "geometry": {"coordinates":[-79.47368,22.06925],"type":"Point"}
}