{
  "type": "Feature",
  "properties": {
    "gn:admin1_code":"13",
    "gn:asciiname":"Omaja",
    "gn:country_code":"CU",
    "gn:dem":59,
    "gn:feature_class":"P",
    "gn:feature_code":"PPL",
    "gn:name":"Omaja",
    "gn:population":0,
    "gn:timezone":"America/Havana",
    "iso:country":"CU",
    "wof:name":"Omaja",
    "wof:placetype":"locality"
},
  "geometry": {"coordinates":[-76.74498,20.83781],"type":"Point"}
}