{
  "type": "Feature",
  "properties": {
    "gn:country":"CU",
    "gn:fcode":"PPL",
    "gn:pop":5843,
    "iso:country":"CU",
    "name:unk_x_variant":[
        "Alcranes"
    ],
    "qs:name":"Alacranes",
    "qs:photos_9r":0,
    "qs:photos_sr":0,
    "qs:pop_sr":"5",
    "wof:name":"Alacranes",
    "wof:placetype":"locality",
    "wof:population":5843
},
  "geometry": {"coordinates":[-81.5675,22.7675],"type":"Point"}
}