{
  "type": "Feature",
  "properties": {
    "gn:admin1_code":"03",
    "gn:asciiname":"Amistad",
    "gn:cc2":"CU",
    "gn:country_code":"CU",
    "gn:dem":17,
    "gn:feature_class":"P",
    "gn:feature_code":"PPL",
    "gn:name":"Amistad",
    "gn:population":0,
    "gn:timezone":"America/Havana",
    "iso:country":"CU",
    "name:und_x_variant":[
        "Batey Amistad",
        "Amistad"
    ],
    "wof:name":"Amistad",
    "wof:placetype":"locality"
},
  "geometry": {"coordinates":[-81.01639,22.95028],"type":"Point"}
}