{
  "type": "Feature",
  "properties": {
    "gn:admin1_code":"01",
    "gn:asciiname":"La Veterana",
    "gn:country_code":"CU",
    "gn:dem":76,
    "gn:feature_class":"P",
    "gn:feature_code":"PPLL",
    "gn:name":"La Veterana",
    "gn:population":0,
    "gn:timezone":"America/Havana",
    "iso:country":"CU",
    "wof:name":"La Veterana",
    "wof:placetype":"locality"
},
  "geometry": {"coordinates":[-83.50694,22.52333],"type":"Point"}
}