{
  "type": "Feature",
  "properties": {
    "gn:admin1_code":"16",
    "gn:asciiname":"Jova",
    "gn:country_code":"CU",
    "gn:dem":23,
    "gn:feature_class":"P",
    "gn:feature_code":"PPLL",
    "gn:name":"Jova",
    "gn:population":0,
    "gn:timezone":"America/Havana",
    "iso:country":"CU",
    "wof:name":"Jova",
    "wof:placetype":"locality"
},
  "geometry": {"coordinates":[-79.90000000000001,22.68333],"type":"Point"}
}