{
  "type": "Feature",
  "properties": {
    "gn:admin1_code":"05",
    "gn:asciiname":"La Guinea",
    "gn:country_code":"CU",
    "gn:dem":23,
    "gn:feature_class":"P",
    "gn:feature_code":"PPL",
    "gn:name":"La Guinea",
    "gn:population":0,
    "gn:timezone":"America/Havana",
    "iso:country":"CU",
    "name:ita_x_preferred":[
        "La Guinea"
    ],
    "name:spa_x_preferred":[
        "La Guinea"
    ],
    "name:zho_x_preferred":[
        "\u62c9\u5e7e\u5167\u4e9e"
    ],
    "wof:name":"La Guinea",
    "wof:placetype":"locality"
},
  "geometry": {"coordinates":[-77.13115000000001,21.36822],"type":"Point"}
}