{
  "type": "Feature",
  "properties": {
    "gn:admin1_code":"02",
    "gn:asciiname":"Sierra Maestra",
    "gn:country_code":"CU",
    "gn:dem":94,
    "gn:feature_class":"P",
    "gn:feature_code":"PPL",
    "gn:name":"Sierra Maestra",
    "gn:population":0,
    "gn:timezone":"America/Havana",
    "iso:country":"CU",
    "name:aze_x_preferred":[
        "Syerra-Maestra"
    ],
    "name:bul_x_preferred":[
        "\u0421\u0438\u0435\u0440\u0430 \u041c\u0430\u0435\u0441\u0442\u0440\u0430"
    ],
    "name:cat_x_preferred":[
        "Sierra Maestra"
    ],
    "name:ceb_x_preferred":[
        "Sierra Maestra"
    ],
    "name:ces_x_preferred":[
        "Sierra Maestra"
    ],
    "name:deu_x_preferred":[
        "Sierra Maestra"
    ],
    "name:epo_x_preferred":[
        "Sierra Maestra"
    ],
    "name:eus_x_preferred":[
        "Sierra Maestra"
    ],
    "name:fin_x_preferred":[
        "Sierra Maestra"
    ],
    "name:fra_x_preferred":[
        "Sierra Maestra"
    ],
    "name:glg_x_preferred":[
        "Sierra Maestra"
    ],
    "name:heb_x_preferred":[
        "\u05e1\u05d9\u05d9\u05e8\u05d4 \u05de\u05d0\u05e1\u05d8\u05e8\u05d4"
    ],
    "name:ind_x_preferred":[
        "Sierra Maestra"
    ],
    "name:ita_x_preferred":[
        "Sierra Maestra"
    ],
    "name:jpn_x_preferred":[
        "\u30de\u30a8\u30b9\u30c8\u30e9\u5c71\u8108"
    ],
    "name:kat_x_preferred":[
        "\u10e1\u10d8\u10d4\u10e0\u10d0-\u10db\u10d0\u10d4\u10e1\u10e2\u10e0\u10d0"
    ],
    "name:lit_x_preferred":[
        "Siera Maestra"
    ],
    "name:nld_x_preferred":[
        "Sierra Maestra"
    ],
    "name:nor_x_preferred":[
        "Sierra Maestra"
    ],
    "name:oss_x_preferred":[
        "\u0421\u044c\u0435\u0440\u0440\u0430-\u041c\u0430\u044d\u0441\u0442\u0440\u00e6"
    ],
    "name:pol_x_preferred":[
        "Sierra Maestra"
    ],
    "name:por_x_preferred":[
        "Serra Maestra"
    ],
    "name:rus_x_preferred":[
        "\u0421\u044c\u0435\u0440\u0440\u0430-\u041c\u0430\u044d\u0441\u0442\u0440\u0430"
    ],
    "name:slk_x_preferred":[
        "Sierra Maestra"
    ],
    "name:spa_x_preferred":[
        "Sierra Maestra"
    ],
    "name:swe_x_preferred":[
        "Sierra Maestra"
    ],
    "name:tur_x_preferred":[
        "Sierra Maestra Da\u011f\u0131"
    ],
    "name:ukr_x_preferred":[
        "\u0421\u044c\u0454\u0440\u0440\u0430-\u041c\u0430\u0435\u0441\u0442\u0440\u0430"
    ],
    "name:und_x_variant":[
        "Reparto Sierra Maestra"
    ],
    "name:vec_x_preferred":[
        "Sierra Maestra"
    ],
    "name:vie_x_preferred":[
        "Sierra Maestra"
    ],
    "name:zho_x_preferred":[
        "\u9a6c\u57c3\u65af\u7279\u814a\u5c71\u8109"
    ],
    "wof:name":"Sierra Maestra",
    "wof:placetype":"locality"
},
  "geometry": {"coordinates":[-82.35638,22.96858],"type":"Point"}
}