{
  "type": "Feature",
  "properties": {
    "gn:admin1_code":"03",
    "gn:asciiname":"Caobas",
    "gn:country_code":"CU",
    "gn:dem":78,
    "gn:feature_class":"P",
    "gn:feature_code":"PPL",
    "gn:name":"Caobas",
    "gn:population":0,
    "gn:timezone":"America/Havana",
    "iso:country":"CU",
    "name:spa_x_preferred":[
        "Caobas"
    ],
    "wof:name":"Caobas",
    "wof:placetype":"locality"
},
  "geometry": {"coordinates":[-81.44778000000002,22.93656],"type":"Point"}
}