{
  "type": "Feature",
  "properties": {
    "gn:admin1_code":"10",
    "gn:asciiname":"Ullao",
    "gn:country_code":"CU",
    "gn:dem":40,
    "gn:feature_class":"P",
    "gn:feature_code":"PPL",
    "gn:name":"Ullao",
    "gn:population":0,
    "gn:timezone":"America/Havana",
    "iso:country":"CU",
    "name:spa_x_preferred":[
        "Ullao"
    ],
    "wof:name":"Ullao",
    "wof:placetype":"locality"
},
  "geometry": {"coordinates":[-75.32046,19.98917],"type":"Point"}
}