{
  "type": "Feature",
  "properties": {
    "gn:admin1_code":"16",
    "gn:asciiname":"La Bandolera",
    "gn:country_code":"CU",
    "gn:dem":689,
    "gn:feature_class":"P",
    "gn:feature_code":"PPLL",
    "gn:name":"La Bandolera",
    "gn:population":0,
    "gn:timezone":"America/Havana",
    "iso:country":"CU",
    "wof:name":"La Bandolera",
    "wof:placetype":"locality"
},
  "geometry": {"coordinates":[-80.03333000000001,21.95],"type":"Point"}
}