{
  "type": "Feature",
  "properties": {
    "gn:admin1_code":"01",
    "gn:asciiname":"Las Taironas",
    "gn:cc2":"CU",
    "gn:country_code":"CU",
    "gn:dem":35,
    "gn:feature_class":"P",
    "gn:feature_code":"PPLL",
    "gn:name":"Las Taironas",
    "gn:population":0,
    "gn:timezone":"America/Havana",
    "iso:country":"CU",
    "name:und_x_variant":[
        "Taironas",
        "Tairona",
        "Las Taironas"
    ],
    "wof:name":"Las Taironas",
    "wof:placetype":"locality"
},
  "geometry": {"coordinates":[-83.66667,22.35],"type":"Point"}
}