{
  "type": "Feature",
  "properties": {
    "gn:admin1_code":"01",
    "gn:asciiname":"La Julia",
    "gn:country_code":"CU",
    "gn:dem":38,
    "gn:feature_class":"P",
    "gn:feature_code":"PPLL",
    "gn:name":"La Julia",
    "gn:population":0,
    "gn:timezone":"America/Havana",
    "iso:country":"CU",
    "name:ceb_x_preferred":[
        "La Julia"
    ],
    "name:swe_x_preferred":[
        "La Julia"
    ],
    "name:urd_x_preferred":[
        "\u0644\u0627 \u062c\u0648\u0644\u06cc\u0627"
    ],
    "wof:name":"La Julia",
    "wof:placetype":"locality"
},
  "geometry": {"coordinates":[-83.65000000000001,22.31667],"type":"Point"}
}