{
  "type": "Feature",
  "properties": {
    "gn:admin1_code":"05",
    "gn:asciiname":"Los Toros",
    "gn:country_code":"CU",
    "gn:dem":50,
    "gn:feature_class":"P",
    "gn:feature_code":"PPL",
    "gn:name":"Los Toros",
    "gn:population":0,
    "gn:timezone":"America/Havana",
    "iso:country":"CU",
    "name:spa_x_preferred":[
        "Los Toros"
    ],
    "wof:name":"Los Toros",
    "wof:placetype":"locality"
},
  "geometry": {"coordinates":[-78.16575,21.11965],"type":"Point"}
}