{
  "type": "Feature",
  "properties": {
    "gn:admin1_code":"14",
    "gn:asciiname":"Loma del Perico",
    "gn:country_code":"CU",
    "gn:dem":143,
    "gn:feature_class":"P",
    "gn:feature_code":"PPL",
    "gn:name":"Loma del Perico",
    "gn:population":0,
    "gn:timezone":"America/Havana",
    "iso:country":"CU",
    "name:spa_x_preferred":[
        "Loma del Perico"
    ],
    "wof:name":"Loma del Perico",
    "wof:placetype":"locality"
},
  "geometry": {"coordinates":[-79.4881,22.08908],"type":"Point"}
}