{
  "type": "Feature",
  "properties": {
    "gn:admin1_code":"AR",
    "gn:asciiname":"El Canonero",
    "gn:country_code":"CU",
    "gn:dem":6,
    "gn:feature_class":"P",
    "gn:feature_code":"PPLL",
    "gn:name":"El Ca\u00f1onero",
    "gn:population":0,
    "gn:timezone":"America/Havana",
    "iso:country":"CU",
    "name:spa_x_preferred":[
        "El Ca\u00f1onero"
    ],
    "wof:name":"El Canonero",
    "wof:placetype":"locality"
},
  "geometry": {"coordinates":[-82.55745,22.76128],"type":"Point"}
}