{
  "type": "Feature",
  "properties": {
    "gn:admin1_code":"16",
    "gn:asciiname":"Progreso",
    "gn:country_code":"CU",
    "gn:dem":221,
    "gn:feature_class":"P",
    "gn:feature_code":"PPLL",
    "gn:name":"Progreso",
    "gn:population":0,
    "gn:timezone":"America/Havana",
    "iso:country":"CU",
    "name:cat_x_preferred":[
        "Progreso"
    ],
    "name:ceb_x_preferred":[
        "Progreso"
    ],
    "name:deu_x_preferred":[
        "Progreso"
    ],
    "name:epo_x_preferred":[
        "Progreso"
    ],
    "name:fra_x_preferred":[
        "Progreso"
    ],
    "name:ina_x_preferred":[
        "Progreso"
    ],
    "name:jpn_x_preferred":[
        "\u30d7\u30ed\u30b0\u30ec\u30c3\u30bd"
    ],
    "name:nds_x_preferred":[
        "Progreso"
    ],
    "name:nld_x_preferred":[
        "Progreso"
    ],
    "name:pol_x_preferred":[
        "Progreso"
    ],
    "name:por_x_preferred":[
        "Progreso"
    ],
    "name:rus_x_preferred":[
        "\u041f\u0440\u043e\u0433\u0440\u0435\u0441\u043e"
    ],
    "name:sco_x_preferred":[
        "Progreso"
    ],
    "name:spa_x_preferred":[
        "Progreso"
    ],
    "name:srp_x_preferred":[
        "\u041f\u0440\u043e\u0433\u0440\u0435\u0441\u043e"
    ],
    "name:swe_x_preferred":[
        "Progreso"
    ],
    "wof:name":"Progreso",
    "wof:placetype":"locality"
},
  "geometry": {"coordinates":[-79.91667,22.25],"type":"Point"}
}