{
  "type": "Feature",
  "properties": {
    "gn:admin1_code":"16",
    "gn:asciiname":"Progreso",
    "gn:country_code":"CU",
    "gn:dem":221,
    "gn:feature_class":"P",
    "gn:feature_code":"PPLL",
    "gn:name":"Progreso",
    "gn:population":0,
    "gn:timezone":"America/Havana",
    "iso:country":"CU",
    "wof:name":"Progreso",
    "wof:placetype":"locality"
},
  "geometry": {"coordinates":[-79.91667,22.25],"type":"Point"}
}