{
  "type": "Feature",
  "properties": {
    "gn:admin1_code":"13",
    "gn:asciiname":"Botijal",
    "gn:country_code":"CU",
    "gn:dem":67,
    "gn:feature_class":"P",
    "gn:feature_code":"PPLL",
    "gn:name":"Botijal",
    "gn:population":0,
    "gn:timezone":"America/Havana",
    "iso:country":"CU",
    "name:spa_x_preferred":[
        "Botijal"
    ],
    "wof:name":"Botijal",
    "wof:placetype":"locality"
},
  "geometry": {"coordinates":[-77.62319000000002,20.87176],"type":"Point"}
}