{
  "type": "Feature",
  "properties": {
    "gn:admin1_code":"03",
    "gn:asciiname":"Quemado Grande",
    "gn:country_code":"CU",
    "gn:dem":12,
    "gn:feature_class":"P",
    "gn:feature_code":"PPLL",
    "gn:name":"Quemado Grande",
    "gn:population":0,
    "gn:timezone":"America/Havana",
    "iso:country":"CU",
    "name:spa_x_preferred":[
        "Quemado Grande"
    ],
    "wof:name":"Quemado Grande",
    "wof:placetype":"locality"
},
  "geometry": {"coordinates":[-81.42984,22.40121],"type":"Point"}
}