{
  "type": "Feature",
  "properties": {
    "gn:country":"CU",
    "gn:fcode":"PPL",
    "gn:pop":15268,
    "iso:country":"CU",
    "name:deu_x_preferred":[
        "Baragu\u00e1"
    ],
    "name:eng_x_preferred":[
        "Baragu\u00e1"
    ],
    "name:fra_x_preferred":[
        "Baragu\u00e1"
    ],
    "name:ita_x_preferred":[
        "Baragu\u00e1"
    ],
    "name:kat_x_preferred":[
        "\u10d1\u10d0\u10e0\u10d0\u10d2\u10e3\u10d0"
    ],
    "name:nld_x_preferred":[
        "Baragu\u00e1"
    ],
    "name:pol_x_preferred":[
        "Baragu\u00e1"
    ],
    "name:swe_x_preferred":[
        "Baragu\u00e1"
    ],
    "name:ukr_x_preferred":[
        "\u0411\u0430\u0440\u0430\u0491\u0443\u0430"
    ],
    "name:vie_x_preferred":[
        "Baragu\u00e1"
    ],
    "name:zho_x_preferred":[
        "\u5df4\u62c9\u74dc"
    ],
    "qs:name":"Baragu\u00e1",
    "qs:photos_9r":0,
    "qs:photos_sr":0,
    "qs:pop_sr":"6",
    "wd:wordcount":137,
    "wof:name":"Baragu\u00e1",
    "wof:placetype":"locality",
    "wof:population":15268
},
  "geometry": {"coordinates":[-78.63278,21.69667],"type":"Point"}
}