{
  "type": "Feature",
  "properties": {
    "gn:admin1_code":"10",
    "gn:asciiname":"La Aguada de la Palma",
    "gn:country_code":"CU",
    "gn:dem":80,
    "gn:feature_class":"P",
    "gn:feature_code":"PPL",
    "gn:name":"La Aguada de la Palma",
    "gn:population":0,
    "gn:timezone":"America/Havana",
    "iso:country":"CU",
    "name:spa_x_preferred":[
        "La Aguada de la Palma"
    ],
    "wof:name":"La Aguada de la Palma",
    "wof:placetype":"locality"
},
  "geometry": {"coordinates":[-74.85486,20.06148],"type":"Point"}
}