{
  "type": "Feature",
  "properties": {
    "gn:admin1_code":"14",
    "gn:asciiname":"El Mamey",
    "gn:country_code":"CU",
    "gn:dem":21,
    "gn:feature_class":"P",
    "gn:feature_code":"PPLL",
    "gn:name":"El Mamey",
    "gn:population":0,
    "gn:timezone":"America/Havana",
    "iso:country":"CU",
    "wof:name":"El Mamey",
    "wof:placetype":"locality"
},
  "geometry": {"coordinates":[-79.41667,21.75],"type":"Point"}
}