{
  "type": "Feature",
  "properties": {
    "gn:admin1_code":"08",
    "gn:asciiname":"Nuestra Senora de Belen",
    "gn:country_code":"CU",
    "gn:dem":47,
    "gn:feature_class":"P",
    "gn:feature_code":"PPLL",
    "gn:name":"Nuestra Se\u00f1ora de Bel\u00e9n",
    "gn:population":0,
    "gn:timezone":"America/Havana",
    "iso:country":"CU",
    "wof:name":"Nuestra Senora de Belen",
    "wof:placetype":"locality"
},
  "geometry": {"coordinates":[-80.76666999999998,22.38333],"type":"Point"}
}