{
  "type": "Feature",
  "properties": {
    "gn:admin1_code":"01",
    "gn:asciiname":"Numero Cuatro",
    "gn:cc2":"CU",
    "gn:country_code":"CU",
    "gn:dem":46,
    "gn:feature_class":"P",
    "gn:feature_code":"PPLL",
    "gn:name":"N\u00famero Cuatro",
    "gn:population":0,
    "gn:timezone":"America/Havana",
    "iso:country":"CU",
    "name:und_x_variant":[
        "N\u00famero 4",
        "N\u00famero Cuatro"
    ],
    "wof:name":"Numero Cuatro",
    "wof:placetype":"locality"
},
  "geometry": {"coordinates":[-83.59999999999999,22.48333],"type":"Point"}
}