{
  "type": "Feature",
  "properties": {
    "gn:admin1_code":"MA",
    "gn:asciiname":"Boris Luis Santa Coloma",
    "gn:country_code":"CU",
    "gn:dem":168,
    "gn:feature_class":"P",
    "gn:feature_code":"PPL",
    "gn:name":"Boris Luis Santa Coloma",
    "gn:population":0,
    "gn:timezone":"America/Havana",
    "iso:country":"CU",
    "name:spa_x_preferred":[
        "Boris Luis Santa Coloma"
    ],
    "wof:name":"Boris Luis Santa Coloma",
    "wof:placetype":"locality"
},
  "geometry": {"coordinates":[-81.87461999999999,22.90806],"type":"Point"}
}