{
  "type": "Feature",
  "properties": {
    "gn:admin1_code":"12",
    "gn:asciiname":"Cantarrana",
    "gn:country_code":"CU",
    "gn:dem":125,
    "gn:feature_class":"P",
    "gn:feature_code":"PPL",
    "gn:name":"Cantarrana",
    "gn:population":0,
    "gn:timezone":"America/Havana",
    "iso:country":"CU",
    "name:spa_x_preferred":[
        "Cantarrana"
    ],
    "wof:name":"Cantarrana",
    "wof:placetype":"locality"
},
  "geometry": {"coordinates":[-75.27004000000002,20.57398],"type":"Point"}
}