{
  "type": "Feature",
  "properties": {
    "gn:admin1_code":"09",
    "gn:asciiname":"La Pimienta",
    "gn:country_code":"CU",
    "gn:dem":194,
    "gn:feature_class":"P",
    "gn:feature_code":"PPL",
    "gn:name":"La Pimienta",
    "gn:population":0,
    "gn:timezone":"America/Havana",
    "iso:country":"CU",
    "name:spa_x_preferred":[
        "La Pimienta"
    ],
    "wof:name":"La Pimienta",
    "wof:placetype":"locality"
},
  "geometry": {"coordinates":[-77.41133000000001,19.95497],"type":"Point"}
}