{
  "type": "Feature",
  "properties": {
    "gn:admin1_code":"03",
    "gn:asciiname":"Santa Isabel",
    "gn:country_code":"CU",
    "gn:dem":29,
    "gn:feature_class":"P",
    "gn:feature_code":"PPLL",
    "gn:name":"Santa Isabel",
    "gn:population":0,
    "gn:timezone":"America/Havana",
    "iso:country":"CU",
    "wof:name":"Santa Isabel",
    "wof:placetype":"locality"
},
  "geometry": {"coordinates":[-81.12139000000001,22.87306],"type":"Point"}
}