{
  "type": "Feature",
  "properties": {
    "gn:admin1_code":"01",
    "gn:asciiname":"El Tomas",
    "gn:country_code":"CU",
    "gn:dem":25,
    "gn:feature_class":"P",
    "gn:feature_code":"PPLL",
    "gn:name":"El Tom\u00e1s",
    "gn:population":0,
    "gn:timezone":"America/Havana",
    "iso:country":"CU",
    "name:spa_x_preferred":[
        "El Tom\u00e1s"
    ],
    "wof:name":"El Tomas",
    "wof:placetype":"locality"
},
  "geometry": {"coordinates":[-83.52628,22.42455],"type":"Point"}
}