{
  "type": "Feature",
  "properties": {
    "gn:admin1_code":"10",
    "gn:asciiname":"Lagunita Abajo",
    "gn:country_code":"CU",
    "gn:dem":272,
    "gn:feature_class":"P",
    "gn:feature_code":"PPL",
    "gn:name":"Lagunita Abajo",
    "gn:population":0,
    "gn:timezone":"America/Havana",
    "iso:country":"CU",
    "name:spa_x_preferred":[
        "Lagunita Abajo"
    ],
    "wof:name":"Lagunita Abajo",
    "wof:placetype":"locality"
},
  "geometry": {"coordinates":[-74.5476,20.1757],"type":"Point"}
}