{
  "type": "Feature",
  "properties": {
    "gn:admin1_code":"03",
    "gn:asciiname":"Cuabalejo",
    "gn:country_code":"CU",
    "gn:dem":72,
    "gn:feature_class":"P",
    "gn:feature_code":"PPLL",
    "gn:name":"Cuabalejo",
    "gn:population":0,
    "gn:timezone":"America/Havana",
    "iso:country":"CU",
    "wof:name":"Cuabalejo",
    "wof:placetype":"locality"
},
  "geometry": {"coordinates":[-81.26666999999998,22.88333],"type":"Point"}
}