{
  "type": "Feature",
  "properties": {
    "gn:admin1_code":"16",
    "gn:asciiname":"Guayabo Nuevo",
    "gn:country_code":"CU",
    "gn:dem":90,
    "gn:feature_class":"P",
    "gn:feature_code":"PPL",
    "gn:name":"Guayabo Nuevo",
    "gn:population":0,
    "gn:timezone":"America/Havana",
    "iso:country":"CU",
    "name:spa_x_preferred":[
        "Guayabo Nuevo"
    ],
    "name:und_x_variant":[
        "Guayabo"
    ],
    "wof:name":"Guayabo Nuevo",
    "wof:placetype":"locality"
},
  "geometry": {"coordinates":[-80.42421999999998,22.82378],"type":"Point"}
}