{
  "type": "Feature",
  "properties": {
    "gn:admin1_code":"12",
    "gn:asciiname":"Jucaral",
    "gn:country_code":"CU",
    "gn:dem":19,
    "gn:feature_class":"P",
    "gn:feature_code":"PPL",
    "gn:name":"Jucaral",
    "gn:population":0,
    "gn:timezone":"America/Havana",
    "iso:country":"CU",
    "name:spa_x_preferred":[
        "Jucaral"
    ],
    "wof:name":"Jucaral",
    "wof:placetype":"locality"
},
  "geometry": {"coordinates":[-76.05747,21.0623],"type":"Point"}
}