{
  "type": "Feature",
  "properties": {
    "gn:admin1_code":"15",
    "gn:asciiname":"Manuelico",
    "gn:country_code":"CU",
    "gn:dem":29,
    "gn:feature_class":"P",
    "gn:feature_code":"PPL",
    "gn:name":"Manuelico",
    "gn:population":0,
    "gn:timezone":"America/Havana",
    "iso:country":"CU",
    "name:und_x_variant":[
        "Manuelica",
        "Manuelico"
    ],
    "wof:name":"Manuelico",
    "wof:placetype":"locality"
},
  "geometry": {"coordinates":[-76.12566,19.9881],"type":"Point"}
}