{
  "type": "Feature",
  "properties": {
    "gn:admin1_code":"13",
    "gn:asciiname":"San Miguel de Manati",
    "gn:country_code":"CU",
    "gn:dem":17,
    "gn:feature_class":"P",
    "gn:feature_code":"PPL",
    "gn:name":"San Miguel de Manat\u00ed",
    "gn:population":0,
    "gn:timezone":"America/Havana",
    "iso:country":"CU",
    "wof:name":"San Miguel de Manati",
    "wof:placetype":"locality"
},
  "geometry": {"coordinates":[-76.88056,21.225],"type":"Point"}
}