{
  "type": "Feature",
  "properties": {
    "gn:admin1_code":"13",
    "gn:asciiname":"Chaparrita",
    "gn:country_code":"CU",
    "gn:dem":18,
    "gn:feature_class":"P",
    "gn:feature_code":"PPL",
    "gn:name":"Chaparrita",
    "gn:population":0,
    "gn:timezone":"America/Havana",
    "iso:country":"CU",
    "name:spa_x_preferred":[
        "Chaparrita"
    ],
    "wof:name":"Chaparrita",
    "wof:placetype":"locality"
},
  "geometry": {"coordinates":[-76.48087,21.14854],"type":"Point"}
}