{
  "type": "Feature",
  "properties": {
    "gn:admin1_code":"10",
    "gn:asciiname":"La Alegria",
    "gn:country_code":"CU",
    "gn:dem":46,
    "gn:feature_class":"P",
    "gn:feature_code":"PPL",
    "gn:name":"La Alegr\u00eda",
    "gn:population":0,
    "gn:timezone":"America/Havana",
    "iso:country":"CU",
    "name:spa_x_preferred":[
        "La Alegr\u00eda"
    ],
    "wof:name":"La Alegria",
    "wof:placetype":"locality"
},
  "geometry": {"coordinates":[-74.4222,20.2725],"type":"Point"}
}