{
  "type": "Feature",
  "properties": {
    "gn:admin1_code":"08",
    "gn:asciiname":"Los Guaos",
    "gn:country_code":"CU",
    "gn:dem":63,
    "gn:feature_class":"P",
    "gn:feature_code":"PPL",
    "gn:name":"Los Guaos",
    "gn:population":0,
    "gn:timezone":"America/Havana",
    "iso:country":"CU",
    "name:spa_x_preferred":[
        "Los Guaos"
    ],
    "wof:name":"Los Guaos",
    "wof:placetype":"locality"
},
  "geometry": {"coordinates":[-80.33313000000003,22.41329],"type":"Point"}
}