{
  "type": "Feature",
  "properties": {
    "gn:admin1_code":"03",
    "gn:asciiname":"Echeverria",
    "gn:country_code":"CU",
    "gn:dem":57,
    "gn:feature_class":"P",
    "gn:feature_code":"PPL",
    "gn:name":"Echeverr\u00eda",
    "gn:population":0,
    "gn:timezone":"America/Havana",
    "iso:country":"CU",
    "name:spa_x_preferred":[
        "Echeverr\u00eda"
    ],
    "name:und_x_variant":[
        "Nueva Echevarria",
        "Eschevarria",
        "Echevarria",
        "Hechevarr\u00eda"
    ],
    "wof:name":"Echeverria",
    "wof:placetype":"locality"
},
  "geometry": {"coordinates":[-80.89596999999998,22.78583],"type":"Point"}
}