{
  "type": "Feature",
  "properties": {
    "gn:admin1_code":"07",
    "gn:asciiname":"Monte Malo",
    "gn:country_code":"CU",
    "gn:dem":9,
    "gn:feature_class":"P",
    "gn:feature_code":"PPL",
    "gn:name":"Monte Malo",
    "gn:population":0,
    "gn:timezone":"America/Havana",
    "iso:country":"CU",
    "name:spa_x_preferred":[
        "Monte Malo"
    ],
    "wof:name":"Monte Malo",
    "wof:placetype":"locality"
},
  "geometry": {"coordinates":[-78.25263000000002,22.09727],"type":"Point"}
}