{
  "type": "Feature",
  "properties": {
    "gn:admin1_code":"03",
    "gn:asciiname":"Buenaventura",
    "gn:country_code":"CU",
    "gn:dem":172,
    "gn:feature_class":"P",
    "gn:feature_code":"PPLL",
    "gn:name":"Buenaventura",
    "gn:population":0,
    "gn:timezone":"America/Havana",
    "iso:country":"CU",
    "wof:name":"Buenaventura",
    "wof:placetype":"locality"
},
  "geometry": {"coordinates":[-81.43333,22.83333],"type":"Point"}
}