{
  "type": "Feature",
  "properties": {
    "gn:admin1_code":"03",
    "gn:asciiname":"Buenaventura",
    "gn:country_code":"CU",
    "gn:dem":172,
    "gn:feature_class":"P",
    "gn:feature_code":"PPLL",
    "gn:name":"Buenaventura",
    "gn:population":0,
    "gn:timezone":"America/Havana",
    "iso:country":"CU",
    "name:cat_x_preferred":[
        "Buenaventura"
    ],
    "name:ceb_x_preferred":[
        "Buenaventura"
    ],
    "name:deu_x_preferred":[
        "Buenaventura"
    ],
    "name:fin_x_preferred":[
        "Buenaventura"
    ],
    "name:fra_x_preferred":[
        "Buenaventura"
    ],
    "name:heb_x_preferred":[
        "\u05d1\u05d5\u05d0\u05e0\u05d5\u05d5\u05e0\u05d8\u05d5\u05e8\u05d4"
    ],
    "name:hun_x_preferred":[
        "Buenaventura"
    ],
    "name:ita_x_preferred":[
        "Buenaventura"
    ],
    "name:mlg_x_preferred":[
        "Buenaventura"
    ],
    "name:nds_x_preferred":[
        "Buenaventura"
    ],
    "name:nld_x_preferred":[
        "Buenaventura"
    ],
    "name:pol_x_preferred":[
        "Buenaventura"
    ],
    "name:por_x_preferred":[
        "Buenaventura"
    ],
    "name:rus_x_preferred":[
        "\u0411\u0443\u044d\u043d\u0430\u0432\u0435\u043d\u0442\u0443\u0440\u0430"
    ],
    "name:sco_x_preferred":[
        "Buenaventura"
    ],
    "name:spa_x_preferred":[
        "Buenaventura"
    ],
    "name:srp_x_preferred":[
        "\u0411\u0443\u0435\u043d\u0430\u0432\u0435\u043d\u0442\u0443\u0440\u0430"
    ],
    "name:swe_x_preferred":[
        "Buenaventura"
    ],
    "name:ukr_x_preferred":[
        "\u0411\u0443\u0435\u043d\u0430\u0432\u0435\u043d\u0442\u0443\u0440\u0430"
    ],
    "wof:name":"Buenaventura",
    "wof:placetype":"locality"
},
  "geometry": {"coordinates":[-81.43333,22.83333],"type":"Point"}
}