{
  "type": "Feature",
  "properties": {
    "gn:admin1_code":"09",
    "gn:asciiname":"Panama",
    "gn:country_code":"CU",
    "gn:dem":154,
    "gn:feature_class":"P",
    "gn:feature_code":"PPL",
    "gn:name":"Panam\u00e1",
    "gn:population":0,
    "gn:timezone":"America/Havana",
    "iso:country":"CU",
    "name:spa_x_preferred":[
        "Panam\u00e1"
    ],
    "wof:name":"Panama",
    "wof:placetype":"locality"
},
  "geometry": {"coordinates":[-77.12505,20.05794],"type":"Point"}
}