{
  "type": "Feature",
  "properties": {
    "gn:admin1_code":"MA",
    "gn:asciiname":"Carmen Osua",
    "gn:country_code":"CU",
    "gn:dem":146,
    "gn:feature_class":"P",
    "gn:feature_code":"PPLL",
    "gn:name":"Carmen Osua",
    "gn:population":0,
    "gn:timezone":"America/Havana",
    "iso:country":"CU",
    "name:spa_x_preferred":[
        "Carmen Osua"
    ],
    "name:und_x_variant":[
        "El Carmen",
        "Carmen"
    ],
    "wof:name":"Carmen Osua",
    "wof:placetype":"locality"
},
  "geometry": {"coordinates":[-82.11211999999998,22.89276],"type":"Point"}
}