{
  "type": "Feature",
  "properties": {
    "gn:admin1_code":"02",
    "gn:asciiname":"Leader",
    "gn:cc2":"CU",
    "gn:country_code":"CU",
    "gn:dem":99,
    "gn:feature_class":"P",
    "gn:feature_code":"PPLL",
    "gn:name":"Leader",
    "gn:population":0,
    "gn:timezone":"America/Havana",
    "iso:country":"CU",
    "name:und_x_variant":[
        "Leeder",
        "Leader"
    ],
    "wof:name":"Leader",
    "wof:placetype":"locality"
},
  "geometry": {"coordinates":[-82.25,23.03333],"type":"Point"}
}