{
  "type": "Feature",
  "properties": {
    "gn:admin1_code":"10",
    "gn:asciiname":"Chafarina",
    "gn:country_code":"CU",
    "gn:dem":429,
    "gn:feature_class":"P",
    "gn:feature_code":"PPL",
    "gn:name":"Chafarina",
    "gn:population":0,
    "gn:timezone":"America/Havana",
    "iso:country":"CU",
    "name:spa_x_preferred":[
        "Chafarina"
    ],
    "wof:name":"Chafarina",
    "wof:placetype":"locality"
},
  "geometry": {"coordinates":[-74.24684999999999,20.16681],"type":"Point"}
}