{
  "type": "Feature",
  "properties": {
    "gn:admin1_code":"12",
    "gn:asciiname":"Tumbadero",
    "gn:country_code":"CU",
    "gn:dem":18,
    "gn:feature_class":"P",
    "gn:feature_code":"PPL",
    "gn:name":"Tumbadero",
    "gn:population":0,
    "gn:timezone":"America/Havana",
    "iso:country":"CU",
    "name:spa_x_preferred":[
        "Tumbadero"
    ],
    "wof:name":"Tumbadero",
    "wof:placetype":"locality"
},
  "geometry": {"coordinates":[-75.97093000000002,21.0706],"type":"Point"}
}