{
  "type": "Feature",
  "properties": {
    "gn:admin1_code":"16",
    "gn:asciiname":"Frescura",
    "gn:country_code":"CU",
    "gn:dem":11,
    "gn:feature_class":"P",
    "gn:feature_code":"PPLL",
    "gn:name":"Frescura",
    "gn:population":0,
    "gn:timezone":"America/Havana",
    "iso:country":"CU",
    "name:spa_x_preferred":[
        "Frescura"
    ],
    "wof:name":"Frescura",
    "wof:placetype":"locality"
},
  "geometry": {"coordinates":[-79.61256999999998,22.55577000000001],"type":"Point"}
}