{
  "type": "Feature",
  "properties": {
    "iso:country":"CU",
    "name:chi_x_preferred":[
        "\u57c3\u65af\u6885\u62c9\u9054"
    ],
    "name:dut_x_preferred":[
        "Esmeralda"
    ],
    "name:eng_x_preferred":[
        "Esmeralda"
    ],
    "name:epo_x_preferred":[
        "Esmeralda"
    ],
    "name:fre_x_preferred":[
        "Esmeralda"
    ],
    "name:geo_x_preferred":[
        "\u10d4\u10e1\u10db\u10d4\u10e0\u10d0\u10da\u10d3\u10d0"
    ],
    "name:ger_x_preferred":[
        "Esmeralda"
    ],
    "name:ita_x_preferred":[
        "Esmeralda"
    ],
    "name:kat_x_preferred":[
        "\u10d4\u10e1\u10db\u10d4\u10e0\u10d0\u10da\u10d3\u10d0"
    ],
    "name:rus_x_preferred":[
        "\u042d\u0441\u043c\u0435\u0440\u0430\u043b\u044c\u0434\u0430"
    ],
    "name:spa_x_preferred":[
        "Esmeralda"
    ],
    "name:swe_x_preferred":[
        "Municipio de Esmeralda"
    ],
    "name:tur_x_preferred":[
        "Esmeralda"
    ],
    "name:unk_x_variant":[
        "La Esmeralda"
    ],
    "name:vie_x_preferred":[
        "Esmeralda"
    ],
    "name:zho_x_preferred":[
        "\u57c3\u65af\u6885\u62c9\u9054"
    ],
    "qs:gn_country":"CU",
    "qs:gn_fcode":"PPL",
    "qs:gn_pop":20274,
    "qs:name":"Esmeralda",
    "qs:name_adm0":"Cuba",
    "qs:name_adm1":"Camaguey",
    "qs:photos":0,
    "qs:photos_1k":0,
    "qs:photos_9k":0,
    "qs:photos_9r":0,
    "qs:photos_all":0,
    "qs:photos_sr":0,
    "qs:placetype":"Town",
    "qs:pop_sr":"7",
    "qs:woe_adm0":23424793,
    "wof:name":"Esmeralda",
    "wof:placetype":"locality",
    "wof:population":20274
},
  "geometry": {"coordinates":[-78.11694,21.8525],"type":"Point"}
}