{
  "type": "Feature",
  "properties": {
    "gn:admin1_code":"03",
    "gn:asciiname":"Cayo Ramona",
    "gn:country_code":"CU",
    "gn:dem":7,
    "gn:feature_class":"P",
    "gn:feature_code":"PPL",
    "gn:name":"Cayo Ramona",
    "gn:population":0,
    "gn:timezone":"America/Havana",
    "iso:country":"CU",
    "name:spa_x_preferred":[
        "Cayo Ramona"
    ],
    "wof:name":"Cayo Ramona",
    "wof:placetype":"locality"
},
  "geometry": {"coordinates":[-81.01886,22.14095],"type":"Point"}
}