{
  "type": "Feature",
  "properties": {
    "gn:admin1_code":"MA",
    "gn:asciiname":"Tienda San Blas",
    "gn:country_code":"CU",
    "gn:dem":101,
    "gn:feature_class":"P",
    "gn:feature_code":"PPLL",
    "gn:name":"Tienda San Blas",
    "gn:population":0,
    "gn:timezone":"America/Havana",
    "iso:country":"CU",
    "wof:name":"Tienda San Blas",
    "wof:placetype":"locality"
},
  "geometry": {"coordinates":[-81.89166999999998,22.87194],"type":"Point"}
}