{
  "type": "Feature",
  "properties": {
    "gn:admin1_code":"08",
    "gn:asciiname":"Santa Felicia",
    "gn:country_code":"CU",
    "gn:dem":25,
    "gn:feature_class":"P",
    "gn:feature_code":"PPLL",
    "gn:name":"Santa Felicia",
    "gn:population":0,
    "gn:timezone":"America/Havana",
    "iso:country":"CU",
    "name:und_x_variant":[
        "Santa Felicita",
        "Santa Felicia"
    ],
    "wof:name":"Santa Felicia",
    "wof:placetype":"locality"
},
  "geometry": {"coordinates":[-80.86521999999999,22.41317],"type":"Point"}
}