{
  "type": "Feature",
  "properties": {
    "gn:admin1_code":"05",
    "gn:asciiname":"Estero del Vicioso",
    "gn:country_code":"CU",
    "gn:dem":0,
    "gn:feature_class":"P",
    "gn:feature_code":"PPLL",
    "gn:name":"Estero del Vicioso",
    "gn:population":0,
    "gn:timezone":"America/Havana",
    "iso:country":"CU",
    "name:spa_x_preferred":[
        "Estero del Vicioso"
    ],
    "wof:name":"Estero del Vicioso",
    "wof:placetype":"locality"
},
  "geometry": {"coordinates":[-77.90000000000001,21.88333],"type":"Point"}
}