{
  "type": "Feature",
  "properties": {
    "gn:admin1_code":"AR",
    "gn:asciiname":"Godinez",
    "gn:country_code":"CU",
    "gn:dem":17,
    "gn:feature_class":"P",
    "gn:feature_code":"PPL",
    "gn:name":"Godinez",
    "gn:population":0,
    "gn:timezone":"America/Havana",
    "iso:country":"CU",
    "name:spa_x_preferred":[
        "Godinez"
    ],
    "wof:name":"Godinez",
    "wof:placetype":"locality"
},
  "geometry": {"coordinates":[-82.55523000000002,23.0436],"type":"Point"}
}