{
  "type": "Feature",
  "properties": {
    "gn:admin1_code":"13",
    "gn:asciiname":"Pintado",
    "gn:cc2":"CU",
    "gn:country_code":"CU",
    "gn:dem":142,
    "gn:feature_class":"P",
    "gn:feature_code":"PPLL",
    "gn:name":"Pintado",
    "gn:population":0,
    "gn:timezone":"America/Havana",
    "iso:country":"CU",
    "name:ceb_x_preferred":[
        "Pintado"
    ],
    "name:deu_x_preferred":[
        "Pintado"
    ],
    "name:fra_x_preferred":[
        "Pintado"
    ],
    "name:jpn_x_preferred":[
        "\u30d4\u30f3\u30bf\u30fc\u30c9"
    ],
    "name:und_x_variant":[
        "La Escondida",
        "Pintado"
    ],
    "wof:name":"Pintado",
    "wof:placetype":"locality"
},
  "geometry": {"coordinates":[-76.64639,20.99278],"type":"Point"}
}