{
  "type": "Feature",
  "properties": {
    "gn:admin1_code":"14",
    "gn:asciiname":"Carbo",
    "gn:country_code":"CU",
    "gn:dem":12,
    "gn:feature_class":"P",
    "gn:feature_code":"PPLL",
    "gn:name":"Carb\u00f3",
    "gn:population":0,
    "gn:timezone":"America/Havana",
    "iso:country":"CU",
    "name:deu_x_preferred":[
        "Carbo"
    ],
    "name:nld_x_preferred":[
        "Carbo"
    ],
    "name:spa_x_preferred":[
        "Carb\u00f3"
    ],
    "name:spa_x_variant":[
        "Carbo"
    ],
    "wof:name":"Carbo",
    "wof:placetype":"locality"
},
  "geometry": {"coordinates":[-79.25763000000001,22.36627],"type":"Point"}
}