{
  "type": "Feature",
  "properties": {
    "gn:admin1_code":"12",
    "gn:asciiname":"Dobales",
    "gn:country_code":"CU",
    "gn:dem":131,
    "gn:feature_class":"P",
    "gn:feature_code":"PPL",
    "gn:name":"Dobales",
    "gn:population":0,
    "gn:timezone":"America/Havana",
    "iso:country":"CU",
    "name:spa_x_preferred":[
        "Dobales"
    ],
    "wof:name":"Dobales",
    "wof:placetype":"locality"
},
  "geometry": {"coordinates":[-76.48489000000002,20.85718],"type":"Point"}
}