{
  "type": "Feature",
  "properties": {
    "gn:admin1_code":"03",
    "gn:asciiname":"Carlos Rodriguez",
    "gn:country_code":"CU",
    "gn:dem":44,
    "gn:feature_class":"P",
    "gn:feature_code":"PPL",
    "gn:name":"Carlos Rodr\u00edguez",
    "gn:population":0,
    "gn:timezone":"America/Havana",
    "iso:country":"CU",
    "name:spa_x_preferred":[
        "Carlos Rodr\u00edguez"
    ],
    "wof:name":"Carlos Rodriguez",
    "wof:placetype":"locality"
},
  "geometry": {"coordinates":[-80.88063000000002,22.89662],"type":"Point"}
}