{
  "type": "Feature",
  "properties": {
    "gn:admin1_code":"07",
    "gn:asciiname":"Dos Hermanas",
    "gn:cc2":"CU",
    "gn:country_code":"CU",
    "gn:dem":11,
    "gn:feature_class":"P",
    "gn:feature_code":"PPLL",
    "gn:name":"Dos Hermanas",
    "gn:population":0,
    "gn:timezone":"America/Havana",
    "iso:country":"CU",
    "name:ara_x_preferred":[
        "\u062f\u0648\u0633 \u0625\u064a\u0631\u0645\u0627\u0646\u0627\u0633"
    ],
    "name:arg_x_preferred":[
        "Dos Hermanas"
    ],
    "name:ast_x_preferred":[
        "Dos Hermanas"
    ],
    "name:azb_x_preferred":[
        "\u062f\u0633 \u0627\u0631\u0645\u0627\u0646\u0627\u0633"
    ],
    "name:bul_x_preferred":[
        "\u0414\u043e\u0441 \u0415\u0440\u043c\u0430\u043d\u0430\u0441"
    ],
    "name:cat_x_preferred":[
        "Dos Hermanas"
    ],
    "name:ceb_x_preferred":[
        "Dos Hermanas"
    ],
    "name:deu_x_preferred":[
        "Dos Hermanas"
    ],
    "name:diq_x_preferred":[
        "Dos Hermanas"
    ],
    "name:epo_x_preferred":[
        "Dos Hermanas"
    ],
    "name:eus_x_preferred":[
        "Dos Hermanas"
    ],
    "name:fas_x_preferred":[
        "\u062f\u0633 \u0627\u0631\u0645\u0627\u0646\u0627\u0633"
    ],
    "name:fin_x_preferred":[
        "Dos Hermanas"
    ],
    "name:fra_x_preferred":[
        "Dos Hermanas"
    ],
    "name:gle_x_preferred":[
        "Dos Hermanas"
    ],
    "name:glg_x_preferred":[
        "Dos Hermanas"
    ],
    "name:hat_x_preferred":[
        "Dos Hermanas"
    ],
    "name:hun_x_preferred":[
        "Dos Hermanas"
    ],
    "name:hye_x_preferred":[
        "\u0534\u0578\u057d \u0537\u0580\u0574\u0561\u0576\u0561\u057d"
    ],
    "name:ind_x_preferred":[
        "Dos Hermanas"
    ],
    "name:ita_x_preferred":[
        "Dos Hermanas"
    ],
    "name:jpn_x_preferred":[
        "\u30c9\u30b9\u30fb\u30a8\u30eb\u30de\u30fc\u30ca\u30b9"
    ],
    "name:kaz_x_preferred":[
        "\u0414\u043e\u0441-\u042d\u0440\u043c\u0430\u043d\u0430\u0441"
    ],
    "name:lit_x_preferred":[
        "Dos Hermanasas"
    ],
    "name:mlg_x_preferred":[
        "Dos Hermanas"
    ],
    "name:msa_x_preferred":[
        "Dos Hermanas"
    ],
    "name:nld_x_preferred":[
        "Dos Hermanas"
    ],
    "name:nno_x_preferred":[
        "Dos Hermanas"
    ],
    "name:oci_x_preferred":[
        "Dos Hermanas"
    ],
    "name:pol_x_preferred":[
        "Dos Hermanas"
    ],
    "name:por_x_preferred":[
        "Dos Hermanas"
    ],
    "name:ron_x_preferred":[
        "Dos Hermanas"
    ],
    "name:rus_x_preferred":[
        "\u0414\u043e\u0441-\u042d\u0440\u043c\u0430\u043d\u0430\u0441"
    ],
    "name:spa_x_preferred":[
        "Dos Hermanas"
    ],
    "name:sqi_x_preferred":[
        "Dos Hermanas"
    ],
    "name:srp_x_preferred":[
        "\u0414\u043e\u0441 \u0415\u0440\u043c\u0430\u043d\u0430\u0441"
    ],
    "name:swe_x_preferred":[
        "Dos Hermanas"
    ],
    "name:tat_x_preferred":[
        "\u0414\u043e\u0441-\u042d\u0440\u043c\u0430\u043d\u0430\u0441"
    ],
    "name:tur_x_preferred":[
        "Dos Hermanas"
    ],
    "name:ukr_x_preferred":[
        "\u0414\u043e\u0441-\u0415\u0440\u043c\u0430\u043d\u0430\u0441"
    ],
    "name:und_x_variant":[
        "Dos Hermanos",
        "Dos Hermanas"
    ],
    "name:uzb_x_preferred":[
        "Dos Hermanas"
    ],
    "name:vie_x_preferred":[
        "Dos Hermanas"
    ],
    "name:war_x_preferred":[
        "Dos Hermanas"
    ],
    "name:zho_x_preferred":[
        "\u4e24\u59ca\u59b9\u9547"
    ],
    "wof:name":"Dos Hermanas",
    "wof:placetype":"locality"
},
  "geometry": {"coordinates":[-78.86111,21.68694],"type":"Point"}
}