{
  "type": "Feature",
  "properties": {
    "gn:admin1_code":"07",
    "gn:asciiname":"Dos Hermanas",
    "gn:cc2":"CU",
    "gn:country_code":"CU",
    "gn:dem":11,
    "gn:feature_class":"P",
    "gn:feature_code":"PPLL",
    "gn:name":"Dos Hermanas",
    "gn:population":0,
    "gn:timezone":"America/Havana",
    "iso:country":"CU",
    "name:und_x_variant":[
        "Dos Hermanos",
        "Dos Hermanas"
    ],
    "wof:name":"Dos Hermanas",
    "wof:placetype":"locality"
},
  "geometry": {"coordinates":[-78.86111,21.68694],"type":"Point"}
}