{
  "type": "Feature",
  "properties": {
    "gn:admin1_code":"08",
    "gn:asciiname":"Pueblo Nuevo",
    "gn:country_code":"CU",
    "gn:dem":39,
    "gn:feature_class":"P",
    "gn:feature_code":"PPL",
    "gn:name":"Pueblo Nuevo",
    "gn:population":0,
    "gn:timezone":"America/Havana",
    "iso:country":"CU",
    "name:spa_x_preferred":[
        "Pueblo Nuevo"
    ],
    "wof:name":"Pueblo Nuevo",
    "wof:placetype":"locality"
},
  "geometry": {"coordinates":[-80.37439999999999,22.19759],"type":"Point"}
}