{
  "type": "Feature",
  "properties": {
    "gn:admin1_code":"05",
    "gn:asciiname":"Entronque de Lugareno",
    "gn:country_code":"CU",
    "gn:dem":32,
    "gn:feature_class":"P",
    "gn:feature_code":"PPL",
    "gn:name":"Entronque de Lugare\u00f1o",
    "gn:population":0,
    "gn:timezone":"America/Havana",
    "iso:country":"CU",
    "name:spa_x_preferred":[
        "Entronque de Lugare\u00f1o"
    ],
    "wof:name":"Entronque de Lugareno",
    "wof:placetype":"locality"
},
  "geometry": {"coordinates":[-77.47010999999998,21.44671],"type":"Point"}
}