{
  "type": "Feature",
  "properties": {
    "gn:admin1_code":"13",
    "gn:asciiname":"Lajas",
    "gn:country_code":"CU",
    "gn:dem":61,
    "gn:feature_class":"P",
    "gn:feature_code":"PPLL",
    "gn:name":"Lajas",
    "gn:population":0,
    "gn:timezone":"America/Havana",
    "iso:country":"CU",
    "name:ceb_x_preferred":[
        "Lajas"
    ],
    "name:fra_x_preferred":[
        "Lajas"
    ],
    "name:ita_x_preferred":[
        "Lajas"
    ],
    "name:nld_x_preferred":[
        "Lajas"
    ],
    "name:pol_x_preferred":[
        "Lajas"
    ],
    "name:swe_x_preferred":[
        "Lajas"
    ],
    "wof:name":"Lajas",
    "wof:placetype":"locality"
},
  "geometry": {"coordinates":[-77.11667,20.91667],"type":"Point"}
}