{
  "type": "Feature",
  "properties": {
    "gn:admin1_code":"10",
    "gn:asciiname":"Los Siguatos",
    "gn:country_code":"CU",
    "gn:dem":56,
    "gn:feature_class":"P",
    "gn:feature_code":"PPL",
    "gn:name":"Los Siguatos",
    "gn:population":0,
    "gn:timezone":"America/Havana",
    "iso:country":"CU",
    "name:spa_x_preferred":[
        "Los Siguatos"
    ],
    "wof:name":"Los Siguatos",
    "wof:placetype":"locality"
},
  "geometry": {"coordinates":[-74.84607,20.05531],"type":"Point"}
}