{
  "type": "Feature",
  "properties": {
    "gn:admin1_code":"03",
    "gn:asciiname":"Alcancia",
    "gn:country_code":"CU",
    "gn:dem":118,
    "gn:feature_class":"P",
    "gn:feature_code":"PPLL",
    "gn:name":"Alcanc\u00eda",
    "gn:population":0,
    "gn:timezone":"America/Havana",
    "iso:country":"CU",
    "wof:name":"Alcancia",
    "wof:placetype":"locality"
},
  "geometry": {"coordinates":[-81.55806,22.83972],"type":"Point"}
}