{
  "type": "Feature",
  "properties": {
    "gn:admin1_code":"15",
    "gn:asciiname":"El Rajon",
    "gn:country_code":"CU",
    "gn:dem":591,
    "gn:feature_class":"P",
    "gn:feature_code":"PPL",
    "gn:name":"El Raj\u00f3n",
    "gn:population":0,
    "gn:timezone":"America/Havana",
    "iso:country":"CU",
    "name:spa_x_preferred":[
        "El Raj\u00f3n"
    ],
    "wof:name":"El Rajon",
    "wof:placetype":"locality"
},
  "geometry": {"coordinates":[-76.37446,20.03042],"type":"Point"}
}