{
  "type": "Feature",
  "properties": {
    "gn:admin1_code":"03",
    "gn:asciiname":"Hato de Jicarita",
    "gn:country_code":"CU",
    "gn:dem":12,
    "gn:feature_class":"P",
    "gn:feature_code":"PPLL",
    "gn:name":"Hato de Jicarita",
    "gn:population":0,
    "gn:timezone":"America/Havana",
    "iso:country":"CU",
    "name:spa_x_preferred":[
        "Hato de Jicarita"
    ],
    "wof:name":"Hato de Jicarita",
    "wof:placetype":"locality"
},
  "geometry": {"coordinates":[-81.46581,22.62328],"type":"Point"}
}