{
  "type": "Feature",
  "properties": {
    "gn:admin1_code":"05",
    "gn:asciiname":"Raul Pena",
    "gn:country_code":"CU",
    "gn:dem":69,
    "gn:feature_class":"P",
    "gn:feature_code":"PPL",
    "gn:name":"Ra\u00fal Pe\u00f1a",
    "gn:population":0,
    "gn:timezone":"America/Havana",
    "iso:country":"CU",
    "name:spa_x_preferred":[
        "Ra\u00fal Pe\u00f1a"
    ],
    "wof:name":"Raul Pena",
    "wof:placetype":"locality"
},
  "geometry": {"coordinates":[-78.09744999999999,21.18847],"type":"Point"}
}