{
  "type": "Feature",
  "properties": {
    "gn:admin1_code":"03",
    "gn:asciiname":"San Gabriel",
    "gn:cc2":"CU",
    "gn:country_code":"CU",
    "gn:dem":76,
    "gn:feature_class":"P",
    "gn:feature_code":"PPLL",
    "gn:name":"San Gabriel",
    "gn:population":0,
    "gn:timezone":"America/Havana",
    "iso:country":"CU",
    "name:cat_x_preferred":[
        "San Gabriel"
    ],
    "name:ceb_x_preferred":[
        "San Gabriel"
    ],
    "name:deu_x_preferred":[
        "San Gabriel"
    ],
    "name:eus_x_preferred":[
        "San Gabriel"
    ],
    "name:fra_x_preferred":[
        "San Gabriel"
    ],
    "name:glg_x_preferred":[
        "San Gabriel"
    ],
    "name:heb_x_preferred":[
        "\u05e1\u05df \u05d2\u05d1\u05e8\u05d9\u05d0\u05dc"
    ],
    "name:ita_x_preferred":[
        "San Gabriel"
    ],
    "name:nld_x_preferred":[
        "San Gabriel"
    ],
    "name:pol_x_preferred":[
        "San Gabriel"
    ],
    "name:por_x_preferred":[
        "San Gabriel"
    ],
    "name:rus_x_preferred":[
        "\u0421\u0430\u043d-\u0413\u0435\u0439\u0431\u0440\u0438\u0435\u043b"
    ],
    "name:sco_x_preferred":[
        "San Gabriel"
    ],
    "name:spa_x_preferred":[
        "San Gabriel"
    ],
    "name:srp_x_preferred":[
        "San Gabriel"
    ],
    "name:swe_x_preferred":[
        "San Gabriel"
    ],
    "name:und_x_variant":[
        "Gabriel",
        "San Gabriel"
    ],
    "name:war_x_preferred":[
        "San Gabriel"
    ],
    "wof:name":"San Gabriel",
    "wof:placetype":"locality"
},
  "geometry": {"coordinates":[-80.59999999999999,22.61667000000001],"type":"Point"}
}