{
  "type": "Feature",
  "properties": {
    "gn:admin1_code":"15",
    "gn:asciiname":"Arroyo Rico",
    "gn:country_code":"CU",
    "gn:dem":191,
    "gn:feature_class":"P",
    "gn:feature_code":"PPL",
    "gn:name":"Arroyo Rico",
    "gn:population":0,
    "gn:timezone":"America/Havana",
    "iso:country":"CU",
    "name:spa_x_preferred":[
        "Arroyo Rico"
    ],
    "wof:name":"Arroyo Rico",
    "wof:placetype":"locality"
},
  "geometry": {"coordinates":[-76.21324,20.14973],"type":"Point"}
}