{
  "type": "Feature",
  "properties": {
    "gn:admin1_code":"MA",
    "gn:asciiname":"Cuzco Las Canas",
    "gn:country_code":"CU",
    "gn:dem":9,
    "gn:feature_class":"P",
    "gn:feature_code":"PPL",
    "gn:name":"Cuzco Las Ca\u00f1as",
    "gn:population":0,
    "gn:timezone":"America/Havana",
    "iso:country":"CU",
    "name:spa_x_preferred":[
        "Cuzco Las Ca\u00f1as"
    ],
    "name:spa_x_variant":[
        "Las Ca\u00f1as"
    ],
    "wof:name":"Cuzco Las Canas",
    "wof:placetype":"locality"
},
  "geometry": {"coordinates":[-81.57778,22.69773],"type":"Point"}
}