{
  "type": "Feature",
  "properties": {
    "gn:admin1_code":"03",
    "gn:asciiname":"Maximo Gomez",
    "gn:country_code":"CU",
    "gn:dem":22,
    "gn:feature_class":"P",
    "gn:feature_code":"PPL",
    "gn:name":"M\u00e1ximo G\u00f3mez",
    "gn:population":0,
    "gn:timezone":"America/Havana",
    "iso:country":"CU",
    "name:und_x_variant":[
        "Recreo",
        "M\u00e1ximo G\u00f3mez"
    ],
    "wof:name":"Maximo Gomez",
    "wof:placetype":"locality"
},
  "geometry": {"coordinates":[-81.03289000000002,22.90182],"type":"Point"}
}