{
  "type": "Feature",
  "properties": {
    "gn:admin1_code":"03",
    "gn:asciiname":"Parque de Las Naciones",
    "gn:country_code":"CU",
    "gn:dem":14,
    "gn:feature_class":"P",
    "gn:feature_code":"PPLL",
    "gn:name":"Parque de Las Naciones",
    "gn:population":0,
    "gn:timezone":"America/Havana",
    "iso:country":"CU",
    "wof:name":"Parque de Las Naciones",
    "wof:placetype":"locality"
},
  "geometry": {"coordinates":[-81.53639,23.03722],"type":"Point"}
}