{
  "type": "Feature",
  "properties": {
    "gn:admin1_code":"10",
    "gn:asciiname":"Colorado",
    "gn:country_code":"CU",
    "gn:dem":717,
    "gn:feature_class":"P",
    "gn:feature_code":"PPL",
    "gn:name":"Colorado",
    "gn:population":0,
    "gn:timezone":"America/Havana",
    "iso:country":"CU",
    "name:spa_x_preferred":[
        "Colorado"
    ],
    "wof:name":"Colorado",
    "wof:placetype":"locality"
},
  "geometry": {"coordinates":[-75.05371,20.36564],"type":"Point"}
}