{
  "type": "Feature",
  "properties": {
    "gn:admin1_code":"13",
    "gn:asciiname":"Playa La Llanita",
    "gn:country_code":"CU",
    "gn:dem":6,
    "gn:feature_class":"P",
    "gn:feature_code":"PPL",
    "gn:name":"Playa La Llanita",
    "gn:population":0,
    "gn:timezone":"America/Havana",
    "iso:country":"CU",
    "name:spa_x_preferred":[
        "Playa La Llanita"
    ],
    "wof:name":"Playa La Llanita",
    "wof:placetype":"locality"
},
  "geometry": {"coordinates":[-76.52301,21.26698],"type":"Point"}
}