{
  "type": "Feature",
  "properties": {
    "gn:admin1_code":"14",
    "gn:asciiname":"Gavilanes",
    "gn:country_code":"CU",
    "gn:dem":234,
    "gn:feature_class":"P",
    "gn:feature_code":"PPL",
    "gn:name":"Gavilanes",
    "gn:population":0,
    "gn:timezone":"America/Havana",
    "iso:country":"CU",
    "name:ara_x_preferred":[
        "\u063a\u0627\u0641\u064a\u0644\u0627\u0646\u0633"
    ],
    "name:cat_x_preferred":[
        "Gavilanes"
    ],
    "name:ceb_x_preferred":[
        "Gavilanes"
    ],
    "name:eus_x_preferred":[
        "Gavilanes"
    ],
    "name:fas_x_preferred":[
        "\u06af\u0627\u0628\u06cc\u0644\u0627\u0646\u0633"
    ],
    "name:fra_x_preferred":[
        "G\u00e1vilanes"
    ],
    "name:glg_x_preferred":[
        "Gavilanes"
    ],
    "name:hun_x_preferred":[
        "Gavilanes"
    ],
    "name:ina_x_preferred":[
        "Gavilanes"
    ],
    "name:ita_x_preferred":[
        "Gavilanes"
    ],
    "name:kaz_x_preferred":[
        "\u0413\u0430\u0432\u0438\u043b\u0430\u043d\u0435\u0441"
    ],
    "name:mkd_x_preferred":[
        "\u0413\u0430\u0432\u0438\u043b\u0430\u043d\u0435\u0441"
    ],
    "name:msa_x_preferred":[
        "Gavilanes"
    ],
    "name:nld_x_preferred":[
        "Gavilanes"
    ],
    "name:oci_x_preferred":[
        "Gavilanes"
    ],
    "name:pol_x_preferred":[
        "Gavilanes"
    ],
    "name:por_x_preferred":[
        "Gavilanes"
    ],
    "name:rus_x_preferred":[
        "\u0413\u0430\u0432\u0438\u043b\u0430\u043d\u0435\u0441"
    ],
    "name:spa_x_preferred":[
        "Gavilanes"
    ],
    "name:swe_x_preferred":[
        "Gavilanes"
    ],
    "name:ukr_x_preferred":[
        "\u0413\u0430\u0432\u0456\u043b\u0430\u043d\u0435\u0441"
    ],
    "name:uzb_x_preferred":[
        "Gavilanes"
    ],
    "name:vie_x_preferred":[
        "Gavilanes"
    ],
    "name:war_x_preferred":[
        "Gavilanes"
    ],
    "name:zho_x_preferred":[
        "\u52a0\u7ef4\u62c9\u5185\u65af"
    ],
    "wof:name":"Gavilanes",
    "wof:placetype":"locality"
},
  "geometry": {"coordinates":[-79.64695999999998,21.93565],"type":"Point"}
}