{
  "type": "Feature",
  "properties": {
    "gn:admin1_code":"09",
    "gn:asciiname":"Las Casimbas",
    "gn:country_code":"CU",
    "gn:dem":28,
    "gn:feature_class":"P",
    "gn:feature_code":"PPL",
    "gn:name":"Las Casimbas",
    "gn:population":0,
    "gn:timezone":"America/Havana",
    "iso:country":"CU",
    "name:spa_x_preferred":[
        "Las Casimbas"
    ],
    "wof:name":"Las Casimbas",
    "wof:placetype":"locality"
},
  "geometry": {"coordinates":[-77.60488000000002,19.97428],"type":"Point"}
}