{
  "type": "Feature",
  "properties": {
    "gn:country":"CU",
    "gn:fcode":"PPL",
    "gn:pop":26761,
    "iso:country":"CU",
    "name:eng_x_preferred":[
        "Pedro Betancourt"
    ],
    "name:fra_x_preferred":[
        "Pedro Betancourt"
    ],
    "name:ita_x_preferred":[
        "Pedro Betancourt"
    ],
    "name:kat_x_preferred":[
        "\u10de\u10d4\u10d3\u10e0\u10dd-\u10d1\u10d4\u10e2\u10d0\u10dc\u10d9\u10e3\u10e0\u10d8"
    ],
    "name:nld_x_preferred":[
        "Pedro Betancourt"
    ],
    "name:por_x_preferred":[
        "Pedro Betancourt"
    ],
    "name:sco_x_preferred":[
        "Pedro Betancourt"
    ],
    "name:swe_x_preferred":[
        "Municipio de Pedro Betancourt"
    ],
    "name:unk_x_variant":[
        "Corral Falso"
    ],
    "name:vie_x_preferred":[
        "Pedro Betancourt"
    ],
    "name:zho_x_preferred":[
        "\u4f69\u5fb7\u7f85\u8c9d\u5766\u5eab\u7279"
    ],
    "qs:name":"Pedro Betancourt",
    "qs:photos_9r":0,
    "qs:photos_sr":0,
    "qs:pop_sr":"7",
    "wd:wordcount":246,
    "wof:name":"Pedro Betancourt",
    "wof:placetype":"locality",
    "wof:population":26761
},
  "geometry": {"coordinates":[-81.29000000000001,22.72722],"type":"Point"}
}