{
  "type": "Feature",
  "properties": {
    "gn:admin1_code":"14",
    "gn:asciiname":"Neiva",
    "gn:country_code":"CU",
    "gn:dem":114,
    "gn:feature_class":"P",
    "gn:feature_code":"PPL",
    "gn:name":"Neiva",
    "gn:population":0,
    "gn:timezone":"America/Havana",
    "iso:country":"CU",
    "name:hun_x_preferred":[
        "Neiva"
    ],
    "name:spa_x_preferred":[
        "Neiva"
    ],
    "wof:name":"Neiva",
    "wof:placetype":"locality"
},
  "geometry": {"coordinates":[-79.44474,22.1041],"type":"Point"}
}