{
  "type": "Feature",
  "properties": {
    "gn:admin1_code":"13",
    "gn:asciiname":"Laura",
    "gn:country_code":"CU",
    "gn:dem":23,
    "gn:feature_class":"P",
    "gn:feature_code":"PPL",
    "gn:name":"Laura",
    "gn:population":0,
    "gn:timezone":"America/Havana",
    "iso:country":"CU",
    "name:spa_x_preferred":[
        "Laura"
    ],
    "wof:name":"Laura",
    "wof:placetype":"locality"
},
  "geometry": {"coordinates":[-77.01353,21.27148],"type":"Point"}
}