{
  "type": "Feature",
  "properties": {
    "gn:admin1_code":"13",
    "gn:asciiname":"Laura",
    "gn:country_code":"CU",
    "gn:dem":23,
    "gn:feature_class":"P",
    "gn:feature_code":"PPL",
    "gn:name":"Laura",
    "gn:population":0,
    "gn:timezone":"America/Havana",
    "iso:country":"CU",
    "name:ara_x_preferred":[
        "\u0644\u0648\u0631\u0627"
    ],
    "name:cat_x_preferred":[
        "Laura"
    ],
    "name:ceb_x_preferred":[
        "Laura"
    ],
    "name:deu_x_preferred":[
        "Laura"
    ],
    "name:ell_x_preferred":[
        "\u039b\u03ac\u03bf\u03c5\u03c1\u03b1"
    ],
    "name:fas_x_preferred":[
        "\u0644\u0648\u0631\u0627"
    ],
    "name:fin_x_preferred":[
        "Laura"
    ],
    "name:fra_x_preferred":[
        "Laura"
    ],
    "name:ita_x_preferred":[
        "Laura"
    ],
    "name:jpn_x_preferred":[
        "\u30ed\u30fc\u30e9"
    ],
    "name:lim_x_preferred":[
        "Laura"
    ],
    "name:nld_x_preferred":[
        "Laura"
    ],
    "name:pol_x_preferred":[
        "Laura"
    ],
    "name:por_x_preferred":[
        "Laura"
    ],
    "name:ron_x_preferred":[
        "Laura"
    ],
    "name:spa_x_preferred":[
        "Laura"
    ],
    "name:srp_x_preferred":[
        "Laura"
    ],
    "name:swe_x_preferred":[
        "Laura"
    ],
    "name:vie_x_preferred":[
        "Laura"
    ],
    "name:zea_x_preferred":[
        "Laura"
    ],
    "wof:name":"Laura",
    "wof:placetype":"locality"
},
  "geometry": {"coordinates":[-77.01353,21.27148],"type":"Point"}
}