{
  "type": "Feature",
  "properties": {
    "gn:admin1_code":"16",
    "gn:asciiname":"Paredes",
    "gn:country_code":"CU",
    "gn:dem":66,
    "gn:feature_class":"P",
    "gn:feature_code":"PPLL",
    "gn:name":"Paredes",
    "gn:population":0,
    "gn:timezone":"America/Havana",
    "iso:country":"CU",
    "name:ast_x_preferred":[
        "Paredes"
    ],
    "name:cat_x_preferred":[
        "Paredes"
    ],
    "name:ceb_x_preferred":[
        "Paredes"
    ],
    "name:deu_x_preferred":[
        "Paredes"
    ],
    "name:eus_x_preferred":[
        "Paredes"
    ],
    "name:fra_x_preferred":[
        "Paredes"
    ],
    "name:glg_x_preferred":[
        "Paredes"
    ],
    "name:heb_x_preferred":[
        "\u05e4\u05d0\u05e8\u05d3\u05e1"
    ],
    "name:hun_x_preferred":[
        "Paredes"
    ],
    "name:ita_x_preferred":[
        "Paredes"
    ],
    "name:msa_x_preferred":[
        "Paredes"
    ],
    "name:nds_x_preferred":[
        "Paredes"
    ],
    "name:nld_x_preferred":[
        "Paredes"
    ],
    "name:pol_x_preferred":[
        "Paredes"
    ],
    "name:por_x_preferred":[
        "Paredes"
    ],
    "name:rus_x_preferred":[
        "\u041f\u0430\u0440\u0435\u0434\u0435\u0441"
    ],
    "name:scn_x_preferred":[
        "Paredes"
    ],
    "name:spa_x_preferred":[
        "Paredes"
    ],
    "name:srp_x_preferred":[
        "\u041f\u0430\u0440\u0435\u0434\u0435\u0441"
    ],
    "name:swe_x_preferred":[
        "Paredes"
    ],
    "name:ukr_x_preferred":[
        "\u041f\u0430\u0440\u0435\u0434\u0435\u0448"
    ],
    "name:und_x_variant":[
        "Mercedes",
        "Paredes"
    ],
    "name:vie_x_preferred":[
        "Paredes"
    ],
    "name:war_x_preferred":[
        "Paredes"
    ],
    "wof:name":"Paredes",
    "wof:placetype":"locality"
},
  "geometry": {"coordinates":[-79.88254000000001,22.53247],"type":"Point"}
}