{
  "type": "Feature",
  "properties": {
    "gn:admin1_code":"16",
    "gn:asciiname":"Paredes",
    "gn:country_code":"CU",
    "gn:dem":66,
    "gn:feature_class":"P",
    "gn:feature_code":"PPLL",
    "gn:name":"Paredes",
    "gn:population":0,
    "gn:timezone":"America/Havana",
    "iso:country":"CU",
    "name:und_x_variant":[
        "Mercedes",
        "Paredes"
    ],
    "wof:name":"Paredes",
    "wof:placetype":"locality"
},
  "geometry": {"coordinates":[-79.88254000000001,22.53247],"type":"Point"}
}