{
  "type": "Feature",
  "properties": {
    "gn:admin1_code":"05",
    "gn:asciiname":"Arroyo Prieto",
    "gn:country_code":"CU",
    "gn:dem":103,
    "gn:feature_class":"P",
    "gn:feature_code":"PPL",
    "gn:name":"Arroyo Prieto",
    "gn:population":0,
    "gn:timezone":"America/Havana",
    "iso:country":"CU",
    "name:spa_x_preferred":[
        "Arroyo Prieto"
    ],
    "wof:name":"Arroyo Prieto",
    "wof:placetype":"locality"
},
  "geometry": {"coordinates":[-77.75796,21.43885],"type":"Point"}
}