{
  "type": "Feature",
  "properties": {
    "gn:admin1_code":"03",
    "gn:asciiname":"La Caridad",
    "gn:country_code":"CU",
    "gn:dem":13,
    "gn:feature_class":"P",
    "gn:feature_code":"PPLL",
    "gn:name":"La Caridad",
    "gn:population":0,
    "gn:timezone":"America/Havana",
    "iso:country":"CU",
    "name:ast_x_preferred":[
        "A Carid\u00e1"
    ],
    "name:deu_x_preferred":[
        "La Caridad"
    ],
    "name:spa_x_preferred":[
        "La Caridad"
    ],
    "name:urd_x_preferred":[
        "\u0644\u0627 \u06a9\u0627\u0631\u06cc\u0688\u0627\u0688"
    ],
    "wof:name":"La Caridad",
    "wof:placetype":"locality"
},
  "geometry": {"coordinates":[-81.51666999999998,22.66667],"type":"Point"}
}