{
  "type": "Feature",
  "properties": {
    "gn:admin1_code":"08",
    "gn:asciiname":"La Milpa",
    "gn:country_code":"CU",
    "gn:dem":7,
    "gn:feature_class":"P",
    "gn:feature_code":"PPL",
    "gn:name":"La Milpa",
    "gn:population":0,
    "gn:timezone":"America/Havana",
    "iso:country":"CU",
    "name:spa_x_preferred":[
        "La Milpa"
    ],
    "name:und_x_variant":[
        "Milpa"
    ],
    "wof:name":"La Milpa",
    "wof:placetype":"locality"
},
  "geometry": {"coordinates":[-80.45397,22.07199],"type":"Point"}
}