{
  "type": "Feature",
  "properties": {
    "gn:admin1_code":"07",
    "gn:asciiname":"Cerro Pelado",
    "gn:country_code":"CU",
    "gn:dem":83,
    "gn:feature_class":"P",
    "gn:feature_code":"PPLL",
    "gn:name":"Cerro Pelado",
    "gn:population":0,
    "gn:timezone":"America/Havana",
    "iso:country":"CU",
    "name:cat_x_preferred":[
        "Cerro Pelado"
    ],
    "name:deu_x_preferred":[
        "Cerro Pelado"
    ],
    "name:fra_x_preferred":[
        "Cerro Pelado"
    ],
    "name:spa_x_preferred":[
        "Cerro Pelado"
    ],
    "wof:name":"Cerro Pelado",
    "wof:placetype":"locality"
},
  "geometry": {"coordinates":[-78.83592,21.91963],"type":"Point"}
}