{
  "type": "Feature",
  "properties": {
    "gn:admin1_code":"MA",
    "gn:asciiname":"Anseimo",
    "gn:country_code":"CU",
    "gn:dem":108,
    "gn:feature_class":"P",
    "gn:feature_code":"PPL",
    "gn:name":"Anseimo",
    "gn:population":0,
    "gn:timezone":"America/Havana",
    "iso:country":"CU",
    "wof:name":"Anseimo",
    "wof:placetype":"locality"
},
  "geometry": {"coordinates":[-82.11667,23.05],"type":"Point"}
}