{
  "type": "Feature",
  "properties": {
    "gn:admin1_code":"09",
    "gn:asciiname":"Blanquizal",
    "gn:country_code":"CU",
    "gn:dem":17,
    "gn:feature_class":"P",
    "gn:feature_code":"PPL",
    "gn:name":"Blanquizal",
    "gn:population":0,
    "gn:timezone":"America/Havana",
    "iso:country":"CU",
    "name:spa_x_preferred":[
        "Blanquizal"
    ],
    "wof:name":"Blanquizal",
    "wof:placetype":"locality"
},
  "geometry": {"coordinates":[-77.50763000000001,20.08637],"type":"Point"}
}