{
  "type": "Feature",
  "properties": {
    "gn:admin1_code":"14",
    "gn:asciiname":"Ciego Gallego",
    "gn:country_code":"CU",
    "gn:dem":18,
    "gn:feature_class":"P",
    "gn:feature_code":"PPLL",
    "gn:name":"Ciego Gallego",
    "gn:population":0,
    "gn:timezone":"America/Havana",
    "iso:country":"CU",
    "wof:name":"Ciego Gallego",
    "wof:placetype":"locality"
},
  "geometry": {"coordinates":[-79.68333,21.71667],"type":"Point"}
}