{
  "type": "Feature",
  "properties": {
    "gn:admin1_code":"05",
    "gn:asciiname":"Maceo",
    "gn:country_code":"CU",
    "gn:dem":51,
    "gn:feature_class":"P",
    "gn:feature_code":"PPLL",
    "gn:name":"Maceo",
    "gn:population":0,
    "gn:timezone":"America/Havana",
    "iso:country":"CU",
    "wof:name":"Maceo",
    "wof:placetype":"locality"
},
  "geometry": {"coordinates":[-78.09999999999999,21.73333],"type":"Point"}
}