{
  "type": "Feature",
  "properties": {
    "gn:admin1_code":"09",
    "gn:asciiname":"Los Lazos",
    "gn:country_code":"CU",
    "gn:dem":389,
    "gn:feature_class":"P",
    "gn:feature_code":"PPLL",
    "gn:name":"Los Lazos",
    "gn:population":0,
    "gn:timezone":"America/Havana",
    "iso:country":"CU",
    "name:spa_x_preferred":[
        "Los Lazos"
    ],
    "wof:name":"Los Lazos",
    "wof:placetype":"locality"
},
  "geometry": {"coordinates":[-77.21388,19.96629],"type":"Point"}
}