{
  "type": "Feature",
  "properties": {
    "gn:admin1_code":"12",
    "gn:asciiname":"Altagracia Uno",
    "gn:country_code":"CU",
    "gn:dem":65,
    "gn:feature_class":"P",
    "gn:feature_code":"PPL",
    "gn:name":"Altagracia Uno",
    "gn:population":0,
    "gn:timezone":"America/Havana",
    "iso:country":"CU",
    "name:spa_x_preferred":[
        "Altagracia Uno"
    ],
    "wof:name":"Altagracia Uno",
    "wof:placetype":"locality"
},
  "geometry": {"coordinates":[-76.28631999999998,20.66258],"type":"Point"}
}