{
  "type": "Feature",
  "properties": {
    "gn:admin1_code":"01",
    "gn:asciiname":"Paso las Piedras",
    "gn:country_code":"CU",
    "gn:dem":8,
    "gn:feature_class":"P",
    "gn:feature_code":"PPLL",
    "gn:name":"Paso las Piedras",
    "gn:population":0,
    "gn:timezone":"America/Havana",
    "iso:country":"CU",
    "wof:name":"Paso las Piedras",
    "wof:placetype":"locality"
},
  "geometry": {"coordinates":[-83.99167,22.10972000000001],"type":"Point"}
}