{
  "type": "Feature",
  "properties": {
    "gn:admin1_code":"MA",
    "gn:asciiname":"La Fe",
    "gn:country_code":"CU",
    "gn:dem":152,
    "gn:feature_class":"P",
    "gn:feature_code":"PPLL",
    "gn:name":"La Fe",
    "gn:population":0,
    "gn:timezone":"America/Havana",
    "iso:country":"CU",
    "wof:name":"La Fe",
    "wof:placetype":"locality"
},
  "geometry": {"coordinates":[-81.76555999999999,22.90667],"type":"Point"}
}