{
  "type": "Feature",
  "properties": {
    "gn:admin1_code":"03",
    "gn:asciiname":"Dupont",
    "gn:cc2":"CU",
    "gn:country_code":"CU",
    "gn:dem":10,
    "gn:feature_class":"P",
    "gn:feature_code":"PPL",
    "gn:name":"Dupont",
    "gn:population":0,
    "gn:timezone":"America/Havana",
    "iso:country":"CU",
    "name:und_x_variant":[
        "Casa Dupont",
        "Dupont"
    ],
    "wof:name":"Dupont",
    "wof:placetype":"locality"
},
  "geometry": {"coordinates":[-81.21583000000003,23.17306],"type":"Point"}
}