{
  "type": "Feature",
  "properties": {
    "gn:admin1_code":"03",
    "gn:asciiname":"Dupont",
    "gn:cc2":"CU",
    "gn:country_code":"CU",
    "gn:dem":10,
    "gn:feature_class":"P",
    "gn:feature_code":"PPL",
    "gn:name":"Dupont",
    "gn:population":0,
    "gn:timezone":"America/Havana",
    "iso:country":"CU",
    "name:bul_x_preferred":[
        "\u0414\u044e\u043f\u043e\u043d"
    ],
    "name:cat_x_preferred":[
        "Dupont"
    ],
    "name:ceb_x_preferred":[
        "Dupont"
    ],
    "name:deu_x_preferred":[
        "Dupont"
    ],
    "name:fas_x_preferred":[
        "\u062f\u0648\u067e\u0648\u0646\u062a"
    ],
    "name:fin_x_preferred":[
        "Dupont"
    ],
    "name:hin_x_preferred":[
        "\u0921\u094d\u092f\u0942\u092a\u0949\u0928\u094d\u091f"
    ],
    "name:ita_x_preferred":[
        "Dupont"
    ],
    "name:jpn_x_preferred":[
        "\u30c7\u30e5\u30dd\u30f3"
    ],
    "name:kor_x_preferred":[
        "\ub4c0\ud3f0\ud2b8"
    ],
    "name:nld_x_preferred":[
        "Dupont"
    ],
    "name:pol_x_preferred":[
        "Dupont"
    ],
    "name:por_x_preferred":[
        "Dupont"
    ],
    "name:rus_x_preferred":[
        "\u0414\u044e\u043f\u043e\u043d"
    ],
    "name:spa_x_preferred":[
        "Dupont"
    ],
    "name:srp_x_preferred":[
        "\u0414\u0443\u043f\u043e\u043d\u0442"
    ],
    "name:swe_x_preferred":[
        "Dupont"
    ],
    "name:ukr_x_preferred":[
        "\u0414\u044e\u043f\u043e\u043d"
    ],
    "name:und_x_variant":[
        "Casa Dupont",
        "Dupont"
    ],
    "name:vol_x_preferred":[
        "Dupont"
    ],
    "wof:name":"Dupont",
    "wof:placetype":"locality"
},
  "geometry": {"coordinates":[-81.21583000000003,23.17306],"type":"Point"}
}