{
  "type": "Feature",
  "properties": {
    "gn:admin1_code":"16",
    "gn:asciiname":"Lutgardita",
    "gn:country_code":"CU",
    "gn:dem":31,
    "gn:feature_class":"P",
    "gn:feature_code":"PPL",
    "gn:name":"Lutgardita",
    "gn:population":0,
    "gn:timezone":"America/Havana",
    "iso:country":"CU",
    "name:spa_x_preferred":[
        "Lutgardita"
    ],
    "name:spa_x_variant":[
        "Lugardita"
    ],
    "wof:name":"Lutgardita",
    "wof:placetype":"locality"
},
  "geometry": {"coordinates":[-80.29983,22.8699],"type":"Point"}
}