{
  "type": "Feature",
  "properties": {
    "gn:admin1_code":"MA",
    "gn:asciiname":"Lechuga",
    "gn:country_code":"CU",
    "gn:dem":27,
    "gn:feature_class":"P",
    "gn:feature_code":"PPL",
    "gn:name":"Lechuga",
    "gn:population":0,
    "gn:timezone":"America/Havana",
    "iso:country":"CU",
    "name:und_x_variant":[
        "Lechugas",
        "Lechuga"
    ],
    "wof:name":"Lechuga",
    "wof:placetype":"locality"
},
  "geometry": {"coordinates":[-82.10961,22.78314],"type":"Point"}
}