{
  "type": "Feature",
  "properties": {
    "gn:admin1_code":"12",
    "gn:asciiname":"Guanabana",
    "gn:cc2":"CU",
    "gn:country_code":"CU",
    "gn:dem":165,
    "gn:feature_class":"P",
    "gn:feature_code":"PPL",
    "gn:name":"Guan\u00e1bana",
    "gn:population":0,
    "gn:timezone":"America/Havana",
    "iso:country":"CU",
    "name:und_x_variant":[
        "Guan\u00e1banas",
        "Guan\u00e1bana"
    ],
    "wof:name":"Guanabana",
    "wof:placetype":"locality"
},
  "geometry": {"coordinates":[-76.31166999999998,20.92389],"type":"Point"}
}