{
  "type": "Feature",
  "properties": {
    "gn:admin1_code":"12",
    "gn:asciiname":"Tomi",
    "gn:country_code":"CU",
    "gn:dem":112,
    "gn:feature_class":"P",
    "gn:feature_code":"PPL",
    "gn:name":"Tomi",
    "gn:population":0,
    "gn:timezone":"America/Havana",
    "iso:country":"CU",
    "name:spa_x_preferred":[
        "Tomi"
    ],
    "wof:name":"Tomi",
    "wof:placetype":"locality"
},
  "geometry": {"coordinates":[-76.36171999999998,20.82848],"type":"Point"}
}