{
  "type": "Feature",
  "properties": {
    "gn:admin1_code":"07",
    "gn:asciiname":"Palo Gordo",
    "gn:country_code":"CU",
    "gn:dem":20,
    "gn:feature_class":"P",
    "gn:feature_code":"PPLL",
    "gn:name":"Palo Gordo",
    "gn:population":0,
    "gn:timezone":"America/Havana",
    "iso:country":"CU",
    "name:spa_x_preferred":[
        "Palo Gordo"
    ],
    "wof:name":"Palo Gordo",
    "wof:placetype":"locality"
},
  "geometry": {"coordinates":[-78.57791999999998,21.96095],"type":"Point"}
}