{
  "type": "Feature",
  "properties": {
    "gn:admin1_code":"MA",
    "gn:asciiname":"Boca de Canasi",
    "gn:country_code":"CU",
    "gn:dem":9,
    "gn:feature_class":"P",
    "gn:feature_code":"PPLL",
    "gn:name":"Boca de Canas\u00ed",
    "gn:population":0,
    "gn:timezone":"America/Havana",
    "iso:country":"CU",
    "name:spa_x_preferred":[
        "Boca de Canas\u00ed"
    ],
    "wof:name":"Boca de Canasi",
    "wof:placetype":"locality"
},
  "geometry": {"coordinates":[-81.78176999999999,23.13971],"type":"Point"}
}