{
  "type": "Feature",
  "properties": {
    "gn:admin1_code":"13",
    "gn:asciiname":"La Ceiba Uno",
    "gn:country_code":"CU",
    "gn:dem":14,
    "gn:feature_class":"P",
    "gn:feature_code":"PPL",
    "gn:name":"La Ceiba Uno",
    "gn:population":0,
    "gn:timezone":"America/Havana",
    "iso:country":"CU",
    "name:spa_x_preferred":[
        "La Ceiba Uno"
    ],
    "name:und_x_variant":[
        "La Ceiba"
    ],
    "wof:name":"La Ceiba Uno",
    "wof:placetype":"locality"
},
  "geometry": {"coordinates":[-77.53715,20.75457],"type":"Point"}
}