{
  "type": "Feature",
  "properties": {
    "gn:admin1_code":"07",
    "gn:asciiname":"Josefina",
    "gn:country_code":"CU",
    "gn:dem":24,
    "gn:feature_class":"P",
    "gn:feature_code":"PPLL",
    "gn:name":"Josefina",
    "gn:population":0,
    "gn:timezone":"America/Havana",
    "iso:country":"CU",
    "wof:name":"Josefina",
    "wof:placetype":"locality"
},
  "geometry": {"coordinates":[-78.38806,21.9675],"type":"Point"}
}