{
  "type": "Feature",
  "properties": {
    "gn:admin1_code":"MA",
    "gn:asciiname":"Venturilla",
    "gn:country_code":"CU",
    "gn:dem":205,
    "gn:feature_class":"P",
    "gn:feature_code":"PPLL",
    "gn:name":"Venturilla",
    "gn:population":0,
    "gn:timezone":"America/Havana",
    "iso:country":"CU",
    "name:spa_x_preferred":[
        "Venturilla"
    ],
    "wof:name":"Venturilla",
    "wof:placetype":"locality"
},
  "geometry": {"coordinates":[-81.73255999999998,22.8962],"type":"Point"}
}