{
  "type": "Feature",
  "properties": {
    "gn:admin1_code":"MA",
    "gn:asciiname":"Las Canas Bravas",
    "gn:country_code":"CU",
    "gn:dem":133,
    "gn:feature_class":"P",
    "gn:feature_code":"PPLL",
    "gn:name":"Las Ca\u00f1as Bravas",
    "gn:population":0,
    "gn:timezone":"America/Havana",
    "iso:country":"CU",
    "wof:name":"Las Canas Bravas",
    "wof:placetype":"locality"
},
  "geometry": {"coordinates":[-82.18333,23.05],"type":"Point"}
}