{
  "type": "Feature",
  "properties": {
    "gn:admin1_code":"10",
    "gn:asciiname":"El Crucero",
    "gn:country_code":"CU",
    "gn:dem":749,
    "gn:feature_class":"P",
    "gn:feature_code":"PPL",
    "gn:name":"El Crucero",
    "gn:population":0,
    "gn:timezone":"America/Havana",
    "iso:country":"CU",
    "name:spa_x_preferred":[
        "El Crucero"
    ],
    "wof:name":"El Crucero",
    "wof:placetype":"locality"
},
  "geometry": {"coordinates":[-74.73978000000002,20.16781],"type":"Point"}
}