{
  "type": "Feature",
  "properties": {
    "gn:admin1_code":"10",
    "gn:asciiname":"El Crucero",
    "gn:country_code":"CU",
    "gn:dem":749,
    "gn:feature_class":"P",
    "gn:feature_code":"PPL",
    "gn:name":"El Crucero",
    "gn:population":0,
    "gn:timezone":"America/Havana",
    "iso:country":"CU",
    "name:ell_x_preferred":[
        "\u0395\u03bb \u039a\u03c1\u03bf\u03c5\u03c3\u03ad\u03c1\u03bf"
    ],
    "name:fra_x_preferred":[
        "El Crucero"
    ],
    "name:ita_x_preferred":[
        "El Crucero"
    ],
    "name:nld_x_preferred":[
        "El Crucero"
    ],
    "name:pol_x_preferred":[
        "El Crucero"
    ],
    "name:spa_x_preferred":[
        "El Crucero"
    ],
    "name:swe_x_preferred":[
        "El Crucero"
    ],
    "name:urd_x_preferred":[
        "\u0627\u06cc\u0644 \u06a9\u0631\u0648\u0633\u06cc\u0631\u0648"
    ],
    "name:vie_x_preferred":[
        "El Crucero"
    ],
    "name:zho_x_preferred":[
        "\u57c3\u723e\u514b\u9b6f\u585e\u7f85"
    ],
    "wof:name":"El Crucero",
    "wof:placetype":"locality"
},
  "geometry": {"coordinates":[-74.73978000000002,20.16781],"type":"Point"}
}