{
  "type": "Feature",
  "properties": {
    "gn:admin1_code":"12",
    "gn:asciiname":"Punta Alegre",
    "gn:country_code":"CU",
    "gn:dem":41,
    "gn:feature_class":"P",
    "gn:feature_code":"PPL",
    "gn:name":"Punta Alegre",
    "gn:population":0,
    "gn:timezone":"America/Havana",
    "iso:country":"CU",
    "name:spa_x_preferred":[
        "Punta Alegre"
    ],
    "wof:name":"Punta Alegre",
    "wof:placetype":"locality"
},
  "geometry": {"coordinates":[-75.82545,20.85192],"type":"Point"}
}