{
  "type": "Feature",
  "properties": {
    "gn:admin1_code":"08",
    "gn:asciiname":"La Lolita",
    "gn:country_code":"CU",
    "gn:dem":35,
    "gn:feature_class":"P",
    "gn:feature_code":"PPL",
    "gn:name":"La Lolita",
    "gn:population":0,
    "gn:timezone":"America/Havana",
    "iso:country":"CU",
    "name:spa_x_preferred":[
        "La Lolita"
    ],
    "wof:name":"La Lolita",
    "wof:placetype":"locality"
},
  "geometry": {"coordinates":[-80.49273000000002,22.37252],"type":"Point"}
}