{
  "type": "Feature",
  "properties": {
    "gn:admin1_code":"15",
    "gn:asciiname":"Latali",
    "gn:country_code":"CU",
    "gn:dem":382,
    "gn:feature_class":"P",
    "gn:feature_code":"PPL",
    "gn:name":"Latali",
    "gn:population":0,
    "gn:timezone":"America/Havana",
    "iso:country":"CU",
    "name:spa_x_preferred":[
        "Latali"
    ],
    "wof:name":"Latali",
    "wof:placetype":"locality"
},
  "geometry": {"coordinates":[-75.58714000000001,20.02264],"type":"Point"}
}