{
  "type": "Feature",
  "properties": {
    "gn:admin1_code":"07",
    "gn:asciiname":"Quemado Nuevo",
    "gn:country_code":"CU",
    "gn:dem":58,
    "gn:feature_class":"P",
    "gn:feature_code":"PPLL",
    "gn:name":"Quemado Nuevo",
    "gn:population":0,
    "gn:timezone":"America/Havana",
    "iso:country":"CU",
    "wof:name":"Quemado Nuevo",
    "wof:placetype":"locality"
},
  "geometry": {"coordinates":[-78.84999999999999,21.85],"type":"Point"}
}