{
  "type": "Feature",
  "properties": {
    "gn:admin1_code":"09",
    "gn:asciiname":"Maldita Sea",
    "gn:country_code":"CU",
    "gn:dem":1219,
    "gn:feature_class":"P",
    "gn:feature_code":"PPL",
    "gn:name":"Maldita Sea",
    "gn:population":0,
    "gn:timezone":"America/Havana",
    "iso:country":"CU",
    "name:spa_x_preferred":[
        "Maldita Sea"
    ],
    "wof:name":"Maldita Sea",
    "wof:placetype":"locality"
},
  "geometry": {"coordinates":[-76.57906,20.06591],"type":"Point"}
}