{
  "type": "Feature",
  "properties": {
    "gn:admin1_code":"13",
    "gn:asciiname":"Santa Lideada",
    "gn:country_code":"CU",
    "gn:dem":78,
    "gn:feature_class":"P",
    "gn:feature_code":"PPLL",
    "gn:name":"Santa Lideada",
    "gn:population":0,
    "gn:timezone":"America/Havana",
    "iso:country":"CU",
    "name:spa_x_preferred":[
        "Santa Lideada"
    ],
    "wof:name":"Santa Lideada",
    "wof:placetype":"locality"
},
  "geometry": {"coordinates":[-77.00173000000002,20.90678],"type":"Point"}
}