{
  "type": "Feature",
  "properties": {
    "gn:admin1_code":"03",
    "gn:asciiname":"La Isabel",
    "gn:country_code":"CU",
    "gn:dem":5,
    "gn:feature_class":"P",
    "gn:feature_code":"PPLL",
    "gn:name":"La Isabel",
    "gn:population":0,
    "gn:timezone":"America/Havana",
    "iso:country":"CU",
    "name:spa_x_preferred":[
        "La Isabel"
    ],
    "name:und_x_variant":[
        "Isabel"
    ],
    "wof:name":"La Isabel",
    "wof:placetype":"locality"
},
  "geometry": {"coordinates":[-81.06384,22.98024],"type":"Point"}
}