{
  "type": "Feature",
  "properties": {
    "gn:admin1_code":"03",
    "gn:asciiname":"Cocodrilo",
    "gn:country_code":"CU",
    "gn:dem":9,
    "gn:feature_class":"P",
    "gn:feature_code":"PPL",
    "gn:name":"Cocodrilo",
    "gn:population":0,
    "gn:timezone":"America/Havana",
    "iso:country":"CU",
    "name:spa_x_preferred":[
        "Cocodrilo"
    ],
    "name:und_x_variant":[
        "Cocodrilos"
    ],
    "wof:name":"Cocodrilo",
    "wof:placetype":"locality"
},
  "geometry": {"coordinates":[-80.74708000000003,22.10051],"type":"Point"}
}