{
  "type": "Feature",
  "properties": {
    "gn:admin1_code":"05",
    "gn:asciiname":"Fomento",
    "gn:country_code":"CU",
    "gn:dem":32,
    "gn:feature_class":"P",
    "gn:feature_code":"PPL",
    "gn:name":"Fomento",
    "gn:population":0,
    "gn:timezone":"America/Havana",
    "iso:country":"CU",
    "name:spa_x_preferred":[
        "Fomento"
    ],
    "wof:name":"Fomento",
    "wof:placetype":"locality"
},
  "geometry": {"coordinates":[-77.47761,21.47218],"type":"Point"}
}