{
  "type": "Feature",
  "properties": {
    "gn:admin1_code":"16",
    "gn:asciiname":"America",
    "gn:country_code":"CU",
    "gn:dem":174,
    "gn:feature_class":"P",
    "gn:feature_code":"PPLL",
    "gn:name":"Am\u00e9rica",
    "gn:population":0,
    "gn:timezone":"America/Havana",
    "iso:country":"CU",
    "wof:name":"America",
    "wof:placetype":"locality"
},
  "geometry": {"coordinates":[-79.65000000000001,22.18333],"type":"Point"}
}