{
  "type": "Feature",
  "properties": {
    "gn:admin1_code":"14",
    "gn:asciiname":"La Onelia",
    "gn:cc2":"CU",
    "gn:country_code":"CU",
    "gn:dem":28,
    "gn:feature_class":"P",
    "gn:feature_code":"PPLL",
    "gn:name":"La Onelia",
    "gn:population":0,
    "gn:timezone":"America/Havana",
    "iso:country":"CU",
    "name:und_x_variant":[
        "Onelia",
        "La Onelia"
    ],
    "wof:name":"La Onelia",
    "wof:placetype":"locality"
},
  "geometry": {"coordinates":[-79.03055999999999,22.25694],"type":"Point"}
}