{
  "type": "Feature",
  "properties": {
    "gn:admin1_code":"AR",
    "gn:asciiname":"La Catalina",
    "gn:country_code":"CU",
    "gn:dem":44,
    "gn:feature_class":"P",
    "gn:feature_code":"PPLL",
    "gn:name":"La Catalina",
    "gn:population":0,
    "gn:timezone":"America/Havana",
    "iso:country":"CU",
    "name:spa_x_preferred":[
        "La Catalina"
    ],
    "name:und_x_variant":[
        "Catalina"
    ],
    "wof:name":"La Catalina",
    "wof:placetype":"locality"
},
  "geometry": {"coordinates":[-82.65954000000001,23.01684],"type":"Point"}
}