{
  "type": "Feature",
  "properties": {
    "gn:admin1_code":"14",
    "gn:asciiname":"Oliva",
    "gn:country_code":"CU",
    "gn:dem":14,
    "gn:feature_class":"P",
    "gn:feature_code":"PPLL",
    "gn:name":"Oliva",
    "gn:population":0,
    "gn:timezone":"America/Havana",
    "iso:country":"CU",
    "name:arg_x_preferred":[
        "Oliva"
    ],
    "name:cat_x_preferred":[
        "Oliva"
    ],
    "name:dan_x_preferred":[
        "Oliva"
    ],
    "name:deu_x_preferred":[
        "Oliva"
    ],
    "name:epo_x_preferred":[
        "Olivo"
    ],
    "name:est_x_preferred":[
        "Oliva"
    ],
    "name:eus_x_preferred":[
        "Oliva"
    ],
    "name:fra_x_preferred":[
        "Oliva"
    ],
    "name:glg_x_preferred":[
        "Oliva"
    ],
    "name:hun_x_preferred":[
        "Oliva"
    ],
    "name:ita_x_preferred":[
        "Oliva"
    ],
    "name:kor_x_preferred":[
        "\uc62c\ub9ac\ubc14"
    ],
    "name:mlg_x_preferred":[
        "Oliva"
    ],
    "name:msa_x_preferred":[
        "Oliva"
    ],
    "name:nld_x_preferred":[
        "Oliva"
    ],
    "name:oci_x_preferred":[
        "Oliva"
    ],
    "name:pol_x_preferred":[
        "Oliva"
    ],
    "name:por_x_preferred":[
        "Oliva"
    ],
    "name:rus_x_preferred":[
        "\u041e\u043b\u0438\u0432\u0430"
    ],
    "name:spa_x_preferred":[
        "Oliva"
    ],
    "name:sqi_x_preferred":[
        "Oliva"
    ],
    "name:srp_x_preferred":[
        "\u041e\u043b\u0438\u0432\u0430"
    ],
    "name:swe_x_preferred":[
        "Oliva"
    ],
    "name:ukr_x_preferred":[
        "\u041e\u043b\u0456\u0432\u0430"
    ],
    "name:war_x_preferred":[
        "Oliva"
    ],
    "name:zho_x_preferred":[
        "\u5965\u5229\u74e6"
    ],
    "wof:name":"Oliva",
    "wof:placetype":"locality"
},
  "geometry": {"coordinates":[-79.86667,21.85],"type":"Point"}
}