{
  "type": "Feature",
  "properties": {
    "gn:admin1_code":"12",
    "gn:asciiname":"Floro Perez",
    "gn:country_code":"CU",
    "gn:dem":65,
    "gn:feature_class":"P",
    "gn:feature_code":"PPL",
    "gn:name":"Floro P\u00e9rez",
    "gn:population":0,
    "gn:timezone":"America/Havana",
    "iso:country":"CU",
    "name:und_x_variant":[
        "Auras",
        "Poblado Auras",
        "Floro P\u00e9rez"
    ],
    "wof:name":"Floro Perez",
    "wof:placetype":"locality"
},
  "geometry": {"coordinates":[-76.23366999999998,21.0204],"type":"Point"}
}