{
  "type": "Feature",
  "properties": {
    "gn:admin1_code":"09",
    "gn:asciiname":"El Corojo",
    "gn:country_code":"CU",
    "gn:dem":183,
    "gn:feature_class":"P",
    "gn:feature_code":"PPL",
    "gn:name":"El Corojo",
    "gn:population":0,
    "gn:timezone":"America/Havana",
    "iso:country":"CU",
    "wof:name":"El Corojo",
    "wof:placetype":"locality"
},
  "geometry": {"coordinates":[-76.58333,20.21667],"type":"Point"}
}