{
  "type": "Feature",
  "properties": {
    "gn:admin1_code":"12",
    "gn:asciiname":"Calderon",
    "gn:country_code":"CU",
    "gn:dem":15,
    "gn:feature_class":"P",
    "gn:feature_code":"PPL",
    "gn:name":"Calder\u00f3n",
    "gn:population":0,
    "gn:timezone":"America/Havana",
    "iso:country":"CU",
    "wof:name":"Calderon",
    "wof:placetype":"locality"
},
  "geometry": {"coordinates":[-76.14083000000002,21.06083],"type":"Point"}
}