{
  "type": "Feature",
  "properties": {
    "gn:admin1_code":"15",
    "gn:asciiname":"Manacal",
    "gn:country_code":"CU",
    "gn:dem":335,
    "gn:feature_class":"P",
    "gn:feature_code":"PPLL",
    "gn:name":"Manacal",
    "gn:population":0,
    "gn:timezone":"America/Havana",
    "iso:country":"CU",
    "name:spa_x_preferred":[
        "Manacal"
    ],
    "wof:name":"Manacal",
    "wof:placetype":"locality"
},
  "geometry": {"coordinates":[-75.64474,20.21953],"type":"Point"}
}