{
  "type": "Feature",
  "properties": {
    "iso:country":"CU",
    "name:spa_x_preferred":[
        "Monte Barreto"
    ],
    "name:spa_x_variant":[
        "Mte Barreto"
    ],
    "name:unk_x_variant":[
        "Monte Barreto"
    ],
    "qs:gn_adm0_cc":"CU",
    "qs:gn_local":3553478,
    "qs:local_max":6362,
    "qs:local_sum":28186,
    "qs:localhoods":23,
    "qs:name":"Monte Barreto",
    "qs:name_adm0":"Cuba",
    "qs:name_adm1":"Ciudad de la Habana",
    "qs:name_local":"La Habana",
    "qs:photo_max":197,
    "qs:photo_sum":865,
    "qs:placetype":"Suburb",
    "qs:quad_count":38,
    "qs:woe_adm0":23424793,
    "qs:woe_adm1":2345107,
    "qs:woe_adm2":0,
    "qs:woe_lau":0,
    "qs:woe_local":63817,
    "qs:woe_ver":"7.10.0",
    "wof:lang":[
        "spa"
    ],
    "wof:name":"Monte Barreto",
    "wof:placetype":"neighbourhood"
},
  "geometry": {"coordinates":[-82.43520100000001,23.1064],"type":"Point"}
}