{
  "type": "Feature",
  "properties": {
    "gn:admin1_code":"03",
    "gn:asciiname":"San Claudio",
    "gn:country_code":"CU",
    "gn:dem":77,
    "gn:feature_class":"P",
    "gn:feature_code":"PPLL",
    "gn:name":"San Claudio",
    "gn:population":0,
    "gn:timezone":"America/Havana",
    "iso:country":"CU",
    "wof:name":"San Claudio",
    "wof:placetype":"locality"
},
  "geometry": {"coordinates":[-81.59694,22.83417],"type":"Point"}
}