{
  "type": "Feature",
  "properties": {
    "gn:admin1_code":"07",
    "gn:asciiname":"Caimito Dos",
    "gn:cc2":"CU",
    "gn:country_code":"CU",
    "gn:dem":32,
    "gn:feature_class":"P",
    "gn:feature_code":"PPL",
    "gn:name":"Caimito Dos",
    "gn:population":0,
    "gn:timezone":"America/Havana",
    "iso:country":"CU",
    "name:und_x_variant":[
        "Caimito",
        "Caimito Dos"
    ],
    "wof:name":"Caimito Dos",
    "wof:placetype":"locality"
},
  "geometry": {"coordinates":[-78.31917,21.88139],"type":"Point"}
}