{
  "type": "Feature",
  "properties": {
    "gn:admin1_code":"04",
    "gn:asciiname":"Patricio Lumumba",
    "gn:country_code":"CU",
    "gn:dem":47,
    "gn:feature_class":"P",
    "gn:feature_code":"PPL",
    "gn:name":"Patric\u00edo Lumumba",
    "gn:population":0,
    "gn:timezone":"America/Havana",
    "iso:country":"CU",
    "name:spa_x_preferred":[
        "Patric\u00edo Lumumba"
    ],
    "wof:name":"Patricio Lumumba",
    "wof:placetype":"locality"
},
  "geometry": {"coordinates":[-82.81721,21.70875],"type":"Point"}
}