{
  "type": "Feature",
  "properties": {
    "gn:admin1_code":"03",
    "gn:asciiname":"Los Paraisos",
    "gn:country_code":"CU",
    "gn:dem":18,
    "gn:feature_class":"P",
    "gn:feature_code":"PPLL",
    "gn:name":"Los Para\u00edsos",
    "gn:population":0,
    "gn:timezone":"America/Havana",
    "iso:country":"CU",
    "wof:name":"Los Paraisos",
    "wof:placetype":"locality"
},
  "geometry": {"coordinates":[-81.28333000000001,22.71667],"type":"Point"}
}