{
  "type": "Feature",
  "properties": {
    "gn:admin1_code":"07",
    "gn:asciiname":"Monte",
    "gn:country_code":"CU",
    "gn:dem":70,
    "gn:feature_class":"P",
    "gn:feature_code":"PPLL",
    "gn:name":"Monte",
    "gn:population":0,
    "gn:timezone":"America/Havana",
    "iso:country":"CU",
    "name:spa_x_preferred":[
        "Monte"
    ],
    "wof:name":"Monte",
    "wof:placetype":"locality"
},
  "geometry": {"coordinates":[-78.24384999999999,21.77871],"type":"Point"}
}