{
  "type": "Feature",
  "properties": {
    "gn:admin1_code":"AR",
    "gn:asciiname":"Piedra",
    "gn:country_code":"CU",
    "gn:dem":17,
    "gn:feature_class":"P",
    "gn:feature_code":"PPL",
    "gn:name":"Piedra",
    "gn:population":0,
    "gn:timezone":"America/Havana",
    "iso:country":"CU",
    "name:ara_x_preferred":[
        "\u0628\u064a\u0635\u0631\u0629"
    ],
    "name:fas_x_preferred":[
        "\u06a9\u0686\u0644\u06cc"
    ],
    "name:swa_x_preferred":[
        "Upara"
    ],
    "wof:name":"Piedra",
    "wof:placetype":"locality"
},
  "geometry": {"coordinates":[-83.01666999999998,22.61667000000001],"type":"Point"}
}