{
  "type": "Feature",
  "properties": {
    "gn:admin1_code":"01",
    "gn:asciiname":"Ruiz",
    "gn:country_code":"CU",
    "gn:dem":14,
    "gn:feature_class":"P",
    "gn:feature_code":"PPLL",
    "gn:name":"Ruiz",
    "gn:population":0,
    "gn:timezone":"America/Havana",
    "iso:country":"CU",
    "name:deu_x_preferred":[
        "Ruiz"
    ],
    "name:ita_x_preferred":[
        "Ruiz"
    ],
    "name:spa_x_preferred":[
        "Ruiz"
    ],
    "wof:name":"Ruiz",
    "wof:placetype":"locality"
},
  "geometry": {"coordinates":[-83.46380000000001,22.31426],"type":"Point"}
}