{
  "type": "Feature",
  "properties": {
    "gn:admin1_code":"10",
    "gn:asciiname":"Florida",
    "gn:country_code":"CU",
    "gn:dem":194,
    "gn:feature_class":"P",
    "gn:feature_code":"PPL",
    "gn:name":"Florida",
    "gn:population":0,
    "gn:timezone":"America/Havana",
    "iso:country":"CU",
    "name:spa_x_preferred":[
        "Florida"
    ],
    "wof:name":"Florida",
    "wof:placetype":"locality"
},
  "geometry": {"coordinates":[-75.14157,20.25803],"type":"Point"}
}