{
  "type": "Feature",
  "properties": {
    "gn:admin1_code":"10",
    "gn:asciiname":"Dos Brazos",
    "gn:country_code":"CU",
    "gn:dem":593,
    "gn:feature_class":"P",
    "gn:feature_code":"PPLL",
    "gn:name":"Dos Brazos",
    "gn:population":0,
    "gn:timezone":"America/Havana",
    "iso:country":"CU",
    "wof:name":"Dos Brazos",
    "wof:placetype":"locality"
},
  "geometry": {"coordinates":[-74.82944000000001,20.25583],"type":"Point"}
}