{
  "type": "Feature",
  "properties": {
    "gn:admin1_code":"12",
    "gn:asciiname":"La Manteca",
    "gn:cc2":"CU",
    "gn:country_code":"CU",
    "gn:dem":91,
    "gn:feature_class":"P",
    "gn:feature_code":"PPL",
    "gn:name":"La Manteca",
    "gn:population":0,
    "gn:timezone":"America/Havana",
    "iso:country":"CU",
    "name:und_x_variant":[
        "Manteca",
        "La Manteca"
    ],
    "wof:name":"La Manteca",
    "wof:placetype":"locality"
},
  "geometry": {"coordinates":[-76.64860999999998,20.82944],"type":"Point"}
}