{
  "type": "Feature",
  "properties": {
    "gn:admin1_code":"16",
    "gn:asciiname":"Las Mercedes",
    "gn:country_code":"CU",
    "gn:dem":52,
    "gn:feature_class":"P",
    "gn:feature_code":"PPLL",
    "gn:name":"Las Mercedes",
    "gn:population":0,
    "gn:timezone":"America/Havana",
    "iso:country":"CU",
    "name:ceb_x_preferred":[
        "Las Mercedes"
    ],
    "name:deu_x_preferred":[
        "Las Mercedes"
    ],
    "name:spa_x_preferred":[
        "Las Mercedes"
    ],
    "name:swe_x_preferred":[
        "Las Mercedes"
    ],
    "wof:name":"Las Mercedes",
    "wof:placetype":"locality"
},
  "geometry": {"coordinates":[-79.84245,22.54647000000001],"type":"Point"}
}