{
  "type": "Feature",
  "properties": {
    "gn:admin1_code":"16",
    "gn:asciiname":"Panque Manacas",
    "gn:country_code":"CU",
    "gn:dem":79,
    "gn:feature_class":"P",
    "gn:feature_code":"PPL",
    "gn:name":"Panqu\u00e9 Manacas",
    "gn:population":0,
    "gn:timezone":"America/Havana",
    "iso:country":"CU",
    "name:spa_x_preferred":[
        "Panque Manacas"
    ],
    "name:spa_x_variant":[
        "Panqu\u00e9 Manacas",
        "Panqu\u00e9 de Manacas"
    ],
    "wof:name":"Panque Manacas",
    "wof:placetype":"locality"
},
  "geometry": {"coordinates":[-80.34935,22.60601],"type":"Point"}
}