{
  "type": "Feature",
  "properties": {
    "iso:country":"CU",
    "name:spa_x_preferred":[
        "Potrerillo"
    ],
    "name:unk_x_variant":[
        "Pueblo Potrerillo"
    ],
    "qs:gn_country":"CU",
    "qs:gn_fcode":"PPL",
    "qs:gn_pop":0,
    "qs:name":"Potrerillo",
    "qs:name_adm0":"Cuba",
    "qs:name_adm1":"Holguin",
    "qs:photos":21,
    "qs:photos_1k":4,
    "qs:photos_9k":1,
    "qs:photos_9r":1,
    "qs:photos_all":21,
    "qs:photos_sr":1,
    "qs:placetype":"Town",
    "qs:pop_sr":"0",
    "qs:woe_adm0":23424793,
    "wd:wordcount":34,
    "wof:name":"Potrerillo",
    "wof:placetype":"locality"
},
  "geometry": {"coordinates":[-76.08972,21.05917],"type":"Point"}
}