{
  "type": "Feature",
  "properties": {
    "gn:admin1_code":"13",
    "gn:asciiname":"San Pedro de Maniabon",
    "gn:cc2":"CU",
    "gn:country_code":"CU",
    "gn:dem":89,
    "gn:feature_class":"P",
    "gn:feature_code":"PPL",
    "gn:name":"San Pedro de Maniab\u00f3n",
    "gn:population":0,
    "gn:timezone":"America/Havana",
    "iso:country":"CU",
    "name:und_x_variant":[
        "Poblado San Pedro de Maniabon",
        "Maniab\u00f3n",
        "San Pedro de Maniab\u00f3n"
    ],
    "wof:name":"San Pedro de Maniabon",
    "wof:placetype":"locality"
},
  "geometry": {"coordinates":[-76.52694,21.07333],"type":"Point"}
}