{
  "type": "Feature",
  "properties": {
    "gn:admin1_code":"09",
    "gn:asciiname":"Jagua",
    "gn:country_code":"CU",
    "gn:dem":25,
    "gn:feature_class":"P",
    "gn:feature_code":"PPL",
    "gn:name":"Jagua",
    "gn:population":0,
    "gn:timezone":"America/Havana",
    "iso:country":"CU",
    "name:ceb_x_preferred":[
        "Jagua"
    ],
    "name:ita_x_preferred":[
        "Jagua"
    ],
    "name:spa_x_preferred":[
        "Jagua"
    ],
    "name:swe_x_preferred":[
        "Jagua"
    ],
    "wof:name":"Jagua",
    "wof:placetype":"locality"
},
  "geometry": {"coordinates":[-77.54686,20.04574],"type":"Point"}
}