{
  "type": "Feature",
  "properties": {
    "gn:admin1_code":"01",
    "gn:asciiname":"Nombre de Dios",
    "gn:country_code":"CU",
    "gn:dem":19,
    "gn:feature_class":"P",
    "gn:feature_code":"PPL",
    "gn:name":"Nombre de Dios",
    "gn:population":0,
    "gn:timezone":"America/Havana",
    "iso:country":"CU",
    "name:srp_x_preferred":[
        "\u041d\u043e\u043c\u0431\u0440\u0435 \u0434\u0435 \u0414\u0438\u043e\u0441"
    ],
    "wof:name":"Nombre de Dios",
    "wof:placetype":"locality"
},
  "geometry": {"coordinates":[-84.01666999999998,22.61667000000001],"type":"Point"}
}