{
  "type": "Feature",
  "properties": {
    "gn:admin1_code":"10",
    "gn:asciiname":"San Pedro",
    "gn:country_code":"CU",
    "gn:dem":131,
    "gn:feature_class":"P",
    "gn:feature_code":"PPLL",
    "gn:name":"San Pedro",
    "gn:population":0,
    "gn:timezone":"America/Havana",
    "iso:country":"CU",
    "wof:name":"San Pedro",
    "wof:placetype":"locality"
},
  "geometry": {"coordinates":[-75.10556,20.20889],"type":"Point"}
}