{
  "type": "Feature",
  "properties": {
    "gn:admin1_code":"08",
    "gn:asciiname":"Jose Chavez",
    "gn:country_code":"CU",
    "gn:dem":73,
    "gn:feature_class":"P",
    "gn:feature_code":"PPLL",
    "gn:name":"Jos\u00e9 Ch\u00e1vez",
    "gn:population":0,
    "gn:timezone":"America/Havana",
    "iso:country":"CU",
    "wof:name":"Jose Chavez",
    "wof:placetype":"locality"
},
  "geometry": {"coordinates":[-80.36667,22.28333],"type":"Point"}
}