{
  "type": "Feature",
  "properties": {
    "gn:admin1_code":"13",
    "gn:asciiname":"Entronque Lebanon",
    "gn:country_code":"CU",
    "gn:dem":102,
    "gn:feature_class":"P",
    "gn:feature_code":"PPL",
    "gn:name":"Entronque Leban\u00f3n",
    "gn:population":0,
    "gn:timezone":"America/Havana",
    "iso:country":"CU",
    "name:spa_x_preferred":[
        "Entronque Leban\u00f3n"
    ],
    "wof:name":"Entronque Lebanon",
    "wof:placetype":"locality"
},
  "geometry": {"coordinates":[-77.08521,21.04723],"type":"Point"}
}