{
  "type": "Feature",
  "properties": {
    "gn:admin1_code":"12",
    "gn:asciiname":"Tacamara",
    "gn:country_code":"CU",
    "gn:dem":110,
    "gn:feature_class":"P",
    "gn:feature_code":"PPL",
    "gn:name":"Tac\u00e1mara",
    "gn:population":0,
    "gn:timezone":"America/Havana",
    "iso:country":"CU",
    "name:und_x_variant":[
        "Hicacos",
        "Tac\u00e1mara"
    ],
    "wof:name":"Tacamara",
    "wof:placetype":"locality"
},
  "geometry": {"coordinates":[-76.04746999999998,20.71762],"type":"Point"}
}