{
  "type": "Feature",
  "properties": {
    "gn:admin1_code":"12",
    "gn:asciiname":"El Palmar de Vallejo",
    "gn:country_code":"CU",
    "gn:dem":127,
    "gn:feature_class":"P",
    "gn:feature_code":"PPLL",
    "gn:name":"El Palmar de Vallejo",
    "gn:population":0,
    "gn:timezone":"America/Havana",
    "iso:country":"CU",
    "wof:name":"El Palmar de Vallejo",
    "wof:placetype":"locality"
},
  "geometry": {"coordinates":[-75.95,20.86667000000001],"type":"Point"}
}