{
  "type": "Feature",
  "properties": {
    "gn:admin1_code":"09",
    "gn:asciiname":"Padron",
    "gn:country_code":"CU",
    "gn:dem":69,
    "gn:feature_class":"P",
    "gn:feature_code":"PPLL",
    "gn:name":"Padr\u00f3n",
    "gn:population":0,
    "gn:timezone":"America/Havana",
    "iso:country":"CU",
    "name:spa_x_preferred":[
        "Padr\u00f3n"
    ],
    "wof:name":"Padron",
    "wof:placetype":"locality"
},
  "geometry": {"coordinates":[-76.60115,20.39736],"type":"Point"}
}