{
  "type": "Feature",
  "properties": {
    "gn:admin1_code":"01",
    "gn:asciiname":"Tres por Ciento",
    "gn:cc2":"CU",
    "gn:country_code":"CU",
    "gn:dem":36,
    "gn:feature_class":"P",
    "gn:feature_code":"PPLL",
    "gn:name":"Tres por Ciento",
    "gn:population":0,
    "gn:timezone":"America/Havana",
    "iso:country":"CU",
    "name:und_x_variant":[
        "Torquiola",
        "Tres por Ciento"
    ],
    "wof:name":"Tres por Ciento",
    "wof:placetype":"locality"
},
  "geometry": {"coordinates":[-83.73333000000002,22.75],"type":"Point"}
}