{
  "type": "Feature",
  "properties": {
    "gn:admin1_code":"12",
    "gn:asciiname":"Sabino",
    "gn:country_code":"CU",
    "gn:dem":145,
    "gn:feature_class":"P",
    "gn:feature_code":"PPLL",
    "gn:name":"Sabino",
    "gn:population":0,
    "gn:timezone":"America/Havana",
    "iso:country":"CU",
    "wof:name":"Sabino",
    "wof:placetype":"locality"
},
  "geometry": {"coordinates":[-76.26721999999999,20.9575],"type":"Point"}
}