{
  "type": "Feature",
  "properties": {
    "gn:admin1_code":"15",
    "gn:asciiname":"Caoba",
    "gn:country_code":"CU",
    "gn:dem":173,
    "gn:feature_class":"P",
    "gn:feature_code":"PPL",
    "gn:name":"Caoba",
    "gn:population":0,
    "gn:timezone":"America/Havana",
    "iso:country":"CU",
    "name:spa_x_preferred":[
        "Caoba"
    ],
    "wof:name":"Caoba",
    "wof:placetype":"locality"
},
  "geometry": {"coordinates":[-75.63918000000002,20.40577],"type":"Point"}
}