{
  "type": "Feature",
  "properties": {
    "gn:admin1_code":"05",
    "gn:asciiname":"El Peru",
    "gn:country_code":"CU",
    "gn:dem":41,
    "gn:feature_class":"P",
    "gn:feature_code":"PPLL",
    "gn:name":"El Per\u00fa",
    "gn:population":0,
    "gn:timezone":"America/Havana",
    "iso:country":"CU",
    "name:spa_x_preferred":[
        "El Per\u00fa"
    ],
    "wof:name":"El Peru",
    "wof:placetype":"locality"
},
  "geometry": {"coordinates":[-78.27028,21.45833],"type":"Point"}
}