{
  "type": "Feature",
  "properties": {
    "gn:admin1_code":"MA",
    "gn:asciiname":"Cuellita",
    "gn:country_code":"CU",
    "gn:dem":109,
    "gn:feature_class":"P",
    "gn:feature_code":"PPLL",
    "gn:name":"Cuellita",
    "gn:population":0,
    "gn:timezone":"America/Havana",
    "iso:country":"CU",
    "wof:name":"Cuellita",
    "wof:placetype":"locality"
},
  "geometry": {"coordinates":[-82.09999999999999,22.93333],"type":"Point"}
}