{
  "type": "Feature",
  "properties": {
    "gn:admin1_code":"10",
    "gn:asciiname":"El Cilindro",
    "gn:country_code":"CU",
    "gn:dem":493,
    "gn:feature_class":"P",
    "gn:feature_code":"PPL",
    "gn:name":"El Cilindro",
    "gn:population":0,
    "gn:timezone":"America/Havana",
    "iso:country":"CU",
    "name:spa_x_preferred":[
        "El Cilindro"
    ],
    "wof:name":"El Cilindro",
    "wof:placetype":"locality"
},
  "geometry": {"coordinates":[-74.92192,20.33307000000001],"type":"Point"}
}