{
  "type": "Feature",
  "properties": {
    "gn:admin1_code":"AR",
    "gn:asciiname":"Minas de Buenavista",
    "gn:country_code":"CU",
    "gn:dem":66,
    "gn:feature_class":"P",
    "gn:feature_code":"PPL",
    "gn:name":"Minas de Buenavista",
    "gn:population":0,
    "gn:timezone":"America/Havana",
    "iso:country":"CU",
    "name:spa_x_preferred":[
        "Minas de Buenavista"
    ],
    "wof:name":"Minas de Buenavista",
    "wof:placetype":"locality"
},
  "geometry": {"coordinates":[-83.04902,22.9093],"type":"Point"}
}