{
  "type": "Feature",
  "properties": {
    "gn:admin1_code":"10",
    "gn:asciiname":"El Platano",
    "gn:country_code":"CU",
    "gn:dem":477,
    "gn:feature_class":"P",
    "gn:feature_code":"PPL",
    "gn:name":"El Pl\u00e1tano",
    "gn:population":0,
    "gn:timezone":"America/Havana",
    "iso:country":"CU",
    "name:spa_x_preferred":[
        "El Pl\u00e1tano"
    ],
    "wof:name":"El Platano",
    "wof:placetype":"locality"
},
  "geometry": {"coordinates":[-74.65348,20.1983],"type":"Point"}
}