{
  "type": "Feature",
  "properties": {
    "gn:admin1_code":"15",
    "gn:asciiname":"El Macho",
    "gn:country_code":"CU",
    "gn:dem":25,
    "gn:feature_class":"P",
    "gn:feature_code":"PPL",
    "gn:name":"El Macho",
    "gn:population":0,
    "gn:timezone":"America/Havana",
    "iso:country":"CU",
    "name:spa_x_preferred":[
        "El Macho"
    ],
    "wof:name":"El Macho",
    "wof:placetype":"locality"
},
  "geometry": {"coordinates":[-77.01065,19.88976],"type":"Point"}
}