{
  "type": "Feature",
  "properties": {
    "gn:admin1_code":"01",
    "gn:asciiname":"Vivanco",
    "gn:country_code":"CU",
    "gn:dem":23,
    "gn:feature_class":"P",
    "gn:feature_code":"PPLL",
    "gn:name":"Vivanco",
    "gn:population":0,
    "gn:timezone":"America/Havana",
    "iso:country":"CU",
    "name:spa_x_preferred":[
        "Vivanco"
    ],
    "wof:name":"Vivanco",
    "wof:placetype":"locality"
},
  "geometry": {"coordinates":[-83.40993,22.45111],"type":"Point"}
}