{
  "type": "Feature",
  "properties": {
    "gn:admin1_code":"03",
    "gn:asciiname":"Dos Rios",
    "gn:country_code":"CU",
    "gn:dem":36,
    "gn:feature_class":"P",
    "gn:feature_code":"PPL",
    "gn:name":"Dos R\u00edos",
    "gn:population":0,
    "gn:timezone":"America/Havana",
    "iso:country":"CU",
    "name:spa_x_preferred":[
        "Dos R\u00edos"
    ],
    "wof:name":"Dos Rios",
    "wof:placetype":"locality"
},
  "geometry": {"coordinates":[-80.79635,22.50867],"type":"Point"}
}