{
  "type": "Feature",
  "properties": {
    "gn:admin1_code":"10",
    "gn:asciiname":"Yarenzal",
    "gn:country_code":"CU",
    "gn:dem":362,
    "gn:feature_class":"P",
    "gn:feature_code":"PPL",
    "gn:name":"Yarenzal",
    "gn:population":0,
    "gn:timezone":"America/Havana",
    "iso:country":"CU",
    "name:spa_x_preferred":[
        "Yarenzal"
    ],
    "wof:name":"Yarenzal",
    "wof:placetype":"locality"
},
  "geometry": {"coordinates":[-74.32865,20.15824],"type":"Point"}
}