{
  "type": "Feature",
  "properties": {
    "gn:admin1_code":"14",
    "gn:asciiname":"Los Cocos",
    "gn:country_code":"CU",
    "gn:dem":13,
    "gn:feature_class":"P",
    "gn:feature_code":"PPL",
    "gn:name":"Los Cocos",
    "gn:population":0,
    "gn:timezone":"America/Havana",
    "iso:country":"CU",
    "name:nld_x_preferred":[
        "Los Cocos"
    ],
    "name:por_x_preferred":[
        "Los Cocos"
    ],
    "name:spa_x_preferred":[
        "Los Cocos"
    ],
    "wof:name":"Los Cocos",
    "wof:placetype":"locality"
},
  "geometry": {"coordinates":[-79.41863000000002,21.69893],"type":"Point"}
}