{
  "type": "Feature",
  "properties": {
    "gn:admin1_code":"01",
    "gn:asciiname":"El Sitio",
    "gn:country_code":"CU",
    "gn:dem":133,
    "gn:feature_class":"P",
    "gn:feature_code":"PPL",
    "gn:name":"El Sitio",
    "gn:population":0,
    "gn:timezone":"America/Havana",
    "iso:country":"CU",
    "name:spa_x_preferred":[
        "El Sitio"
    ],
    "wof:name":"El Sitio",
    "wof:placetype":"locality"
},
  "geometry": {"coordinates":[-83.51293000000003,22.73768],"type":"Point"}
}