{
  "type": "Feature",
  "properties": {
    "gn:admin1_code":"13",
    "gn:asciiname":"Sabanita",
    "gn:country_code":"CU",
    "gn:dem":90,
    "gn:feature_class":"P",
    "gn:feature_code":"PPLL",
    "gn:name":"Sabanita",
    "gn:population":0,
    "gn:timezone":"America/Havana",
    "iso:country":"CU",
    "wof:name":"Sabanita",
    "wof:placetype":"locality"
},
  "geometry": {"coordinates":[-77.11667,20.98333],"type":"Point"}
}