{
  "type": "Feature",
  "properties": {
    "gn:admin1_code":"05",
    "gn:asciiname":"Cubitas",
    "gn:country_code":"CU",
    "gn:dem":53,
    "gn:feature_class":"P",
    "gn:feature_code":"PPLA2",
    "gn:name":"Cubitas",
    "gn:population":0,
    "gn:timezone":"America/Havana",
    "iso:country":"CU",
    "name:spa_x_preferred":[
        "Cubitas"
    ],
    "wof:name":"Cubitas",
    "wof:placetype":"locality"
},
  "geometry": {"coordinates":[-77.76130000000001,21.71212],"type":"Point"}
}