{
  "type": "Feature",
  "properties": {
    "gn:admin1_code":"05",
    "gn:asciiname":"Cubitas",
    "gn:country_code":"CU",
    "gn:dem":53,
    "gn:feature_class":"P",
    "gn:feature_code":"PPLA2",
    "gn:name":"Cubitas",
    "gn:population":0,
    "gn:timezone":"America/Havana",
    "iso:country":"CU",
    "name:kat_x_preferred":[
        "\u10e1\u10d8\u10d4\u10e0\u10d0-\u10d3\u10d4-\u10d9\u10e3\u10d1\u10d8\u10e2\u10d0\u10e1\u10d8"
    ],
    "name:spa_x_preferred":[
        "Cubitas"
    ],
    "name:zho_x_preferred":[
        "\u5eab\u7dad\u5854\u65af\u5c71"
    ],
    "wof:name":"Cubitas",
    "wof:placetype":"locality"
},
  "geometry": {"coordinates":[-77.76130000000001,21.71212],"type":"Point"}
}