{
  "type": "Feature",
  "properties": {
    "gn:admin1_code":"03",
    "gn:asciiname":"Las Charcas",
    "gn:country_code":"CU",
    "gn:dem":65,
    "gn:feature_class":"P",
    "gn:feature_code":"PPLL",
    "gn:name":"Las Charcas",
    "gn:population":0,
    "gn:timezone":"America/Havana",
    "iso:country":"CU",
    "name:ceb_x_preferred":[
        "Las Charcas"
    ],
    "name:ita_x_preferred":[
        "Las Charcas"
    ],
    "name:por_x_preferred":[
        "Las Charcas"
    ],
    "name:slv_x_preferred":[
        "Las Charcas"
    ],
    "name:spa_x_preferred":[
        "Las Charcas"
    ],
    "name:swe_x_preferred":[
        "Las Charcas"
    ],
    "name:und_x_variant":[
        "Los Charcas"
    ],
    "name:urd_x_preferred":[
        "\u0644\u0627\u0633 \u0686\u0627\u0631\u06a9\u0627\u0633"
    ],
    "name:zho_x_preferred":[
        "\u62c9\u65af\u67e5\u723e\u5361\u65af"
    ],
    "wof:name":"Las Charcas",
    "wof:placetype":"locality"
},
  "geometry": {"coordinates":[-80.62528,22.80065],"type":"Point"}
}