{
  "type": "Feature",
  "properties": {
    "gn:admin1_code":"03",
    "gn:asciiname":"Las Charcas",
    "gn:country_code":"CU",
    "gn:dem":65,
    "gn:feature_class":"P",
    "gn:feature_code":"PPLL",
    "gn:name":"Las Charcas",
    "gn:population":0,
    "gn:timezone":"America/Havana",
    "iso:country":"CU",
    "name:spa_x_preferred":[
        "Las Charcas"
    ],
    "name:und_x_variant":[
        "Los Charcas"
    ],
    "wof:name":"Las Charcas",
    "wof:placetype":"locality"
},
  "geometry": {"coordinates":[-80.62528,22.80065],"type":"Point"}
}