{
  "type": "Feature",
  "properties": {
    "gn:admin1_code":"09",
    "gn:asciiname":"El Puntico",
    "gn:country_code":"CU",
    "gn:dem":37,
    "gn:feature_class":"P",
    "gn:feature_code":"PPL",
    "gn:name":"El Puntico",
    "gn:population":0,
    "gn:timezone":"America/Havana",
    "iso:country":"CU",
    "name:und_x_variant":[
        "El Puntizo",
        "El Puntico"
    ],
    "wof:name":"El Puntico",
    "wof:placetype":"locality"
},
  "geometry": {"coordinates":[-77.27112,20.21172],"type":"Point"}
}