{
  "type": "Feature",
  "properties": {
    "gn:admin1_code":"05",
    "gn:asciiname":"Candido Gonzalez",
    "gn:country_code":"CU",
    "gn:dem":16,
    "gn:feature_class":"P",
    "gn:feature_code":"PPL",
    "gn:name":"C\u00e1ndido Gonz\u00e1lez",
    "gn:population":0,
    "gn:timezone":"America/Havana",
    "iso:country":"CU",
    "name:und_x_variant":[
        "Santa Marta",
        "C\u00e1ndido Gonz\u00e1les",
        "C\u00e1ndido Gonz\u00e1lez"
    ],
    "wof:name":"Candido Gonzalez",
    "wof:placetype":"locality"
},
  "geometry": {"coordinates":[-78.01475000000001,20.81375],"type":"Point"}
}