{
  "type": "Feature",
  "properties": {
    "gn:admin1_code":"13",
    "gn:asciiname":"La Escondida",
    "gn:country_code":"CU",
    "gn:dem":35,
    "gn:feature_class":"P",
    "gn:feature_code":"PPL",
    "gn:name":"La Escondida",
    "gn:population":0,
    "gn:timezone":"America/Havana",
    "iso:country":"CU",
    "name:spa_x_preferred":[
        "La Escondida"
    ],
    "wof:name":"La Escondida",
    "wof:placetype":"locality"
},
  "geometry": {"coordinates":[-76.46766,21.09613],"type":"Point"}
}