{
  "type": "Feature",
  "properties": {
    "gn:admin1_code":"12",
    "gn:asciiname":"Santa",
    "gn:country_code":"CU",
    "gn:dem":33,
    "gn:feature_class":"P",
    "gn:feature_code":"PPL",
    "gn:name":"Santa",
    "gn:population":0,
    "gn:timezone":"America/Havana",
    "iso:country":"CU",
    "wof:name":"Santa",
    "wof:placetype":"locality"
},
  "geometry": {"coordinates":[-75.77333,21.11833],"type":"Point"}
}