{
  "type": "Feature",
  "properties": {
    "gn:admin1_code":"15",
    "gn:asciiname":"San Miguel",
    "gn:country_code":"CU",
    "gn:dem":329,
    "gn:feature_class":"P",
    "gn:feature_code":"PPLL",
    "gn:name":"San Miguel",
    "gn:population":0,
    "gn:timezone":"America/Havana",
    "iso:country":"CU",
    "wof:name":"San Miguel",
    "wof:placetype":"locality"
},
  "geometry": {"coordinates":[-75.84028000000001,20.09806],"type":"Point"}
}