{
  "type": "Feature",
  "properties": {
    "gn:admin1_code":"10",
    "gn:asciiname":"Carolina",
    "gn:country_code":"CU",
    "gn:dem":461,
    "gn:feature_class":"P",
    "gn:feature_code":"PPLL",
    "gn:name":"Carolina",
    "gn:population":0,
    "gn:timezone":"America/Havana",
    "iso:country":"CU",
    "wof:name":"Carolina",
    "wof:placetype":"locality"
},
  "geometry": {"coordinates":[-74.98305999999999,20.34111],"type":"Point"}
}