{
  "type": "Feature",
  "properties": {
    "gn:admin1_code":"05",
    "gn:asciiname":"Antiguo Berrocal",
    "gn:cc2":"CU",
    "gn:country_code":"CU",
    "gn:dem":60,
    "gn:feature_class":"P",
    "gn:feature_code":"PPLL",
    "gn:name":"Antiguo Berrocal",
    "gn:population":0,
    "gn:timezone":"America/Havana",
    "iso:country":"CU",
    "name:und_x_variant":[
        "Berrocal Viejo",
        "Antiguo Berrocal"
    ],
    "wof:name":"Antiguo Berrocal",
    "wof:placetype":"locality"
},
  "geometry": {"coordinates":[-77.34999999999999,20.96667],"type":"Point"}
}