{
  "type": "Feature",
  "properties": {
    "iso:country":"CU",
    "qs:gn_country":"CU",
    "qs:gn_fcode":"PPLX",
    "qs:gn_pop":0,
    "qs:name":"Reparto Los Olmos",
    "qs:name_adm0":"Cuba",
    "qs:name_adm1":"Santiago de Cuba",
    "qs:photos":263,
    "qs:photos_1k":53,
    "qs:photos_9k":1,
    "qs:photos_9r":4,
    "qs:photos_all":263,
    "qs:photos_sr":5,
    "qs:placetype":"Suburb",
    "qs:pop_sr":"0",
    "qs:woe_adm0":23424793,
    "wof:name":"Reparto Los Olmos",
    "wof:placetype":"neighbourhood"
},
  "geometry": {"coordinates":[-75.81667,20.03333],"type":"Point"}
}