{
  "type": "Feature",
  "properties": {
    "gn:admin1_code":"13",
    "gn:asciiname":"Adelaida Dos",
    "gn:country_code":"CU",
    "gn:dem":42,
    "gn:feature_class":"P",
    "gn:feature_code":"PPL",
    "gn:name":"Adelaida Dos",
    "gn:population":0,
    "gn:timezone":"America/Havana",
    "iso:country":"CU",
    "name:spa_x_preferred":[
        "Adelaida Dos"
    ],
    "wof:name":"Adelaida Dos",
    "wof:placetype":"locality"
},
  "geometry": {"coordinates":[-77.5834,20.91147],"type":"Point"}
}