{
  "type": "Feature",
  "properties": {
    "gn:admin1_code":"13",
    "gn:asciiname":"Maranon Uno",
    "gn:country_code":"CU",
    "gn:dem":12,
    "gn:feature_class":"P",
    "gn:feature_code":"PPL",
    "gn:name":"Mara\u00f1\u00f3n Uno",
    "gn:population":0,
    "gn:timezone":"America/Havana",
    "iso:country":"CU",
    "name:spa_x_preferred":[
        "Mara\u00f1\u00f3n Uno"
    ],
    "wof:name":"Maranon Uno",
    "wof:placetype":"locality"
},
  "geometry": {"coordinates":[-76.7856,21.24986],"type":"Point"}
}