{
  "type": "Feature",
  "properties": {
    "gn:admin1_code":"12",
    "gn:asciiname":"Montoto",
    "gn:country_code":"CU",
    "gn:dem":75,
    "gn:feature_class":"P",
    "gn:feature_code":"PPLL",
    "gn:name":"Montoto",
    "gn:population":0,
    "gn:timezone":"America/Havana",
    "iso:country":"CU",
    "wof:name":"Montoto",
    "wof:placetype":"locality"
},
  "geometry": {"coordinates":[-76.38083,20.74806],"type":"Point"}
}