{
  "type": "Feature",
  "properties": {
    "gn:admin1_code":"16",
    "gn:asciiname":"Luisa",
    "gn:country_code":"CU",
    "gn:dem":39,
    "gn:feature_class":"P",
    "gn:feature_code":"PPL",
    "gn:name":"Luisa",
    "gn:population":0,
    "gn:timezone":"America/Havana",
    "iso:country":"CU",
    "name:spa_x_preferred":[
        "Luisa"
    ],
    "wof:name":"Luisa",
    "wof:placetype":"locality"
},
  "geometry": {"coordinates":[-79.76869000000001,22.57418],"type":"Point"}
}