{
  "type": "Feature",
  "properties": {
    "gn:admin1_code":"16",
    "gn:asciiname":"Juan Francisco de Aro",
    "gn:country_code":"CU",
    "gn:dem":85,
    "gn:feature_class":"P",
    "gn:feature_code":"PPL",
    "gn:name":"Juan Francisco de Aro",
    "gn:population":0,
    "gn:timezone":"America/Havana",
    "iso:country":"CU",
    "name:spa_x_preferred":[
        "Juan Francisco Aro"
    ],
    "name:spa_x_variant":[
        "Juan Francisco de Aro"
    ],
    "wof:name":"Juan Francisco de Aro",
    "wof:placetype":"locality"
},
  "geometry": {"coordinates":[-79.90361,22.53612],"type":"Point"}
}