{
  "type": "Feature",
  "properties": {
    "gn:admin1_code":"12",
    "gn:asciiname":"Canoa",
    "gn:country_code":"CU",
    "gn:dem":77,
    "gn:feature_class":"P",
    "gn:feature_code":"PPLL",
    "gn:name":"Canoa",
    "gn:population":0,
    "gn:timezone":"America/Havana",
    "iso:country":"CU",
    "name:pol_x_preferred":[
        "Canoa"
    ],
    "name:zho_x_preferred":[
        "\u5361\u8bfa\u963f"
    ],
    "wof:name":"Canoa",
    "wof:placetype":"locality"
},
  "geometry": {"coordinates":[-75.09999999999999,20.58333],"type":"Point"}
}