{
  "type": "Feature",
  "properties": {
    "gn:admin1_code":"15",
    "gn:asciiname":"El Quemado",
    "gn:country_code":"CU",
    "gn:dem":270,
    "gn:feature_class":"P",
    "gn:feature_code":"PPLL",
    "gn:name":"El Quemado",
    "gn:population":0,
    "gn:timezone":"America/Havana",
    "iso:country":"CU",
    "wof:name":"El Quemado",
    "wof:placetype":"locality"
},
  "geometry": {"coordinates":[-75.70833,20.13333],"type":"Point"}
}