{
  "type": "Feature",
  "properties": {
    "gn:admin1_code":"MA",
    "gn:asciiname":"Bosmenier",
    "gn:country_code":"CU",
    "gn:dem":142,
    "gn:feature_class":"P",
    "gn:feature_code":"PPLL",
    "gn:name":"Bosmenier",
    "gn:population":0,
    "gn:timezone":"America/Havana",
    "iso:country":"CU",
    "wof:name":"Bosmenier",
    "wof:placetype":"locality"
},
  "geometry": {"coordinates":[-82.09999999999999,22.96667],"type":"Point"}
}