{
  "type": "Feature",
  "properties": {
    "gn:admin1_code":"16",
    "gn:asciiname":"Baez",
    "gn:country_code":"CU",
    "gn:dem":77,
    "gn:feature_class":"P",
    "gn:feature_code":"PPLL",
    "gn:name":"B\u00e1ez",
    "gn:population":0,
    "gn:timezone":"America/Havana",
    "iso:country":"CU",
    "name:spa_x_preferred":[
        "B\u00e1ez"
    ],
    "wof:name":"Baez",
    "wof:placetype":"locality"
},
  "geometry": {"coordinates":[-80.58844000000001,22.9621],"type":"Point"}
}