{
  "type": "Feature",
  "properties": {
    "gn:admin1_code":"01",
    "gn:asciiname":"Bien Parado",
    "gn:country_code":"CU",
    "gn:dem":16,
    "gn:feature_class":"P",
    "gn:feature_code":"PPL",
    "gn:name":"Bien Parado",
    "gn:population":0,
    "gn:timezone":"America/Havana",
    "iso:country":"CU",
    "name:spa_x_preferred":[
        "Bien Parado"
    ],
    "wof:name":"Bien Parado",
    "wof:placetype":"locality"
},
  "geometry": {"coordinates":[-84.38665,21.93988],"type":"Point"}
}