{
  "type": "Feature",
  "properties": {
    "gn:admin1_code":"13",
    "gn:asciiname":"Leiva",
    "gn:cc2":"CU",
    "gn:country_code":"CU",
    "gn:dem":12,
    "gn:feature_class":"P",
    "gn:feature_code":"PPLL",
    "gn:name":"Leiva",
    "gn:population":0,
    "gn:timezone":"America/Havana",
    "iso:country":"CU",
    "name:und_x_variant":[
        "Loma Blanca",
        "Leiva"
    ],
    "wof:name":"Leiva",
    "wof:placetype":"locality"
},
  "geometry": {"coordinates":[-76.54722,21.16833],"type":"Point"}
}