{
  "type": "Feature",
  "properties": {
    "gn:admin1_code":"05",
    "gn:asciiname":"La Union",
    "gn:country_code":"CU",
    "gn:dem":89,
    "gn:feature_class":"P",
    "gn:feature_code":"PPL",
    "gn:name":"La Uni\u00f3n",
    "gn:population":0,
    "gn:timezone":"America/Havana",
    "iso:country":"CU",
    "name:ace_x_preferred":[
        "Propinsi La Union"
    ],
    "name:ara_x_preferred":[
        "\u0644\u0627 \u064a\u0648\u0646\u064a\u0648\u0646"
    ],
    "name:azb_x_preferred":[
        "\u0644\u0627 \u06cc\u0648\u0646\u06cc\u0648\u0646"
    ],
    "name:bcl_x_preferred":[
        "La Union"
    ],
    "name:ceb_x_preferred":[
        "La Union"
    ],
    "name:deu_x_preferred":[
        "La Union"
    ],
    "name:epo_x_preferred":[
        "La-Unio"
    ],
    "name:fas_x_preferred":[
        "\u0644\u0627 \u06cc\u0648\u0646\u06cc\u0648\u0646"
    ],
    "name:fin_x_preferred":[
        "La Union"
    ],
    "name:fra_x_preferred":[
        "La Union"
    ],
    "name:hin_x_preferred":[
        "\u0932\u093e \u092f\u0941\u0928\u093f\u092f\u094b\u0928 \u092a\u094d\u0930\u093e\u0928\u094d\u0924"
    ],
    "name:ilo_x_preferred":[
        "La Union"
    ],
    "name:ind_x_preferred":[
        "La Union"
    ],
    "name:jpn_x_preferred":[
        "\u30e9\u30a6\u30cb\u30aa\u30f3\u5dde"
    ],
    "name:kor_x_preferred":[
        "\ub77c\uc6b0\ub2c8\uc628\uc8fc"
    ],
    "name:mkd_x_preferred":[
        "\u041b\u0430 \u0423\u043d\u0438\u043e\u043d"
    ],
    "name:nor_x_preferred":[
        "La Union"
    ],
    "name:oci_x_preferred":[
        "La Union"
    ],
    "name:pag_x_preferred":[
        "La Union"
    ],
    "name:pam_x_preferred":[
        "La Union"
    ],
    "name:pol_x_preferred":[
        "La Union"
    ],
    "name:por_x_preferred":[
        "La Uni\u00f3n"
    ],
    "name:rus_x_preferred":[
        "\u041b\u0430-\u0423\u043d\u0438\u043e\u043d"
    ],
    "name:sco_x_preferred":[
        "La Union"
    ],
    "name:spa_x_preferred":[
        "La Uni\u00f3n"
    ],
    "name:swe_x_preferred":[
        "La Union"
    ],
    "name:tam_x_preferred":[
        "\u0bb2\u0bbe \u0baf\u0bc2\u0ba9\u0bbf\u0baf\u0ba9\u0bcd"
    ],
    "name:tgl_x_preferred":[
        "La Union"
    ],
    "name:tha_x_preferred":[
        "\u0e08\u0e31\u0e07\u0e2b\u0e27\u0e31\u0e14\u0e25\u0e32\u0e2d\u0e39\u0e19\u0e35\u0e42\u0e22\u0e19"
    ],
    "name:tur_x_preferred":[
        "La Union"
    ],
    "name:ukr_x_preferred":[
        "\u041b\u0430 \u0423\u043d\u0456\u043e\u043d"
    ],
    "name:urd_x_preferred":[
        "\u0644\u0627 \u06cc\u0648\u0646\u06cc\u0646"
    ],
    "name:vie_x_preferred":[
        "La Union"
    ],
    "name:war_x_preferred":[
        "La Union"
    ],
    "name:zho_x_preferred":[
        "\u62c9\u4e4c\u5c3c\u7fc1\u7701"
    ],
    "wof:name":"La Union",
    "wof:placetype":"locality"
},
  "geometry": {"coordinates":[-77.59153000000001,21.09069],"type":"Point"}
}