{
  "type": "Feature",
  "properties": {
    "gn:admin1_code":"15",
    "gn:asciiname":"Surgidero de Sigua",
    "gn:country_code":"CU",
    "gn:dem":14,
    "gn:feature_class":"P",
    "gn:feature_code":"PPL",
    "gn:name":"Surgidero de Sigua",
    "gn:population":0,
    "gn:timezone":"America/Havana",
    "iso:country":"CU",
    "name:spa_x_preferred":[
        "Surgidero de Sigua"
    ],
    "wof:name":"Surgidero de Sigua",
    "wof:placetype":"locality"
},
  "geometry": {"coordinates":[-75.52226999999998,19.8878],"type":"Point"}
}