{
  "type": "Feature",
  "properties": {
    "gn:admin1_code":"07",
    "gn:asciiname":"Pesqueria",
    "gn:country_code":"CU",
    "gn:dem":28,
    "gn:feature_class":"P",
    "gn:feature_code":"PPL",
    "gn:name":"Pesquer\u00eda",
    "gn:population":0,
    "gn:timezone":"America/Havana",
    "iso:country":"CU",
    "name:spa_x_preferred":[
        "Pesquer\u00eda"
    ],
    "wof:name":"Pesqueria",
    "wof:placetype":"locality"
},
  "geometry": {"coordinates":[-78.50176999999999,21.87005],"type":"Point"}
}