{
  "type": "Feature",
  "properties": {
    "gn:admin1_code":"16",
    "gn:asciiname":"Cuatro Hermanos",
    "gn:country_code":"CU",
    "gn:dem":49,
    "gn:feature_class":"P",
    "gn:feature_code":"PPLL",
    "gn:name":"Cuatro Hermanos",
    "gn:population":0,
    "gn:timezone":"America/Havana",
    "iso:country":"CU",
    "wof:name":"Cuatro Hermanos",
    "wof:placetype":"locality"
},
  "geometry": {"coordinates":[-79.73333000000002,22.56667],"type":"Point"}
}