{
  "type": "Feature",
  "properties": {
    "gn:admin1_code":"08",
    "gn:asciiname":"Chucho Rose",
    "gn:country_code":"CU",
    "gn:dem":60,
    "gn:feature_class":"P",
    "gn:feature_code":"PPL",
    "gn:name":"Chucho Rose",
    "gn:population":0,
    "gn:timezone":"America/Havana",
    "iso:country":"CU",
    "name:spa_x_preferred":[
        "San Marcos Dos"
    ],
    "name:spa_x_variant":[
        "Chucho Rose"
    ],
    "wof:name":"Chucho Rose",
    "wof:placetype":"locality"
},
  "geometry": {"coordinates":[-80.26765,22.54301],"type":"Point"}
}