{
  "type": "Feature",
  "properties": {
    "gn:admin1_code":"01",
    "gn:asciiname":"Playa Las Canas",
    "gn:country_code":"CU",
    "gn:dem":5,
    "gn:feature_class":"P",
    "gn:feature_code":"PPL",
    "gn:name":"Playa Las Canas",
    "gn:population":0,
    "gn:timezone":"America/Havana",
    "iso:country":"CU",
    "name:spa_x_preferred":[
        "Playa Las Canas"
    ],
    "wof:name":"Playa Las Canas",
    "wof:placetype":"locality"
},
  "geometry": {"coordinates":[-83.59204,22.22022],"type":"Point"}
}