{
  "type": "Feature",
  "properties": {
    "gn:admin1_code":"16",
    "gn:asciiname":"Enriqueta",
    "gn:country_code":"CU",
    "gn:dem":87,
    "gn:feature_class":"P",
    "gn:feature_code":"PPL",
    "gn:name":"Enriqueta",
    "gn:population":0,
    "gn:timezone":"America/Havana",
    "iso:country":"CU",
    "name:spa_x_preferred":[
        "Enriqueta"
    ],
    "wof:name":"Enriqueta",
    "wof:placetype":"locality"
},
  "geometry": {"coordinates":[-80.37850999999998,22.81376],"type":"Point"}
}