{
  "type": "Feature",
  "properties": {
    "gn:gn_country":"CU",
    "gn:gn_fcode":"PPLX",
    "gn:gn_pop":0,
    "iso:country":"CU",
    "name:spa_x_preferred":[
        "Aldecoa"
    ],
    "name:unk_x_variant":[
        "Aldecoa"
    ],
    "qs_pg:aaroncc":"CU",
    "qs_pg:gn_country":"CU",
    "qs_pg:gn_fcode":"PPLX",
    "qs_pg:gn_pop":0,
    "qs_pg:name":"Aldecoa",
    "qs_pg:name_adm0":"Cuba",
    "qs_pg:name_adm1":"Ciudad de la Habana",
    "qs_pg:photos":1649,
    "qs_pg:photos_1k":334,
    "qs_pg:photos_9k":7,
    "qs_pg:photos_9r":8,
    "qs_pg:photos_all":1649,
    "qs_pg:photos_sr":13,
    "qs_pg:pop_sr":0,
    "qs_pg:qs_pg_placetype":"neighbourhood",
    "qs_pg:qs_pg_placetype_gp":"Suburb",
    "qs_pg:woe_adm0":23424793,
    "woe:adm0_id":23424793,
    "woe:name_adm0":"Cuba",
    "woe:name_adm1":"Ciudad de la Habana",
    "woe:placetype":"Suburb",
    "wof:name":"Aldecoa",
    "wof:placetype":"neighbourhood"
},
  "geometry": {"coordinates":[-82.40000000000001,23.11667],"type":"Point"}
}