{
  "type": "Feature",
  "properties": {
    "gn:admin1_code":"03",
    "gn:asciiname":"Delicias",
    "gn:country_code":"CU",
    "gn:dem":49,
    "gn:feature_class":"P",
    "gn:feature_code":"PPLL",
    "gn:name":"Delicias",
    "gn:population":0,
    "gn:timezone":"America/Havana",
    "iso:country":"CU",
    "name:arg_x_preferred":[
        "Delicias"
    ],
    "name:cat_x_preferred":[
        "Delicias"
    ],
    "name:ceb_x_preferred":[
        "Delicias"
    ],
    "name:deu_x_preferred":[
        "Delicias"
    ],
    "name:fra_x_preferred":[
        "Delicias"
    ],
    "name:ita_x_preferred":[
        "Delicias"
    ],
    "name:mlg_x_preferred":[
        "Delicias"
    ],
    "name:nld_x_preferred":[
        "Delicias"
    ],
    "name:rus_x_preferred":[
        "\u0414\u0435\u043b\u0438\u0441\u044c\u044f\u0441"
    ],
    "name:spa_x_preferred":[
        "Las Delicias"
    ],
    "name:swe_x_preferred":[
        "Delicias"
    ],
    "wof:name":"Delicias",
    "wof:placetype":"locality"
},
  "geometry": {"coordinates":[-80.86667,22.58333],"type":"Point"}
}