{
  "type": "Feature",
  "properties": {
    "gn:admin1_code":"08",
    "gn:asciiname":"Tres Picos",
    "gn:country_code":"CU",
    "gn:dem":10,
    "gn:feature_class":"P",
    "gn:feature_code":"PPLL",
    "gn:name":"Tres Picos",
    "gn:population":0,
    "gn:timezone":"America/Havana",
    "iso:country":"CU",
    "wof:name":"Tres Picos",
    "wof:placetype":"locality"
},
  "geometry": {"coordinates":[-80.65000000000001,22.15],"type":"Point"}
}