{
  "type": "Feature",
  "properties": {
    "gn:admin1_code":"AR",
    "gn:asciiname":"Montana",
    "gn:country_code":"CU",
    "gn:dem":22,
    "gn:feature_class":"P",
    "gn:feature_code":"PPL",
    "gn:name":"Monta\u00f1a",
    "gn:population":0,
    "gn:timezone":"America/Havana",
    "iso:country":"CU",
    "name:spa_x_preferred":[
        "Monta\u00f1a"
    ],
    "wof:name":"Montana",
    "wof:placetype":"locality"
},
  "geometry": {"coordinates":[-83.14158,22.9078],"type":"Point"}
}