{
  "type": "Feature",
  "properties": {
    "gn:admin1_code":"09",
    "gn:asciiname":"Caureje",
    "gn:country_code":"CU",
    "gn:dem":34,
    "gn:feature_class":"P",
    "gn:feature_code":"PPL",
    "gn:name":"Caureje",
    "gn:population":0,
    "gn:timezone":"America/Havana",
    "iso:country":"CU",
    "name:spa_x_preferred":[
        "Caureje"
    ],
    "wof:name":"Caureje",
    "wof:placetype":"locality"
},
  "geometry": {"coordinates":[-76.69686,20.46518],"type":"Point"}
}