{
  "type": "Feature",
  "properties": {
    "gn:admin1_code":"16",
    "gn:asciiname":"Caguaguas de Sagua",
    "gn:country_code":"CU",
    "gn:dem":9,
    "gn:feature_class":"P",
    "gn:feature_code":"PPL",
    "gn:name":"Caguaguas de Sagua",
    "gn:population":0,
    "gn:timezone":"America/Havana",
    "iso:country":"CU",
    "name:spa_x_preferred":[
        "Caguaguas de Sagua"
    ],
    "name:und_x_variant":[
        "Caguagua",
        "Caguaguas"
    ],
    "wof:name":"Caguaguas de Sagua",
    "wof:placetype":"locality"
},
  "geometry": {"coordinates":[-80.19835,22.83582],"type":"Point"}
}