{
  "type": "Feature",
  "properties": {
    "gn:admin1_code":"AR",
    "gn:asciiname":"Guanimar",
    "gn:country_code":"CU",
    "gn:dem":4,
    "gn:feature_class":"P",
    "gn:feature_code":"PPL",
    "gn:name":"Guan\u00edmar",
    "gn:population":0,
    "gn:timezone":"America/Havana",
    "iso:country":"CU",
    "name:spa_x_preferred":[
        "Guan\u00edmar"
    ],
    "wof:name":"Guanimar",
    "wof:placetype":"locality"
},
  "geometry": {"coordinates":[-82.65472,22.68794],"type":"Point"}
}