{
  "type": "Feature",
  "properties": {
    "gn:admin1_code":"07",
    "gn:asciiname":"Tablones",
    "gn:country_code":"CU",
    "gn:dem":66,
    "gn:feature_class":"P",
    "gn:feature_code":"PPL",
    "gn:name":"Tablones",
    "gn:population":0,
    "gn:timezone":"America/Havana",
    "iso:country":"CU",
    "name:spa_x_preferred":[
        "Tablones"
    ],
    "wof:name":"Tablones",
    "wof:placetype":"locality"
},
  "geometry": {"coordinates":[-78.86848000000001,21.87778],"type":"Point"}
}