{
  "type": "Feature",
  "properties": {
    "gn:admin1_code":"MA",
    "gn:asciiname":"La Granada",
    "gn:country_code":"CU",
    "gn:dem":11,
    "gn:feature_class":"P",
    "gn:feature_code":"PPLL",
    "gn:name":"La Granada",
    "gn:population":0,
    "gn:timezone":"America/Havana",
    "iso:country":"CU",
    "wof:name":"La Granada",
    "wof:placetype":"locality"
},
  "geometry": {"coordinates":[-82.18333,22.73333],"type":"Point"}
}