{
  "type": "Feature",
  "properties": {
    "gn:admin1_code":"07",
    "gn:asciiname":"Lote Diecinueve",
    "gn:cc2":"CU",
    "gn:country_code":"CU",
    "gn:dem":58,
    "gn:feature_class":"P",
    "gn:feature_code":"PPLL",
    "gn:name":"Lote Diecinueve",
    "gn:population":0,
    "gn:timezone":"America/Havana",
    "iso:country":"CU",
    "name:und_x_variant":[
        "Lote 19",
        "Lote Diecinueve"
    ],
    "wof:name":"Lote Diecinueve",
    "wof:placetype":"locality"
},
  "geometry": {"coordinates":[-78.4075,21.6925],"type":"Point"}
}