{
  "type": "Feature",
  "properties": {
    "gn:admin1_code":"01",
    "gn:asciiname":"Las Tumbas",
    "gn:country_code":"CU",
    "gn:dem":128,
    "gn:feature_class":"P",
    "gn:feature_code":"PPL",
    "gn:name":"Las Tumbas",
    "gn:population":0,
    "gn:timezone":"America/Havana",
    "iso:country":"CU",
    "name:spa_x_preferred":[
        "Las Tumbas"
    ],
    "wof:name":"Las Tumbas",
    "wof:placetype":"locality"
},
  "geometry": {"coordinates":[-83.86459000000001,22.47884],"type":"Point"}
}