{
  "type": "Feature",
  "properties": {
    "gn:admin1_code":"10",
    "gn:asciiname":"La Jaragua",
    "gn:country_code":"CU",
    "gn:dem":10,
    "gn:feature_class":"P",
    "gn:feature_code":"PPL",
    "gn:name":"La Jaragua",
    "gn:population":0,
    "gn:timezone":"America/Havana",
    "iso:country":"CU",
    "name:und_x_variant":[
        "Jangua",
        "La Jaragua"
    ],
    "wof:name":"La Jaragua",
    "wof:placetype":"locality"
},
  "geometry": {"coordinates":[-74.63630000000001,20.4879],"type":"Point"}
}