{
  "type": "Feature",
  "properties": {
    "gn:admin1_code":"05",
    "gn:asciiname":"La Vega",
    "gn:country_code":"CU",
    "gn:dem":54,
    "gn:feature_class":"P",
    "gn:feature_code":"PPL",
    "gn:name":"La Vega",
    "gn:population":0,
    "gn:timezone":"America/Havana",
    "iso:country":"CU",
    "name:ast_x_preferred":[
        "La Vega"
    ],
    "name:bre_x_preferred":[
        "La Vega"
    ],
    "name:ceb_x_preferred":[
        "La Vega"
    ],
    "name:fas_x_preferred":[
        "\u0644\u0627 \u0648\u06af\u0627"
    ],
    "name:fra_x_preferred":[
        "La Vega"
    ],
    "name:heb_x_preferred":[
        "\u05dc\u05d4 \u05d5\u05d2\u05d4"
    ],
    "name:hun_x_preferred":[
        "La Vega"
    ],
    "name:ita_x_preferred":[
        "La Vega"
    ],
    "name:nld_x_preferred":[
        "La Vega"
    ],
    "name:pol_x_preferred":[
        "La Vega"
    ],
    "name:sco_x_preferred":[
        "La Vega"
    ],
    "name:spa_x_preferred":[
        "La Vega"
    ],
    "name:srp_x_preferred":[
        "\u041b\u0430 \u0412\u0435\u0433\u0430"
    ],
    "name:swe_x_preferred":[
        "La Vega"
    ],
    "wof:name":"La Vega",
    "wof:placetype":"locality"
},
  "geometry": {"coordinates":[-77.61667,21.36667],"type":"Point"}
}