{
  "type": "Feature",
  "properties": {
    "gn:admin1_code":"12",
    "gn:asciiname":"Aguada de Piedra",
    "gn:country_code":"CU",
    "gn:dem":36,
    "gn:feature_class":"P",
    "gn:feature_code":"PPL",
    "gn:name":"Aguada de Piedra",
    "gn:population":0,
    "gn:timezone":"America/Havana",
    "iso:country":"CU",
    "name:spa_x_preferred":[
        "Aguada de Piedra"
    ],
    "wof:name":"Aguada de Piedra",
    "wof:placetype":"locality"
},
  "geometry": {"coordinates":[-75.84735999999999,21.10579],"type":"Point"}
}