{
  "type": "Feature",
  "properties": {
    "gn:admin1_code":"10",
    "gn:asciiname":"El Palmar",
    "gn:country_code":"CU",
    "gn:dem":226,
    "gn:feature_class":"P",
    "gn:feature_code":"PPL",
    "gn:name":"El Palmar",
    "gn:population":0,
    "gn:timezone":"America/Havana",
    "iso:country":"CU",
    "name:ceb_x_preferred":[
        "El Palmar"
    ],
    "name:fra_x_preferred":[
        "El Palmar"
    ],
    "name:glg_x_preferred":[
        "El Palmar"
    ],
    "name:lit_x_preferred":[
        "El Palmaras"
    ],
    "name:spa_x_preferred":[
        "El Palmar"
    ],
    "name:srp_x_preferred":[
        "\u0415\u043b \u041f\u0430\u043b\u043c\u0430\u0440"
    ],
    "name:swe_x_preferred":[
        "El Palmar"
    ],
    "name:und_x_variant":[
        "Palmar",
        "Palma",
        "El Palmar"
    ],
    "wof:name":"El Palmar",
    "wof:placetype":"locality"
},
  "geometry": {"coordinates":[-75.11126,20.26752],"type":"Point"}
}