{
  "type": "Feature",
  "properties": {
    "gn:admin1_code":"03",
    "gn:asciiname":"La Caridad",
    "gn:country_code":"CU",
    "gn:dem":182,
    "gn:feature_class":"P",
    "gn:feature_code":"PPLL",
    "gn:name":"La Caridad",
    "gn:population":0,
    "gn:timezone":"America/Havana",
    "iso:country":"CU",
    "wof:name":"La Caridad",
    "wof:placetype":"locality"
},
  "geometry": {"coordinates":[-81.45,22.86667000000001],"type":"Point"}
}