{
  "type": "Feature",
  "properties": {
    "gn:admin1_code":"16",
    "gn:asciiname":"La Maria",
    "gn:country_code":"CU",
    "gn:dem":138,
    "gn:feature_class":"P",
    "gn:feature_code":"PPLL",
    "gn:name":"La Mar\u00eda",
    "gn:population":0,
    "gn:timezone":"America/Havana",
    "iso:country":"CU",
    "name:spa_x_preferred":[
        "La Mar\u00eda"
    ],
    "wof:name":"La Maria",
    "wof:placetype":"locality"
},
  "geometry": {"coordinates":[-79.88505000000001,22.37241],"type":"Point"}
}