{
  "type": "Feature",
  "properties": {
    "gn:admin1_code":"03",
    "gn:asciiname":"Carbonera",
    "gn:country_code":"CU",
    "gn:dem":44,
    "gn:feature_class":"P",
    "gn:feature_code":"PPLL",
    "gn:name":"Carbonera",
    "gn:population":0,
    "gn:timezone":"America/Havana",
    "iso:country":"CU",
    "name:ceb_x_preferred":[
        "Carbonera"
    ],
    "name:ita_x_preferred":[
        "Carbonera"
    ],
    "name:lat_x_preferred":[
        "Carbonera"
    ],
    "name:lmo_x_preferred":[
        "Carbonera"
    ],
    "name:spa_x_preferred":[
        "Carbonera"
    ],
    "name:srp_x_preferred":[
        "Carbonera"
    ],
    "name:swe_x_preferred":[
        "Carbonera"
    ],
    "name:und_x_variant":[
        "Batey Carbonera",
        "Carboneras",
        "Carbonera"
    ],
    "wof:name":"Carbonera",
    "wof:placetype":"locality"
},
  "geometry": {"coordinates":[-80.9324,22.80768],"type":"Point"}
}