{
  "type": "Feature",
  "properties": {
    "gn:admin1_code":"09",
    "gn:asciiname":"Colon",
    "gn:country_code":"CU",
    "gn:dem":1214,
    "gn:feature_class":"P",
    "gn:feature_code":"PPL",
    "gn:name":"Colon",
    "gn:population":0,
    "gn:timezone":"America/Havana",
    "iso:country":"CU",
    "wof:name":"Colon",
    "wof:placetype":"locality"
},
  "geometry": {"coordinates":[-76.53333000000001,20.05],"type":"Point"}
}