{
  "type": "Feature",
  "properties": {
    "gn:admin1_code":"16",
    "gn:asciiname":"Aguijon",
    "gn:country_code":"CU",
    "gn:dem":76,
    "gn:feature_class":"P",
    "gn:feature_code":"PPLL",
    "gn:name":"Aguij\u00f3n",
    "gn:population":0,
    "gn:timezone":"America/Havana",
    "iso:country":"CU",
    "wof:name":"Aguijon",
    "wof:placetype":"locality"
},
  "geometry": {"coordinates":[-79.78333000000001,22.48333],"type":"Point"}
}