{
  "type": "Feature",
  "properties": {
    "gn:admin1_code":"13",
    "gn:asciiname":"El Junquito",
    "gn:country_code":"CU",
    "gn:dem":149,
    "gn:feature_class":"P",
    "gn:feature_code":"PPL",
    "gn:name":"El Junquito",
    "gn:population":0,
    "gn:timezone":"America/Havana",
    "iso:country":"CU",
    "name:fra_x_preferred":[
        "El Junquito"
    ],
    "name:spa_x_preferred":[
        "El Junquito"
    ],
    "name:spa_x_variant":[
        "Parroquia El Junquito"
    ],
    "wof:name":"El Junquito",
    "wof:placetype":"locality"
},
  "geometry": {"coordinates":[-76.63053000000002,20.99887],"type":"Point"}
}