{
  "type": "Feature",
  "properties": {
    "gn:admin1_code":"05",
    "gn:asciiname":"Pino",
    "gn:country_code":"CU",
    "gn:dem":19,
    "gn:feature_class":"P",
    "gn:feature_code":"PPL",
    "gn:name":"Pino",
    "gn:population":0,
    "gn:timezone":"America/Havana",
    "iso:country":"CU",
    "name:spa_x_preferred":[
        "Pino"
    ],
    "wof:name":"Pino",
    "wof:placetype":"locality"
},
  "geometry": {"coordinates":[-78.03686999999999,20.85196],"type":"Point"}
}