{
  "type": "Feature",
  "properties": {
    "gn:admin1_code":"13",
    "gn:asciiname":"Melilla",
    "gn:country_code":"CU",
    "gn:dem":20,
    "gn:feature_class":"P",
    "gn:feature_code":"PPLL",
    "gn:name":"Melilla",
    "gn:population":0,
    "gn:timezone":"America/Havana",
    "iso:country":"CU",
    "wof:name":"Melilla",
    "wof:placetype":"locality"
},
  "geometry": {"coordinates":[-77.07666999999999,21.28806],"type":"Point"}
}