{
  "type": "Feature",
  "properties": {
    "iso:country":"CU",
    "name:ara_x_preferred":[
        "\u0645\u0648\u0627"
    ],
    "name:arz_x_preferred":[
        "\u0645\u0648\u0627"
    ],
    "name:ast_x_preferred":[
        "Moa"
    ],
    "name:ben_x_preferred":[
        "\u09ae\u09cb\u09af\u09bc\u09be"
    ],
    "name:ceb_x_preferred":[
        "Moa"
    ],
    "name:cym_x_preferred":[
        "Moa"
    ],
    "name:dan_x_preferred":[
        "Moa"
    ],
    "name:deu_x_preferred":[
        "Moa"
    ],
    "name:ell_x_preferred":[
        "\u039c\u03cc\u03b1"
    ],
    "name:eng_x_preferred":[
        "Moa"
    ],
    "name:epo_x_preferred":[
        "Moa"
    ],
    "name:fas_x_preferred":[
        "\u0645\u0648\u0627"
    ],
    "name:fin_x_preferred":[
        "Moa"
    ],
    "name:fra_x_preferred":[
        "Moa"
    ],
    "name:gle_x_preferred":[
        "Moa"
    ],
    "name:guj_x_preferred":[
        "\u0aae\u0acb\u0a86"
    ],
    "name:hat_x_preferred":[
        "Moa"
    ],
    "name:hin_x_preferred":[
        "\u092e\u094b\u0906"
    ],
    "name:ind_x_preferred":[
        "Moa"
    ],
    "name:ita_x_preferred":[
        "Moa"
    ],
    "name:jpn_x_preferred":[
        "\u30e2\u30a2"
    ],
    "name:kan_x_preferred":[
        "\u0cae\u0ccb\u0cb5\u0cbe"
    ],
    "name:kat_x_preferred":[
        "\u10db\u10dd\u10d0"
    ],
    "name:kor_x_preferred":[
        "\ubaa8\uc544"
    ],
    "name:lav_x_preferred":[
        "Moa"
    ],
    "name:lit_x_preferred":[
        "Moa"
    ],
    "name:mar_x_preferred":[
        "\u092e\u094b\u0906"
    ],
    "name:msa_x_preferred":[
        "Moa"
    ],
    "name:nld_x_preferred":[
        "Moa"
    ],
    "name:nob_x_preferred":[
        "Moa"
    ],
    "name:oci_x_preferred":[
        "Moa"
    ],
    "name:pol_x_preferred":[
        "Moa"
    ],
    "name:por_x_preferred":[
        "Moa"
    ],
    "name:rus_x_preferred":[
        "\u041c\u043e\u0430"
    ],
    "name:sco_x_preferred":[
        "Moa"
    ],
    "name:sin_x_preferred":[
        "\u0db8\u0ddc\u0d86"
    ],
    "name:spa_x_preferred":[
        "Moa"
    ],
    "name:srp_x_preferred":[
        "\u041c\u043e\u0430"
    ],
    "name:swe_x_preferred":[
        "Moa"
    ],
    "name:tam_x_preferred":[
        "\u0bae\u0bcb"
    ],
    "name:tel_x_preferred":[
        "\u0c2e\u0c4b\u0c06"
    ],
    "name:tha_x_preferred":[
        "\u0e42\u0e21\u0e2d\u0e31\u0e1a"
    ],
    "name:tur_x_preferred":[
        "Moa"
    ],
    "name:ukr_x_preferred":[
        "\u041c\u043e\u0430"
    ],
    "name:unk_x_variant":[
        "Puerto Cayo Moa"
    ],
    "name:urd_x_preferred":[
        "\u0645\u0648\u0627\u060c \u06a9\u06cc\u0648\u0628\u0627"
    ],
    "name:urd_x_variant":[
        "\u0645\u0648\u0627"
    ],
    "name:uzb_x_preferred":[
        "Moa"
    ],
    "name:vie_x_preferred":[
        "Moa"
    ],
    "name:zho_x_preferred":[
        "\u83ab\u4e9e"
    ],
    "qs:gn_country":"CU",
    "qs:gn_fcode":"PPL",
    "qs:gn_pop":92852,
    "qs:name":"Moa",
    "qs:name_adm0":"Cuba",
    "qs:name_adm1":"Holguin",
    "qs:photos":76,
    "qs:photos_1k":15,
    "qs:photos_9k":1,
    "qs:photos_9r":3,
    "qs:photos_all":76,
    "qs:photos_sr":3,
    "qs:placetype":"Town",
    "qs:pop_sr":"8",
    "qs:woe_adm0":23424793,
    "wd:wordcount":286,
    "wof:name":"Moa",
    "wof:placetype":"locality",
    "wof:population":92852
},
  "geometry": {"coordinates":[-74.94028,20.65694],"type":"Point"}
}