{
  "type": "Feature",
  "properties": {
    "gn:admin1_code":"07",
    "gn:asciiname":"Alonso",
    "gn:country_code":"CU",
    "gn:dem":66,
    "gn:feature_class":"P",
    "gn:feature_code":"PPLL",
    "gn:name":"Alonso",
    "gn:population":0,
    "gn:timezone":"America/Havana",
    "iso:country":"CU",
    "name:deu_x_preferred":[
        "Alonso"
    ],
    "name:glg_x_preferred":[
        "Alonso"
    ],
    "name:lav_x_preferred":[
        "Alonso"
    ],
    "name:rus_x_preferred":[
        "\u0410\u043b\u043e\u043d\u0441\u043e"
    ],
    "name:swe_x_preferred":[
        "Alonso"
    ],
    "name:tur_x_preferred":[
        "Alonso"
    ],
    "wof:name":"Alonso",
    "wof:placetype":"locality"
},
  "geometry": {"coordinates":[-78.36667,21.73333],"type":"Point"}
}