{
  "type": "Feature",
  "properties": {
    "gn:admin1_code":"04",
    "gn:asciiname":"La Sacra",
    "gn:country_code":"CU",
    "gn:dem":20,
    "gn:feature_class":"P",
    "gn:feature_code":"PPL",
    "gn:name":"La Sacra",
    "gn:population":0,
    "gn:timezone":"America/Havana",
    "iso:country":"CU",
    "name:spa_x_preferred":[
        "La Sacra"
    ],
    "wof:name":"La Sacra",
    "wof:placetype":"locality"
},
  "geometry": {"coordinates":[-82.94519,21.82875],"type":"Point"}
}