{
  "type": "Feature",
  "properties": {
    "gn:admin1_code":"14",
    "gn:asciiname":"Los Ramones",
    "gn:country_code":"CU",
    "gn:dem":196,
    "gn:feature_class":"P",
    "gn:feature_code":"PPL",
    "gn:name":"Los Ramones",
    "gn:population":0,
    "gn:timezone":"America/Havana",
    "iso:country":"CU",
    "name:spa_x_preferred":[
        "Los Ramones"
    ],
    "wof:name":"Los Ramones",
    "wof:placetype":"locality"
},
  "geometry": {"coordinates":[-79.05458,22.10191],"type":"Point"}
}