{
  "type": "Feature",
  "properties": {
    "gn:admin1_code":"16",
    "gn:asciiname":"El Claro",
    "gn:country_code":"CU",
    "gn:dem":253,
    "gn:feature_class":"P",
    "gn:feature_code":"PPLL",
    "gn:name":"El Claro",
    "gn:population":0,
    "gn:timezone":"America/Havana",
    "iso:country":"CU",
    "name:spa_x_preferred":[
        "El Claro"
    ],
    "wof:name":"El Claro",
    "wof:placetype":"locality"
},
  "geometry": {"coordinates":[-79.45661,22.32164],"type":"Point"}
}