{
  "type": "Feature",
  "properties": {
    "gn:admin1_code":"15",
    "gn:asciiname":"Ramon de Guaninao",
    "gn:country_code":"CU",
    "gn:dem":211,
    "gn:feature_class":"P",
    "gn:feature_code":"PPL",
    "gn:name":"Ram\u00f3n de Guaninao",
    "gn:population":0,
    "gn:timezone":"America/Havana",
    "iso:country":"CU",
    "name:spa_x_preferred":[
        "Ram\u00f3n de Guaninao"
    ],
    "name:und_x_variant":[
        "El Ram\u00f3n de Guaninao",
        "Ram\u00f3n de Cuaninao"
    ],
    "wof:name":"Ramon de Guaninao",
    "wof:placetype":"locality"
},
  "geometry": {"coordinates":[-76.13401,20.18204],"type":"Point"}
}