{
  "type": "Feature",
  "properties": {
    "gn:admin1_code":"13",
    "gn:asciiname":"Velazco Veinte y Nueve",
    "gn:country_code":"CU",
    "gn:dem":65,
    "gn:feature_class":"P",
    "gn:feature_code":"PPL",
    "gn:name":"Velazco Veinte y Nueve",
    "gn:population":0,
    "gn:timezone":"America/Havana",
    "iso:country":"CU",
    "name:spa_x_preferred":[
        "Velazco Veinte y Nueve"
    ],
    "wof:name":"Velazco Veinte y Nueve",
    "wof:placetype":"locality"
},
  "geometry": {"coordinates":[-76.82415,21.11633],"type":"Point"}
}