{
  "type": "Feature",
  "properties": {
    "gn:admin1_code":"05",
    "gn:asciiname":"La Prudencia",
    "gn:country_code":"CU",
    "gn:dem":26,
    "gn:feature_class":"P",
    "gn:feature_code":"PPL",
    "gn:name":"La Prudencia",
    "gn:population":0,
    "gn:timezone":"America/Havana",
    "iso:country":"CU",
    "name:spa_x_preferred":[
        "La Prudencia"
    ],
    "wof:name":"La Prudencia",
    "wof:placetype":"locality"
},
  "geometry": {"coordinates":[-77.43271999999997,21.45977],"type":"Point"}
}