{
  "type": "Feature",
  "properties": {
    "gn:admin1_code":"09",
    "gn:asciiname":"El Realengo",
    "gn:country_code":"CU",
    "gn:dem":31,
    "gn:feature_class":"P",
    "gn:feature_code":"PPL",
    "gn:name":"El Real\u00e9ngo",
    "gn:population":0,
    "gn:timezone":"America/Havana",
    "iso:country":"CU",
    "name:spa_x_preferred":[
        "El Real\u00e9ngo"
    ],
    "name:und_x_variant":[
        "Realengo de Ojo de Agua"
    ],
    "wof:name":"El Realengo",
    "wof:placetype":"locality"
},
  "geometry": {"coordinates":[-77.3456,20.18738],"type":"Point"}
}