{
  "type": "Feature",
  "properties": {
    "gn:admin1_code":"09",
    "gn:asciiname":"Maguanos",
    "gn:country_code":"CU",
    "gn:dem":36,
    "gn:feature_class":"P",
    "gn:feature_code":"PPLL",
    "gn:name":"Maguanos",
    "gn:population":0,
    "gn:timezone":"America/Havana",
    "iso:country":"CU",
    "name:spa_x_preferred":[
        "Maguanos"
    ],
    "wof:name":"Maguanos",
    "wof:placetype":"locality"
},
  "geometry": {"coordinates":[-76.59799,20.67341],"type":"Point"}
}