{
  "type": "Feature",
  "properties": {
    "gn:admin1_code":"09",
    "gn:asciiname":"Pardo",
    "gn:country_code":"CU",
    "gn:dem":236,
    "gn:feature_class":"P",
    "gn:feature_code":"PPLL",
    "gn:name":"Pardo",
    "gn:population":0,
    "gn:timezone":"America/Havana",
    "iso:country":"CU",
    "name:ara_x_preferred":[
        "\u0628\u0627\u0631\u062f\u0648"
    ],
    "name:ben_x_preferred":[
        "\u09aa\u09be\u09b0\u09a6\u09cb"
    ],
    "name:deu_x_preferred":[
        "Pardo River"
    ],
    "name:ell_x_preferred":[
        "\u03a0\u03ac\u03c1\u03bd\u03c4\u03bf"
    ],
    "name:fas_x_preferred":[
        "\u067e\u0627\u0631\u062f\u0648"
    ],
    "name:heb_x_preferred":[
        "\u05e4\u05d0\u05e8\u05d3\u05d5"
    ],
    "name:hin_x_preferred":[
        "\u092a\u093e\u0930\u094d\u0921\u094b"
    ],
    "name:hun_x_preferred":[
        "Pardo"
    ],
    "name:ind_x_preferred":[
        "Pardo"
    ],
    "name:ita_x_preferred":[
        "Pardo"
    ],
    "name:jpn_x_preferred":[
        "\u30d1\u30eb\u30c9\u5ddd"
    ],
    "name:kor_x_preferred":[
        "\ud30c\ub974\ub3c4"
    ],
    "name:nld_x_preferred":[
        "Pardo"
    ],
    "name:pol_x_preferred":[
        "Pardo"
    ],
    "name:rus_x_preferred":[
        "\u0440\u0435\u043a\u0430 \u041f\u0430\u0440\u0434\u0443"
    ],
    "name:spa_x_preferred":[
        "Pardo"
    ],
    "name:tur_x_preferred":[
        "Pardo"
    ],
    "name:ukr_x_preferred":[
        "\u041f\u0430\u0440\u0434\u043e"
    ],
    "name:urd_x_preferred":[
        "\u067e\u0627\u0631\u0688\u0648"
    ],
    "name:vie_x_preferred":[
        "S\u00f4ng Pardo"
    ],
    "name:zho_cn_x_preferred":[
        "\u5e15\u5c14\u675c\u6cb3"
    ],
    "name:zho_tw_x_preferred":[
        "\u5e15\u723e\u591a\u6cb3"
    ],
    "wof:name":"Pardo",
    "wof:placetype":"locality"
},
  "geometry": {"coordinates":[-77.19016999999999,20.02836],"type":"Point"}
}