{
  "type": "Feature",
  "properties": {
    "gn:admin1_code":"09",
    "gn:asciiname":"Pardo",
    "gn:country_code":"CU",
    "gn:dem":236,
    "gn:feature_class":"P",
    "gn:feature_code":"PPLL",
    "gn:name":"Pardo",
    "gn:population":0,
    "gn:timezone":"America/Havana",
    "iso:country":"CU",
    "name:spa_x_preferred":[
        "Pardo"
    ],
    "wof:name":"Pardo",
    "wof:placetype":"locality"
},
  "geometry": {"coordinates":[-77.19016999999999,20.02836],"type":"Point"}
}