{
  "type": "Feature",
  "properties": {
    "gn:admin1_code":"MA",
    "gn:asciiname":"Ravelo",
    "gn:country_code":"CU",
    "gn:dem":113,
    "gn:feature_class":"P",
    "gn:feature_code":"PPL",
    "gn:name":"Ravelo",
    "gn:population":0,
    "gn:timezone":"America/Havana",
    "iso:country":"CU",
    "wof:name":"Ravelo",
    "wof:placetype":"locality"
},
  "geometry": {"coordinates":[-82.10194,22.93444],"type":"Point"}
}