{
  "type": "Feature",
  "properties": {
    "gn:admin1_code":"13",
    "gn:asciiname":"Los Yayales",
    "gn:country_code":"CU",
    "gn:dem":27,
    "gn:feature_class":"P",
    "gn:feature_code":"PPL",
    "gn:name":"Los Yayales",
    "gn:population":0,
    "gn:timezone":"America/Havana",
    "iso:country":"CU",
    "name:und_x_variant":[
        "Yayales",
        "Los Yayales"
    ],
    "wof:name":"Los Yayales",
    "wof:placetype":"locality"
},
  "geometry": {"coordinates":[-76.84486,21.20011],"type":"Point"}
}