{
  "type": "Feature",
  "properties": {
    "gn:admin1_code":"07",
    "gn:asciiname":"Pablo",
    "gn:country_code":"CU",
    "gn:dem":35,
    "gn:feature_class":"P",
    "gn:feature_code":"PPL",
    "gn:name":"Pablo",
    "gn:population":0,
    "gn:timezone":"America/Havana",
    "iso:country":"CU",
    "name:und_x_variant":[
        "San Pablo",
        "Pablo"
    ],
    "wof:name":"Pablo",
    "wof:placetype":"locality"
},
  "geometry": {"coordinates":[-78.42184,21.8113],"type":"Point"}
}