{
  "type": "Feature",
  "properties": {
    "gn:admin1_code":"10",
    "gn:asciiname":"Aguanta",
    "gn:country_code":"CU",
    "gn:dem":101,
    "gn:feature_class":"P",
    "gn:feature_code":"PPLL",
    "gn:name":"Aguanta",
    "gn:population":0,
    "gn:timezone":"America/Havana",
    "iso:country":"CU",
    "wof:name":"Aguanta",
    "wof:placetype":"locality"
},
  "geometry": {"coordinates":[-74.45,20.28333],"type":"Point"}
}