{
  "type": "Feature",
  "properties": {
    "gn:admin1_code":"MA",
    "gn:asciiname":"El Palomo",
    "gn:country_code":"CU",
    "gn:dem":121,
    "gn:feature_class":"P",
    "gn:feature_code":"PPLL",
    "gn:name":"El Palomo",
    "gn:population":0,
    "gn:timezone":"America/Havana",
    "iso:country":"CU",
    "name:und_x_variant":[
        "Palomo",
        "El Palomo"
    ],
    "wof:name":"El Palomo",
    "wof:placetype":"locality"
},
  "geometry": {"coordinates":[-81.93333,23.06667],"type":"Point"}
}