{
  "type": "Feature",
  "properties": {
    "gn:admin1_code":"10",
    "gn:asciiname":"Babiney Colorado",
    "gn:country_code":"CU",
    "gn:dem":125,
    "gn:feature_class":"P",
    "gn:feature_code":"PPLL",
    "gn:name":"Babiney Colorado",
    "gn:population":0,
    "gn:timezone":"America/Havana",
    "iso:country":"CU",
    "wof:name":"Babiney Colorado",
    "wof:placetype":"locality"
},
  "geometry": {"coordinates":[-75.24556,20.24361],"type":"Point"}
}