{
  "type": "Feature",
  "properties": {
    "gn:admin1_code":"10",
    "gn:asciiname":"La Yagruma",
    "gn:country_code":"CU",
    "gn:dem":296,
    "gn:feature_class":"P",
    "gn:feature_code":"PPL",
    "gn:name":"La Yagruma",
    "gn:population":0,
    "gn:timezone":"America/Havana",
    "iso:country":"CU",
    "name:spa_x_preferred":[
        "La Yagruma"
    ],
    "wof:name":"La Yagruma",
    "wof:placetype":"locality"
},
  "geometry": {"coordinates":[-74.22086,20.20227],"type":"Point"}
}