{
  "type": "Feature",
  "properties": {
    "gn:admin1_code":"02",
    "gn:asciiname":"Boca Ciega",
    "gn:country_code":"CU",
    "gn:dem":40,
    "gn:feature_class":"P",
    "gn:feature_code":"PPL",
    "gn:name":"Boca Ciega",
    "gn:population":0,
    "gn:timezone":"America/Havana",
    "iso:country":"CU",
    "wof:name":"Boca Ciega",
    "wof:placetype":"locality"
},
  "geometry": {"coordinates":[-82.16667,23.16667],"type":"Point"}
}