{
  "type": "Feature",
  "properties": {
    "gn:admin1_code":"13",
    "gn:asciiname":"Cuatro Veredas",
    "gn:country_code":"CU",
    "gn:dem":49,
    "gn:feature_class":"P",
    "gn:feature_code":"PPL",
    "gn:name":"Cuatro Veredas",
    "gn:population":0,
    "gn:timezone":"America/Havana",
    "iso:country":"CU",
    "name:spa_x_preferred":[
        "Cuatro Veredas"
    ],
    "wof:name":"Cuatro Veredas",
    "wof:placetype":"locality"
},
  "geometry": {"coordinates":[-76.51054000000001,21.11482],"type":"Point"}
}