{
  "type": "Feature",
  "properties": {
    "gn:admin1_code":"12",
    "gn:asciiname":"Castro",
    "gn:country_code":"CU",
    "gn:dem":99,
    "gn:feature_class":"P",
    "gn:feature_code":"PPLL",
    "gn:name":"Castro",
    "gn:population":0,
    "gn:timezone":"America/Havana",
    "iso:country":"CU",
    "wof:name":"Castro",
    "wof:placetype":"locality"
},
  "geometry": {"coordinates":[-75.16667,20.53333],"type":"Point"}
}