{
  "type": "Feature",
  "properties": {
    "gn:admin1_code":"15",
    "gn:asciiname":"El Mijial",
    "gn:country_code":"CU",
    "gn:dem":281,
    "gn:feature_class":"P",
    "gn:feature_code":"PPL",
    "gn:name":"El Mijial",
    "gn:population":0,
    "gn:timezone":"America/Havana",
    "iso:country":"CU",
    "name:spa_x_preferred":[
        "El Mijial"
    ],
    "wof:name":"El Mijial",
    "wof:placetype":"locality"
},
  "geometry": {"coordinates":[-75.65741,20.15112],"type":"Point"}
}