{
  "type": "Feature",
  "properties": {
    "gn:admin1_code":"15",
    "gn:asciiname":"La Valeriana",
    "gn:country_code":"CU",
    "gn:dem":212,
    "gn:feature_class":"P",
    "gn:feature_code":"PPL",
    "gn:name":"La Valeriana",
    "gn:population":0,
    "gn:timezone":"America/Havana",
    "iso:country":"CU",
    "name:rus_x_preferred":[
        "La-Veder\u2019yana"
    ],
    "name:spa_x_preferred":[
        "La Valeriana"
    ],
    "name:und_x_variant":[
        "Veridiana"
    ],
    "wof:name":"La Valeriana",
    "wof:placetype":"locality"
},
  "geometry": {"coordinates":[-75.53837,20.02187],"type":"Point"}
}