{
  "type": "Feature",
  "properties": {
    "gn:admin1_code":"16",
    "gn:asciiname":"Cumbre",
    "gn:country_code":"CU",
    "gn:dem":197,
    "gn:feature_class":"P",
    "gn:feature_code":"PPL",
    "gn:name":"Cumbre",
    "gn:population":0,
    "gn:timezone":"America/Havana",
    "iso:country":"CU",
    "name:ceb_x_preferred":[
        "Cumbre"
    ],
    "name:nld_x_preferred":[
        "Cumbre"
    ],
    "name:nor_x_preferred":[
        "Cumbre"
    ],
    "name:spa_x_preferred":[
        "Cumbre"
    ],
    "name:swe_x_preferred":[
        "Cumbre"
    ],
    "name:vie_x_preferred":[
        "Cumbre"
    ],
    "name:war_x_preferred":[
        "Cumbre"
    ],
    "wof:name":"Cumbre",
    "wof:placetype":"locality"
},
  "geometry": {"coordinates":[-79.68221,22.29471],"type":"Point"}
}