{
  "type": "Feature",
  "properties": {
    "gn:admin1_code":"07",
    "gn:asciiname":"Mamanantuabo",
    "gn:country_code":"CU",
    "gn:dem":51,
    "gn:feature_class":"P",
    "gn:feature_code":"PPL",
    "gn:name":"Mamanantuabo",
    "gn:population":0,
    "gn:timezone":"America/Havana",
    "iso:country":"CU",
    "name:spa_x_preferred":[
        "Mamanantuabo"
    ],
    "wof:name":"Mamanantuabo",
    "wof:placetype":"locality"
},
  "geometry": {"coordinates":[-78.18035,21.77647],"type":"Point"}
}