{
  "type": "Feature",
  "properties": {
    "gn:admin1_code":"09",
    "gn:asciiname":"Palmarito",
    "gn:country_code":"CU",
    "gn:dem":25,
    "gn:feature_class":"P",
    "gn:feature_code":"PPL",
    "gn:name":"Palmarito",
    "gn:population":0,
    "gn:timezone":"America/Havana",
    "iso:country":"CU",
    "name:spa_x_preferred":[
        "Palmarito"
    ],
    "wof:name":"Palmarito",
    "wof:placetype":"locality"
},
  "geometry": {"coordinates":[-77.28813000000002,20.19958],"type":"Point"}
}