{
  "type": "Feature",
  "properties": {
    "gn:admin1_code":"14",
    "gn:asciiname":"Nueva Union",
    "gn:country_code":"CU",
    "gn:dem":128,
    "gn:feature_class":"P",
    "gn:feature_code":"PPL",
    "gn:name":"Nueva Uni\u00f3n",
    "gn:population":0,
    "gn:timezone":"America/Havana",
    "iso:country":"CU",
    "name:spa_x_preferred":[
        "Nueva Uni\u00f3n"
    ],
    "wof:name":"Nueva Union",
    "wof:placetype":"locality"
},
  "geometry": {"coordinates":[-79.70057,22.0157],"type":"Point"}
}