{
  "type": "Feature",
  "properties": {
    "gn:admin1_code":"13",
    "gn:asciiname":"Los Cocos",
    "gn:country_code":"CU",
    "gn:dem":12,
    "gn:feature_class":"P",
    "gn:feature_code":"PPLL",
    "gn:name":"Los Cocos",
    "gn:population":0,
    "gn:timezone":"America/Havana",
    "iso:country":"CU",
    "name:nld_x_preferred":[
        "Los Cocos"
    ],
    "name:por_x_preferred":[
        "Los Cocos"
    ],
    "name:spa_x_preferred":[
        "Los Cocos"
    ],
    "wof:name":"Los Cocos",
    "wof:placetype":"locality"
},
  "geometry": {"coordinates":[-77.39624999999999,20.76352],"type":"Point"}
}