{
  "type": "Feature",
  "properties": {
    "gn:admin1_code":"AR",
    "gn:asciiname":"Mi Refugio",
    "gn:country_code":"CU",
    "gn:dem":60,
    "gn:feature_class":"P",
    "gn:feature_code":"PPL",
    "gn:name":"Mi Refugio",
    "gn:population":0,
    "gn:timezone":"America/Havana",
    "iso:country":"CU",
    "name:spa_x_preferred":[
        "Mi Refugio"
    ],
    "wof:name":"Mi Refugio",
    "wof:placetype":"locality"
},
  "geometry": {"coordinates":[-82.97490000000001,22.75071],"type":"Point"}
}