{
  "type": "Feature",
  "properties": {
    "gn:admin1_code":"13",
    "gn:asciiname":"Las Peluas",
    "gn:country_code":"CU",
    "gn:dem":21,
    "gn:feature_class":"P",
    "gn:feature_code":"PPL",
    "gn:name":"Las Pel\u00faas",
    "gn:population":0,
    "gn:timezone":"America/Havana",
    "iso:country":"CU",
    "name:spa_x_preferred":[
        "Las Pel\u00faas"
    ],
    "wof:name":"Las Peluas",
    "wof:placetype":"locality"
},
  "geometry": {"coordinates":[-76.95811999999999,21.22308],"type":"Point"}
}