{
  "type": "Feature",
  "properties": {
    "gn:admin1_code":"AR",
    "gn:asciiname":"Pablo Torres",
    "gn:country_code":"CU",
    "gn:dem":80,
    "gn:feature_class":"P",
    "gn:feature_code":"PPL",
    "gn:name":"Pablo Torres",
    "gn:population":0,
    "gn:timezone":"America/Havana",
    "iso:country":"CU",
    "name:spa_x_preferred":[
        "Pablo Torres"
    ],
    "wof:name":"Pablo Torres",
    "wof:placetype":"locality"
},
  "geometry": {"coordinates":[-82.75620000000001,22.83585],"type":"Point"}
}