{
  "type": "Feature",
  "properties": {
    "gn:admin1_code":"09",
    "gn:asciiname":"Jobo Dulce",
    "gn:country_code":"CU",
    "gn:dem":234,
    "gn:feature_class":"P",
    "gn:feature_code":"PPLL",
    "gn:name":"Jobo Dulce",
    "gn:population":0,
    "gn:timezone":"America/Havana",
    "iso:country":"CU",
    "name:spa_x_preferred":[
        "Jobo Dulce"
    ],
    "wof:name":"Jobo Dulce",
    "wof:placetype":"locality"
},
  "geometry": {"coordinates":[-76.58275,20.14513],"type":"Point"}
}