{
  "type": "Feature",
  "properties": {
    "gn:admin1_code":"05",
    "gn:asciiname":"Sao Tumbado",
    "gn:cc2":"CU",
    "gn:country_code":"CU",
    "gn:dem":86,
    "gn:feature_class":"P",
    "gn:feature_code":"PPLL",
    "gn:name":"Sao Tumbado",
    "gn:population":0,
    "gn:timezone":"America/Havana",
    "iso:country":"CU",
    "name:und_x_variant":[
        "Sao Tumbao",
        "Sao Tumbado"
    ],
    "wof:name":"Sao Tumbado",
    "wof:placetype":"locality"
},
  "geometry": {"coordinates":[-78.06917,21.38583],"type":"Point"}
}