{
  "type": "Feature",
  "properties": {
    "gn:admin1_code":"15",
    "gn:asciiname":"Negritos",
    "gn:country_code":"CU",
    "gn:dem":378,
    "gn:feature_class":"P",
    "gn:feature_code":"PPL",
    "gn:name":"Negritos",
    "gn:population":0,
    "gn:timezone":"America/Havana",
    "iso:country":"CU",
    "wof:name":"Negritos",
    "wof:placetype":"locality"
},
  "geometry": {"coordinates":[-76.33333,20.21667],"type":"Point"}
}