{
  "type": "Feature",
  "properties": {
    "gn:admin1_code":"10",
    "gn:asciiname":"Ojo de Agua",
    "gn:country_code":"CU",
    "gn:dem":419,
    "gn:feature_class":"P",
    "gn:feature_code":"PPLL",
    "gn:name":"Ojo de Agua",
    "gn:population":0,
    "gn:timezone":"America/Havana",
    "iso:country":"CU",
    "name:spa_x_preferred":[
        "Ojo de Agua"
    ],
    "wof:name":"Ojo de Agua",
    "wof:placetype":"locality"
},
  "geometry": {"coordinates":[-74.9156,20.20645],"type":"Point"}
}