{
  "type": "Feature",
  "properties": {
    "gn:admin1_code":"02",
    "gn:asciiname":"Barbosa",
    "gn:country_code":"CU",
    "gn:dem":78,
    "gn:feature_class":"P",
    "gn:feature_code":"PPL",
    "gn:name":"Barbosa",
    "gn:population":0,
    "gn:timezone":"America/Havana",
    "iso:country":"CU",
    "name:ceb_x_preferred":[
        "Barbosa"
    ],
    "name:ces_x_preferred":[
        "Barbosa"
    ],
    "name:deu_x_preferred":[
        "Barbosa"
    ],
    "name:fra_x_preferred":[
        "Barbosa"
    ],
    "name:glg_x_preferred":[
        "Barbosa"
    ],
    "name:heb_x_preferred":[
        "\u05d1\u05e8\u05d1\u05d5\u05d6\u05d4"
    ],
    "name:ita_x_preferred":[
        "Barbosa"
    ],
    "name:jpn_x_preferred":[
        "\u30d0\u30eb\u30dc\u30b5"
    ],
    "name:nld_x_preferred":[
        "Barbosa"
    ],
    "name:pol_x_preferred":[
        "Barbosa"
    ],
    "name:por_x_preferred":[
        "Barbosa"
    ],
    "name:rus_x_preferred":[
        "\u0411\u0430\u0440\u0431\u043e\u0437\u0430"
    ],
    "name:slv_x_preferred":[
        "Barbosa"
    ],
    "name:spa_x_preferred":[
        "Barbosa"
    ],
    "name:srp_x_preferred":[
        "\u0411\u0430\u0440\u0431\u043e\u0441\u0430"
    ],
    "name:swe_x_preferred":[
        "Barbosa"
    ],
    "name:ukr_x_preferred":[
        "\u0411\u0430\u0440\u0431\u043e\u0437\u0430"
    ],
    "wof:name":"Barbosa",
    "wof:placetype":"locality"
},
  "geometry": {"coordinates":[-82.31667,23.06667],"type":"Point"}
}