{
  "type": "Feature",
  "properties": {
    "gn:admin1_code":"07",
    "gn:asciiname":"Oriente",
    "gn:country_code":"CU",
    "gn:dem":39,
    "gn:feature_class":"P",
    "gn:feature_code":"PPLL",
    "gn:name":"Oriente",
    "gn:population":0,
    "gn:timezone":"America/Havana",
    "iso:country":"CU",
    "name:ast_x_preferred":[
        "Oriente"
    ],
    "name:bre_x_preferred":[
        "Oriente"
    ],
    "name:ceb_x_preferred":[
        "Oriente"
    ],
    "name:deu_x_preferred":[
        "Oriente"
    ],
    "name:epo_x_preferred":[
        "Oriente"
    ],
    "name:fra_x_preferred":[
        "Oriente"
    ],
    "name:ita_x_preferred":[
        "Oriente"
    ],
    "name:nld_x_preferred":[
        "Oriente"
    ],
    "name:por_x_preferred":[
        "Oriente"
    ],
    "name:spa_x_preferred":[
        "Oriente"
    ],
    "name:swe_x_preferred":[
        "Oriente"
    ],
    "wof:name":"Oriente",
    "wof:placetype":"locality"
},
  "geometry": {"coordinates":[-78.66667,21.93333],"type":"Point"}
}