{
  "type": "Feature",
  "properties": {
    "gn:admin1_code":"12",
    "gn:asciiname":"La Alcarraza",
    "gn:country_code":"CU",
    "gn:dem":343,
    "gn:feature_class":"P",
    "gn:feature_code":"PPL",
    "gn:name":"La Alcarraza",
    "gn:population":0,
    "gn:timezone":"America/Havana",
    "iso:country":"CU",
    "name:spa_x_preferred":[
        "La Alcarraza"
    ],
    "wof:name":"La Alcarraza",
    "wof:placetype":"locality"
},
  "geometry": {"coordinates":[-75.32014000000002,20.44732],"type":"Point"}
}