{
  "type": "Feature",
  "properties": {
    "gn:admin1_code":"12",
    "gn:asciiname":"Alto de los Negritos",
    "gn:country_code":"CU",
    "gn:dem":181,
    "gn:feature_class":"P",
    "gn:feature_code":"PPL",
    "gn:name":"Alto de los Negritos",
    "gn:population":0,
    "gn:timezone":"America/Havana",
    "iso:country":"CU",
    "name:spa_x_preferred":[
        "Alto de los Negritos"
    ],
    "wof:name":"Alto de los Negritos",
    "wof:placetype":"locality"
},
  "geometry": {"coordinates":[-75.23855999999998,20.42335],"type":"Point"}
}