{
  "type": "Feature",
  "properties": {
    "gn:admin1_code":"03",
    "gn:asciiname":"Mexico",
    "gn:country_code":"CU",
    "gn:dem":72,
    "gn:feature_class":"P",
    "gn:feature_code":"PPL",
    "gn:name":"M\u00e9xico",
    "gn:population":0,
    "gn:timezone":"America/Havana",
    "iso:country":"CU",
    "name:spa_x_preferred":[
        "M\u00e9xico"
    ],
    "wof:name":"Mexico",
    "wof:placetype":"locality"
},
  "geometry": {"coordinates":[-80.83468000000001,22.7706],"type":"Point"}
}