{
  "type": "Feature",
  "properties": {
    "gn:admin1_code":"01",
    "gn:asciiname":"Valle San Juan",
    "gn:country_code":"CU",
    "gn:dem":14,
    "gn:feature_class":"P",
    "gn:feature_code":"PPLL",
    "gn:name":"Valle San Juan",
    "gn:population":0,
    "gn:timezone":"America/Havana",
    "iso:country":"CU",
    "name:spa_x_preferred":[
        "Valle San Juan"
    ],
    "wof:name":"Valle San Juan",
    "wof:placetype":"locality"
},
  "geometry": {"coordinates":[-84.34421999999998,21.93581],"type":"Point"}
}