{
  "type": "Feature",
  "properties": {
    "gn:admin1_code":"15",
    "gn:asciiname":"Cuatro Veredas",
    "gn:country_code":"CU",
    "gn:dem":251,
    "gn:feature_class":"P",
    "gn:feature_code":"PPL",
    "gn:name":"Cuatro Veredas",
    "gn:population":0,
    "gn:timezone":"America/Havana",
    "iso:country":"CU",
    "name:spa_x_preferred":[
        "Cuatro Veredas"
    ],
    "wof:name":"Cuatro Veredas",
    "wof:placetype":"locality"
},
  "geometry": {"coordinates":[-76.36544000000001,20.27903],"type":"Point"}
}