{
  "type": "Feature",
  "properties": {
    "gn:admin1_code":"AR",
    "gn:asciiname":"El Junco",
    "gn:country_code":"CU",
    "gn:dem":10,
    "gn:feature_class":"P",
    "gn:feature_code":"PPL",
    "gn:name":"El Junco",
    "gn:population":0,
    "gn:timezone":"America/Havana",
    "iso:country":"CU",
    "name:ceb_x_preferred":[
        "Laguna El Junco"
    ],
    "name:fin_x_preferred":[
        "El Junco"
    ],
    "name:fra_x_preferred":[
        "El Junco"
    ],
    "name:spa_x_preferred":[
        "Laguna El Junco"
    ],
    "name:swe_x_preferred":[
        "Laguna El Junco"
    ],
    "name:und_x_variant":[
        "Junco",
        "El Junco"
    ],
    "wof:name":"El Junco",
    "wof:placetype":"locality"
},
  "geometry": {"coordinates":[-82.51692,22.73901],"type":"Point"}
}