{
  "type": "Feature",
  "properties": {
    "gn:admin1_code":"13",
    "gn:asciiname":"El Sesenta",
    "gn:country_code":"CU",
    "gn:dem":66,
    "gn:feature_class":"P",
    "gn:feature_code":"PPL",
    "gn:name":"El Sesenta",
    "gn:population":0,
    "gn:timezone":"America/Havana",
    "iso:country":"CU",
    "name:spa_x_preferred":[
        "El Sesenta"
    ],
    "wof:name":"El Sesenta",
    "wof:placetype":"locality"
},
  "geometry": {"coordinates":[-77.27965,20.95443],"type":"Point"}
}