{
  "type": "Feature",
  "properties": {
    "gn:admin1_code":"08",
    "gn:asciiname":"El Negrito",
    "gn:country_code":"CU",
    "gn:dem":35,
    "gn:feature_class":"P",
    "gn:feature_code":"PPL",
    "gn:name":"El Negrito",
    "gn:population":0,
    "gn:timezone":"America/Havana",
    "iso:country":"CU",
    "name:spa_x_preferred":[
        "El Negrito"
    ],
    "wof:name":"El Negrito",
    "wof:placetype":"locality"
},
  "geometry": {"coordinates":[-80.28712,22.04856],"type":"Point"}
}