{
  "type": "Feature",
  "properties": {
    "gn:admin1_code":"15",
    "gn:asciiname":"La Lucia",
    "gn:country_code":"CU",
    "gn:dem":265,
    "gn:feature_class":"P",
    "gn:feature_code":"PPL",
    "gn:name":"La Lucia",
    "gn:population":0,
    "gn:timezone":"America/Havana",
    "iso:country":"CU",
    "name:spa_x_preferred":[
        "La Lucia"
    ],
    "wof:name":"La Lucia",
    "wof:placetype":"locality"
},
  "geometry": {"coordinates":[-75.57701,20.07876],"type":"Point"}
}