{
  "type": "Feature",
  "properties": {
    "gn:admin1_code":"09",
    "gn:asciiname":"Chicolongo",
    "gn:country_code":"CU",
    "gn:dem":820,
    "gn:feature_class":"P",
    "gn:feature_code":"PPL",
    "gn:name":"Chicolongo",
    "gn:population":0,
    "gn:timezone":"America/Havana",
    "iso:country":"CU",
    "name:spa_x_preferred":[
        "Chicolongo"
    ],
    "wof:name":"Chicolongo",
    "wof:placetype":"locality"
},
  "geometry": {"coordinates":[-76.49366999999999,20.12119],"type":"Point"}
}