{
  "type": "Feature",
  "properties": {
    "gn:admin1_code":"MA",
    "gn:asciiname":"Zayas",
    "gn:country_code":"CU",
    "gn:dem":16,
    "gn:feature_class":"P",
    "gn:feature_code":"PPL",
    "gn:name":"Zayas",
    "gn:population":0,
    "gn:timezone":"America/Havana",
    "iso:country":"CU",
    "name:spa_x_preferred":[
        "Zayas"
    ],
    "wof:name":"Zayas",
    "wof:placetype":"locality"
},
  "geometry": {"coordinates":[-82.25962,22.74324],"type":"Point"}
}