{
  "type": "Feature",
  "properties": {
    "gn:admin1_code":"12",
    "gn:asciiname":"Chavaleta",
    "gn:country_code":"CU",
    "gn:dem":20,
    "gn:feature_class":"P",
    "gn:feature_code":"PPL",
    "gn:name":"Chavaleta",
    "gn:population":0,
    "gn:timezone":"America/Havana",
    "iso:country":"CU",
    "name:spa_x_preferred":[
        "Chavaleta"
    ],
    "wof:name":"Chavaleta",
    "wof:placetype":"locality"
},
  "geometry": {"coordinates":[-75.66649,20.65724],"type":"Point"}
}