{
  "type": "Feature",
  "properties": {
    "gn:admin1_code":"05",
    "gn:asciiname":"La Catalina",
    "gn:country_code":"CU",
    "gn:dem":6,
    "gn:feature_class":"P",
    "gn:feature_code":"PPLL",
    "gn:name":"La Catalina",
    "gn:population":0,
    "gn:timezone":"America/Havana",
    "iso:country":"CU",
    "name:spa_x_preferred":[
        "La Catalina"
    ],
    "name:und_x_variant":[
        "Las Catalinas"
    ],
    "wof:name":"La Catalina",
    "wof:placetype":"locality"
},
  "geometry": {"coordinates":[-78.07500999999998,20.77615],"type":"Point"}
}