{
  "type": "Feature",
  "properties": {
    "gn:admin1_code":"16",
    "gn:asciiname":"Refugio",
    "gn:country_code":"CU",
    "gn:dem":16,
    "gn:feature_class":"P",
    "gn:feature_code":"PPL",
    "gn:name":"Refugio",
    "gn:population":0,
    "gn:timezone":"America/Havana",
    "iso:country":"CU",
    "name:ceb_x_preferred":[
        "Refugio"
    ],
    "name:deu_x_preferred":[
        "Refugio"
    ],
    "name:nld_x_preferred":[
        "Refugio"
    ],
    "name:pol_x_preferred":[
        "Refugio"
    ],
    "name:por_x_preferred":[
        "Ref\u00fagio"
    ],
    "name:spa_x_preferred":[
        "Refugio"
    ],
    "name:srp_x_preferred":[
        "\u0420\u0435\u0444\u0458\u0443\u0440\u0438\u043e"
    ],
    "name:swe_x_preferred":[
        "Refugio"
    ],
    "wof:name":"Refugio",
    "wof:placetype":"locality"
},
  "geometry": {"coordinates":[-79.63738000000002,22.56138],"type":"Point"}
}