{
  "type": "Feature",
  "properties": {
    "gn:admin1_code":"12",
    "gn:admin2_code":"3211",
    "gn:asciiname":"Juan Vicente",
    "gn:country_code":"CU",
    "gn:dem":18,
    "gn:feature_class":"P",
    "gn:feature_code":"PPL",
    "gn:name":"Juan Vicente",
    "gn:population":0,
    "gn:timezone":"America/Havana",
    "iso:country":"CU",
    "wof:name":"Juan Vicente",
    "wof:placetype":"locality"
},
  "geometry": {"coordinates":[-75.71889,20.67346],"type":"Point"}
}