{
  "type": "Feature",
  "properties": {
    "gn:admin1_code":"09",
    "gn:asciiname":"Siete Piezas",
    "gn:country_code":"CU",
    "gn:dem":58,
    "gn:feature_class":"P",
    "gn:feature_code":"PPL",
    "gn:name":"Siete Piezas",
    "gn:population":0,
    "gn:timezone":"America/Havana",
    "iso:country":"CU",
    "name:spa_x_preferred":[
        "Siete Piezas"
    ],
    "wof:name":"Siete Piezas",
    "wof:placetype":"locality"
},
  "geometry": {"coordinates":[-77.62719,19.93707],"type":"Point"}
}