{
  "type": "Feature",
  "properties": {
    "gn:admin1_code":"01",
    "gn:asciiname":"Juan Gomez",
    "gn:country_code":"CU",
    "gn:dem":21,
    "gn:feature_class":"P",
    "gn:feature_code":"PPLL",
    "gn:name":"Juan G\u00f3mez",
    "gn:population":0,
    "gn:timezone":"America/Havana",
    "iso:country":"CU",
    "name:spa_x_preferred":[
        "Juan G\u00f3mez"
    ],
    "wof:name":"Juan Gomez",
    "wof:placetype":"locality"
},
  "geometry": {"coordinates":[-84.14909,22.19237],"type":"Point"}
}