{
  "type": "Feature",
  "properties": {
    "gn:admin1_code":"MA",
    "gn:asciiname":"Rivas",
    "gn:country_code":"CU",
    "gn:dem":167,
    "gn:feature_class":"P",
    "gn:feature_code":"PPLL",
    "gn:name":"Rivas",
    "gn:population":0,
    "gn:timezone":"America/Havana",
    "iso:country":"CU",
    "wof:name":"Rivas",
    "wof:placetype":"locality"
},
  "geometry": {"coordinates":[-82.06667,23.01667],"type":"Point"}
}