{
  "type": "Feature",
  "properties": {
    "gn:admin1_code":"13",
    "gn:asciiname":"La Caoba",
    "gn:country_code":"CU",
    "gn:dem":18,
    "gn:feature_class":"P",
    "gn:feature_code":"PPL",
    "gn:name":"La Caoba",
    "gn:population":0,
    "gn:timezone":"America/Havana",
    "iso:country":"CU",
    "name:spa_x_preferred":[
        "La Caoba"
    ],
    "wof:name":"La Caoba",
    "wof:placetype":"locality"
},
  "geometry": {"coordinates":[-77.49498,20.76464],"type":"Point"}
}