{
  "type": "Feature",
  "properties": {
    "gn:admin1_code":"03",
    "gn:asciiname":"Guacamaya",
    "gn:country_code":"CU",
    "gn:dem":34,
    "gn:feature_class":"P",
    "gn:feature_code":"PPLL",
    "gn:name":"Guacamaya",
    "gn:population":0,
    "gn:timezone":"America/Havana",
    "iso:country":"CU",
    "name:ceb_x_preferred":[
        "Guacamaya"
    ],
    "name:swe_x_preferred":[
        "Guacamaya"
    ],
    "wof:name":"Guacamaya",
    "wof:placetype":"locality"
},
  "geometry": {"coordinates":[-80.78333000000001,22.46667],"type":"Point"}
}