{
  "type": "Feature",
  "properties": {
    "gn:admin1_code":"03",
    "gn:asciiname":"Dos Hermanos",
    "gn:country_code":"CU",
    "gn:dem":21,
    "gn:feature_class":"P",
    "gn:feature_code":"PPL",
    "gn:name":"Dos Hermanos",
    "gn:population":0,
    "gn:timezone":"America/Havana",
    "iso:country":"CU",
    "name:spa_x_preferred":[
        "Dos Hermanos"
    ],
    "wof:name":"Dos Hermanos",
    "wof:placetype":"locality"
},
  "geometry": {"coordinates":[-81.22164000000002,22.68686],"type":"Point"}
}