{
  "type": "Feature",
  "properties": {
    "gn:admin1_code":"15",
    "gn:asciiname":"Puerto Boniato",
    "gn:country_code":"CU",
    "gn:dem":323,
    "gn:feature_class":"P",
    "gn:feature_code":"PPL",
    "gn:name":"Puerto Boniato",
    "gn:population":0,
    "gn:timezone":"America/Havana",
    "iso:country":"CU",
    "name:spa_x_preferred":[
        "Puerto Boniato"
    ],
    "wof:name":"Puerto Boniato",
    "wof:placetype":"locality"
},
  "geometry": {"coordinates":[-75.79868,20.10318],"type":"Point"}
}