{
  "type": "Feature",
  "properties": {
    "gn:admin1_code":"05",
    "gn:asciiname":"Barreto",
    "gn:country_code":"CU",
    "gn:dem":45,
    "gn:feature_class":"P",
    "gn:feature_code":"PPLL",
    "gn:name":"Barreto",
    "gn:population":0,
    "gn:timezone":"America/Havana",
    "iso:country":"CU",
    "name:spa_x_preferred":[
        "Barreto"
    ],
    "wof:name":"Barreto",
    "wof:placetype":"locality"
},
  "geometry": {"coordinates":[-77.51791999999998,21.47017],"type":"Point"}
}