{
  "type": "Feature",
  "properties": {
    "gn:admin1_code":"AR",
    "gn:asciiname":"La Majagua",
    "gn:country_code":"CU",
    "gn:dem":20,
    "gn:feature_class":"P",
    "gn:feature_code":"PPLL",
    "gn:name":"La Majagua",
    "gn:population":0,
    "gn:timezone":"America/Havana",
    "iso:country":"CU",
    "name:spa_x_preferred":[
        "La Majagua"
    ],
    "wof:name":"La Majagua",
    "wof:placetype":"locality"
},
  "geometry": {"coordinates":[-83.04836999999998,22.64258],"type":"Point"}
}