{
  "type": "Feature",
  "properties": {
    "gn:admin1_code":"15",
    "gn:asciiname":"Concepcion",
    "gn:country_code":"CU",
    "gn:dem":169,
    "gn:feature_class":"P",
    "gn:feature_code":"PPLL",
    "gn:name":"Concepci\u00f3n",
    "gn:population":0,
    "gn:timezone":"America/Havana",
    "iso:country":"CU",
    "wof:name":"Concepcion",
    "wof:placetype":"locality"
},
  "geometry": {"coordinates":[-75.97944,20.19333],"type":"Point"}
}