{
  "type": "Feature",
  "properties": {
    "gn:admin1_code":"14",
    "gn:asciiname":"Almendron",
    "gn:country_code":"CU",
    "gn:dem":23,
    "gn:feature_class":"P",
    "gn:feature_code":"PPL",
    "gn:name":"Almendr\u00f3n",
    "gn:population":0,
    "gn:timezone":"America/Havana",
    "iso:country":"CU",
    "name:spa_x_preferred":[
        "Almendr\u00f3n"
    ],
    "wof:name":"Almendron",
    "wof:placetype":"locality"
},
  "geometry": {"coordinates":[-79.196,21.70258],"type":"Point"}
}