{
  "type": "Feature",
  "properties": {
    "gn:admin1_code":"13",
    "gn:asciiname":"Arroyon",
    "gn:country_code":"CU",
    "gn:dem":17,
    "gn:feature_class":"P",
    "gn:feature_code":"PPL",
    "gn:name":"Arroy\u00f3n",
    "gn:population":0,
    "gn:timezone":"America/Havana",
    "iso:country":"CU",
    "name:spa_x_preferred":[
        "Arroy\u00f3n"
    ],
    "wof:name":"Arroyon",
    "wof:placetype":"locality"
},
  "geometry": {"coordinates":[-76.42523,21.16686],"type":"Point"}
}