{
  "type": "Feature",
  "properties": {
    "gn:admin1_code":"09",
    "gn:asciiname":"Tejas",
    "gn:country_code":"CU",
    "gn:dem":117,
    "gn:feature_class":"P",
    "gn:feature_code":"PPLL",
    "gn:name":"Tejas",
    "gn:population":0,
    "gn:timezone":"America/Havana",
    "iso:country":"CU",
    "name:ceb_x_preferred":[
        "Tejas"
    ],
    "name:fra_x_preferred":[
        "Tejas"
    ],
    "name:ita_x_preferred":[
        "Tejas"
    ],
    "name:spa_x_preferred":[
        "Tejas"
    ],
    "name:swe_x_preferred":[
        "Tejas"
    ],
    "wof:name":"Tejas",
    "wof:placetype":"locality"
},
  "geometry": {"coordinates":[-76.46666999999999,20.33333],"type":"Point"}
}