{
  "type": "Feature",
  "properties": {
    "gn:admin1_code":"05",
    "gn:asciiname":"Carrasco",
    "gn:country_code":"CU",
    "gn:dem":91,
    "gn:feature_class":"P",
    "gn:feature_code":"PPLL",
    "gn:name":"Carrasco",
    "gn:population":0,
    "gn:timezone":"America/Havana",
    "iso:country":"CU",
    "name:spa_x_preferred":[
        "Carrasco"
    ],
    "name:und_x_variant":[
        "Carasco"
    ],
    "wof:name":"Carrasco",
    "wof:placetype":"locality"
},
  "geometry": {"coordinates":[-77.74257,20.99168],"type":"Point"}
}