{
  "type": "Feature",
  "properties": {
    "gn:admin1_code":"12",
    "gn:asciiname":"Punto Abajo",
    "gn:country_code":"CU",
    "gn:dem":264,
    "gn:feature_class":"P",
    "gn:feature_code":"PPL",
    "gn:name":"Punto Abajo",
    "gn:population":0,
    "gn:timezone":"America/Havana",
    "iso:country":"CU",
    "name:spa_x_preferred":[
        "Punto Abajo"
    ],
    "wof:name":"Punto Abajo",
    "wof:placetype":"locality"
},
  "geometry": {"coordinates":[-75.76806999999999,20.4499],"type":"Point"}
}