{
  "type": "Feature",
  "properties": {
    "gn:admin1_code":"AR",
    "gn:asciiname":"Abraham Lincoln",
    "gn:country_code":"CU",
    "gn:dem":42,
    "gn:feature_class":"P",
    "gn:feature_code":"PPL",
    "gn:name":"Abraham Lincoln",
    "gn:population":0,
    "gn:timezone":"America/Havana",
    "iso:country":"CU",
    "name:spa_x_preferred":[
        "Abraham Lincoln"
    ],
    "wof:name":"Abraham Lincoln",
    "wof:placetype":"locality"
},
  "geometry": {"coordinates":[-82.79666999999998,22.79942],"type":"Point"}
}