{
  "type": "Feature",
  "properties": {
    "gn:admin1_code":"03",
    "gn:asciiname":"Las Morlas",
    "gn:country_code":"CU",
    "gn:dem":5,
    "gn:feature_class":"P",
    "gn:feature_code":"PPL",
    "gn:name":"Las Morlas",
    "gn:population":0,
    "gn:timezone":"America/Havana",
    "iso:country":"CU",
    "name:spa_x_preferred":[
        "Las Morlas"
    ],
    "wof:name":"Las Morlas",
    "wof:placetype":"locality"
},
  "geometry": {"coordinates":[-81.14584000000001,23.19347],"type":"Point"}
}