{
  "type": "Feature",
  "properties": {
    "gn:admin1_code":"15",
    "gn:asciiname":"Santa Maria",
    "gn:country_code":"CU",
    "gn:dem":141,
    "gn:feature_class":"P",
    "gn:feature_code":"PPL",
    "gn:name":"Santa Mar\u00eda",
    "gn:population":0,
    "gn:timezone":"America/Havana",
    "iso:country":"CU",
    "name:spa_x_preferred":[
        "Santa Mar\u00eda"
    ],
    "wof:name":"Santa Maria",
    "wof:placetype":"locality"
},
  "geometry": {"coordinates":[-75.61998,19.96592],"type":"Point"}
}