{
  "type": "Feature",
  "properties": {
    "gn:admin1_code":"16",
    "gn:asciiname":"Sierra Morena",
    "gn:country_code":"CU",
    "gn:dem":44,
    "gn:feature_class":"P",
    "gn:feature_code":"PPL",
    "gn:name":"Sierra Morena",
    "gn:population":0,
    "gn:timezone":"America/Havana",
    "iso:country":"CU",
    "name:spa_x_preferred":[
        "Sierra Morena"
    ],
    "wof:name":"Sierra Morena",
    "wof:placetype":"locality"
},
  "geometry": {"coordinates":[-80.5168,22.9518],"type":"Point"}
}