{
  "type": "Feature",
  "properties": {
    "gn:admin1_code":"16",
    "gn:asciiname":"Sierra Morena",
    "gn:country_code":"CU",
    "gn:dem":44,
    "gn:feature_class":"P",
    "gn:feature_code":"PPL",
    "gn:name":"Sierra Morena",
    "gn:population":0,
    "gn:timezone":"America/Havana",
    "iso:country":"CU",
    "name:ben_x_preferred":[
        "\u09b8\u09bf\u09af\u09bc\u09c7\u09b0\u09be \u09ae\u09cb\u09b0\u09c7\u09a8\u09be"
    ],
    "name:fas_x_preferred":[
        "\u0633\u06cc\u0631\u0627 \u0645\u0648\u0631\u0646\u0627"
    ],
    "name:hun_x_preferred":[
        "Sierra Morena"
    ],
    "name:ind_x_preferred":[
        "Sierra Morena"
    ],
    "name:kor_x_preferred":[
        "\uc2dc\uc5d0\ub77c \ubaa8\ub808\ub098"
    ],
    "name:spa_x_preferred":[
        "Sierra Morena"
    ],
    "name:tur_x_preferred":[
        "Sierra Morena"
    ],
    "name:ukr_x_preferred":[
        "\u0421\u2019\u0454\u0440\u0440\u0430-\u041c\u043e\u0440\u0435\u043d\u0430"
    ],
    "name:urd_x_preferred":[
        "\u0633\u06cc\u0626\u0631\u0627 \u0645\u0648\u0631\u06cc\u0646\u0627"
    ],
    "name:vie_x_preferred":[
        "D\u00e3y Sierra Morena"
    ],
    "wof:name":"Sierra Morena",
    "wof:placetype":"locality"
},
  "geometry": {"coordinates":[-80.5168,22.9518],"type":"Point"}
}