{
  "type": "Feature",
  "properties": {
    "gn:admin1_code":"15",
    "gn:asciiname":"Matahambre",
    "gn:country_code":"CU",
    "gn:dem":307,
    "gn:feature_class":"P",
    "gn:feature_code":"PPL",
    "gn:name":"Matahambre",
    "gn:population":0,
    "gn:timezone":"America/Havana",
    "iso:country":"CU",
    "name:spa_x_preferred":[
        "Matahambre"
    ],
    "wof:name":"Matahambre",
    "wof:placetype":"locality"
},
  "geometry": {"coordinates":[-75.50364,20.28488],"type":"Point"}
}