{
  "type": "Feature",
  "properties": {
    "gn:admin1_code":"07",
    "gn:asciiname":"Punta Alegre",
    "gn:country_code":"CU",
    "gn:dem":13,
    "gn:feature_class":"P",
    "gn:feature_code":"PPL",
    "gn:name":"Punta Alegre",
    "gn:population":0,
    "gn:timezone":"America/Havana",
    "iso:country":"CU",
    "name:eng_x_preferred":[
        "Punta Alegre"
    ],
    "wof:name":"Punta Alegre",
    "wof:placetype":"locality"
},
  "geometry": {"coordinates":[-78.81986999999999,22.37937],"type":"Point"}
}