{
  "type": "Feature",
  "properties": {
    "gn:admin1_code":"14",
    "gn:asciiname":"Crucero Quemadito",
    "gn:country_code":"CU",
    "gn:dem":177,
    "gn:feature_class":"P",
    "gn:feature_code":"PPL",
    "gn:name":"Crucero Quemadito",
    "gn:population":0,
    "gn:timezone":"America/Havana",
    "iso:country":"CU",
    "name:spa_x_preferred":[
        "Crucero Quemadito"
    ],
    "wof:name":"Crucero Quemadito",
    "wof:placetype":"locality"
},
  "geometry": {"coordinates":[-79.64912,22.10696],"type":"Point"}
}