{
  "type": "Feature",
  "properties": {
    "gn:admin1_code":"10",
    "gn:asciiname":"Paso Llano",
    "gn:country_code":"CU",
    "gn:dem":523,
    "gn:feature_class":"P",
    "gn:feature_code":"PPLL",
    "gn:name":"Paso Llano",
    "gn:population":0,
    "gn:timezone":"America/Havana",
    "iso:country":"CU",
    "name:spa_x_preferred":[
        "Paso Llano"
    ],
    "wof:name":"Paso Llano",
    "wof:placetype":"locality"
},
  "geometry": {"coordinates":[-74.94575,20.2611],"type":"Point"}
}