{
  "type": "Feature",
  "properties": {
    "gn:admin1_code":"AR",
    "gn:asciiname":"La Encrucijada",
    "gn:country_code":"CU",
    "gn:dem":40,
    "gn:feature_class":"P",
    "gn:feature_code":"PPLL",
    "gn:name":"La Encrucijada",
    "gn:population":0,
    "gn:timezone":"America/Havana",
    "iso:country":"CU",
    "name:und_x_variant":[
        "Encrucijada",
        "La Encrucijada"
    ],
    "wof:name":"La Encrucijada",
    "wof:placetype":"locality"
},
  "geometry": {"coordinates":[-82.55,22.85],"type":"Point"}
}