{
  "type": "Feature",
  "properties": {
    "gn:admin1_code":"03",
    "gn:asciiname":"Pica Pica",
    "gn:country_code":"CU",
    "gn:dem":30,
    "gn:feature_class":"P",
    "gn:feature_code":"PPLL",
    "gn:name":"Pica Pica",
    "gn:population":0,
    "gn:timezone":"America/Havana",
    "iso:country":"CU",
    "wof:name":"Pica Pica",
    "wof:placetype":"locality"
},
  "geometry": {"coordinates":[-80.84999999999999,22.86667000000001],"type":"Point"}
}