{
  "type": "Feature",
  "properties": {
    "gn:admin1_code":"12",
    "gn:asciiname":"Los Pajantos",
    "gn:country_code":"CU",
    "gn:dem":132,
    "gn:feature_class":"P",
    "gn:feature_code":"PPL",
    "gn:name":"Los Pajantos",
    "gn:population":0,
    "gn:timezone":"America/Havana",
    "iso:country":"CU",
    "name:spa_x_preferred":[
        "Los Pajantos"
    ],
    "wof:name":"Los Pajantos",
    "wof:placetype":"locality"
},
  "geometry": {"coordinates":[-76.29604,21.12173],"type":"Point"}
}