{
  "type": "Feature",
  "properties": {
    "iso:country":"CU",
    "name:chi_x_preferred":[
        "\u8056\u8def\u6613"
    ],
    "name:dut_x_preferred":[
        "San Luis"
    ],
    "name:eng_x_preferred":[
        "San Luis"
    ],
    "name:fin_x_preferred":[
        "San Luis"
    ],
    "name:fre_x_preferred":[
        "San Luis"
    ],
    "name:geo_x_preferred":[
        "\u10e1\u10d0\u10dc-\u10da\u10e3\u10d8\u10e1\u10d8"
    ],
    "name:ger_x_preferred":[
        "San Luis"
    ],
    "name:hat_x_preferred":[
        "San Luis"
    ],
    "name:heb_x_preferred":[
        "\u05e1\u05df \u05dc\u05d5\u05d0\u05d9\u05e1"
    ],
    "name:ita_x_preferred":[
        "San Luis"
    ],
    "name:mac_x_preferred":[
        "\u0421\u0430\u043d \u041b\u0443\u0438\u0441"
    ],
    "name:por_x_preferred":[
        "San Lu\u00eds"
    ],
    "name:rus_x_preferred":[
        "\u0421\u0430\u043d-\u041b\u0443\u0438\u0441"
    ],
    "name:spa_x_preferred":[
        "San Luis"
    ],
    "name:swe_x_preferred":[
        "Municipio de San Luis"
    ],
    "name:vie_x_preferred":[
        "San Luis"
    ],
    "qs:gn_country":"CU",
    "qs:gn_fcode":"PPL",
    "qs:gn_pop":6690,
    "qs:name":"San Luis",
    "qs:name_adm0":"Cuba",
    "qs:name_adm1":"Pinar del Rio",
    "qs:photos":12,
    "qs:photos_1k":2,
    "qs:photos_9k":1,
    "qs:photos_9r":1,
    "qs:photos_all":12,
    "qs:photos_sr":1,
    "qs:placetype":"Town",
    "qs:pop_sr":"5",
    "qs:woe_adm0":23424793,
    "wof:name":"San Luis",
    "wof:placetype":"locality",
    "wof:population":6690
},
  "geometry": {"coordinates":[-83.76111,22.27861],"type":"Point"}
}