{
  "type": "Feature",
  "properties": {
    "iso:country":"CU",
    "name:ara_x_preferred":[
        "\u0633\u0627\u0646 \u0644\u0648\u064a\u0633"
    ],
    "name:ast_x_preferred":[
        "San Luis"
    ],
    "name:ben_x_preferred":[
        "\u09b8\u09be\u09a8 \u09b2\u09c1\u0987"
    ],
    "name:deu_x_preferred":[
        "San Luis"
    ],
    "name:ell_x_preferred":[
        "\u03a3\u03b1\u03bd \u039b\u03bf\u03c5\u03cc\u03c2"
    ],
    "name:eng_x_preferred":[
        "San Luis"
    ],
    "name:fas_x_preferred":[
        "\u0633\u0646 \u0644\u0648\u0626\u06cc\u0632"
    ],
    "name:fin_x_preferred":[
        "San Luis"
    ],
    "name:fra_x_preferred":[
        "San Luis"
    ],
    "name:gle_x_preferred":[
        "San Luis"
    ],
    "name:hat_x_preferred":[
        "San Luis"
    ],
    "name:heb_x_preferred":[
        "\u05e1\u05df \u05dc\u05d5\u05d0\u05d9\u05e1"
    ],
    "name:hin_x_preferred":[
        "\u0938\u0948\u0928 \u0932\u0941\u0908"
    ],
    "name:hun_x_preferred":[
        "San Luis"
    ],
    "name:ind_x_preferred":[
        "San Luis"
    ],
    "name:ita_x_preferred":[
        "San Luis"
    ],
    "name:jpn_x_preferred":[
        "\u30b5\u30f3\u30eb\u30a4\u30b9"
    ],
    "name:kat_x_preferred":[
        "\u10e1\u10d0\u10dc-\u10da\u10e3\u10d8\u10e1\u10d8"
    ],
    "name:kor_x_preferred":[
        "\uc0b0 \ub8e8\uc774\uc2a4"
    ],
    "name:mkd_x_preferred":[
        "\u0421\u0430\u043d \u041b\u0443\u0438\u0441"
    ],
    "name:nld_x_preferred":[
        "San Luis"
    ],
    "name:por_x_preferred":[
        "San Lu\u00eds"
    ],
    "name:rus_x_preferred":[
        "\u0421\u0430\u043d-\u041b\u0443\u0438\u0441"
    ],
    "name:spa_x_preferred":[
        "San Luis"
    ],
    "name:swe_x_preferred":[
        "Municipio de San Luis"
    ],
    "name:tur_x_preferred":[
        "San Luis"
    ],
    "name:ukr_x_preferred":[
        "\u0421\u0430\u043d-\u041b\u0443\u0457\u0441"
    ],
    "name:urd_x_preferred":[
        "\u0633\u0627\u0646 \u0644\u0648\u0626\u0633"
    ],
    "name:uzb_x_preferred":[
        "San Luis"
    ],
    "name:vie_x_preferred":[
        "San Luis"
    ],
    "name:zho_x_preferred":[
        "\u8056\u8def\u6613"
    ],
    "qs:gn_country":"CU",
    "qs:gn_fcode":"PPL",
    "qs:gn_pop":6690,
    "qs:name":"San Luis",
    "qs:name_adm0":"Cuba",
    "qs:name_adm1":"Pinar del Rio",
    "qs:photos":12,
    "qs:photos_1k":2,
    "qs:photos_9k":1,
    "qs:photos_9r":1,
    "qs:photos_all":12,
    "qs:photos_sr":1,
    "qs:placetype":"Town",
    "qs:pop_sr":"5",
    "qs:woe_adm0":23424793,
    "wof:name":"San Luis",
    "wof:placetype":"locality",
    "wof:population":6690
},
  "geometry": {"coordinates":[-83.76111,22.27861],"type":"Point"}
}