{
  "type": "Feature",
  "properties": {
    "gn:admin1_code":"16",
    "gn:asciiname":"La Corona",
    "gn:country_code":"CU",
    "gn:dem":125,
    "gn:feature_class":"P",
    "gn:feature_code":"PPL",
    "gn:name":"La Corona",
    "gn:population":0,
    "gn:timezone":"America/Havana",
    "iso:country":"CU",
    "name:spa_x_preferred":[
        "La Corona"
    ],
    "wof:name":"La Corona",
    "wof:placetype":"locality"
},
  "geometry": {"coordinates":[-79.83589000000001,22.36919],"type":"Point"}
}