{
  "type": "Feature",
  "properties": {
    "gn:admin1_code":"05",
    "gn:asciiname":"El Ingenito",
    "gn:country_code":"CU",
    "gn:dem":92,
    "gn:feature_class":"P",
    "gn:feature_code":"PPLL",
    "gn:name":"El Ingenito",
    "gn:population":0,
    "gn:timezone":"America/Havana",
    "iso:country":"CU",
    "wof:name":"El Ingenito",
    "wof:placetype":"locality"
},
  "geometry": {"coordinates":[-77.33333,21.06667],"type":"Point"}
}