{
  "type": "Feature",
  "properties": {
    "gn:admin1_code":"13",
    "gn:asciiname":"Vista Hermosa",
    "gn:country_code":"CU",
    "gn:dem":41,
    "gn:feature_class":"P",
    "gn:feature_code":"PPL",
    "gn:name":"Vista Hermosa",
    "gn:population":0,
    "gn:timezone":"America/Havana",
    "iso:country":"CU",
    "name:ceb_x_preferred":[
        "Vista Hermosa"
    ],
    "name:deu_x_preferred":[
        "Vista Hermosa"
    ],
    "name:spa_x_preferred":[
        "Vista Hermosa"
    ],
    "name:swe_x_preferred":[
        "Vista Hermosa"
    ],
    "name:vie_x_preferred":[
        "Vista Hermosa"
    ],
    "wof:name":"Vista Hermosa",
    "wof:placetype":"locality"
},
  "geometry": {"coordinates":[-77.02512,21.22347],"type":"Point"}
}