{
  "type": "Feature",
  "properties": {
    "gn:admin1_code":"05",
    "gn:asciiname":"Valle Grande",
    "gn:country_code":"CU",
    "gn:dem":56,
    "gn:feature_class":"P",
    "gn:feature_code":"PPL",
    "gn:name":"Valle Grande",
    "gn:population":0,
    "gn:timezone":"America/Havana",
    "iso:country":"CU",
    "name:ceb_x_preferred":[
        "Valle Grande"
    ],
    "name:nld_x_preferred":[
        "Valle Grande"
    ],
    "name:spa_x_preferred":[
        "Valle Grande"
    ],
    "name:swe_x_preferred":[
        "Valle Grande"
    ],
    "wof:name":"Valle Grande",
    "wof:placetype":"locality"
},
  "geometry": {"coordinates":[-78.15791,21.33311],"type":"Point"}
}