{
  "type": "Feature",
  "properties": {
    "gn:admin1_code":"09",
    "gn:asciiname":"La Guira",
    "gn:country_code":"CU",
    "gn:dem":157,
    "gn:feature_class":"P",
    "gn:feature_code":"PPL",
    "gn:name":"La G\u00fcira",
    "gn:population":0,
    "gn:timezone":"America/Havana",
    "iso:country":"CU",
    "name:spa_x_preferred":[
        "La G\u00fcira"
    ],
    "wof:name":"La Guira",
    "wof:placetype":"locality"
},
  "geometry": {"coordinates":[-77.30400999999998,19.99256],"type":"Point"}
}