{
  "type": "Feature",
  "properties": {
    "gn:admin1_code":"16",
    "gn:asciiname":"Pepilla",
    "gn:country_code":"CU",
    "gn:dem":38,
    "gn:feature_class":"P",
    "gn:feature_code":"PPL",
    "gn:name":"Pepilla",
    "gn:population":0,
    "gn:timezone":"America/Havana",
    "iso:country":"CU",
    "wof:name":"Pepilla",
    "wof:placetype":"locality"
},
  "geometry": {"coordinates":[-80.21556,22.67889],"type":"Point"}
}