{
  "type": "Feature",
  "properties": {
    "gn:admin1_code":"14",
    "gn:asciiname":"Paso Viejo",
    "gn:country_code":"CU",
    "gn:dem":13,
    "gn:feature_class":"P",
    "gn:feature_code":"PPLL",
    "gn:name":"Paso Viejo",
    "gn:population":0,
    "gn:timezone":"America/Havana",
    "iso:country":"CU",
    "wof:name":"Paso Viejo",
    "wof:placetype":"locality"
},
  "geometry": {"coordinates":[-79.16667,21.65],"type":"Point"}
}