{
  "type": "Feature",
  "properties": {
    "gn:admin1_code":"03",
    "gn:asciiname":"Alambique",
    "gn:country_code":"CU",
    "gn:dem":153,
    "gn:feature_class":"P",
    "gn:feature_code":"PPLL",
    "gn:name":"Alambique",
    "gn:population":0,
    "gn:timezone":"America/Havana",
    "iso:country":"CU",
    "wof:name":"Alambique",
    "wof:placetype":"locality"
},
  "geometry": {"coordinates":[-81.46666999999999,22.83333],"type":"Point"}
}