{
  "type": "Feature",
  "properties": {
    "gn:admin1_code":"15",
    "gn:asciiname":"Purial Arriba",
    "gn:country_code":"CU",
    "gn:dem":469,
    "gn:feature_class":"P",
    "gn:feature_code":"PPL",
    "gn:name":"Purial Arriba",
    "gn:population":0,
    "gn:timezone":"America/Havana",
    "iso:country":"CU",
    "name:spa_x_preferred":[
        "Purial Arriba"
    ],
    "wof:name":"Purial Arriba",
    "wof:placetype":"locality"
},
  "geometry": {"coordinates":[-76.39894,20.13673],"type":"Point"}
}