{
  "type": "Feature",
  "properties": {
    "gn:admin1_code":"MA",
    "gn:asciiname":"Palmarito",
    "gn:country_code":"CU",
    "gn:dem":191,
    "gn:feature_class":"P",
    "gn:feature_code":"PPLL",
    "gn:name":"Palmarito",
    "gn:population":0,
    "gn:timezone":"America/Havana",
    "iso:country":"CU",
    "wof:name":"Palmarito",
    "wof:placetype":"locality"
},
  "geometry": {"coordinates":[-81.71194,22.88556],"type":"Point"}
}