{
  "type": "Feature",
  "properties": {
    "gn:admin1_code":"03",
    "gn:asciiname":"Dolores",
    "gn:country_code":"CU",
    "gn:dem":91,
    "gn:feature_class":"P",
    "gn:feature_code":"PPLL",
    "gn:name":"Dolores",
    "gn:population":0,
    "gn:timezone":"America/Havana",
    "iso:country":"CU",
    "name:spa_x_preferred":[
        "Dolores"
    ],
    "wof:name":"Dolores",
    "wof:placetype":"locality"
},
  "geometry": {"coordinates":[-81.34050000000001,22.78808],"type":"Point"}
}