{
  "type": "Feature",
  "properties": {
    "gn:admin1_code":"13",
    "gn:asciiname":"La Demolida",
    "gn:country_code":"CU",
    "gn:dem":38,
    "gn:feature_class":"P",
    "gn:feature_code":"PPL",
    "gn:name":"La Demolida",
    "gn:population":0,
    "gn:timezone":"America/Havana",
    "iso:country":"CU",
    "name:spa_x_preferred":[
        "La Demolida"
    ],
    "wof:name":"La Demolida",
    "wof:placetype":"locality"
},
  "geometry": {"coordinates":[-76.58020999999999,21.13013],"type":"Point"}
}