{
  "type": "Feature",
  "properties": {
    "gn:admin1_code":"15",
    "gn:asciiname":"El Pajon",
    "gn:country_code":"CU",
    "gn:dem":291,
    "gn:feature_class":"P",
    "gn:feature_code":"PPL",
    "gn:name":"El Paj\u00f3n",
    "gn:population":0,
    "gn:timezone":"America/Havana",
    "iso:country":"CU",
    "name:spa_x_preferred":[
        "El Paj\u00f3n"
    ],
    "wof:name":"El Pajon",
    "wof:placetype":"locality"
},
  "geometry": {"coordinates":[-76.01158000000002,20.03082],"type":"Point"}
}