{
  "type": "Feature",
  "properties": {
    "gn:admin1_code":"AR",
    "gn:asciiname":"Falcon",
    "gn:country_code":"CU",
    "gn:dem":32,
    "gn:feature_class":"P",
    "gn:feature_code":"PPL",
    "gn:name":"Falcon",
    "gn:population":0,
    "gn:timezone":"America/Havana",
    "iso:country":"CU",
    "name:spa_x_preferred":[
        "Falcon"
    ],
    "wof:name":"Falcon",
    "wof:placetype":"locality"
},
  "geometry": {"coordinates":[-82.6152,23.02179],"type":"Point"}
}