{
  "type": "Feature",
  "properties": {
    "gn:admin1_code":"10",
    "gn:asciiname":"Vilorio",
    "gn:country_code":"CU",
    "gn:dem":62,
    "gn:feature_class":"P",
    "gn:feature_code":"PPL",
    "gn:name":"Vilorio",
    "gn:population":0,
    "gn:timezone":"America/Havana",
    "iso:country":"CU",
    "name:und_x_variant":[
        "Bilorio",
        "Vilorio"
    ],
    "wof:name":"Vilorio",
    "wof:placetype":"locality"
},
  "geometry": {"coordinates":[-75.30830999999998,20.08742],"type":"Point"}
}