{
  "type": "Feature",
  "properties": {
    "gn:admin1_code":"13",
    "gn:asciiname":"La Concepcion",
    "gn:country_code":"CU",
    "gn:dem":51,
    "gn:feature_class":"P",
    "gn:feature_code":"PPLL",
    "gn:name":"La Concepci\u00f3n",
    "gn:population":0,
    "gn:timezone":"America/Havana",
    "iso:country":"CU",
    "name:spa_x_preferred":[
        "La Concepci\u00f3n"
    ],
    "wof:name":"La Concepcion",
    "wof:placetype":"locality"
},
  "geometry": {"coordinates":[-77.35467,20.92843],"type":"Point"}
}