{
  "type": "Feature",
  "properties": {
    "gn:admin1_code":"05",
    "gn:asciiname":"Los Coguitos",
    "gn:country_code":"CU",
    "gn:dem":50,
    "gn:feature_class":"P",
    "gn:feature_code":"PPLL",
    "gn:name":"Los Coguitos",
    "gn:population":0,
    "gn:timezone":"America/Havana",
    "iso:country":"CU",
    "name:spa_x_preferred":[
        "Los Coguitos"
    ],
    "name:und_x_variant":[
        "Coguitos"
    ],
    "wof:name":"Los Coguitos",
    "wof:placetype":"locality"
},
  "geometry": {"coordinates":[-77.91554000000002,20.89683],"type":"Point"}
}