{
  "type": "Feature",
  "properties": {
    "gn:admin1_code":"09",
    "gn:asciiname":"Estrada",
    "gn:country_code":"CU",
    "gn:dem":33,
    "gn:feature_class":"P",
    "gn:feature_code":"PPL",
    "gn:name":"Estrada",
    "gn:population":0,
    "gn:timezone":"America/Havana",
    "iso:country":"CU",
    "name:spa_x_preferred":[
        "Estrada"
    ],
    "name:und_x_variant":[
        "Pil\u00f3n del Media",
        "Pil\u00f3n del Medio"
    ],
    "wof:name":"Estrada",
    "wof:placetype":"locality"
},
  "geometry": {"coordinates":[-77.3563,19.90261],"type":"Point"}
}