{
  "type": "Feature",
  "properties": {
    "gn:admin1_code":"03",
    "gn:asciiname":"Reserva",
    "gn:country_code":"CU",
    "gn:dem":48,
    "gn:feature_class":"P",
    "gn:feature_code":"PPLL",
    "gn:name":"Reserva",
    "gn:population":0,
    "gn:timezone":"America/Havana",
    "iso:country":"CU",
    "name:spa_x_preferred":[
        "Reserva"
    ],
    "wof:name":"Reserva",
    "wof:placetype":"locality"
},
  "geometry": {"coordinates":[-80.68047,22.78705],"type":"Point"}
}