{
  "type": "Feature",
  "properties": {
    "gn:admin1_code":"15",
    "gn:asciiname":"La Calabaza",
    "gn:country_code":"CU",
    "gn:dem":279,
    "gn:feature_class":"P",
    "gn:feature_code":"PPL",
    "gn:name":"La Calabaza",
    "gn:population":0,
    "gn:timezone":"America/Havana",
    "iso:country":"CU",
    "name:spa_x_preferred":[
        "La Calabaza"
    ],
    "name:und_x_variant":[
        "El Calabaza"
    ],
    "wof:name":"La Calabaza",
    "wof:placetype":"locality"
},
  "geometry": {"coordinates":[-75.56321,20.35522000000001],"type":"Point"}
}