{
  "type": "Feature",
  "properties": {
    "gn:admin1_code":"14",
    "gn:asciiname":"Mapos",
    "gn:country_code":"CU",
    "gn:dem":13,
    "gn:feature_class":"P",
    "gn:feature_code":"PPL",
    "gn:name":"Mapos",
    "gn:population":0,
    "gn:timezone":"America/Havana",
    "iso:country":"CU",
    "name:und_x_variant":[
        "Amazonas",
        "Mapos"
    ],
    "wof:name":"Mapos",
    "wof:placetype":"locality"
},
  "geometry": {"coordinates":[-79.43805999999999,21.68425],"type":"Point"}
}