{
  "type": "Feature",
  "properties": {
    "gn:admin1_code":"14",
    "gn:asciiname":"El Meso",
    "gn:country_code":"CU",
    "gn:dem":79,
    "gn:feature_class":"P",
    "gn:feature_code":"PPLL",
    "gn:name":"El Meso",
    "gn:population":0,
    "gn:timezone":"America/Havana",
    "iso:country":"CU",
    "name:spa_x_preferred":[
        "El Meso"
    ],
    "wof:name":"El Meso",
    "wof:placetype":"locality"
},
  "geometry": {"coordinates":[-79.17694,21.98278],"type":"Point"}
}