{
  "type": "Feature",
  "properties": {
    "gn:admin1_code":"MA",
    "gn:asciiname":"El Conde",
    "gn:country_code":"CU",
    "gn:dem":116,
    "gn:feature_class":"P",
    "gn:feature_code":"PPLL",
    "gn:name":"El Conde",
    "gn:population":0,
    "gn:timezone":"America/Havana",
    "iso:country":"CU",
    "name:und_x_variant":[
        "Conde",
        "El Conde"
    ],
    "wof:name":"El Conde",
    "wof:placetype":"locality"
},
  "geometry": {"coordinates":[-81.95668000000001,23.08707],"type":"Point"}
}