{
  "type": "Feature",
  "properties": {
    "gn:admin1_code":"MA",
    "gn:asciiname":"San Juan Nepomuceno",
    "gn:country_code":"CU",
    "gn:dem":108,
    "gn:feature_class":"P",
    "gn:feature_code":"PPLL",
    "gn:name":"San Juan Nepomuceno",
    "gn:population":0,
    "gn:timezone":"America/Havana",
    "iso:country":"CU",
    "name:und_x_variant":[
        "San Juan Nepopuceno",
        "San Juan Nepomuceno"
    ],
    "wof:name":"San Juan Nepomuceno",
    "wof:placetype":"locality"
},
  "geometry": {"coordinates":[-82.11667,23.05],"type":"Point"}
}