{
  "type": "Feature",
  "properties": {
    "gn:admin1_code":"12",
    "gn:asciiname":"Charco Prieto",
    "gn:country_code":"CU",
    "gn:dem":149,
    "gn:feature_class":"P",
    "gn:feature_code":"PPL",
    "gn:name":"Charco Prieto",
    "gn:population":0,
    "gn:timezone":"America/Havana",
    "iso:country":"CU",
    "name:und_x_variant":[
        "Charco del Guayabal",
        "Charco Prieto"
    ],
    "wof:name":"Charco Prieto",
    "wof:placetype":"locality"
},
  "geometry": {"coordinates":[-76.13806,20.85152],"type":"Point"}
}