{
  "type": "Feature",
  "properties": {
    "gn:admin1_code":"10",
    "gn:asciiname":"El Loro",
    "gn:country_code":"CU",
    "gn:dem":93,
    "gn:feature_class":"P",
    "gn:feature_code":"PPL",
    "gn:name":"El Loro",
    "gn:population":0,
    "gn:timezone":"America/Havana",
    "iso:country":"CU",
    "name:spa_x_preferred":[
        "El Loro"
    ],
    "wof:name":"El Loro",
    "wof:placetype":"locality"
},
  "geometry": {"coordinates":[-74.81399,20.08936],"type":"Point"}
}