{
  "type": "Feature",
  "properties": {
    "gn:admin1_code":"01",
    "gn:asciiname":"El Moncada",
    "gn:country_code":"CU",
    "gn:dem":139,
    "gn:feature_class":"P",
    "gn:feature_code":"PPL",
    "gn:name":"El Moncada",
    "gn:population":0,
    "gn:timezone":"America/Havana",
    "iso:country":"CU",
    "name:spa_x_preferred":[
        "El Moncada"
    ],
    "wof:name":"El Moncada",
    "wof:placetype":"locality"
},
  "geometry": {"coordinates":[-83.83797,22.5481],"type":"Point"}
}