{
  "type": "Feature",
  "properties": {
    "gn:admin1_code":"16",
    "gn:asciiname":"Boquerones",
    "gn:country_code":"CU",
    "gn:dem":351,
    "gn:feature_class":"P",
    "gn:feature_code":"PPL",
    "gn:name":"Boquerones",
    "gn:population":0,
    "gn:timezone":"America/Havana",
    "iso:country":"CU",
    "name:spa_x_preferred":[
        "Boquerones"
    ],
    "wof:name":"Boquerones",
    "wof:placetype":"locality"
},
  "geometry": {"coordinates":[-80.01137,22.0513],"type":"Point"}
}