{
  "type": "Feature",
  "properties": {
    "gn:admin1_code":"MA",
    "gn:asciiname":"El Mamey",
    "gn:country_code":"CU",
    "gn:dem":52,
    "gn:feature_class":"P",
    "gn:feature_code":"PPL",
    "gn:name":"El Mamey",
    "gn:population":0,
    "gn:timezone":"America/Havana",
    "iso:country":"CU",
    "name:und_x_variant":[
        "Mamey",
        "El Mamey"
    ],
    "wof:name":"El Mamey",
    "wof:placetype":"locality"
},
  "geometry": {"coordinates":[-81.91939000000001,22.8209],"type":"Point"}
}