{
  "type": "Feature",
  "properties": {
    "gn:admin1_code":"15",
    "gn:asciiname":"Amarito",
    "gn:country_code":"CU",
    "gn:dem":384,
    "gn:feature_class":"P",
    "gn:feature_code":"PPLL",
    "gn:name":"Amarito",
    "gn:population":0,
    "gn:timezone":"America/Havana",
    "iso:country":"CU",
    "wof:name":"Amarito",
    "wof:placetype":"locality"
},
  "geometry": {"coordinates":[-76.18333,20.13333],"type":"Point"}
}