{
  "type": "Feature",
  "properties": {
    "gn:admin1_code":"15",
    "gn:asciiname":"Hicotea",
    "gn:country_code":"CU",
    "gn:dem":187,
    "gn:feature_class":"P",
    "gn:feature_code":"PPL",
    "gn:name":"Hicotea",
    "gn:population":0,
    "gn:timezone":"America/Havana",
    "iso:country":"CU",
    "name:spa_x_preferred":[
        "Hicotea"
    ],
    "wof:name":"Hicotea",
    "wof:placetype":"locality"
},
  "geometry": {"coordinates":[-76.02944000000002,20.11748],"type":"Point"}
}