{
  "type": "Feature",
  "properties": {
    "gn:admin1_code":"16",
    "gn:asciiname":"La Sierra",
    "gn:country_code":"CU",
    "gn:dem":175,
    "gn:feature_class":"P",
    "gn:feature_code":"PPLL",
    "gn:name":"La Sierra",
    "gn:population":0,
    "gn:timezone":"America/Havana",
    "iso:country":"CU",
    "name:ast_x_preferred":[
        "La Sierra"
    ],
    "name:ceb_x_preferred":[
        "La Sierra"
    ],
    "name:ita_x_preferred":[
        "La Sierra"
    ],
    "name:spa_x_preferred":[
        "La Sierra"
    ],
    "name:swe_x_preferred":[
        "La Sierra"
    ],
    "name:vie_x_preferred":[
        "La Sierra"
    ],
    "wof:name":"La Sierra",
    "wof:placetype":"locality"
},
  "geometry": {"coordinates":[-79.36667,22.23333],"type":"Point"}
}