{
  "type": "Feature",
  "properties": {
    "gn:admin1_code":"15",
    "gn:asciiname":"Gladys",
    "gn:country_code":"CU",
    "gn:dem":168,
    "gn:feature_class":"P",
    "gn:feature_code":"PPL",
    "gn:name":"Gladys",
    "gn:population":0,
    "gn:timezone":"America/Havana",
    "iso:country":"CU",
    "name:bre_x_preferred":[
        "Gladys"
    ],
    "name:deu_x_preferred":[
        "Gladys"
    ],
    "name:fra_x_preferred":[
        "Gladys"
    ],
    "name:jpn_x_preferred":[
        "\u30b0\u30e9\u30c7\u30a3\u30b9"
    ],
    "name:spa_x_preferred":[
        "Gladys"
    ],
    "wof:name":"Gladys",
    "wof:placetype":"locality"
},
  "geometry": {"coordinates":[-76.16417,20.26414],"type":"Point"}
}