{
  "type": "Feature",
  "properties": {
    "gn:admin1_code":"AR",
    "gn:asciiname":"Los Arroyos",
    "gn:country_code":"CU",
    "gn:dem":99,
    "gn:feature_class":"P",
    "gn:feature_code":"PPLL",
    "gn:name":"Los Arroyos",
    "gn:population":0,
    "gn:timezone":"America/Havana",
    "iso:country":"CU",
    "wof:name":"Los Arroyos",
    "wof:placetype":"locality"
},
  "geometry": {"coordinates":[-83.09999999999999,22.73333],"type":"Point"}
}