{
  "type": "Feature",
  "properties": {
    "gn:admin1_code":"12",
    "gn:asciiname":"La Zarza",
    "gn:country_code":"CU",
    "gn:dem":224,
    "gn:feature_class":"P",
    "gn:feature_code":"PPLL",
    "gn:name":"La Zarza",
    "gn:population":0,
    "gn:timezone":"America/Havana",
    "iso:country":"CU",
    "wof:name":"La Zarza",
    "wof:placetype":"locality"
},
  "geometry": {"coordinates":[-75.31667,20.43333],"type":"Point"}
}