{
  "type": "Feature",
  "properties": {
    "gn:admin1_code":"12",
    "gn:asciiname":"La Zarza",
    "gn:country_code":"CU",
    "gn:dem":224,
    "gn:feature_class":"P",
    "gn:feature_code":"PPLL",
    "gn:name":"La Zarza",
    "gn:population":0,
    "gn:timezone":"America/Havana",
    "iso:country":"CU",
    "name:arg_x_preferred":[
        "La Zarza"
    ],
    "name:cat_x_preferred":[
        "La Zarza"
    ],
    "name:ceb_x_preferred":[
        "La Zarza"
    ],
    "name:ces_x_preferred":[
        "La Zarza"
    ],
    "name:deu_x_preferred":[
        "La Zarza"
    ],
    "name:eus_x_preferred":[
        "La Zarza"
    ],
    "name:fra_x_preferred":[
        "La Zarza"
    ],
    "name:glg_x_preferred":[
        "La Zarza"
    ],
    "name:hun_x_preferred":[
        "La Zarza"
    ],
    "name:ido_x_preferred":[
        "La Zarza"
    ],
    "name:ina_x_preferred":[
        "La Zarza"
    ],
    "name:ita_x_preferred":[
        "La Zarza"
    ],
    "name:msa_x_preferred":[
        "La Zarza"
    ],
    "name:nld_x_preferred":[
        "La Zarza"
    ],
    "name:oci_x_preferred":[
        "La Zarza"
    ],
    "name:pol_x_preferred":[
        "La Zarza"
    ],
    "name:por_x_preferred":[
        "La Zarza"
    ],
    "name:ron_x_preferred":[
        "La Zarza"
    ],
    "name:rus_x_preferred":[
        "\u041b\u0430-\u0421\u0430\u0440\u0441\u0430"
    ],
    "name:sco_x_preferred":[
        "La Zarza"
    ],
    "name:spa_x_preferred":[
        "La Zarza"
    ],
    "name:srp_x_preferred":[
        "\u041b\u0430 \u0417\u0430\u0440\u0437\u0430"
    ],
    "name:swe_x_preferred":[
        "La Zarza"
    ],
    "name:ukr_x_preferred":[
        "\u041b\u0430-\u0421\u0430\u0440\u0441\u0430"
    ],
    "name:uzb_x_preferred":[
        "La Zarza"
    ],
    "name:vie_x_preferred":[
        "La Zarza"
    ],
    "name:war_x_preferred":[
        "La Zarza"
    ],
    "wof:name":"La Zarza",
    "wof:placetype":"locality"
},
  "geometry": {"coordinates":[-75.31667,20.43333],"type":"Point"}
}