{
  "type": "Feature",
  "properties": {
    "gn:admin1_code":"12",
    "gn:asciiname":"La Juba",
    "gn:country_code":"CU",
    "gn:dem":126,
    "gn:feature_class":"P",
    "gn:feature_code":"PPLL",
    "gn:name":"La Juba",
    "gn:population":0,
    "gn:timezone":"America/Havana",
    "iso:country":"CU",
    "wof:name":"La Juba",
    "wof:placetype":"locality"
},
  "geometry": {"coordinates":[-76.08861,20.89278],"type":"Point"}
}