{
  "type": "Feature",
  "properties": {
    "gn:admin1_code":"15",
    "gn:asciiname":"La Socapa",
    "gn:country_code":"CU",
    "gn:dem":18,
    "gn:feature_class":"P",
    "gn:feature_code":"PPL",
    "gn:name":"La Socapa",
    "gn:population":0,
    "gn:timezone":"America/Havana",
    "iso:country":"CU",
    "name:und_x_variant":[
        "Socapa",
        "Socapa Battery",
        "La Socapa"
    ],
    "wof:name":"La Socapa",
    "wof:placetype":"locality"
},
  "geometry": {"coordinates":[-75.87276,19.97201],"type":"Point"}
}