{
  "type": "Feature",
  "properties": {
    "gn:admin1_code":"01",
    "gn:asciiname":"El Guayabo",
    "gn:country_code":"CU",
    "gn:dem":118,
    "gn:feature_class":"P",
    "gn:feature_code":"PPLL",
    "gn:name":"El Guayabo",
    "gn:population":0,
    "gn:timezone":"America/Havana",
    "iso:country":"CU",
    "name:und_x_variant":[
        "Guayabe",
        "El Guayabo"
    ],
    "wof:name":"El Guayabo",
    "wof:placetype":"locality"
},
  "geometry": {"coordinates":[-83.79631999999999,22.42279],"type":"Point"}
}