{
  "type": "Feature",
  "properties": {
    "gn:admin1_code":"03",
    "gn:asciiname":"Manuelita",
    "gn:country_code":"CU",
    "gn:dem":160,
    "gn:feature_class":"P",
    "gn:feature_code":"PPL",
    "gn:name":"Manuelita",
    "gn:population":0,
    "gn:timezone":"America/Havana",
    "iso:country":"CU",
    "name:und_x_variant":[
        "Batey Manuelita",
        "Manuelita Bolondr\u00f3n",
        "Manuelita"
    ],
    "wof:name":"Manuelita",
    "wof:placetype":"locality"
},
  "geometry": {"coordinates":[-81.40714,22.81724],"type":"Point"}
}