{
  "type": "Feature",
  "properties": {
    "gn:admin1_code":"03",
    "gn:asciiname":"La Luisa",
    "gn:country_code":"CU",
    "gn:dem":60,
    "gn:feature_class":"P",
    "gn:feature_code":"PPLL",
    "gn:name":"La Luisa",
    "gn:population":0,
    "gn:timezone":"America/Havana",
    "iso:country":"CU",
    "wof:name":"La Luisa",
    "wof:placetype":"locality"
},
  "geometry": {"coordinates":[-80.92556,22.74444],"type":"Point"}
}