{
  "type": "Feature",
  "properties": {
    "gn:admin1_code":"16",
    "gn:asciiname":"Santa Clarita",
    "gn:country_code":"CU",
    "gn:dem":139,
    "gn:feature_class":"P",
    "gn:feature_code":"PPLL",
    "gn:name":"Santa Clarita",
    "gn:population":0,
    "gn:timezone":"America/Havana",
    "iso:country":"CU",
    "name:ceb_x_preferred":[
        "Santa Clarita"
    ],
    "name:spa_x_preferred":[
        "Santa Clarita"
    ],
    "name:swe_x_preferred":[
        "Santa Clarita"
    ],
    "wof:name":"Santa Clarita",
    "wof:placetype":"locality"
},
  "geometry": {"coordinates":[-79.71355,22.3675],"type":"Point"}
}