{
  "type": "Feature",
  "properties": {
    "gn:admin1_code":"14",
    "gn:asciiname":"Echenique",
    "gn:country_code":"CU",
    "gn:dem":72,
    "gn:feature_class":"P",
    "gn:feature_code":"PPL",
    "gn:name":"Echenique",
    "gn:population":0,
    "gn:timezone":"America/Havana",
    "iso:country":"CU",
    "name:und_x_variant":[
        "Colonia Echenique",
        "Echenique"
    ],
    "wof:name":"Echenique",
    "wof:placetype":"locality"
},
  "geometry": {"coordinates":[-79.43483000000001,22.15863],"type":"Point"}
}