{
  "type": "Feature",
  "properties": {
    "gn:admin1_code":"05",
    "gn:asciiname":"Rincon Hondo",
    "gn:country_code":"CU",
    "gn:dem":55,
    "gn:feature_class":"P",
    "gn:feature_code":"PPLL",
    "gn:name":"Rinc\u00f3n Hondo",
    "gn:population":0,
    "gn:timezone":"America/Havana",
    "iso:country":"CU",
    "name:spa_x_preferred":[
        "Rinc\u00f3n Hondo"
    ],
    "wof:name":"Rincon Hondo",
    "wof:placetype":"locality"
},
  "geometry": {"coordinates":[-78.40236,21.62035],"type":"Point"}
}