{
  "type": "Feature",
  "properties": {
    "gn:admin1_code":"10",
    "gn:asciiname":"El Cerro de Capiro",
    "gn:country_code":"CU",
    "gn:dem":260,
    "gn:feature_class":"P",
    "gn:feature_code":"PPL",
    "gn:name":"El Cerro de Capiro",
    "gn:population":0,
    "gn:timezone":"America/Havana",
    "iso:country":"CU",
    "name:spa_x_preferred":[
        "El Cerro de Capiro"
    ],
    "wof:name":"El Cerro de Capiro",
    "wof:placetype":"locality"
},
  "geometry": {"coordinates":[-74.39490000000001,20.2377],"type":"Point"}
}