{
  "type": "Feature",
  "properties": {
    "gn:admin1_code":"16",
    "gn:asciiname":"El Saltico",
    "gn:country_code":"CU",
    "gn:dem":414,
    "gn:feature_class":"P",
    "gn:feature_code":"PPLL",
    "gn:name":"El Saltico",
    "gn:population":0,
    "gn:timezone":"America/Havana",
    "iso:country":"CU",
    "wof:name":"El Saltico",
    "wof:placetype":"locality"
},
  "geometry": {"coordinates":[-80.05,21.96667],"type":"Point"}
}