{
  "type": "Feature",
  "properties": {
    "gn:admin1_code":"09",
    "gn:asciiname":"El Almirante",
    "gn:country_code":"CU",
    "gn:dem":57,
    "gn:feature_class":"P",
    "gn:feature_code":"PPLL",
    "gn:name":"El Almirante",
    "gn:population":0,
    "gn:timezone":"America/Havana",
    "iso:country":"CU",
    "wof:name":"El Almirante",
    "wof:placetype":"locality"
},
  "geometry": {"coordinates":[-76.65000000000001,20.33333],"type":"Point"}
}