{
  "type": "Feature",
  "properties": {
    "gn:admin1_code":"16",
    "gn:asciiname":"Macagual",
    "gn:country_code":"CU",
    "gn:dem":20,
    "gn:feature_class":"P",
    "gn:feature_code":"PPL",
    "gn:name":"Macagual",
    "gn:population":0,
    "gn:timezone":"America/Havana",
    "iso:country":"CU",
    "name:spa_x_preferred":[
        "Macagual"
    ],
    "wof:name":"Macagual",
    "wof:placetype":"locality"
},
  "geometry": {"coordinates":[-79.69843,22.60358],"type":"Point"}
}