{
  "type": "Feature",
  "properties": {
    "gn:admin1_code":"10",
    "gn:asciiname":"Arroyo Blanco",
    "gn:country_code":"CU",
    "gn:dem":531,
    "gn:feature_class":"P",
    "gn:feature_code":"PPLL",
    "gn:name":"Arroyo Blanco",
    "gn:population":0,
    "gn:timezone":"America/Havana",
    "iso:country":"CU",
    "wof:name":"Arroyo Blanco",
    "wof:placetype":"locality"
},
  "geometry": {"coordinates":[-74.99250000000001,20.23111],"type":"Point"}
}