{
  "type": "Feature",
  "properties": {
    "gn:admin1_code":"01",
    "gn:asciiname":"Punta de la Lena",
    "gn:cc2":"CU",
    "gn:country_code":"CU",
    "gn:dem":44,
    "gn:feature_class":"P",
    "gn:feature_code":"PPLL",
    "gn:name":"Punta de la Le\u00f1a",
    "gn:population":0,
    "gn:timezone":"America/Havana",
    "iso:country":"CU",
    "name:und_x_variant":[
        "La Le\u00f1a",
        "Punta de la Le\u00f1a"
    ],
    "wof:name":"Punta de la Lena",
    "wof:placetype":"locality"
},
  "geometry": {"coordinates":[-83.55,22.53333],"type":"Point"}
}