{
  "type": "Feature",
  "properties": {
    "gn:admin1_code":"09",
    "gn:asciiname":"Cholonguito",
    "gn:cc2":"CU",
    "gn:country_code":"CU",
    "gn:dem":9,
    "gn:feature_class":"P",
    "gn:feature_code":"PPLL",
    "gn:name":"Cholonguito",
    "gn:population":0,
    "gn:timezone":"America/Havana",
    "iso:country":"CU",
    "name:und_x_variant":[
        "Cholongo",
        "Cholonguito"
    ],
    "wof:name":"Cholonguito",
    "wof:placetype":"locality"
},
  "geometry": {"coordinates":[-76.91667,20.63333],"type":"Point"}
}