{
  "type": "Feature",
  "properties": {
    "gn:admin1_code":"01",
    "gn:asciiname":"Blanca Nieves",
    "gn:country_code":"CU",
    "gn:dem":71,
    "gn:feature_class":"P",
    "gn:feature_code":"PPLL",
    "gn:name":"Blanca Nieves",
    "gn:population":0,
    "gn:timezone":"America/Havana",
    "iso:country":"CU",
    "wof:name":"Blanca Nieves",
    "wof:placetype":"locality"
},
  "geometry": {"coordinates":[-83.46666999999999,22.56667],"type":"Point"}
}