{
  "type": "Feature",
  "properties": {
    "gn:admin1_code":"14",
    "gn:asciiname":"Caguazal",
    "gn:country_code":"CU",
    "gn:dem":31,
    "gn:feature_class":"P",
    "gn:feature_code":"PPL",
    "gn:name":"Caguazal",
    "gn:population":0,
    "gn:timezone":"America/Havana",
    "iso:country":"CU",
    "name:spa_x_preferred":[
        "Caguazal"
    ],
    "name:und_x_variant":[
        "El Caguasal"
    ],
    "wof:name":"Caguazal",
    "wof:placetype":"locality"
},
  "geometry": {"coordinates":[-79.14931999999997,21.7396],"type":"Point"}
}