{
  "type": "Feature",
  "properties": {
    "gn:admin1_code":"07",
    "gn:asciiname":"Jiquimal",
    "gn:country_code":"CU",
    "gn:dem":10,
    "gn:feature_class":"P",
    "gn:feature_code":"PPL",
    "gn:name":"Jiquimal",
    "gn:population":0,
    "gn:timezone":"America/Havana",
    "iso:country":"CU",
    "name:und_x_variant":[
        "Viquinal",
        "Jiquimal"
    ],
    "wof:name":"Jiquimal",
    "wof:placetype":"locality"
},
  "geometry": {"coordinates":[-78.65449,21.7198],"type":"Point"}
}