{
  "type": "Feature",
  "properties": {
    "gn:admin1_code":"03",
    "gn:asciiname":"El Polvorin",
    "gn:country_code":"CU",
    "gn:dem":8,
    "gn:feature_class":"P",
    "gn:feature_code":"PPLL",
    "gn:name":"El Polvor\u00edn",
    "gn:population":0,
    "gn:timezone":"America/Havana",
    "iso:country":"CU",
    "name:spa_x_preferred":[
        "El Polvorin"
    ],
    "name:spa_x_variant":[
        "El Polvor\u00edn"
    ],
    "wof:name":"El Polvorin",
    "wof:placetype":"locality"
},
  "geometry": {"coordinates":[-81.02101,22.0669],"type":"Point"}
}