{
  "type": "Feature",
  "properties": {
    "gn:admin1_code":"02",
    "gn:asciiname":"Cuatro Caminos de Falcon",
    "gn:cc2":"CU",
    "gn:country_code":"CU",
    "gn:dem":38,
    "gn:feature_class":"P",
    "gn:feature_code":"PPL",
    "gn:name":"Cuatro Caminos de Falc\u00f3n",
    "gn:population":0,
    "gn:timezone":"America/Havana",
    "iso:country":"CU",
    "name:und_x_variant":[
        "Falcon",
        "Cuatro Caminos de Falc\u00f3n"
    ],
    "wof:name":"Cuatro Caminos de Falcon",
    "wof:placetype":"locality"
},
  "geometry": {"coordinates":[-82.48333000000002,23.05],"type":"Point"}
}