{
  "type": "Feature",
  "properties": {
    "gn:admin1_code":"03",
    "gn:asciiname":"Santo Tomas",
    "gn:country_code":"CU",
    "gn:dem":6,
    "gn:feature_class":"P",
    "gn:feature_code":"PPLL",
    "gn:name":"Santo Tom\u00e1s",
    "gn:population":0,
    "gn:timezone":"America/Havana",
    "iso:country":"CU",
    "name:ceb_x_preferred":[
        "Santo Tomas"
    ],
    "name:deu_x_preferred":[
        "Santo Tomas"
    ],
    "name:ilo_x_preferred":[
        "Santo Tomas"
    ],
    "name:lit_x_preferred":[
        "Santo Tomas"
    ],
    "name:nld_x_preferred":[
        "Santo Tomas"
    ],
    "name:sco_x_preferred":[
        "Santo Tomas"
    ],
    "name:srp_x_preferred":[
        "\u0421\u0430\u043d\u0442\u043e \u0422\u043e\u043c\u0430\u0441"
    ],
    "name:swe_x_preferred":[
        "Santo Tomas"
    ],
    "name:und_x_variant":[
        "Asiento Santo Thom\u00e3s",
        "Santo Tom\u00e1s"
    ],
    "name:war_x_preferred":[
        "Santo Tomas"
    ],
    "wof:name":"Santo Tomas",
    "wof:placetype":"locality"
},
  "geometry": {"coordinates":[-81.44370000000001,22.40527],"type":"Point"}
}