{
  "type": "Feature",
  "properties": {
    "gn:admin1_code":"05",
    "gn:asciiname":"Seoane",
    "gn:country_code":"CU",
    "gn:dem":41,
    "gn:feature_class":"P",
    "gn:feature_code":"PPLL",
    "gn:name":"Seoane",
    "gn:population":0,
    "gn:timezone":"America/Havana",
    "iso:country":"CU",
    "name:spa_x_preferred":[
        "Seoane"
    ],
    "wof:name":"Seoane",
    "wof:placetype":"locality"
},
  "geometry": {"coordinates":[-78.14206999999998,21.77892],"type":"Point"}
}