{
  "type": "Feature",
  "properties": {
    "gn:admin1_code":"08",
    "gn:asciiname":"Caimito",
    "gn:country_code":"CU",
    "gn:dem":29,
    "gn:feature_class":"P",
    "gn:feature_code":"PPLL",
    "gn:name":"Caimito",
    "gn:population":0,
    "gn:timezone":"America/Havana",
    "iso:country":"CU",
    "name:ceb_x_preferred":[
        "Caimito"
    ],
    "name:ita_x_preferred":[
        "Caimito"
    ],
    "name:nld_x_preferred":[
        "Caimito"
    ],
    "name:que_x_preferred":[
        "Caimito"
    ],
    "name:spa_x_preferred":[
        "Caimito"
    ],
    "name:swe_x_preferred":[
        "Caimito"
    ],
    "wof:name":"Caimito",
    "wof:placetype":"locality"
},
  "geometry": {"coordinates":[-80.81667,22.46667],"type":"Point"}
}