{
  "type": "Feature",
  "properties": {
    "gn:admin1_code":"15",
    "gn:asciiname":"El Cupey",
    "gn:country_code":"CU",
    "gn:dem":137,
    "gn:feature_class":"P",
    "gn:feature_code":"PPL",
    "gn:name":"El Cupey",
    "gn:population":0,
    "gn:timezone":"America/Havana",
    "iso:country":"CU",
    "wof:name":"El Cupey",
    "wof:placetype":"locality"
},
  "geometry": {"coordinates":[-75.60139000000002,19.92833],"type":"Point"}
}