{
  "type": "Feature",
  "properties": {
    "gn:admin1_code":"16",
    "gn:asciiname":"Clavellinas",
    "gn:country_code":"CU",
    "gn:dem":84,
    "gn:feature_class":"P",
    "gn:feature_code":"PPLL",
    "gn:name":"Clavellinas",
    "gn:population":0,
    "gn:timezone":"America/Havana",
    "iso:country":"CU",
    "wof:name":"Clavellinas",
    "wof:placetype":"locality"
},
  "geometry": {"coordinates":[-79.92749999999999,22.59972],"type":"Point"}
}