{
  "type": "Feature",
  "properties": {
    "gn:admin1_code":"15",
    "gn:asciiname":"Ferrando",
    "gn:country_code":"CU",
    "gn:dem":120,
    "gn:feature_class":"P",
    "gn:feature_code":"PPL",
    "gn:name":"Ferrando",
    "gn:population":0,
    "gn:timezone":"America/Havana",
    "iso:country":"CU",
    "name:spa_x_preferred":[
        "Ferrando"
    ],
    "wof:name":"Ferrando",
    "wof:placetype":"locality"
},
  "geometry": {"coordinates":[-76.00232,20.53959],"type":"Point"}
}