{
  "type": "Feature",
  "properties": {
    "gn:admin1_code":"14",
    "gn:asciiname":"San Jose del Lago",
    "gn:country_code":"CU",
    "gn:dem":62,
    "gn:feature_class":"P",
    "gn:feature_code":"PPLL",
    "gn:name":"San Jos\u00e9 del Lago",
    "gn:population":0,
    "gn:timezone":"America/Havana",
    "iso:country":"CU",
    "wof:name":"San Jose del Lago",
    "wof:placetype":"locality"
},
  "geometry": {"coordinates":[-79.07167,22.22861],"type":"Point"}
}