{
  "type": "Feature",
  "properties": {
    "gn:admin1_code":"01",
    "gn:asciiname":"El Pilar",
    "gn:country_code":"CU",
    "gn:dem":32,
    "gn:feature_class":"P",
    "gn:feature_code":"PPLL",
    "gn:name":"El Pilar",
    "gn:population":0,
    "gn:timezone":"America/Havana",
    "iso:country":"CU",
    "name:deu_x_preferred":[
        "El Pilar"
    ],
    "name:epo_x_preferred":[
        "El Pilar"
    ],
    "name:ita_x_preferred":[
        "El Pilar"
    ],
    "name:lit_x_preferred":[
        "El Pilaras"
    ],
    "name:pol_x_preferred":[
        "El Pilar"
    ],
    "name:spa_x_preferred":[
        "El Pilar"
    ],
    "name:ukr_x_preferred":[
        "\u0415\u043b\u044c-\u041f\u0456\u043b\u0430\u0440"
    ],
    "wof:name":"El Pilar",
    "wof:placetype":"locality"
},
  "geometry": {"coordinates":[-83.45,22.46667],"type":"Point"}
}