{
  "type": "Feature",
  "properties": {
    "gn:admin1_code":"04",
    "gn:asciiname":"Reparto Columbia",
    "gn:cc2":"CU",
    "gn:country_code":"CU",
    "gn:dem":15,
    "gn:feature_class":"P",
    "gn:feature_code":"PPLL",
    "gn:name":"Reparto Columbia",
    "gn:population":0,
    "gn:timezone":"America/Havana",
    "iso:country":"CU",
    "name:und_x_variant":[
        "Columbia",
        "Reparto Columbia"
    ],
    "wof:name":"Reparto Columbia",
    "wof:placetype":"locality"
},
  "geometry": {"coordinates":[-82.73222,21.83556],"type":"Point"}
}