{
  "type": "Feature",
  "properties": {
    "gn:admin1_code":"13",
    "gn:asciiname":"La Cana",
    "gn:country_code":"CU",
    "gn:dem":35,
    "gn:feature_class":"P",
    "gn:feature_code":"PPLL",
    "gn:name":"La Cana",
    "gn:population":0,
    "gn:timezone":"America/Havana",
    "iso:country":"CU",
    "wof:name":"La Cana",
    "wof:placetype":"locality"
},
  "geometry": {"coordinates":[-76.83333,21.15],"type":"Point"}
}