{
  "type": "Feature",
  "properties": {
    "gn:admin1_code":"10",
    "gn:asciiname":"El Purial",
    "gn:country_code":"CU",
    "gn:dem":163,
    "gn:feature_class":"P",
    "gn:feature_code":"PPL",
    "gn:name":"El Purial",
    "gn:population":0,
    "gn:timezone":"America/Havana",
    "iso:country":"CU",
    "name:spa_x_preferred":[
        "El Purial"
    ],
    "wof:name":"El Purial",
    "wof:placetype":"locality"
},
  "geometry": {"coordinates":[-75.44954,20.22615],"type":"Point"}
}