{
  "type": "Feature",
  "properties": {
    "gn:admin1_code":"12",
    "gn:asciiname":"Realengo Juan Pablo",
    "gn:country_code":"CU",
    "gn:dem":47,
    "gn:feature_class":"P",
    "gn:feature_code":"PPLL",
    "gn:name":"Realengo Juan Pablo",
    "gn:population":0,
    "gn:timezone":"America/Havana",
    "iso:country":"CU",
    "wof:name":"Realengo Juan Pablo",
    "wof:placetype":"locality"
},
  "geometry": {"coordinates":[-75.84971999999998,21.04694],"type":"Point"}
}