{
  "type": "Feature",
  "properties": {
    "gn:admin1_code":"14",
    "gn:asciiname":"Cancio",
    "gn:country_code":"CU",
    "gn:dem":145,
    "gn:feature_class":"P",
    "gn:feature_code":"PPLL",
    "gn:name":"Cancio",
    "gn:population":0,
    "gn:timezone":"America/Havana",
    "iso:country":"CU",
    "wof:name":"Cancio",
    "wof:placetype":"locality"
},
  "geometry": {"coordinates":[-79.51666999999998,21.93333],"type":"Point"}
}