{
  "type": "Feature",
  "properties": {
    "gn:admin1_code":"05",
    "gn:asciiname":"Porvenir",
    "gn:country_code":"CU",
    "gn:dem":38,
    "gn:feature_class":"P",
    "gn:feature_code":"PPLL",
    "gn:name":"Porvenir",
    "gn:population":0,
    "gn:timezone":"America/Havana",
    "iso:country":"CU",
    "name:ceb_x_preferred":[
        "Porvenir"
    ],
    "name:deu_x_preferred":[
        "Porvenir"
    ],
    "name:hye_x_preferred":[
        "\u054a\u0578\u0580\u057e\u0565\u0576\u056b\u0580"
    ],
    "name:ita_x_preferred":[
        "Porvenir"
    ],
    "name:nld_x_preferred":[
        "Porvenir"
    ],
    "name:por_x_preferred":[
        "Porvenir"
    ],
    "name:rus_x_preferred":[
        "\u041f\u043e\u0440\u0432\u0435\u043d\u0438\u0440"
    ],
    "name:spa_x_preferred":[
        "Porvenir"
    ],
    "name:swe_x_preferred":[
        "Porvenir"
    ],
    "wof:name":"Porvenir",
    "wof:placetype":"locality"
},
  "geometry": {"coordinates":[-78.43583000000002,21.64194],"type":"Point"}
}