{
  "type": "Feature",
  "properties": {
    "gn:admin1_code":"16",
    "gn:asciiname":"Manga Larga",
    "gn:cc2":"CU",
    "gn:country_code":"CU",
    "gn:dem":45,
    "gn:feature_class":"P",
    "gn:feature_code":"PPL",
    "gn:name":"Manga Larga",
    "gn:population":0,
    "gn:timezone":"America/Havana",
    "iso:country":"CU",
    "name:und_x_variant":[
        "Poblado Manga Larga",
        "Manga Larga"
    ],
    "wof:name":"Manga Larga",
    "wof:placetype":"locality"
},
  "geometry": {"coordinates":[-80.30806,22.70417],"type":"Point"}
}