{
  "type": "Feature",
  "properties": {
    "gn:admin1_code":"10",
    "gn:asciiname":"La Quijada",
    "gn:country_code":"CU",
    "gn:dem":510,
    "gn:feature_class":"P",
    "gn:feature_code":"PPL",
    "gn:name":"La Quijada",
    "gn:population":0,
    "gn:timezone":"America/Havana",
    "iso:country":"CU",
    "name:und_x_variant":[
        "Quijada",
        "La Quijada"
    ],
    "wof:name":"La Quijada",
    "wof:placetype":"locality"
},
  "geometry": {"coordinates":[-75.33581,20.34532],"type":"Point"}
}