{
  "type": "Feature",
  "properties": {
    "gn:admin1_code":"AR",
    "gn:asciiname":"Perfecto",
    "gn:country_code":"CU",
    "gn:dem":32,
    "gn:feature_class":"P",
    "gn:feature_code":"PPLL",
    "gn:name":"Perfecto",
    "gn:population":0,
    "gn:timezone":"America/Havana",
    "iso:country":"CU",
    "name:spa_x_preferred":[
        "Perfecto"
    ],
    "wof:name":"Perfecto",
    "wof:placetype":"locality"
},
  "geometry": {"coordinates":[-82.60005,23.0089],"type":"Point"}
}