{
  "type": "Feature",
  "properties": {
    "gn:admin1_code":"07",
    "gn:asciiname":"Miraflores",
    "gn:country_code":"CU",
    "gn:dem":20,
    "gn:feature_class":"P",
    "gn:feature_code":"PPL",
    "gn:name":"Miraflores",
    "gn:population":0,
    "gn:timezone":"America/Havana",
    "iso:country":"CU",
    "name:cat_x_preferred":[
        "Miraflores"
    ],
    "name:ceb_x_preferred":[
        "Miraflores"
    ],
    "name:deu_x_preferred":[
        "Miraflores"
    ],
    "name:fra_x_preferred":[
        "Miraflores"
    ],
    "name:glg_x_preferred":[
        "Miraflores"
    ],
    "name:ita_x_preferred":[
        "Miraflores"
    ],
    "name:nld_x_preferred":[
        "Miraflores"
    ],
    "name:pol_x_preferred":[
        "Miraflores"
    ],
    "name:por_x_preferred":[
        "Miraflores"
    ],
    "name:spa_x_preferred":[
        "Miraflores"
    ],
    "name:spa_x_variant":[
        "Miraflores Viejo"
    ],
    "name:srp_x_preferred":[
        "\u041c\u0438\u0440\u0430\u0444\u043b\u043e\u0440\u0435\u0441"
    ],
    "name:swe_x_preferred":[
        "Miraflores"
    ],
    "wof:name":"Miraflores",
    "wof:placetype":"locality"
},
  "geometry": {"coordinates":[-78.27084000000001,21.98311],"type":"Point"}
}