{
  "type": "Feature",
  "properties": {
    "gn:admin1_code":"10",
    "gn:asciiname":"Cayo Hueso",
    "gn:country_code":"CU",
    "gn:dem":511,
    "gn:feature_class":"P",
    "gn:feature_code":"PPL",
    "gn:name":"Cayo Hueso",
    "gn:population":0,
    "gn:timezone":"America/Havana",
    "iso:country":"CU",
    "name:spa_x_preferred":[
        "Cayo Hueso"
    ],
    "wof:name":"Cayo Hueso",
    "wof:placetype":"locality"
},
  "geometry": {"coordinates":[-74.86778000000002,20.27306],"type":"Point"}
}