{
  "type": "Feature",
  "properties": {
    "gn:admin1_code":"12",
    "gn:asciiname":"Jagueyes",
    "gn:country_code":"CU",
    "gn:dem":64,
    "gn:feature_class":"P",
    "gn:feature_code":"PPLL",
    "gn:name":"Jag\u00fceyes",
    "gn:population":0,
    "gn:timezone":"America/Havana",
    "iso:country":"CU",
    "wof:name":"Jagueyes",
    "wof:placetype":"locality"
},
  "geometry": {"coordinates":[-75.95,20.63333],"type":"Point"}
}