{
  "type": "Feature",
  "properties": {
    "gn:admin1_code":"13",
    "gn:asciiname":"La Irma",
    "gn:country_code":"CU",
    "gn:dem":84,
    "gn:feature_class":"P",
    "gn:feature_code":"PPL",
    "gn:name":"La Irma",
    "gn:population":0,
    "gn:timezone":"America/Havana",
    "iso:country":"CU",
    "name:spa_x_preferred":[
        "La Irma"
    ],
    "wof:name":"La Irma",
    "wof:placetype":"locality"
},
  "geometry": {"coordinates":[-77.06156,21.06964],"type":"Point"}
}