{
  "type": "Feature",
  "properties": {
    "gn:admin1_code":"05",
    "gn:asciiname":"El Cafetal",
    "gn:country_code":"CU",
    "gn:dem":16,
    "gn:feature_class":"P",
    "gn:feature_code":"PPL",
    "gn:name":"El Cafetal",
    "gn:population":0,
    "gn:timezone":"America/Havana",
    "iso:country":"CU",
    "name:spa_x_preferred":[
        "El Cafetal"
    ],
    "wof:name":"El Cafetal",
    "wof:placetype":"locality"
},
  "geometry": {"coordinates":[-77.29414,21.38672],"type":"Point"}
}