{
  "type": "Feature",
  "properties": {
    "gn:admin1_code":"07",
    "gn:asciiname":"Galan Tres",
    "gn:country_code":"CU",
    "gn:dem":8,
    "gn:feature_class":"P",
    "gn:feature_code":"PPLL",
    "gn:name":"Gal\u00e1n Tres",
    "gn:population":0,
    "gn:timezone":"America/Havana",
    "iso:country":"CU",
    "name:spa_x_preferred":[
        "Gal\u00e1n Tres"
    ],
    "wof:name":"Galan Tres",
    "wof:placetype":"locality"
},
  "geometry": {"coordinates":[-78.43178,22.12787],"type":"Point"}
}