{
  "type": "Feature",
  "properties": {
    "gn:gn_country":"CU",
    "gn:gn_fcode":"PPL",
    "gn:gn_pop":13832,
    "gn:population":13832,
    "iso:country":"CU",
    "name:ast_x_preferred":[
        "Bataban\u00f3"
    ],
    "name:cat_x_preferred":[
        "Bataban\u00f3"
    ],
    "name:ceb_x_preferred":[
        "Bataban\u00f3"
    ],
    "name:cym_x_preferred":[
        "Bataban\u00f3"
    ],
    "name:deu_x_preferred":[
        "Bataban\u00f3"
    ],
    "name:eng_x_preferred":[
        "Bataban\u00f3"
    ],
    "name:fas_x_preferred":[
        "\u0628\u0627\u062a\u0627\u0628\u0627\u0646\u0648"
    ],
    "name:fra_x_preferred":[
        "Bataban\u00f3"
    ],
    "name:gle_x_preferred":[
        "Bataban\u00f3"
    ],
    "name:hat_x_preferred":[
        "Surgidero de Batabano"
    ],
    "name:ita_x_preferred":[
        "Bataban\u00f3"
    ],
    "name:jpn_x_preferred":[
        "\u30d0\u30bf\u30d0\u30ce"
    ],
    "name:kat_x_preferred":[
        "\u10d1\u10d0\u10e2\u10d0\u10d1\u10d0\u10dc\u10dd"
    ],
    "name:nld_x_preferred":[
        "Bataban\u00f3"
    ],
    "name:por_x_preferred":[
        "Bataban\u00f3"
    ],
    "name:rus_x_preferred":[
        "\u0411\u0430\u0442\u0430\u0431\u0430\u043d\u043e"
    ],
    "name:sco_x_preferred":[
        "Bataban\u00f3"
    ],
    "name:spa_x_preferred":[
        "Bataban\u00f3"
    ],
    "name:swe_x_preferred":[
        "Surgidero de Bataban\u00f3"
    ],
    "name:swe_x_variant":[
        "Bataban\u00f3"
    ],
    "name:uzb_x_preferred":[
        "Batabano"
    ],
    "name:vie_x_preferred":[
        "Bataban\u00f3"
    ],
    "name:zho_x_preferred":[
        "\u5df4\u5854\u74e6\u8afe"
    ],
    "qs_pg:aaroncc":"CU",
    "qs_pg:gn_country":"CU",
    "qs_pg:gn_fcode":"PPL",
    "qs_pg:gn_pop":13832,
    "qs_pg:name":"Bataban\u00f3",
    "qs_pg:photos_9r":0,
    "qs_pg:photos_sr":0,
    "qs_pg:pop_sr":6,
    "qs_pg:qs_pg_placetype":"locality",
    "wof:name":"Bataban\u00f3",
    "wof:placetype":"locality",
    "wof:population":13832
},
  "geometry": {"coordinates":[-82.28806,22.71639],"type":"Point"}
}