{
  "type": "Feature",
  "properties": {
    "gn:admin1_code":"13",
    "gn:asciiname":"Santa Teresa Dos",
    "gn:country_code":"CU",
    "gn:dem":15,
    "gn:feature_class":"P",
    "gn:feature_code":"PPL",
    "gn:name":"Santa Teresa Dos",
    "gn:population":0,
    "gn:timezone":"America/Havana",
    "iso:country":"CU",
    "name:spa_x_preferred":[
        "Santa Teresa Dos"
    ],
    "name:und_x_variant":[
        "Santa Teresa"
    ],
    "wof:name":"Santa Teresa Dos",
    "wof:placetype":"locality"
},
  "geometry": {"coordinates":[-76.79127,21.2391],"type":"Point"}
}