{
  "type": "Feature",
  "properties": {
    "gn:admin1_code":"16",
    "gn:asciiname":"Pinon",
    "gn:country_code":"CU",
    "gn:dem":4,
    "gn:feature_class":"P",
    "gn:feature_code":"PPLL",
    "gn:name":"Pi\u00f1\u00f3n",
    "gn:population":0,
    "gn:timezone":"America/Havana",
    "iso:country":"CU",
    "name:spa_x_preferred":[
        "Pi\u00f1\u00f3n"
    ],
    "name:und_x_variant":[
        "El Pi\u00f1\u00f3n"
    ],
    "wof:name":"Pinon",
    "wof:placetype":"locality"
},
  "geometry": {"coordinates":[-79.90949999999999,22.80855],"type":"Point"}
}