{
  "type": "Feature",
  "properties": {
    "gn:admin1_code":"16",
    "gn:asciiname":"Caiguaje",
    "gn:country_code":"CU",
    "gn:dem":7,
    "gn:feature_class":"P",
    "gn:feature_code":"PPLL",
    "gn:name":"Caiguaje",
    "gn:population":0,
    "gn:timezone":"America/Havana",
    "iso:country":"CU",
    "name:spa_x_preferred":[
        "Caiguaje"
    ],
    "name:und_x_variant":[
        "Caiguage"
    ],
    "wof:name":"Caiguaje",
    "wof:placetype":"locality"
},
  "geometry": {"coordinates":[-79.56667,22.55],"type":"Point"}
}