{
  "type": "Feature",
  "properties": {
    "gn:admin1_code":"14",
    "gn:asciiname":"Portada Prieta",
    "gn:country_code":"CU",
    "gn:dem":73,
    "gn:feature_class":"P",
    "gn:feature_code":"PPL",
    "gn:name":"Portada Prieta",
    "gn:population":0,
    "gn:timezone":"America/Havana",
    "iso:country":"CU",
    "name:und_x_variant":[
        "Puerta Prieta"
    ],
    "wof:name":"Portada Prieta",
    "wof:placetype":"locality"
},
  "geometry": {"coordinates":[-79.33771,22.03276],"type":"Point"}
}