{
  "type": "Feature",
  "properties": {
    "gn:admin1_code":"12",
    "gn:asciiname":"El Cedrito",
    "gn:country_code":"CU",
    "gn:dem":39,
    "gn:feature_class":"P",
    "gn:feature_code":"PPL",
    "gn:name":"El Cedrito",
    "gn:population":0,
    "gn:timezone":"America/Havana",
    "iso:country":"CU",
    "name:spa_x_preferred":[
        "El Cedrito"
    ],
    "wof:name":"El Cedrito",
    "wof:placetype":"locality"
},
  "geometry": {"coordinates":[-75.2116,20.62011],"type":"Point"}
}