{
  "type": "Feature",
  "properties": {
    "gn:admin1_code":"16",
    "gn:asciiname":"Machado",
    "gn:country_code":"CU",
    "gn:dem":23,
    "gn:feature_class":"P",
    "gn:feature_code":"PPLL",
    "gn:name":"Machado",
    "gn:population":0,
    "gn:timezone":"America/Havana",
    "iso:country":"CU",
    "name:epo_x_preferred":[
        "Machado"
    ],
    "name:rus_x_preferred":[
        "\u041c\u0430\u0448\u0430\u0434\u0443"
    ],
    "name:ukr_x_preferred":[
        "\u041c\u0430\u0448\u0430\u0434\u0443"
    ],
    "wof:name":"Machado",
    "wof:placetype":"locality"
},
  "geometry": {"coordinates":[-80.33333,22.88333],"type":"Point"}
}