{
  "type": "Feature",
  "properties": {
    "gn:admin1_code":"09",
    "gn:asciiname":"Piloncito",
    "gn:country_code":"CU",
    "gn:dem":161,
    "gn:feature_class":"P",
    "gn:feature_code":"PPL",
    "gn:name":"Piloncito",
    "gn:population":0,
    "gn:timezone":"America/Havana",
    "iso:country":"CU",
    "name:spa_x_preferred":[
        "Piloncito"
    ],
    "wof:name":"Piloncito",
    "wof:placetype":"locality"
},
  "geometry": {"coordinates":[-77.44571999999999,19.98382],"type":"Point"}
}