{
  "type": "Feature",
  "properties": {
    "gn:admin1_code":"08",
    "gn:asciiname":"Hortensia",
    "gn:country_code":"CU",
    "gn:dem":76,
    "gn:feature_class":"P",
    "gn:feature_code":"PPLL",
    "gn:name":"Hortensia",
    "gn:population":0,
    "gn:timezone":"America/Havana",
    "iso:country":"CU",
    "wof:name":"Hortensia",
    "wof:placetype":"locality"
},
  "geometry": {"coordinates":[-80.36667,22.31667],"type":"Point"}
}