{
  "type": "Feature",
  "properties": {
    "iso:country":"CU",
    "name:bar_x_preferred":[
        "Belvedere"
    ],
    "name:bul_x_preferred":[
        "\u0411\u0435\u043b\u0432\u0435\u0434\u0435\u0440\u0435"
    ],
    "name:cat_x_preferred":[
        "Belvedere"
    ],
    "name:ceb_x_preferred":[
        "Belvedere"
    ],
    "name:deu_x_preferred":[
        "Belvedere"
    ],
    "name:fra_x_preferred":[
        "Belvedere"
    ],
    "name:heb_x_preferred":[
        "\u05d1\u05dc\u05d5\u05d5\u05d3\u05d9\u05e8"
    ],
    "name:hun_x_preferred":[
        "Belvedere"
    ],
    "name:ind_x_preferred":[
        "Belvedere"
    ],
    "name:ita_x_preferred":[
        "Belvedere"
    ],
    "name:kor_x_preferred":[
        "\ubca8\ubca0\ub370\ub808"
    ],
    "name:lat_x_preferred":[
        "Belvederium"
    ],
    "name:lit_x_preferred":[
        "Belvederis"
    ],
    "name:nld_x_preferred":[
        "Belved\u00e8re"
    ],
    "name:pol_x_preferred":[
        "Belvedere"
    ],
    "name:por_x_preferred":[
        "Belvedere"
    ],
    "name:ron_x_preferred":[
        "Belvedere"
    ],
    "name:rus_x_preferred":[
        "\u0411\u0435\u043b\u044c\u0432\u0435\u0434\u0435\u0440"
    ],
    "name:slk_x_preferred":[
        "Belvedere"
    ],
    "name:spa_x_preferred":[
        "Belvedere"
    ],
    "name:srp_x_preferred":[
        "\u0411\u0435\u043b\u0432\u0435\u0434\u0438\u0440"
    ],
    "name:swe_x_preferred":[
        "Belvedere"
    ],
    "name:tgl_x_preferred":[
        "Belvedere"
    ],
    "name:ukr_x_preferred":[
        "\u0411\u0435\u043b\u044c\u0432\u0435\u0434\u0435\u0440"
    ],
    "name:unk_x_variant":[
        "Belvedere"
    ],
    "name:vol_x_preferred":[
        "Belvedere"
    ],
    "qs:gn_adm0_cc":"CU",
    "qs:gn_fcode":"PPLX",
    "qs:gn_local":3553478,
    "qs:gn_namadm1":"02",
    "qs:gn_name":"Belvedere",
    "qs:local_max":6362,
    "qs:local_sum":28186,
    "qs:localhoods":23,
    "qs:name":"Belvedere",
    "qs:name_adm0":"Cuba",
    "qs:name_adm1":"Ciudad de la Habana",
    "qs:name_local":"La Habana",
    "qs:photo_max":20,
    "qs:photo_sum":73,
    "qs:placetype":"Suburb",
    "qs:quad_count":12,
    "qs:woe_adm0":23424793,
    "qs:woe_adm1":2345107,
    "qs:woe_adm2":0,
    "qs:woe_lau":0,
    "qs:woe_local":63817,
    "qs:woe_ver":"7.10.0",
    "wof:lang":[
        "spa"
    ],
    "wof:name":"Belvedere",
    "wof:placetype":"neighbourhood"
},
  "geometry": {"coordinates":[-82.341599,23.14754],"type":"Point"}
}