{
  "type": "Feature",
  "properties": {
    "iso:country":"CU",
    "name:spa_x_preferred":[
        "Belvedere"
    ],
    "name:unk_x_variant":[
        "Belvedere"
    ],
    "qs:gn_adm0_cc":"CU",
    "qs:gn_fcode":"PPLX",
    "qs:gn_local":3553478,
    "qs:gn_namadm1":"02",
    "qs:gn_name":"Belvedere",
    "qs:local_max":6362,
    "qs:local_sum":28186,
    "qs:localhoods":23,
    "qs:name":"Belvedere",
    "qs:name_adm0":"Cuba",
    "qs:name_adm1":"Ciudad de la Habana",
    "qs:name_local":"La Habana",
    "qs:photo_max":20,
    "qs:photo_sum":73,
    "qs:placetype":"Suburb",
    "qs:quad_count":12,
    "qs:woe_adm0":23424793,
    "qs:woe_adm1":2345107,
    "qs:woe_adm2":0,
    "qs:woe_lau":0,
    "qs:woe_local":63817,
    "qs:woe_ver":"7.10.0",
    "wof:lang":[
        "spa"
    ],
    "wof:name":"Belvedere",
    "wof:placetype":"neighbourhood"
},
  "geometry": {"coordinates":[-82.341599,23.14754],"type":"Point"}
}