{
  "type": "Feature",
  "properties": {
    "gn:admin1_code":"03",
    "gn:asciiname":"Garcia",
    "gn:cc2":"CU",
    "gn:country_code":"CU",
    "gn:dem":26,
    "gn:feature_class":"P",
    "gn:feature_code":"PPL",
    "gn:name":"Garc\u00eda",
    "gn:population":0,
    "gn:timezone":"America/Havana",
    "iso:country":"CU",
    "name:und_x_variant":[
        "Batey Garcia",
        "Garc\u00eda"
    ],
    "wof:name":"Garcia",
    "wof:placetype":"locality"
},
  "geometry": {"coordinates":[-81.12306,22.82833],"type":"Point"}
}