{
  "type": "Feature",
  "properties": {
    "gn:admin1_code":"16",
    "gn:asciiname":"Vegas",
    "gn:cc2":"CU",
    "gn:country_code":"CU",
    "gn:dem":195,
    "gn:feature_class":"P",
    "gn:feature_code":"PPLL",
    "gn:name":"Vegas",
    "gn:population":0,
    "gn:timezone":"America/Havana",
    "iso:country":"CU",
    "name:und_x_variant":[
        "Vegaso",
        "Vegas"
    ],
    "wof:name":"Vegas",
    "wof:placetype":"locality"
},
  "geometry": {"coordinates":[-79.93333,22.16667],"type":"Point"}
}