{
  "type": "Feature",
  "properties": {
    "gn:admin1_code":"12",
    "gn:asciiname":"Punto Fijo",
    "gn:country_code":"CU",
    "gn:dem":107,
    "gn:feature_class":"P",
    "gn:feature_code":"PPL",
    "gn:name":"Punto Fijo",
    "gn:population":0,
    "gn:timezone":"America/Havana",
    "iso:country":"CU",
    "name:spa_x_preferred":[
        "Punto Fijo"
    ],
    "wof:name":"Punto Fijo",
    "wof:placetype":"locality"
},
  "geometry": {"coordinates":[-76.43415,20.92101],"type":"Point"}
}