{
  "type": "Feature",
  "properties": {
    "gn:admin1_code":"12",
    "gn:asciiname":"Mensura Dos",
    "gn:country_code":"CU",
    "gn:dem":651,
    "gn:feature_class":"P",
    "gn:feature_code":"PPL",
    "gn:name":"Mensura Dos",
    "gn:population":0,
    "gn:timezone":"America/Havana",
    "iso:country":"CU",
    "name:spa_x_preferred":[
        "Mensura Dos"
    ],
    "wof:name":"Mensura Dos",
    "wof:placetype":"locality"
},
  "geometry": {"coordinates":[-75.78957,20.48717000000001],"type":"Point"}
}