{
  "type": "Feature",
  "properties": {
    "gn:admin1_code":"09",
    "gn:asciiname":"Las Puercas",
    "gn:country_code":"CU",
    "gn:dem":91,
    "gn:feature_class":"P",
    "gn:feature_code":"PPL",
    "gn:name":"Las Puercas",
    "gn:population":0,
    "gn:timezone":"America/Havana",
    "iso:country":"CU",
    "name:spa_x_preferred":[
        "Las Puercas"
    ],
    "wof:name":"Las Puercas",
    "wof:placetype":"locality"
},
  "geometry": {"coordinates":[-77.4071,19.88348],"type":"Point"}
}