{
  "type": "Feature",
  "properties": {
    "gn:admin1_code":"12",
    "gn:asciiname":"Sao Arriba",
    "gn:country_code":"CU",
    "gn:dem":107,
    "gn:feature_class":"P",
    "gn:feature_code":"PPL",
    "gn:name":"Sao Arriba",
    "gn:population":0,
    "gn:timezone":"America/Havana",
    "iso:country":"CU",
    "name:spa_x_preferred":[
        "Sao Arriba"
    ],
    "wof:name":"Sao Arriba",
    "wof:placetype":"locality"
},
  "geometry": {"coordinates":[-76.19055999999998,20.92783],"type":"Point"}
}