{
  "type": "Feature",
  "properties": {
    "gn:admin1_code":"13",
    "gn:asciiname":"Berrocal",
    "gn:country_code":"CU",
    "gn:dem":56,
    "gn:feature_class":"P",
    "gn:feature_code":"PPL",
    "gn:name":"Berrocal",
    "gn:population":0,
    "gn:timezone":"America/Havana",
    "iso:country":"CU",
    "name:ara_x_preferred":[
        "\u0628\u064a\u0631\u0648\u0643\u0627\u0644"
    ],
    "name:cat_x_preferred":[
        "Berrocal"
    ],
    "name:epo_x_preferred":[
        "Berrocal"
    ],
    "name:eus_x_preferred":[
        "Berrocal"
    ],
    "name:fra_x_preferred":[
        "Berrocal"
    ],
    "name:hat_x_preferred":[
        "Berrocal"
    ],
    "name:hun_x_preferred":[
        "Berrocal"
    ],
    "name:hye_x_preferred":[
        "\u0532\u0565\u057c\u0578\u056f\u0561\u056c"
    ],
    "name:hyw_x_preferred":[
        "\u054a\u0565\u057c\u0578\u056f\u0561\u056c"
    ],
    "name:ita_x_preferred":[
        "Berrocal"
    ],
    "name:kaz_x_preferred":[
        "\u0411\u0435\u0440\u0440\u043e\u043a\u0430\u043b\u044c"
    ],
    "name:msa_x_preferred":[
        "Berrocal"
    ],
    "name:nld_x_preferred":[
        "Berrocal"
    ],
    "name:oci_x_preferred":[
        "Berrocal"
    ],
    "name:pol_x_preferred":[
        "Berrocal"
    ],
    "name:por_x_preferred":[
        "Berrocal"
    ],
    "name:rus_x_preferred":[
        "\u0411\u0435\u0440\u0440\u043e\u043a\u0430\u043b\u044c"
    ],
    "name:spa_x_preferred":[
        "Berrocal"
    ],
    "name:tur_x_preferred":[
        "Berrocal"
    ],
    "name:ukr_x_preferred":[
        "\u0411\u0435\u0440\u0440\u043e\u043a\u0430\u043b\u044c"
    ],
    "name:und_x_variant":[
        "Berracal",
        "Berrocal"
    ],
    "name:uzb_x_preferred":[
        "Berrocal"
    ],
    "name:vie_x_preferred":[
        "Berrocal"
    ],
    "name:war_x_preferred":[
        "Berrocal"
    ],
    "name:zho_x_preferred":[
        "\u8d1d\u7f57\u5361\u5c14"
    ],
    "wof:name":"Berrocal",
    "wof:placetype":"locality"
},
  "geometry": {"coordinates":[-77.35338,20.94642],"type":"Point"}
}