{
  "type": "Feature",
  "properties": {
    "gn:admin1_code":"13",
    "gn:asciiname":"Berrocal",
    "gn:country_code":"CU",
    "gn:dem":56,
    "gn:feature_class":"P",
    "gn:feature_code":"PPL",
    "gn:name":"Berrocal",
    "gn:population":0,
    "gn:timezone":"America/Havana",
    "iso:country":"CU",
    "name:und_x_variant":[
        "Berracal",
        "Berrocal"
    ],
    "wof:name":"Berrocal",
    "wof:placetype":"locality"
},
  "geometry": {"coordinates":[-77.35338,20.94642],"type":"Point"}
}