{
  "type": "Feature",
  "properties": {
    "gn:admin1_code":"09",
    "gn:asciiname":"La America",
    "gn:country_code":"CU",
    "gn:dem":66,
    "gn:feature_class":"P",
    "gn:feature_code":"PPLL",
    "gn:name":"La Am\u00e9rica",
    "gn:population":0,
    "gn:timezone":"America/Havana",
    "iso:country":"CU",
    "name:lad_x_preferred":[
        "La Amerika"
    ],
    "name:spa_x_preferred":[
        "La Am\u00e9rica"
    ],
    "wof:name":"La America",
    "wof:placetype":"locality"
},
  "geometry": {"coordinates":[-76.33783000000003,20.46567000000001],"type":"Point"}
}