{
  "type": "Feature",
  "properties": {
    "gn:admin1_code":"09",
    "gn:asciiname":"Palo Quemado",
    "gn:country_code":"CU",
    "gn:dem":48,
    "gn:feature_class":"P",
    "gn:feature_code":"PPL",
    "gn:name":"Palo Quemado",
    "gn:population":0,
    "gn:timezone":"America/Havana",
    "iso:country":"CU",
    "name:spa_x_preferred":[
        "Palo Quemado"
    ],
    "wof:name":"Palo Quemado",
    "wof:placetype":"locality"
},
  "geometry": {"coordinates":[-77.23397,20.10513],"type":"Point"}
}