{
  "type": "Feature",
  "properties": {
    "gn:admin1_code":"AR",
    "gn:asciiname":"El Valle",
    "gn:country_code":"CU",
    "gn:dem":49,
    "gn:feature_class":"P",
    "gn:feature_code":"PPL",
    "gn:name":"El Valle",
    "gn:population":0,
    "gn:timezone":"America/Havana",
    "iso:country":"CU",
    "name:spa_x_preferred":[
        "El Valle"
    ],
    "wof:name":"El Valle",
    "wof:placetype":"locality"
},
  "geometry": {"coordinates":[-82.48333000000002,22.88333],"type":"Point"}
}