{
  "type": "Feature",
  "properties": {
    "gn:admin1_code":"12",
    "gn:asciiname":"El Cocal",
    "gn:country_code":"CU",
    "gn:dem":32,
    "gn:feature_class":"P",
    "gn:feature_code":"PPL",
    "gn:name":"El Cocal",
    "gn:population":0,
    "gn:timezone":"America/Havana",
    "iso:country":"CU",
    "name:ita_x_preferred":[
        "El Cocal"
    ],
    "name:spa_x_preferred":[
        "El Cocal"
    ],
    "name:und_x_variant":[
        "Cocal",
        "El Cocal"
    ],
    "name:zho_x_preferred":[
        "\u57c3\u5c14\u79d1\u5361\u5c14"
    ],
    "wof:name":"El Cocal",
    "wof:placetype":"locality"
},
  "geometry": {"coordinates":[-75.69804000000001,20.63468],"type":"Point"}
}