{
  "type": "Feature",
  "properties": {
    "gn:admin1_code":"08",
    "gn:asciiname":"Cuba Libre",
    "gn:country_code":"CU",
    "gn:dem":45,
    "gn:feature_class":"P",
    "gn:feature_code":"PPL",
    "gn:name":"Cuba Libre",
    "gn:population":0,
    "gn:timezone":"America/Havana",
    "iso:country":"CU",
    "name:spa_x_preferred":[
        "Cuba Libre"
    ],
    "wof:name":"Cuba Libre",
    "wof:placetype":"locality"
},
  "geometry": {"coordinates":[-80.42049,22.20814],"type":"Point"}
}