{
  "type": "Feature",
  "properties": {
    "gn:admin1_code":"09",
    "gn:asciiname":"San Pablo de Yao Arriba",
    "gn:country_code":"CU",
    "gn:dem":175,
    "gn:feature_class":"P",
    "gn:feature_code":"PPL",
    "gn:name":"San Pablo de Yao Arriba",
    "gn:population":0,
    "gn:timezone":"America/Havana",
    "iso:country":"CU",
    "name:und_x_variant":[
        "San Pablo de Yao",
        "San Pablo de Yao Arriba"
    ],
    "wof:name":"San Pablo de Yao Arriba",
    "wof:placetype":"locality"
},
  "geometry": {"coordinates":[-76.70069000000002,20.14834],"type":"Point"}
}