{
  "type": "Feature",
  "properties": {
    "gn:admin1_code":"14",
    "gn:asciiname":"Narcisa",
    "gn:country_code":"CU",
    "gn:dem":16,
    "gn:feature_class":"P",
    "gn:feature_code":"PPL",
    "gn:name":"Narcisa",
    "gn:population":0,
    "gn:timezone":"America/Havana",
    "iso:country":"CU",
    "name:deu_x_preferred":[
        "Narcisa"
    ],
    "name:slv_x_preferred":[
        "Narcisa"
    ],
    "name:spa_x_preferred":[
        "Narcisa"
    ],
    "name:spa_x_variant":[
        "Obdulio Morales"
    ],
    "wof:name":"Narcisa",
    "wof:placetype":"locality"
},
  "geometry": {"coordinates":[-79.24675999999999,22.34189],"type":"Point"}
}