{
  "type": "Feature",
  "properties": {
    "gn:admin1_code":"16",
    "gn:asciiname":"El Pelao",
    "gn:country_code":"CU",
    "gn:dem":153,
    "gn:feature_class":"P",
    "gn:feature_code":"PPLL",
    "gn:name":"El Pelao",
    "gn:population":0,
    "gn:timezone":"America/Havana",
    "iso:country":"CU",
    "wof:name":"El Pelao",
    "wof:placetype":"locality"
},
  "geometry": {"coordinates":[-79.93333,22.28333],"type":"Point"}
}