{
  "type": "Feature",
  "properties": {
    "gn:admin1_code":"MA",
    "gn:asciiname":"Guatao",
    "gn:country_code":"CU",
    "gn:dem":66,
    "gn:feature_class":"P",
    "gn:feature_code":"PPL",
    "gn:name":"Guatao",
    "gn:population":0,
    "gn:timezone":"America/Havana",
    "iso:country":"CU",
    "name:spa_x_preferred":[
        "Guatao"
    ],
    "wof:name":"Guatao",
    "wof:placetype":"locality"
},
  "geometry": {"coordinates":[-82.49684999999999,23.00207],"type":"Point"}
}