{
  "type": "Feature",
  "properties": {
    "gn:admin1_code":"14",
    "gn:asciiname":"Palmera",
    "gn:country_code":"CU",
    "gn:dem":32,
    "gn:feature_class":"P",
    "gn:feature_code":"PPLL",
    "gn:name":"Palmera",
    "gn:population":0,
    "gn:timezone":"America/Havana",
    "iso:country":"CU",
    "name:arg_x_preferred":[
        "Palmera"
    ],
    "name:cat_x_preferred":[
        "Palmera"
    ],
    "name:ceb_x_preferred":[
        "Palmera"
    ],
    "name:eus_x_preferred":[
        "Palmera"
    ],
    "name:fra_x_preferred":[
        "Palmera"
    ],
    "name:hun_x_preferred":[
        "Palmera"
    ],
    "name:ita_x_preferred":[
        "Palmera"
    ],
    "name:msa_x_preferred":[
        "Palmera"
    ],
    "name:oci_x_preferred":[
        "Palmera"
    ],
    "name:pol_x_preferred":[
        "Palmera"
    ],
    "name:por_x_preferred":[
        "Palmera"
    ],
    "name:spa_x_preferred":[
        "Palmera"
    ],
    "name:sqi_x_preferred":[
        "Palmera"
    ],
    "name:swe_x_preferred":[
        "Palmera"
    ],
    "name:war_x_preferred":[
        "Palmera"
    ],
    "name:zho_x_preferred":[
        "\u5e15\u5c14\u6885\u62c9"
    ],
    "wof:name":"Palmera",
    "wof:placetype":"locality"
},
  "geometry": {"coordinates":[-79.1825,21.75222],"type":"Point"}
}