{
  "type": "Feature",
  "properties": {
    "gn:admin1_code":"16",
    "gn:asciiname":"Libertad o Muerte",
    "gn:country_code":"CU",
    "gn:dem":138,
    "gn:feature_class":"P",
    "gn:feature_code":"PPL",
    "gn:name":"Libertad o Muerte",
    "gn:population":0,
    "gn:timezone":"America/Havana",
    "iso:country":"CU",
    "name:spa_x_preferred":[
        "Libertad o Muerte"
    ],
    "wof:name":"Libertad o Muerte",
    "wof:placetype":"locality"
},
  "geometry": {"coordinates":[-79.83094,22.18605],"type":"Point"}
}