{
  "type": "Feature",
  "properties": {
    "gn:admin1_code":"13",
    "gn:asciiname":"Cincuenta y Dos",
    "gn:country_code":"CU",
    "gn:dem":41,
    "gn:feature_class":"P",
    "gn:feature_code":"PPL",
    "gn:name":"Cincuenta y Dos",
    "gn:population":0,
    "gn:timezone":"America/Havana",
    "iso:country":"CU",
    "name:spa_x_preferred":[
        "Cincuenta y Dos"
    ],
    "wof:name":"Cincuenta y Dos",
    "wof:placetype":"locality"
},
  "geometry": {"coordinates":[-77.19416,20.87899],"type":"Point"}
}