{
  "type": "Feature",
  "properties": {
    "gn:admin1_code":"08",
    "gn:asciiname":"La Macagua",
    "gn:country_code":"CU",
    "gn:dem":114,
    "gn:feature_class":"P",
    "gn:feature_code":"PPL",
    "gn:name":"La Macagua",
    "gn:population":0,
    "gn:timezone":"America/Havana",
    "iso:country":"CU",
    "name:spa_x_preferred":[
        "La Macagua"
    ],
    "wof:name":"La Macagua",
    "wof:placetype":"locality"
},
  "geometry": {"coordinates":[-80.09166999999999,22.15417],"type":"Point"}
}