{
  "type": "Feature",
  "properties": {
    "gn:admin1_code":"03",
    "gn:asciiname":"La Lima",
    "gn:cc2":"CU",
    "gn:country_code":"CU",
    "gn:dem":35,
    "gn:feature_class":"P",
    "gn:feature_code":"PPL",
    "gn:name":"La Lima",
    "gn:population":0,
    "gn:timezone":"America/Havana",
    "iso:country":"CU",
    "name:bul_x_preferred":[
        "\u041b\u0438\u043c\u0430"
    ],
    "name:fra_x_preferred":[
        "La Lima"
    ],
    "name:ita_x_preferred":[
        "La Lima"
    ],
    "name:lit_x_preferred":[
        "La Lima"
    ],
    "name:nld_x_preferred":[
        "La Lima"
    ],
    "name:pol_x_preferred":[
        "La Lima"
    ],
    "name:por_x_preferred":[
        "La Lima"
    ],
    "name:rus_x_preferred":[
        "\u041b\u0430-\u041b\u0438\u043c\u0430"
    ],
    "name:spa_x_preferred":[
        "La Lima"
    ],
    "name:und_x_variant":[
        "Batey La Lima",
        "La Lima"
    ],
    "name:zho_x_preferred":[
        "\u62c9\u5229\u99ac"
    ],
    "wof:name":"La Lima",
    "wof:placetype":"locality"
},
  "geometry": {"coordinates":[-80.98333000000002,22.86667000000001],"type":"Point"}
}