{
  "type": "Feature",
  "properties": {
    "gn:admin1_code":"03",
    "gn:asciiname":"La Lima",
    "gn:cc2":"CU",
    "gn:country_code":"CU",
    "gn:dem":35,
    "gn:feature_class":"P",
    "gn:feature_code":"PPL",
    "gn:name":"La Lima",
    "gn:population":0,
    "gn:timezone":"America/Havana",
    "iso:country":"CU",
    "name:und_x_variant":[
        "Batey La Lima",
        "La Lima"
    ],
    "wof:name":"La Lima",
    "wof:placetype":"locality"
},
  "geometry": {"coordinates":[-80.98333000000002,22.86667000000001],"type":"Point"}
}