{
  "type": "Feature",
  "properties": {
    "gn:admin1_code":"05",
    "gn:asciiname":"Las Casimbas",
    "gn:country_code":"CU",
    "gn:dem":100,
    "gn:feature_class":"P",
    "gn:feature_code":"PPLL",
    "gn:name":"Las Casimbas",
    "gn:population":0,
    "gn:timezone":"America/Havana",
    "iso:country":"CU",
    "name:und_x_variant":[
        "Casimba",
        "Las Casimbas"
    ],
    "wof:name":"Las Casimbas",
    "wof:placetype":"locality"
},
  "geometry": {"coordinates":[-77.8242,20.94183],"type":"Point"}
}