{
  "type": "Feature",
  "properties": {
    "iso:country":"CU",
    "name:ceb_x_preferred":[
        "Municipio de Fomento"
    ],
    "name:cym_x_preferred":[
        "Fomento"
    ],
    "name:deu_x_preferred":[
        "Fomento"
    ],
    "name:eng_x_preferred":[
        "Fomento"
    ],
    "name:fra_x_preferred":[
        "Fomento"
    ],
    "name:gle_x_preferred":[
        "Fomento"
    ],
    "name:hat_x_preferred":[
        "Fomento"
    ],
    "name:ita_x_preferred":[
        "Fomento"
    ],
    "name:jpn_x_preferred":[
        "\u30d5\u30a9\u30e1\u30f3\u30c8"
    ],
    "name:kat_x_preferred":[
        "\u10e4\u10dd\u10db\u10d4\u10dc\u10e2\u10dd"
    ],
    "name:nld_x_preferred":[
        "Fomento"
    ],
    "name:por_x_preferred":[
        "Fomento"
    ],
    "name:sco_x_preferred":[
        "Fomento"
    ],
    "name:spa_x_preferred":[
        "Fomento"
    ],
    "name:swe_x_preferred":[
        "Municipio de Fomento"
    ],
    "name:uzb_x_preferred":[
        "Fomento"
    ],
    "name:vie_x_preferred":[
        "Fomento"
    ],
    "name:zho_x_preferred":[
        "\u798f\u9580\u6258"
    ],
    "qs:gn_country":"CU",
    "qs:gn_fcode":"PPL",
    "qs:gn_pop":19991,
    "qs:name":"Fomento",
    "qs:name_adm0":"Cuba",
    "qs:name_adm1":"Sancti Spiritus",
    "qs:photos":18,
    "qs:photos_1k":4,
    "qs:photos_9k":1,
    "qs:photos_9r":1,
    "qs:photos_all":18,
    "qs:photos_sr":1,
    "qs:placetype":"Town",
    "qs:pop_sr":"6",
    "qs:woe_adm0":23424793,
    "wd:wordcount":181,
    "wof:name":"Fomento",
    "wof:placetype":"locality",
    "wof:population":19991
},
  "geometry": {"coordinates":[-79.72167,22.10389],"type":"Point"}
}