{
  "type": "Feature",
  "properties": {
    "gn:admin1_code":"09",
    "gn:asciiname":"Corojito",
    "gn:country_code":"CU",
    "gn:dem":104,
    "gn:feature_class":"P",
    "gn:feature_code":"PPL",
    "gn:name":"Corojito",
    "gn:population":0,
    "gn:timezone":"America/Havana",
    "iso:country":"CU",
    "name:spa_x_preferred":[
        "Corojito"
    ],
    "wof:name":"Corojito",
    "wof:placetype":"locality"
},
  "geometry": {"coordinates":[-76.74139,20.22279],"type":"Point"}
}