{
  "type": "Feature",
  "properties": {
    "gn:admin1_code":"13",
    "gn:asciiname":"Arroyo del Estero",
    "gn:country_code":"CU",
    "gn:dem":9,
    "gn:feature_class":"P",
    "gn:feature_code":"PPLL",
    "gn:name":"Arroyo del Estero",
    "gn:population":0,
    "gn:timezone":"America/Havana",
    "iso:country":"CU",
    "wof:name":"Arroyo del Estero",
    "wof:placetype":"locality"
},
  "geometry": {"coordinates":[-77.68333,20.71667],"type":"Point"}
}