{
  "type": "Feature",
  "properties": {
    "gn:admin1_code":"12",
    "gn:asciiname":"Unas",
    "gn:country_code":"CU",
    "gn:dem":93,
    "gn:feature_class":"P",
    "gn:feature_code":"PPLL",
    "gn:name":"U\u00f1as",
    "gn:population":0,
    "gn:timezone":"America/Havana",
    "iso:country":"CU",
    "wof:name":"Unas",
    "wof:placetype":"locality"
},
  "geometry": {"coordinates":[-76.34111,21.015],"type":"Point"}
}