{
  "type": "Feature",
  "properties": {
    "gn:admin1_code":"14",
    "gn:asciiname":"San Jose de Las Canas",
    "gn:country_code":"CU",
    "gn:dem":29,
    "gn:feature_class":"P",
    "gn:feature_code":"PPLL",
    "gn:name":"San Jos\u00e9 de Las Ca\u00f1as",
    "gn:population":0,
    "gn:timezone":"America/Havana",
    "iso:country":"CU",
    "wof:name":"San Jose de Las Canas",
    "wof:placetype":"locality"
},
  "geometry": {"coordinates":[-79.88333,21.78333],"type":"Point"}
}