{
  "type": "Feature",
  "properties": {
    "gn:admin1_code":"15",
    "gn:asciiname":"Union",
    "gn:country_code":"CU",
    "gn:dem":537,
    "gn:feature_class":"P",
    "gn:feature_code":"PPL",
    "gn:name":"Uni\u00f3n",
    "gn:population":0,
    "gn:timezone":"America/Havana",
    "iso:country":"CU",
    "wof:name":"Union",
    "wof:placetype":"locality"
},
  "geometry": {"coordinates":[-76.36667,20.21667],"type":"Point"}
}