{
  "type": "Feature",
  "properties": {
    "gn:admin1_code":"16",
    "gn:asciiname":"Potrero de Monteagudo",
    "gn:country_code":"CU",
    "gn:dem":18,
    "gn:feature_class":"P",
    "gn:feature_code":"PPLL",
    "gn:name":"Potrero de Monteagudo",
    "gn:population":0,
    "gn:timezone":"America/Havana",
    "iso:country":"CU",
    "wof:name":"Potrero de Monteagudo",
    "wof:placetype":"locality"
},
  "geometry": {"coordinates":[-79.46666999999999,22.45],"type":"Point"}
}