{
  "type": "Feature",
  "properties": {
    "gn:admin1_code":"12",
    "gn:asciiname":"Cayo Grande",
    "gn:country_code":"CU",
    "gn:dem":93,
    "gn:feature_class":"P",
    "gn:feature_code":"PPL",
    "gn:name":"Cayo Grande",
    "gn:population":0,
    "gn:timezone":"America/Havana",
    "iso:country":"CU",
    "name:spa_x_preferred":[
        "Cayo Grande"
    ],
    "wof:name":"Cayo Grande",
    "wof:placetype":"locality"
},
  "geometry": {"coordinates":[-74.77254000000001,20.59103],"type":"Point"}
}