{
  "type": "Feature",
  "properties": {
    "gn:admin1_code":"09",
    "gn:asciiname":"Cabo Cruz",
    "gn:country_code":"CU",
    "gn:dem":8,
    "gn:feature_class":"P",
    "gn:feature_code":"PPL",
    "gn:name":"Cabo Cruz",
    "gn:population":0,
    "gn:timezone":"America/Havana",
    "iso:country":"CU",
    "name:ceb_x_preferred":[
        "Cabo Cruz"
    ],
    "name:fra_x_preferred":[
        "Cap Cruz"
    ],
    "name:kat_x_preferred":[
        "\u10d9\u10e0\u10e3\u10e1\u10d8\u10e1 \u10d9\u10dd\u10dc\u10ea\u10ee\u10d8"
    ],
    "name:por_x_preferred":[
        "Cabo Cruz"
    ],
    "name:spa_x_preferred":[
        "Cabo Cruz"
    ],
    "wof:name":"Cabo Cruz",
    "wof:placetype":"locality"
},
  "geometry": {"coordinates":[-77.72677,19.84116],"type":"Point"}
}