{
  "type": "Feature",
  "properties": {
    "gn:admin1_code":"03",
    "gn:asciiname":"China",
    "gn:cc2":"CU",
    "gn:country_code":"CU",
    "gn:dem":47,
    "gn:feature_class":"P",
    "gn:feature_code":"PPL",
    "gn:name":"China",
    "gn:population":0,
    "gn:timezone":"America/Havana",
    "iso:country":"CU",
    "name:und_x_variant":[
        "Central China",
        "China"
    ],
    "wof:name":"China",
    "wof:placetype":"locality"
},
  "geometry": {"coordinates":[-81.66778000000002,22.96139],"type":"Point"}
}