{
  "type": "Feature",
  "properties": {
    "gn:admin1_code":"16",
    "gn:asciiname":"Colmenar",
    "gn:country_code":"CU",
    "gn:dem":117,
    "gn:feature_class":"P",
    "gn:feature_code":"PPLL",
    "gn:name":"Colmenar",
    "gn:population":0,
    "gn:timezone":"America/Havana",
    "iso:country":"CU",
    "name:spa_x_preferred":[
        "Colmenar"
    ],
    "wof:name":"Colmenar",
    "wof:placetype":"locality"
},
  "geometry": {"coordinates":[-79.68964,22.40981],"type":"Point"}
}