{
  "type": "Feature",
  "properties": {
    "gn:admin1_code":"07",
    "gn:asciiname":"Pablo Pelegrin Silva",
    "gn:country_code":"CU",
    "gn:dem":17,
    "gn:feature_class":"P",
    "gn:feature_code":"PPLL",
    "gn:name":"Pablo Pelegr\u00edn Silva",
    "gn:population":0,
    "gn:timezone":"America/Havana",
    "iso:country":"CU",
    "name:und_x_variant":[
        "Pablo Pelagrin Silva",
        "Pablo Pelegr\u00edn Silva"
    ],
    "wof:name":"Pablo Pelegrin Silva",
    "wof:placetype":"locality"
},
  "geometry": {"coordinates":[-78.24162,21.9814],"type":"Point"}
}