{
  "type": "Feature",
  "properties": {
    "gn:admin1_code":"12",
    "gn:asciiname":"Las Cuarenta",
    "gn:country_code":"CU",
    "gn:dem":77,
    "gn:feature_class":"P",
    "gn:feature_code":"PPL",
    "gn:name":"Las Cuarenta",
    "gn:population":0,
    "gn:timezone":"America/Havana",
    "iso:country":"CU",
    "name:spa_x_preferred":[
        "Las Cuarenta"
    ],
    "wof:name":"Las Cuarenta",
    "wof:placetype":"locality"
},
  "geometry": {"coordinates":[-76.16681,20.55593],"type":"Point"}
}