{
  "type": "Feature",
  "properties": {
    "gn:admin1_code":"AR",
    "gn:asciiname":"Cuartel Coronel Hevia",
    "gn:country_code":"CU",
    "gn:dem":2,
    "gn:feature_class":"P",
    "gn:feature_code":"PPLL",
    "gn:name":"Cuartel Coronel Hevia",
    "gn:population":0,
    "gn:timezone":"America/Havana",
    "iso:country":"CU",
    "wof:name":"Cuartel Coronel Hevia",
    "wof:placetype":"locality"
},
  "geometry": {"coordinates":[-82.63333,22.73333],"type":"Point"}
}