{
  "type": "Feature",
  "properties": {
    "gn:admin1_code":"10",
    "gn:asciiname":"Bejuquera",
    "gn:country_code":"CU",
    "gn:dem":145,
    "gn:feature_class":"P",
    "gn:feature_code":"PPL",
    "gn:name":"Bejuquera",
    "gn:population":0,
    "gn:timezone":"America/Havana",
    "iso:country":"CU",
    "name:spa_x_preferred":[
        "Bejuquera"
    ],
    "wof:name":"Bejuquera",
    "wof:placetype":"locality"
},
  "geometry": {"coordinates":[-75.40746,19.98892],"type":"Point"}
}