{
  "type": "Feature",
  "properties": {
    "gn:admin1_code":"MA",
    "gn:asciiname":"Melena Dos",
    "gn:country_code":"CU",
    "gn:dem":23,
    "gn:feature_class":"P",
    "gn:feature_code":"PPL",
    "gn:name":"Melena Dos",
    "gn:population":0,
    "gn:timezone":"America/Havana",
    "iso:country":"CU",
    "name:spa_x_preferred":[
        "Melena Dos"
    ],
    "wof:name":"Melena Dos",
    "wof:placetype":"locality"
},
  "geometry": {"coordinates":[-82.13602,22.76615],"type":"Point"}
}