{
  "type": "Feature",
  "properties": {
    "gn:admin1_code":"12",
    "gn:asciiname":"La Ceja",
    "gn:country_code":"CU",
    "gn:dem":93,
    "gn:feature_class":"P",
    "gn:feature_code":"PPL",
    "gn:name":"La Ceja",
    "gn:population":0,
    "gn:timezone":"America/Havana",
    "iso:country":"CU",
    "name:ceb_x_preferred":[
        "La Ceja"
    ],
    "name:spa_x_preferred":[
        "La Ceja"
    ],
    "name:swe_x_preferred":[
        "La Ceja"
    ],
    "wof:name":"La Ceja",
    "wof:placetype":"locality"
},
  "geometry": {"coordinates":[-76.08279,20.96585],"type":"Point"}
}