{
  "type": "Feature",
  "properties": {
    "gn:admin1_code":"14",
    "gn:asciiname":"La Esperanza",
    "gn:country_code":"CU",
    "gn:dem":88,
    "gn:feature_class":"P",
    "gn:feature_code":"PPLL",
    "gn:name":"La Esperanza",
    "gn:population":0,
    "gn:timezone":"America/Havana",
    "iso:country":"CU",
    "wof:name":"La Esperanza",
    "wof:placetype":"locality"
},
  "geometry": {"coordinates":[-79.93333,21.85],"type":"Point"}
}