{
  "type": "Feature",
  "properties": {
    "iso:country":"CU",
    "name:eng_x_preferred":[
        "Arcos de Canas\u00ed"
    ],
    "name:nld_x_preferred":[
        "Arcos de Canas\u00ed"
    ],
    "name:sco_x_preferred":[
        "Arcos de Canas\u00ed"
    ],
    "name:spa_x_preferred":[
        "Arcos de Canas\u00ed"
    ],
    "name:unk_x_variant":[
        "Canas\u00ed"
    ],
    "qs:gn_country":"CU",
    "qs:gn_fcode":"PPL",
    "qs:gn_pop":0,
    "qs:name":"Arcos de Canas\u00ed",
    "qs:name_adm0":"Cuba",
    "qs:name_adm1":"La Habana",
    "qs:photos":136,
    "qs:photos_1k":28,
    "qs:photos_9k":1,
    "qs:photos_9r":3,
    "qs:photos_all":136,
    "qs:photos_sr":3,
    "qs:placetype":"Town",
    "qs:pop_sr":"4",
    "qs:woe_adm0":23424793,
    "wd:wordcount":162,
    "wof:name":"Arcos de Canas\u00ed",
    "wof:placetype":"locality"
},
  "geometry": {"coordinates":[-81.78139,23.1125],"type":"Point"}
}