{
  "type": "Feature",
  "properties": {
    "gn:admin1_code":"16",
    "gn:asciiname":"El Jiqui",
    "gn:country_code":"CU",
    "gn:dem":70,
    "gn:feature_class":"P",
    "gn:feature_code":"PPL",
    "gn:name":"El Jiqu\u00ed",
    "gn:population":0,
    "gn:timezone":"America/Havana",
    "iso:country":"CU",
    "wof:name":"El Jiqui",
    "wof:placetype":"locality"
},
  "geometry": {"coordinates":[-80.46666999999999,22.58333],"type":"Point"}
}