{
  "type": "Feature",
  "properties": {
    "gn:admin1_code":"09",
    "gn:asciiname":"Blanquizal",
    "gn:country_code":"CU",
    "gn:dem":17,
    "gn:feature_class":"P",
    "gn:feature_code":"PPL",
    "gn:name":"Blanquizal",
    "gn:population":0,
    "gn:timezone":"America/Havana",
    "iso:country":"CU",
    "name:und_x_variant":[
        "Poblado Blanquizal",
        "Blanquizal"
    ],
    "wof:name":"Blanquizal",
    "wof:placetype":"locality"
},
  "geometry": {"coordinates":[-77.08348000000002,20.34475],"type":"Point"}
}