{
  "type": "Feature",
  "properties": {
    "gn:admin1_code":"MA",
    "gn:asciiname":"Union",
    "gn:country_code":"CU",
    "gn:dem":180,
    "gn:feature_class":"P",
    "gn:feature_code":"PPLL",
    "gn:name":"Uni\u00f3n",
    "gn:population":0,
    "gn:timezone":"America/Havana",
    "iso:country":"CU",
    "wof:name":"Union",
    "wof:placetype":"locality"
},
  "geometry": {"coordinates":[-82.16667,22.93333],"type":"Point"}
}