{
  "type": "Feature",
  "properties": {
    "gn:admin1_code":"14",
    "gn:asciiname":"Trece de Marzo",
    "gn:country_code":"CU",
    "gn:dem":144,
    "gn:feature_class":"P",
    "gn:feature_code":"PPL",
    "gn:name":"Trece de Marzo",
    "gn:population":0,
    "gn:timezone":"America/Havana",
    "iso:country":"CU",
    "name:spa_x_preferred":[
        "Trece de Marzo"
    ],
    "name:spa_x_variant":[
        "13 de Marzo"
    ],
    "wof:name":"Trece de Marzo",
    "wof:placetype":"locality"
},
  "geometry": {"coordinates":[-79.58625000000001,22.0619],"type":"Point"}
}