{
  "type": "Feature",
  "properties": {
    "gn:admin1_code":"12",
    "gn:asciiname":"Palmarito",
    "gn:country_code":"CU",
    "gn:dem":10,
    "gn:feature_class":"P",
    "gn:feature_code":"PPL",
    "gn:name":"Palmarito",
    "gn:population":0,
    "gn:timezone":"America/Havana",
    "iso:country":"CU",
    "name:spa_x_preferred":[
        "Palmarito"
    ],
    "wof:name":"Palmarito",
    "wof:placetype":"locality"
},
  "geometry": {"coordinates":[-75.56000999999998,20.73448],"type":"Point"}
}