{
  "type": "Feature",
  "properties": {
    "gn:admin1_code":"16",
    "gn:asciiname":"Los Millares",
    "gn:country_code":"CU",
    "gn:dem":151,
    "gn:feature_class":"P",
    "gn:feature_code":"PPL",
    "gn:name":"Los Millares",
    "gn:population":0,
    "gn:timezone":"America/Havana",
    "iso:country":"CU",
    "name:spa_x_preferred":[
        "Los Millares"
    ],
    "wof:name":"Los Millares",
    "wof:placetype":"locality"
},
  "geometry": {"coordinates":[-79.99635000000001,22.22261],"type":"Point"}
}