{
  "type": "Feature",
  "properties": {
    "gn:admin1_code":"16",
    "gn:asciiname":"Los Millares",
    "gn:country_code":"CU",
    "gn:dem":151,
    "gn:feature_class":"P",
    "gn:feature_code":"PPL",
    "gn:name":"Los Millares",
    "gn:population":0,
    "gn:timezone":"America/Havana",
    "iso:country":"CU",
    "name:ceb_x_preferred":[
        "Los Millares"
    ],
    "name:deu_x_preferred":[
        "Los Millares"
    ],
    "name:epo_x_preferred":[
        "Los Millares"
    ],
    "name:eus_x_preferred":[
        "Los Millares"
    ],
    "name:fin_x_preferred":[
        "Los Millaresin kulttuuri"
    ],
    "name:fra_x_preferred":[
        "Los Millares"
    ],
    "name:glg_x_preferred":[
        "Los Millares"
    ],
    "name:ita_x_preferred":[
        "Los Millares"
    ],
    "name:nld_x_preferred":[
        "Los Millares"
    ],
    "name:pol_x_preferred":[
        "Los Millares"
    ],
    "name:rus_x_preferred":[
        "\u041b\u043e\u0441-\u041c\u0438\u043b\u044c\u044f\u0440\u0435\u0441"
    ],
    "name:spa_x_preferred":[
        "Los Millares"
    ],
    "name:swe_x_preferred":[
        "Los Millares"
    ],
    "wof:name":"Los Millares",
    "wof:placetype":"locality"
},
  "geometry": {"coordinates":[-79.99635000000001,22.22261],"type":"Point"}
}