{
  "type": "Feature",
  "properties": {
    "gn:admin1_code":"AR",
    "gn:asciiname":"Frias",
    "gn:country_code":"CU",
    "gn:dem":25,
    "gn:feature_class":"P",
    "gn:feature_code":"PPL",
    "gn:name":"Fr\u00edas",
    "gn:population":0,
    "gn:timezone":"America/Havana",
    "iso:country":"CU",
    "name:ceb_x_preferred":[
        "Frias"
    ],
    "name:spa_x_preferred":[
        "Fr\u00edas"
    ],
    "name:swe_x_preferred":[
        "Frias"
    ],
    "wof:name":"Frias",
    "wof:placetype":"locality"
},
  "geometry": {"coordinates":[-83.01470999999999,22.99554],"type":"Point"}
}