{
  "type": "Feature",
  "properties": {
    "gn:admin1_code":"AR",
    "gn:asciiname":"Frias",
    "gn:country_code":"CU",
    "gn:dem":25,
    "gn:feature_class":"P",
    "gn:feature_code":"PPL",
    "gn:name":"Fr\u00edas",
    "gn:population":0,
    "gn:timezone":"America/Havana",
    "iso:country":"CU",
    "name:ben_x_preferred":[
        "\u09ab\u09cd\u09b0\u09bf\u09df\u09be\u09b8"
    ],
    "name:ceb_x_preferred":[
        "Frias"
    ],
    "name:ell_x_preferred":[
        "\u03a6\u03c1\u03af\u03b1\u03c2"
    ],
    "name:heb_x_preferred":[
        "\u05e4\u05e8\u05d9\u05d0\u05e1"
    ],
    "name:hin_x_preferred":[
        "\u092b\u093c\u094d\u0930\u093f\u092f\u093e\u0938"
    ],
    "name:hun_x_preferred":[
        "Frias"
    ],
    "name:ind_x_preferred":[
        "Frias"
    ],
    "name:jpn_x_preferred":[
        "\u30d5\u30ea\u30a2\u30b9"
    ],
    "name:kor_x_preferred":[
        "\ud504\ub9ac\uc544\uc2a4"
    ],
    "name:rus_x_preferred":[
        "\u0424\u0440\u0438\u0430\u0441"
    ],
    "name:spa_x_preferred":[
        "Fr\u00edas"
    ],
    "name:swe_x_preferred":[
        "Frias"
    ],
    "name:tur_x_preferred":[
        "Frias"
    ],
    "name:urd_x_preferred":[
        "\u0641\u0631\u0627\u0626\u06cc\u0627\u0633"
    ],
    "name:vie_x_preferred":[
        "Frias"
    ],
    "wof:name":"Frias",
    "wof:placetype":"locality"
},
  "geometry": {"coordinates":[-83.01470999999999,22.99554],"type":"Point"}
}