{
  "type": "Feature",
  "properties": {
    "gn:admin1_code":"05",
    "gn:asciiname":"La Virginia",
    "gn:country_code":"CU",
    "gn:dem":67,
    "gn:feature_class":"P",
    "gn:feature_code":"PPL",
    "gn:name":"La Virginia",
    "gn:population":0,
    "gn:timezone":"America/Havana",
    "iso:country":"CU",
    "name:spa_x_preferred":[
        "La Virginia"
    ],
    "wof:name":"La Virginia",
    "wof:placetype":"locality"
},
  "geometry": {"coordinates":[-77.88913000000002,21.0966],"type":"Point"}
}