{
  "type": "Feature",
  "properties": {
    "gn:admin1_code":"10",
    "gn:asciiname":"Yumuri del Sur",
    "gn:country_code":"CU",
    "gn:dem":352,
    "gn:feature_class":"P",
    "gn:feature_code":"PPL",
    "gn:name":"Yumur\u00ed del Sur",
    "gn:population":0,
    "gn:timezone":"America/Havana",
    "iso:country":"CU",
    "name:spa_x_preferred":[
        "Yumur\u00ed del Sur"
    ],
    "wof:name":"Yumuri del Sur",
    "wof:placetype":"locality"
},
  "geometry": {"coordinates":[-74.48118000000002,20.18683],"type":"Point"}
}