{
  "type": "Feature",
  "properties": {
    "gn:admin1_code":"14",
    "gn:asciiname":"La Hormiga",
    "gn:country_code":"CU",
    "gn:dem":122,
    "gn:feature_class":"P",
    "gn:feature_code":"PPL",
    "gn:name":"La Hormiga",
    "gn:population":0,
    "gn:timezone":"America/Havana",
    "iso:country":"CU",
    "name:spa_x_preferred":[
        "La Hormiga"
    ],
    "wof:name":"La Hormiga",
    "wof:placetype":"locality"
},
  "geometry": {"coordinates":[-79.70595,22.02228],"type":"Point"}
}