{
  "type": "Feature",
  "properties": {
    "gn:admin1_code":"04",
    "gn:asciiname":"Argelia Libre",
    "gn:country_code":"CU",
    "gn:dem":43,
    "gn:feature_class":"P",
    "gn:feature_code":"PPL",
    "gn:name":"Argelia Libre",
    "gn:population":0,
    "gn:timezone":"America/Havana",
    "iso:country":"CU",
    "name:spa_x_preferred":[
        "Argelia Libre"
    ],
    "wof:name":"Argelia Libre",
    "wof:placetype":"locality"
},
  "geometry": {"coordinates":[-82.90205999999998,21.67697],"type":"Point"}
}