{
  "type": "Feature",
  "properties": {
    "gn:admin1_code":"07",
    "gn:asciiname":"La Angelina",
    "gn:country_code":"CU",
    "gn:dem":97,
    "gn:feature_class":"P",
    "gn:feature_code":"PPLL",
    "gn:name":"La Angelina",
    "gn:population":0,
    "gn:timezone":"America/Havana",
    "iso:country":"CU",
    "wof:name":"La Angelina",
    "wof:placetype":"locality"
},
  "geometry": {"coordinates":[-79.02221999999998,21.89722],"type":"Point"}
}