{
  "type": "Feature",
  "properties": {
    "gn:admin1_code":"05",
    "gn:asciiname":"Cayo del Medio",
    "gn:country_code":"CU",
    "gn:dem":69,
    "gn:feature_class":"P",
    "gn:feature_code":"PPL",
    "gn:name":"Cayo del Medio",
    "gn:population":0,
    "gn:timezone":"America/Havana",
    "iso:country":"CU",
    "name:spa_x_preferred":[
        "Cayo del Medio"
    ],
    "wof:name":"Cayo del Medio",
    "wof:placetype":"locality"
},
  "geometry": {"coordinates":[-77.60120999999999,21.5018],"type":"Point"}
}