{
  "type": "Feature",
  "properties": {
    "gn:admin1_code":"07",
    "gn:asciiname":"Ciro Frias",
    "gn:country_code":"CU",
    "gn:dem":26,
    "gn:feature_class":"P",
    "gn:feature_code":"PPL",
    "gn:name":"Ciro Fr\u00edas",
    "gn:population":0,
    "gn:timezone":"America/Havana",
    "iso:country":"CU",
    "name:spa_x_preferred":[
        "Ciro Fr\u00edas"
    ],
    "wof:name":"Ciro Frias",
    "wof:placetype":"locality"
},
  "geometry": {"coordinates":[-78.58409,22.2512],"type":"Point"}
}