{
  "type": "Feature",
  "properties": {
    "gn:admin1_code":"09",
    "gn:asciiname":"El Pato",
    "gn:country_code":"CU",
    "gn:dem":59,
    "gn:feature_class":"P",
    "gn:feature_code":"PPLL",
    "gn:name":"El Pato",
    "gn:population":0,
    "gn:timezone":"America/Havana",
    "iso:country":"CU",
    "wof:name":"El Pato",
    "wof:placetype":"locality"
},
  "geometry": {"coordinates":[-76.84999999999999,20.21667],"type":"Point"}
}