{
  "type": "Feature",
  "properties": {
    "gn:admin1_code":"09",
    "gn:asciiname":"Anton Sanchez",
    "gn:country_code":"CU",
    "gn:dem":15,
    "gn:feature_class":"P",
    "gn:feature_code":"PPL",
    "gn:name":"Ant\u00f3n S\u00e1nchez",
    "gn:population":0,
    "gn:timezone":"America/Havana",
    "iso:country":"CU",
    "wof:name":"Anton Sanchez",
    "wof:placetype":"locality"
},
  "geometry": {"coordinates":[-77.23333000000002,20.16667],"type":"Point"}
}