{
  "type": "Feature",
  "properties": {
    "gn:admin1_code":"13",
    "gn:asciiname":"Las Tasajeras",
    "gn:country_code":"CU",
    "gn:dem":14,
    "gn:feature_class":"P",
    "gn:feature_code":"PPLL",
    "gn:name":"Las Tasajeras",
    "gn:population":0,
    "gn:timezone":"America/Havana",
    "iso:country":"CU",
    "wof:name":"Las Tasajeras",
    "wof:placetype":"locality"
},
  "geometry": {"coordinates":[-77.05389,21.30972],"type":"Point"}
}