{
  "type": "Feature",
  "properties": {
    "gn:admin1_code":"10",
    "gn:asciiname":"El Manguito",
    "gn:country_code":"CU",
    "gn:dem":173,
    "gn:feature_class":"P",
    "gn:feature_code":"PPLL",
    "gn:name":"El Manguito",
    "gn:population":0,
    "gn:timezone":"America/Havana",
    "iso:country":"CU",
    "wof:name":"El Manguito",
    "wof:placetype":"locality"
},
  "geometry": {"coordinates":[-75.18111,20.24556],"type":"Point"}
}