{
  "type": "Feature",
  "properties": {
    "gn:admin1_code":"07",
    "gn:asciiname":"La Palma",
    "gn:country_code":"CU",
    "gn:dem":90,
    "gn:feature_class":"P",
    "gn:feature_code":"PPLL",
    "gn:name":"La Palma",
    "gn:population":0,
    "gn:timezone":"America/Havana",
    "iso:country":"CU",
    "name:afr_x_preferred":[
        "La Palma"
    ],
    "name:ara_x_preferred":[
        "\u0644\u0627 \u0628\u0627\u0644\u0645\u0627"
    ],
    "name:arz_x_preferred":[
        "\u0644\u0627 \u0628\u0627\u0644\u0645\u0627"
    ],
    "name:ast_x_preferred":[
        "La Palma"
    ],
    "name:bel_x_preferred":[
        "\u041f\u0430\u043b\u044c\u043c\u0430"
    ],
    "name:bre_x_preferred":[
        "La Palma"
    ],
    "name:bul_x_preferred":[
        "\u041f\u0430\u043b\u043c\u0430"
    ],
    "name:cat_x_preferred":[
        "La Palma"
    ],
    "name:ces_x_preferred":[
        "La Palma"
    ],
    "name:dan_x_preferred":[
        "La Palma"
    ],
    "name:deu_x_preferred":[
        "La Palma"
    ],
    "name:ell_x_preferred":[
        "\u039b\u03b1 \u03a0\u03ac\u03bb\u03bc\u03b1"
    ],
    "name:epo_x_preferred":[
        "La Palma"
    ],
    "name:est_x_preferred":[
        "La Palma"
    ],
    "name:eus_x_preferred":[
        "La Palma"
    ],
    "name:fas_x_preferred":[
        "\u0644\u0627 \u067e\u0627\u0644\u0645\u0627"
    ],
    "name:fin_x_preferred":[
        "La Palma"
    ],
    "name:fra_x_preferred":[
        "La Palma"
    ],
    "name:frr_x_preferred":[
        "La Palma"
    ],
    "name:fry_x_preferred":[
        "La Palma"
    ],
    "name:gla_x_preferred":[
        "La Palma"
    ],
    "name:glg_x_preferred":[
        "La Palma"
    ],
    "name:hun_x_preferred":[
        "La Palma"
    ],
    "name:ind_x_preferred":[
        "La Palma"
    ],
    "name:isl_x_preferred":[
        "La Palma"
    ],
    "name:ita_x_preferred":[
        "La Palma"
    ],
    "name:jpn_x_preferred":[
        "\u30e9\u30fb\u30d1\u30eb\u30de\u5cf6"
    ],
    "name:kor_x_preferred":[
        "\ub77c\ud314\ub9c8\uc12c"
    ],
    "name:lit_x_preferred":[
        "La Palma"
    ],
    "name:ltz_x_preferred":[
        "La Palma"
    ],
    "name:mkd_x_preferred":[
        "\u041b\u0430 \u041f\u0430\u043b\u043c\u0430"
    ],
    "name:mrj_x_preferred":[
        "\u041f\u0430\u043b\u044c\u043c\u0430"
    ],
    "name:nld_x_preferred":[
        "La Palma"
    ],
    "name:nno_x_preferred":[
        "La Palma"
    ],
    "name:nor_x_preferred":[
        "La Palma"
    ],
    "name:oci_x_preferred":[
        "La Palma"
    ],
    "name:pol_x_preferred":[
        "La Palma"
    ],
    "name:por_x_preferred":[
        "La Palma"
    ],
    "name:ron_x_preferred":[
        "La Palma"
    ],
    "name:rus_x_preferred":[
        "\u041f\u0430\u043b\u044c\u043c\u0430"
    ],
    "name:sco_x_preferred":[
        "La Palma"
    ],
    "name:spa_x_preferred":[
        "La Palma"
    ],
    "name:srp_x_preferred":[
        "\u041b\u0430 \u041f\u0430\u043b\u043c\u0430"
    ],
    "name:swe_x_preferred":[
        "La Palma"
    ],
    "name:tur_x_preferred":[
        "La Palma"
    ],
    "name:ukr_x_preferred":[
        "\u041b\u0430-\u041f\u0430\u043b\u044c\u043c\u0430"
    ],
    "name:vie_x_preferred":[
        "La Palma"
    ],
    "name:war_x_preferred":[
        "La Palma"
    ],
    "name:zho_x_preferred":[
        "\u62c9\u5e15\u723e\u99ac\u5cf6"
    ],
    "wof:name":"La Palma",
    "wof:placetype":"locality"
},
  "geometry": {"coordinates":[-78.98885,22.19098],"type":"Point"}
}