{
  "type": "Feature",
  "properties": {
    "gn:admin1_code":"03",
    "gn:asciiname":"Camarioca",
    "gn:country_code":"CU",
    "gn:dem":47,
    "gn:feature_class":"P",
    "gn:feature_code":"PPL",
    "gn:name":"Camarioca",
    "gn:population":0,
    "gn:timezone":"America/Havana",
    "iso:country":"CU",
    "name:spa_x_preferred":[
        "Camarioca"
    ],
    "wof:name":"Camarioca",
    "wof:placetype":"locality"
},
  "geometry": {"coordinates":[-81.35545999999999,23.06142],"type":"Point"}
}