{
  "type": "Feature",
  "properties": {
    "gn:admin1_code":"05",
    "gn:asciiname":"San Bartolo",
    "gn:country_code":"CU",
    "gn:dem":34,
    "gn:feature_class":"P",
    "gn:feature_code":"PPLL",
    "gn:name":"San Bartolo",
    "gn:population":0,
    "gn:timezone":"America/Havana",
    "iso:country":"CU",
    "name:und_x_variant":[
        "Bartolo",
        "San Bartolo"
    ],
    "wof:name":"San Bartolo",
    "wof:placetype":"locality"
},
  "geometry": {"coordinates":[-77.38275,21.34427],"type":"Point"}
}