{
  "type": "Feature",
  "properties": {
    "gn:admin1_code":"03",
    "gn:asciiname":"Esperanza",
    "gn:country_code":"CU",
    "gn:dem":57,
    "gn:feature_class":"P",
    "gn:feature_code":"PPLL",
    "gn:name":"Esperanza",
    "gn:population":0,
    "gn:timezone":"America/Havana",
    "iso:country":"CU",
    "name:spa_x_preferred":[
        "Esperanza"
    ],
    "name:und_x_variant":[
        "La Esperanza"
    ],
    "wof:name":"Esperanza",
    "wof:placetype":"locality"
},
  "geometry": {"coordinates":[-80.70125,22.56723],"type":"Point"}
}