{
  "type": "Feature",
  "properties": {
    "gn:country":"CU",
    "gn:fcode":"PPL",
    "gn:pop":70438,
    "iso:country":"CU",
    "name:ceb_x_preferred":[
        "Contramaestre"
    ],
    "name:deu_x_preferred":[
        "Contramaestre"
    ],
    "name:eng_x_preferred":[
        "Contramaestre"
    ],
    "name:fra_x_preferred":[
        "Contramaestre"
    ],
    "name:glg_x_preferred":[
        "Contramaestre"
    ],
    "name:hun_x_preferred":[
        "Contramaestre"
    ],
    "name:ita_x_preferred":[
        "Contramaestre"
    ],
    "name:kat_x_preferred":[
        "\u10d9\u10dd\u10dc\u10e2\u10e0\u10d0\u10db\u10d0\u10d4\u10e1\u10e2\u10e0\u10d4"
    ],
    "name:nld_x_preferred":[
        "Contramaestre"
    ],
    "name:pol_x_preferred":[
        "Contramaestre"
    ],
    "name:por_x_preferred":[
        "Contramaestre"
    ],
    "name:ron_x_preferred":[
        "Contramaestre"
    ],
    "name:sco_x_preferred":[
        "Contramaestre"
    ],
    "name:spa_x_preferred":[
        "Contramaestre"
    ],
    "name:srp_x_preferred":[
        "\u041a\u043e\u043d\u0442\u0440\u0430\u043c\u0430\u0435\u0441\u0442\u0440\u0435"
    ],
    "name:swe_x_preferred":[
        "Contramaestre"
    ],
    "name:urd_x_preferred":[
        "\u06a9\u0648\u0646\u062a\u0631\u0627\u0645\u06cc\u0633\u062a\u0631\u06d2"
    ],
    "name:vie_x_preferred":[
        "Contramaestre"
    ],
    "name:zho_x_preferred":[
        "\u5b54\u7279\u62c9\u99ac\u57c3\u65af\u7279\u96f7"
    ],
    "qs:name":"Contramaestre",
    "qs:photos_9r":0,
    "qs:photos_sr":0,
    "qs:pop_sr":"8",
    "wd:wordcount":122,
    "wof:name":"Contramaestre",
    "wof:placetype":"locality",
    "wof:population":70438
},
  "geometry": {"coordinates":[-76.24139,20.29778],"type":"Point"}
}