{
  "type": "Feature",
  "properties": {
    "gn:admin1_code":"01",
    "gn:asciiname":"El Caimital",
    "gn:country_code":"CU",
    "gn:dem":34,
    "gn:feature_class":"P",
    "gn:feature_code":"PPLL",
    "gn:name":"El Caimital",
    "gn:population":0,
    "gn:timezone":"America/Havana",
    "iso:country":"CU",
    "name:spa_x_preferred":[
        "El Caimital"
    ],
    "name:und_x_variant":[
        "Caimital"
    ],
    "wof:name":"El Caimital",
    "wof:placetype":"locality"
},
  "geometry": {"coordinates":[-83.27254000000001,22.56112000000001],"type":"Point"}
}