{
  "type": "Feature",
  "properties": {
    "gn:admin1_code":"09",
    "gn:asciiname":"Limones",
    "gn:country_code":"CU",
    "gn:dem":110,
    "gn:feature_class":"P",
    "gn:feature_code":"PPL",
    "gn:name":"Limones",
    "gn:population":0,
    "gn:timezone":"America/Havana",
    "iso:country":"CU",
    "name:und_x_variant":[
        "Salto de Limones",
        "Limones"
    ],
    "wof:name":"Limones",
    "wof:placetype":"locality"
},
  "geometry": {"coordinates":[-77.51801999999998,19.97857],"type":"Point"}
}