{
  "type": "Feature",
  "properties": {
    "gn:admin1_code":"MA",
    "gn:asciiname":"Congojas",
    "gn:country_code":"CU",
    "gn:dem":12,
    "gn:feature_class":"P",
    "gn:feature_code":"PPL",
    "gn:name":"Congojas",
    "gn:population":0,
    "gn:timezone":"America/Havana",
    "iso:country":"CU",
    "name:spa_x_preferred":[
        "Congojas"
    ],
    "wof:name":"Congojas",
    "wof:placetype":"locality"
},
  "geometry": {"coordinates":[-82.02580999999998,22.73414],"type":"Point"}
}