{
  "type": "Feature",
  "properties": {
    "gn:admin1_code":"13",
    "gn:asciiname":"Mastrapa",
    "gn:country_code":"CU",
    "gn:dem":64,
    "gn:feature_class":"P",
    "gn:feature_code":"PPL",
    "gn:name":"Mastrapa",
    "gn:population":0,
    "gn:timezone":"America/Havana",
    "iso:country":"CU",
    "name:spa_x_preferred":[
        "Mastrapa"
    ],
    "wof:name":"Mastrapa",
    "wof:placetype":"locality"
},
  "geometry": {"coordinates":[-77.05425,21.10855],"type":"Point"}
}