{
  "type": "Feature",
  "properties": {
    "gn:admin1_code":"12",
    "gn:asciiname":"Loma Blanca",
    "gn:country_code":"CU",
    "gn:dem":144,
    "gn:feature_class":"P",
    "gn:feature_code":"PPLL",
    "gn:name":"Loma Blanca",
    "gn:population":0,
    "gn:timezone":"America/Havana",
    "iso:country":"CU",
    "name:hye_x_preferred":[
        "\u053c\u0578\u0574\u0561 \u0532\u056c\u0561\u0576\u056f\u0561"
    ],
    "name:rus_x_preferred":[
        "\u041b\u043e\u043c\u0430-\u0411\u043b\u0430\u043d\u043a\u0430"
    ],
    "name:spa_x_preferred":[
        "Loma Blanca"
    ],
    "wof:name":"Loma Blanca",
    "wof:placetype":"locality"
},
  "geometry": {"coordinates":[-76.08473000000002,20.6218],"type":"Point"}
}