{
  "type": "Feature",
  "properties": {
    "gn:admin1_code":"13",
    "gn:asciiname":"Mono Ciego",
    "gn:country_code":"CU",
    "gn:dem":9,
    "gn:feature_class":"P",
    "gn:feature_code":"PPLL",
    "gn:name":"Mono Ciego",
    "gn:population":0,
    "gn:timezone":"America/Havana",
    "iso:country":"CU",
    "name:spa_x_preferred":[
        "Mono Ciego"
    ],
    "wof:name":"Mono Ciego",
    "wof:placetype":"locality"
},
  "geometry": {"coordinates":[-76.82132,21.38426],"type":"Point"}
}