{
  "type": "Feature",
  "properties": {
    "gn:admin1_code":"08",
    "gn:asciiname":"Vista Alegre",
    "gn:country_code":"CU",
    "gn:dem":46,
    "gn:feature_class":"P",
    "gn:feature_code":"PPLL",
    "gn:name":"Vista Alegre",
    "gn:population":0,
    "gn:timezone":"America/Havana",
    "iso:country":"CU",
    "name:cat_x_preferred":[
        "Vista Alegre"
    ],
    "name:ceb_x_preferred":[
        "Vista Alegre"
    ],
    "name:deu_x_preferred":[
        "Vista Alegre"
    ],
    "name:epo_x_preferred":[
        "Vista Alegre"
    ],
    "name:eus_x_preferred":[
        "Vista Alegre"
    ],
    "name:fra_x_preferred":[
        "Vista Alegre"
    ],
    "name:glg_x_preferred":[
        "Vista Alegre"
    ],
    "name:ita_x_preferred":[
        "Vista Alegre"
    ],
    "name:nld_x_preferred":[
        "Vista Alegre"
    ],
    "name:nor_x_preferred":[
        "Vista Alegre"
    ],
    "name:por_x_preferred":[
        "Vista Alegre"
    ],
    "name:spa_x_preferred":[
        "Vista Alegre"
    ],
    "name:srp_x_preferred":[
        "\u0412\u0438\u0441\u0442\u0430 \u0410\u043b\u0435\u0433\u0440\u0435"
    ],
    "name:swe_x_preferred":[
        "Vista Alegre"
    ],
    "wof:name":"Vista Alegre",
    "wof:placetype":"locality"
},
  "geometry": {"coordinates":[-80.34999999999999,22.41667],"type":"Point"}
}