{
  "type": "Feature",
  "properties": {
    "gn:admin1_code":"01",
    "gn:asciiname":"El Hato",
    "gn:country_code":"CU",
    "gn:dem":74,
    "gn:feature_class":"P",
    "gn:feature_code":"PPLL",
    "gn:name":"El Hato",
    "gn:population":0,
    "gn:timezone":"America/Havana",
    "iso:country":"CU",
    "name:ita_x_preferred":[
        "El Hato"
    ],
    "name:spa_x_preferred":[
        "El Hato"
    ],
    "name:zho_x_preferred":[
        "\u57c3\u723e\u963f\u6258"
    ],
    "wof:name":"El Hato",
    "wof:placetype":"locality"
},
  "geometry": {"coordinates":[-83.36667,22.65],"type":"Point"}
}