{
  "type": "Feature",
  "properties": {
    "gn:admin1_code":"02",
    "gn:asciiname":"Poco a Poco",
    "gn:country_code":"CU",
    "gn:dem":12,
    "gn:feature_class":"P",
    "gn:feature_code":"PPLL",
    "gn:name":"Poco a Poco",
    "gn:population":0,
    "gn:timezone":"America/Havana",
    "iso:country":"CU",
    "wof:name":"Poco a Poco",
    "wof:placetype":"locality"
},
  "geometry": {"coordinates":[-82.25,23.15],"type":"Point"}
}