{
  "type": "Feature",
  "properties": {
    "gn:admin1_code":"12",
    "gn:asciiname":"Alentado",
    "gn:country_code":"CU",
    "gn:dem":60,
    "gn:feature_class":"P",
    "gn:feature_code":"PPL",
    "gn:name":"Alentado",
    "gn:population":0,
    "gn:timezone":"America/Havana",
    "iso:country":"CU",
    "name:spa_x_preferred":[
        "Alentado"
    ],
    "wof:name":"Alentado",
    "wof:placetype":"locality"
},
  "geometry": {"coordinates":[-75.86801,21.02208],"type":"Point"}
}