{
  "type": "Feature",
  "properties": {
    "gn:admin1_code":"16",
    "gn:asciiname":"Malpaez",
    "gn:country_code":"CU",
    "gn:dem":55,
    "gn:feature_class":"P",
    "gn:feature_code":"PPL",
    "gn:name":"Malp\u00e1ez",
    "gn:population":0,
    "gn:timezone":"America/Havana",
    "iso:country":"CU",
    "name:spa_x_preferred":[
        "Malpaez"
    ],
    "name:spa_x_variant":[
        "Malp\u00e1ez"
    ],
    "wof:name":"Malpaez",
    "wof:placetype":"locality"
},
  "geometry": {"coordinates":[-80.17685,22.76758],"type":"Point"}
}