{
  "type": "Feature",
  "properties": {
    "gn:admin1_code":"14",
    "gn:asciiname":"Manaca Ranzola",
    "gn:country_code":"CU",
    "gn:dem":189,
    "gn:feature_class":"P",
    "gn:feature_code":"PPL",
    "gn:name":"Manaca Ranzola",
    "gn:population":0,
    "gn:timezone":"America/Havana",
    "iso:country":"CU",
    "name:spa_x_preferred":[
        "Manacas Ransola"
    ],
    "name:spa_x_variant":[
        "Manaca Ranzola",
        "Manacas Ransolas"
    ],
    "name:und_x_variant":[
        "Manacas Ranzola"
    ],
    "wof:name":"Manaca Ranzola",
    "wof:placetype":"locality"
},
  "geometry": {"coordinates":[-79.64881,21.99602],"type":"Point"}
}