{
  "type": "Feature",
  "properties": {
    "gn:admin1_code":"12",
    "gn:asciiname":"Collazo Cuatro",
    "gn:country_code":"CU",
    "gn:dem":29,
    "gn:feature_class":"P",
    "gn:feature_code":"PPL",
    "gn:name":"Collazo Cuatro",
    "gn:population":0,
    "gn:timezone":"America/Havana",
    "iso:country":"CU",
    "name:spa_x_preferred":[
        "Collazo Cuatro"
    ],
    "wof:name":"Collazo Cuatro",
    "wof:placetype":"locality"
},
  "geometry": {"coordinates":[-75.33723000000001,20.65819],"type":"Point"}
}