{
  "type": "Feature",
  "properties": {
    "gn:admin1_code":"03",
    "gn:asciiname":"Cayo Palmar",
    "gn:country_code":"CU",
    "gn:dem":45,
    "gn:feature_class":"P",
    "gn:feature_code":"PPLL",
    "gn:name":"Cayo Palmar",
    "gn:population":0,
    "gn:timezone":"America/Havana",
    "iso:country":"CU",
    "wof:name":"Cayo Palmar",
    "wof:placetype":"locality"
},
  "geometry": {"coordinates":[-80.73333000000002,22.48333],"type":"Point"}
}