{
  "type": "Feature",
  "properties": {
    "gn:admin1_code":"16",
    "gn:asciiname":"Baez",
    "gn:country_code":"CU",
    "gn:dem":165,
    "gn:feature_class":"P",
    "gn:feature_code":"PPL",
    "gn:name":"B\u00e1ez",
    "gn:population":0,
    "gn:timezone":"America/Havana",
    "iso:country":"CU",
    "name:und_x_variant":[
        "Poblado Baez",
        "B\u00e1es",
        "B\u00e1ez"
    ],
    "wof:name":"Baez",
    "wof:placetype":"locality"
},
  "geometry": {"coordinates":[-79.75461999999997,22.21728],"type":"Point"}
}