{
  "type": "Feature",
  "properties": {
    "gn:admin1_code":"MA",
    "gn:asciiname":"Tinaja",
    "gn:country_code":"CU",
    "gn:dem":19,
    "gn:feature_class":"P",
    "gn:feature_code":"PPL",
    "gn:name":"Tinaja",
    "gn:population":0,
    "gn:timezone":"America/Havana",
    "iso:country":"CU",
    "name:und_x_variant":[
        "Batey Tinaja",
        "Tinaja"
    ],
    "wof:name":"Tinaja",
    "wof:placetype":"locality"
},
  "geometry": {"coordinates":[-81.95111,22.76556],"type":"Point"}
}