{
  "type": "Feature",
  "properties": {
    "gn:admin1_code":"12",
    "gn:asciiname":"Guiros",
    "gn:country_code":"CU",
    "gn:dem":32,
    "gn:feature_class":"P",
    "gn:feature_code":"PPLL",
    "gn:name":"G\u00fciros",
    "gn:population":0,
    "gn:timezone":"America/Havana",
    "iso:country":"CU",
    "wof:name":"Guiros",
    "wof:placetype":"locality"
},
  "geometry": {"coordinates":[-75.28333000000001,20.55],"type":"Point"}
}