{
  "type": "Feature",
  "properties": {
    "gn:admin1_code":"MA",
    "gn:asciiname":"Purial del Malherbe",
    "gn:country_code":"CU",
    "gn:dem":77,
    "gn:feature_class":"P",
    "gn:feature_code":"PPLL",
    "gn:name":"Purial del Malherbe",
    "gn:population":0,
    "gn:timezone":"America/Havana",
    "iso:country":"CU",
    "wof:name":"Purial del Malherbe",
    "wof:placetype":"locality"
},
  "geometry": {"coordinates":[-81.86055999999998,22.84556],"type":"Point"}
}