{
  "type": "Feature",
  "properties": {
    "gn:admin1_code":"05",
    "gn:asciiname":"Ingenio Chiquito",
    "gn:country_code":"CU",
    "gn:dem":130,
    "gn:feature_class":"P",
    "gn:feature_code":"PPL",
    "gn:name":"Ingenio Chiquito",
    "gn:population":0,
    "gn:timezone":"America/Havana",
    "iso:country":"CU",
    "name:spa_x_preferred":[
        "Ingenio Chiquito"
    ],
    "wof:name":"Ingenio Chiquito",
    "wof:placetype":"locality"
},
  "geometry": {"coordinates":[-77.83077,21.31592],"type":"Point"}
}