{
  "type": "Feature",
  "properties": {
    "gn:admin1_code":"01",
    "gn:asciiname":"Arroyo Hondo",
    "gn:country_code":"CU",
    "gn:dem":55,
    "gn:feature_class":"P",
    "gn:feature_code":"PPLL",
    "gn:name":"Arroyo Hondo",
    "gn:population":0,
    "gn:timezone":"America/Havana",
    "iso:country":"CU",
    "name:spa_x_preferred":[
        "Arroyo Hondo"
    ],
    "wof:name":"Arroyo Hondo",
    "wof:placetype":"locality"
},
  "geometry": {"coordinates":[-83.83847,22.33439],"type":"Point"}
}