{
  "type": "Feature",
  "properties": {
    "gn:admin1_code":"08",
    "gn:asciiname":"Turquino",
    "gn:country_code":"CU",
    "gn:dem":36,
    "gn:feature_class":"P",
    "gn:feature_code":"PPL",
    "gn:name":"Turquino",
    "gn:population":0,
    "gn:timezone":"America/Havana",
    "iso:country":"CU",
    "name:spa_x_preferred":[
        "Turquino"
    ],
    "wof:name":"Turquino",
    "wof:placetype":"locality"
},
  "geometry": {"coordinates":[-80.50837,22.42685],"type":"Point"}
}