{
  "type": "Feature",
  "properties": {
    "gn:admin1_code":"10",
    "gn:asciiname":"Limones Diez y Seis",
    "gn:country_code":"CU",
    "gn:dem":186,
    "gn:feature_class":"P",
    "gn:feature_code":"PPL",
    "gn:name":"Limones Diez y Seis",
    "gn:population":0,
    "gn:timezone":"America/Havana",
    "iso:country":"CU",
    "name:spa_x_preferred":[
        "Limones Diez y Seis"
    ],
    "wof:name":"Limones Diez y Seis",
    "wof:placetype":"locality"
},
  "geometry": {"coordinates":[-75.35498,20.19778],"type":"Point"}
}