{
  "type": "Feature",
  "properties": {
    "gn:admin1_code":"16",
    "gn:asciiname":"Embarcadero",
    "gn:country_code":"CU",
    "gn:dem":12,
    "gn:feature_class":"P",
    "gn:feature_code":"PPL",
    "gn:name":"Embarcadero",
    "gn:population":0,
    "gn:timezone":"America/Havana",
    "iso:country":"CU",
    "name:deu_x_preferred":[
        "Embarcadero"
    ],
    "name:nld_x_preferred":[
        "Embarcadero"
    ],
    "name:spa_x_preferred":[
        "Embarcadero"
    ],
    "wof:name":"Embarcadero",
    "wof:placetype":"locality"
},
  "geometry": {"coordinates":[-79.7236,22.67014],"type":"Point"}
}