{
  "type": "Feature",
  "properties": {
    "gn:admin1_code":"09",
    "gn:asciiname":"Portada de la Libertad",
    "gn:country_code":"CU",
    "gn:dem":6,
    "gn:feature_class":"P",
    "gn:feature_code":"PPLL",
    "gn:name":"Portada de la Libertad",
    "gn:population":0,
    "gn:timezone":"America/Havana",
    "iso:country":"CU",
    "name:spa_x_preferred":[
        "Portada de la Libertad"
    ],
    "wof:name":"Portada de la Libertad",
    "wof:placetype":"locality"
},
  "geometry": {"coordinates":[-77.69736,19.91388],"type":"Point"}
}