{
  "type": "Feature",
  "properties": {
    "gn:admin1_code":"13",
    "gn:asciiname":"El Tropezon",
    "gn:country_code":"CU",
    "gn:dem":8,
    "gn:feature_class":"P",
    "gn:feature_code":"PPL",
    "gn:name":"El Tropez\u00f3n",
    "gn:population":0,
    "gn:timezone":"America/Havana",
    "iso:country":"CU",
    "name:spa_x_preferred":[
        "El Tropez\u00f3n"
    ],
    "wof:name":"El Tropezon",
    "wof:placetype":"locality"
},
  "geometry": {"coordinates":[-77.09581999999997,21.39869],"type":"Point"}
}