{
  "type": "Feature",
  "properties": {
    "gn:admin1_code":"14",
    "gn:asciiname":"La Dalia",
    "gn:country_code":"CU",
    "gn:dem":200,
    "gn:feature_class":"P",
    "gn:feature_code":"PPL",
    "gn:name":"La Dalia",
    "gn:population":0,
    "gn:timezone":"America/Havana",
    "iso:country":"CU",
    "name:spa_x_preferred":[
        "La Dalia"
    ],
    "name:und_x_variant":[
        "Sitio Nuevo"
    ],
    "wof:name":"La Dalia",
    "wof:placetype":"locality"
},
  "geometry": {"coordinates":[-79.15885,22.17343],"type":"Point"}
}