{
  "type": "Feature",
  "properties": {
    "gn:admin1_code":"08",
    "gn:asciiname":"Rincon Malo",
    "gn:cc2":"CU",
    "gn:country_code":"CU",
    "gn:dem":16,
    "gn:feature_class":"P",
    "gn:feature_code":"PPLL",
    "gn:name":"Rinc\u00f3n Malo",
    "gn:population":0,
    "gn:timezone":"America/Havana",
    "iso:country":"CU",
    "name:und_x_variant":[
        "Ricon Malo",
        "Rinc\u00f3n Malo"
    ],
    "wof:name":"Rincon Malo",
    "wof:placetype":"locality"
},
  "geometry": {"coordinates":[-80.75,22.21667],"type":"Point"}
}