{
  "type": "Feature",
  "properties": {
    "gn:admin1_code":"MA",
    "gn:asciiname":"Marteato",
    "gn:country_code":"CU",
    "gn:dem":51,
    "gn:feature_class":"P",
    "gn:feature_code":"PPL",
    "gn:name":"Marteato",
    "gn:population":0,
    "gn:timezone":"America/Havana",
    "iso:country":"CU",
    "name:und_x_variant":[
        "Maltealto",
        "Marteato"
    ],
    "wof:name":"Marteato",
    "wof:placetype":"locality"
},
  "geometry": {"coordinates":[-81.80056,22.82472000000001],"type":"Point"}
}