{
  "type": "Feature",
  "properties": {
    "gn:admin1_code":"16",
    "gn:asciiname":"La Camelia",
    "gn:country_code":"CU",
    "gn:dem":95,
    "gn:feature_class":"P",
    "gn:feature_code":"PPL",
    "gn:name":"La Camelia",
    "gn:population":0,
    "gn:timezone":"America/Havana",
    "iso:country":"CU",
    "name:spa_x_preferred":[
        "La Camelia"
    ],
    "name:und_x_variant":[
        "Camelia",
        "Carmelia"
    ],
    "wof:name":"La Camelia",
    "wof:placetype":"locality"
},
  "geometry": {"coordinates":[-80.11662,22.52667000000001],"type":"Point"}
}