{
  "type": "Feature",
  "properties": {
    "gn:admin1_code":"05",
    "gn:asciiname":"Sitio del Medio",
    "gn:country_code":"CU",
    "gn:dem":29,
    "gn:feature_class":"P",
    "gn:feature_code":"PPL",
    "gn:name":"Sitio del Medio",
    "gn:population":0,
    "gn:timezone":"America/Havana",
    "iso:country":"CU",
    "name:spa_x_preferred":[
        "Sitio del Medio"
    ],
    "wof:name":"Sitio del Medio",
    "wof:placetype":"locality"
},
  "geometry": {"coordinates":[-77.99077,20.86455],"type":"Point"}
}