{
  "type": "Feature",
  "properties": {
    "iso:country":"CU",
    "name:dut_x_preferred":[
        "Guanabo"
    ],
    "name:eng_x_preferred":[
        "Guanabo"
    ],
    "name:fra_x_preferred":[
        "Guanabo"
    ],
    "name:fre_x_preferred":[
        "Guanabo"
    ],
    "name:jpn_x_preferred":[
        "\u30b0\u30a2\u30ca\u30dc"
    ],
    "name:por_x_preferred":[
        "Guanabo"
    ],
    "name:spa_x_preferred":[
        "Guanabo"
    ],
    "name:unk_x_variant":[
        "Boca de Guanabo"
    ],
    "qs:gn_country":"CU",
    "qs:gn_fcode":"PPL",
    "qs:gn_pop":0,
    "qs:name":"Guanabo",
    "qs:name_adm0":"Cuba",
    "qs:name_adm1":"Ciudad de la Habana",
    "qs:photos":513,
    "qs:photos_1k":104,
    "qs:photos_9k":2,
    "qs:photos_9r":5,
    "qs:photos_all":513,
    "qs:photos_sr":7,
    "qs:placetype":"Town",
    "qs:pop_sr":"0",
    "qs:woe_adm0":23424793,
    "wd:wordcount":140,
    "wof:name":"Guanabo",
    "wof:placetype":"locality"
},
  "geometry": {"coordinates":[-82.12778,23.17111],"type":"Point"}
}