{
  "type": "Feature",
  "properties": {
    "gn:admin1_code":"15",
    "gn:asciiname":"Cojimar",
    "gn:country_code":"CU",
    "gn:dem":15,
    "gn:feature_class":"P",
    "gn:feature_code":"PPL",
    "gn:name":"Coj\u00edmar",
    "gn:population":0,
    "gn:timezone":"America/Havana",
    "iso:country":"CU",
    "name:spa_x_preferred":[
        "Coj\u00edmar"
    ],
    "wof:name":"Cojimar",
    "wof:placetype":"locality"
},
  "geometry": {"coordinates":[-76.10429000000001,19.97406],"type":"Point"}
}