{
  "type": "Feature",
  "properties": {
    "gn:admin1_code":"14",
    "gn:asciiname":"Las Noventa",
    "gn:country_code":"CU",
    "gn:dem":9,
    "gn:feature_class":"P",
    "gn:feature_code":"PPLL",
    "gn:name":"Las Noventa",
    "gn:population":0,
    "gn:timezone":"America/Havana",
    "iso:country":"CU",
    "name:spa_x_preferred":[
        "Las Noventa"
    ],
    "wof:name":"Las Noventa",
    "wof:placetype":"locality"
},
  "geometry": {"coordinates":[-79.03273,22.32999],"type":"Point"}
}