{
  "type": "Feature",
  "properties": {
    "gn:admin1_code":"16",
    "gn:asciiname":"Tarafa",
    "gn:country_code":"CU",
    "gn:dem":69,
    "gn:feature_class":"P",
    "gn:feature_code":"PPL",
    "gn:name":"Tarafa",
    "gn:population":0,
    "gn:timezone":"America/Havana",
    "iso:country":"CU",
    "name:hye_x_preferred":[
        "\u054f\u0561\u0580\u0561\u0586\u0561"
    ],
    "name:ita_x_preferred":[
        "Tarafa"
    ],
    "name:rus_x_preferred":[
        "\u0422\u0430\u0440\u0430\u0444\u0430"
    ],
    "name:spa_x_preferred":[
        "Tarafa"
    ],
    "name:srp_x_preferred":[
        "\u0422\u0430\u0440\u0430\u0444\u0430"
    ],
    "wof:name":"Tarafa",
    "wof:placetype":"locality"
},
  "geometry": {"coordinates":[-79.75439,22.46656],"type":"Point"}
}