{
  "type": "Feature",
  "properties": {
    "gn:admin1_code":"09",
    "gn:asciiname":"Cuentas Claras",
    "gn:country_code":"CU",
    "gn:dem":40,
    "gn:feature_class":"P",
    "gn:feature_code":"PPL",
    "gn:name":"Cuentas Claras",
    "gn:population":0,
    "gn:timezone":"America/Havana",
    "iso:country":"CU",
    "name:und_x_variant":[
        "Claras",
        "Cuentas Claras"
    ],
    "wof:name":"Cuentas Claras",
    "wof:placetype":"locality"
},
  "geometry": {"coordinates":[-77.07975999999999,20.29498],"type":"Point"}
}