{
  "type": "Feature",
  "properties": {
    "gn:admin1_code":"08",
    "gn:asciiname":"Morales",
    "gn:country_code":"CU",
    "gn:dem":14,
    "gn:feature_class":"P",
    "gn:feature_code":"PPLL",
    "gn:name":"Morales",
    "gn:population":0,
    "gn:timezone":"America/Havana",
    "iso:country":"CU",
    "name:ces_x_preferred":[
        "Morales"
    ],
    "name:deu_x_preferred":[
        "Morales"
    ],
    "name:lav_x_preferred":[
        "Moraless"
    ],
    "name:spa_x_preferred":[
        "Morales"
    ],
    "name:srp_x_preferred":[
        "\u041c\u043e\u0440\u0430\u043b\u0435\u0441"
    ],
    "wof:name":"Morales",
    "wof:placetype":"locality"
},
  "geometry": {"coordinates":[-80.90000000000001,22.38333],"type":"Point"}
}