{
  "type": "Feature",
  "properties": {
    "gn:admin1_code":"05",
    "gn:asciiname":"Las Ciegas",
    "gn:country_code":"CU",
    "gn:dem":36,
    "gn:feature_class":"P",
    "gn:feature_code":"PPLL",
    "gn:name":"Las Ciegas",
    "gn:population":0,
    "gn:timezone":"America/Havana",
    "iso:country":"CU",
    "name:spa_x_preferred":[
        "Las Ciegas"
    ],
    "wof:name":"Las Ciegas",
    "wof:placetype":"locality"
},
  "geometry": {"coordinates":[-78.31833,21.37833],"type":"Point"}
}