{
  "type": "Feature",
  "properties": {
    "gn:admin1_code":"10",
    "gn:asciiname":"La Colorada",
    "gn:country_code":"CU",
    "gn:dem":65,
    "gn:feature_class":"P",
    "gn:feature_code":"PPL",
    "gn:name":"La Colorada",
    "gn:population":0,
    "gn:timezone":"America/Havana",
    "iso:country":"CU",
    "name:und_x_variant":[
        "La-Kolorada",
        "La Colorada"
    ],
    "wof:name":"La Colorada",
    "wof:placetype":"locality"
},
  "geometry": {"coordinates":[-74.97136,20.01259],"type":"Point"}
}