{
  "type": "Feature",
  "properties": {
    "gn:admin1_code":"05",
    "gn:asciiname":"Paso de Vilato",
    "gn:country_code":"CU",
    "gn:dem":110,
    "gn:feature_class":"P",
    "gn:feature_code":"PPL",
    "gn:name":"Paso de Vilat\u00f3",
    "gn:population":0,
    "gn:timezone":"America/Havana",
    "iso:country":"CU",
    "name:spa_x_preferred":[
        "Paso de Vilat\u00f3"
    ],
    "wof:name":"Paso de Vilato",
    "wof:placetype":"locality"
},
  "geometry": {"coordinates":[-77.80203,21.65738],"type":"Point"}
}