{
  "type": "Feature",
  "properties": {
    "gn:admin1_code":"10",
    "gn:asciiname":"San Salvador",
    "gn:country_code":"CU",
    "gn:dem":255,
    "gn:feature_class":"P",
    "gn:feature_code":"PPLL",
    "gn:name":"San Salvador",
    "gn:population":0,
    "gn:timezone":"America/Havana",
    "iso:country":"CU",
    "wof:name":"San Salvador",
    "wof:placetype":"locality"
},
  "geometry": {"coordinates":[-74.32083,20.27944],"type":"Point"}
}