{
  "type": "Feature",
  "properties": {
    "gn:admin1_code":"05",
    "gn:asciiname":"Pajones Dos",
    "gn:country_code":"CU",
    "gn:dem":43,
    "gn:feature_class":"P",
    "gn:feature_code":"PPL",
    "gn:name":"Pajones Dos",
    "gn:population":0,
    "gn:timezone":"America/Havana",
    "iso:country":"CU",
    "name:spa_x_preferred":[
        "Pajones Dos"
    ],
    "wof:name":"Pajones Dos",
    "wof:placetype":"locality"
},
  "geometry": {"coordinates":[-78.16705,21.1536],"type":"Point"}
}