{
  "type": "Feature",
  "properties": {
    "gn:admin1_code":"03",
    "gn:asciiname":"Playa Maceo",
    "gn:country_code":"CU",
    "gn:dem":8,
    "gn:feature_class":"P",
    "gn:feature_code":"PPLL",
    "gn:name":"Playa Maceo",
    "gn:population":0,
    "gn:timezone":"America/Havana",
    "iso:country":"CU",
    "name:spa_x_preferred":[
        "Playa Maceo"
    ],
    "wof:name":"Playa Maceo",
    "wof:placetype":"locality"
},
  "geometry": {"coordinates":[-80.96854,22.04492],"type":"Point"}
}