{
  "type": "Feature",
  "properties": {
    "gn:admin1_code":"16",
    "gn:asciiname":"Hierro",
    "gn:cc2":"CU",
    "gn:country_code":"CU",
    "gn:dem":113,
    "gn:feature_class":"P",
    "gn:feature_code":"PPLL",
    "gn:name":"Hierro",
    "gn:population":0,
    "gn:timezone":"America/Havana",
    "iso:country":"CU",
    "name:und_x_variant":[
        "Chucho Hierro",
        "Hierro"
    ],
    "wof:name":"Hierro",
    "wof:placetype":"locality"
},
  "geometry": {"coordinates":[-80.11667,22.31667],"type":"Point"}
}