{
  "type": "Feature",
  "properties": {
    "gn:admin1_code":"15",
    "gn:asciiname":"Los Negros",
    "gn:country_code":"CU",
    "gn:dem":226,
    "gn:feature_class":"P",
    "gn:feature_code":"PPL",
    "gn:name":"Los Negros",
    "gn:population":0,
    "gn:timezone":"America/Havana",
    "iso:country":"CU",
    "name:ita_x_preferred":[
        "Los Negros"
    ],
    "name:jpn_x_preferred":[
        "\u30ed\u30b9\u30fb\u30cd\u30b0\u30ed\u30b9"
    ],
    "name:rus_x_preferred":[
        "\u041b\u043e\u0441-\u041d\u0435\u0433\u0440\u043e\u0441"
    ],
    "name:spa_x_preferred":[
        "Los Negros"
    ],
    "wof:name":"Los Negros",
    "wof:placetype":"locality"
},
  "geometry": {"coordinates":[-76.31173000000003,20.23157],"type":"Point"}
}