{
  "type": "Feature",
  "properties": {
    "gn:admin1_code":"03",
    "gn:asciiname":"Cespedes",
    "gn:country_code":"CU",
    "gn:dem":42,
    "gn:feature_class":"P",
    "gn:feature_code":"PPL",
    "gn:name":"C\u00e9spedes",
    "gn:population":0,
    "gn:timezone":"America/Havana",
    "iso:country":"CU",
    "name:spa_x_preferred":[
        "C\u00e9spedes"
    ],
    "wof:name":"Cespedes",
    "wof:placetype":"locality"
},
  "geometry": {"coordinates":[-80.85181,22.54665],"type":"Point"}
}