{
  "type": "Feature",
  "properties": {
    "gn:admin1_code":"16",
    "gn:asciiname":"Palenque",
    "gn:country_code":"CU",
    "gn:dem":39,
    "gn:feature_class":"P",
    "gn:feature_code":"PPL",
    "gn:name":"Palenque",
    "gn:population":0,
    "gn:timezone":"America/Havana",
    "iso:country":"CU",
    "name:spa_x_preferred":[
        "Palenque"
    ],
    "name:spa_x_variant":[
        "Palanque"
    ],
    "wof:name":"Palenque",
    "wof:placetype":"locality"
},
  "geometry": {"coordinates":[-79.61341999999998,22.48791],"type":"Point"}
}