{
  "type": "Feature",
  "properties": {
    "gn:admin1_code":"12",
    "gn:asciiname":"Boca de Tanamo",
    "gn:country_code":"CU",
    "gn:dem":0,
    "gn:feature_class":"P",
    "gn:feature_code":"PPLL",
    "gn:name":"Boca de T\u00e1namo",
    "gn:population":0,
    "gn:timezone":"America/Havana",
    "iso:country":"CU",
    "name:spa_x_preferred":[
        "Boca de T\u00e1namo"
    ],
    "wof:name":"Boca de Tanamo",
    "wof:placetype":"locality"
},
  "geometry": {"coordinates":[-75.3241,20.70929],"type":"Point"}
}