{
  "type": "Feature",
  "properties": {
    "gn:admin1_code":"13",
    "gn:asciiname":"Brinquito",
    "gn:country_code":"CU",
    "gn:dem":58,
    "gn:feature_class":"P",
    "gn:feature_code":"PPL",
    "gn:name":"Brinquito",
    "gn:population":0,
    "gn:timezone":"America/Havana",
    "iso:country":"CU",
    "name:spa_x_preferred":[
        "Brinquito"
    ],
    "wof:name":"Brinquito",
    "wof:placetype":"locality"
},
  "geometry": {"coordinates":[-77.40923000000002,20.94122],"type":"Point"}
}