{
  "type": "Feature",
  "properties": {
    "gn:admin1_code":"14",
    "gn:asciiname":"El Bajao",
    "gn:country_code":"CU",
    "gn:dem":119,
    "gn:feature_class":"P",
    "gn:feature_code":"PPLL",
    "gn:name":"El Bajao",
    "gn:population":0,
    "gn:timezone":"America/Havana",
    "iso:country":"CU",
    "name:spa_x_preferred":[
        "El Bajao"
    ],
    "name:und_x_variant":[
        "El Dajao"
    ],
    "wof:name":"El Bajao",
    "wof:placetype":"locality"
},
  "geometry": {"coordinates":[-79.48976,22.04899],"type":"Point"}
}