{
  "type": "Feature",
  "properties": {
    "gn:admin1_code":"01",
    "gn:asciiname":"Bella Maria",
    "gn:country_code":"CU",
    "gn:dem":69,
    "gn:feature_class":"P",
    "gn:feature_code":"PPLL",
    "gn:name":"Bella Mar\u00eda",
    "gn:population":0,
    "gn:timezone":"America/Havana",
    "iso:country":"CU",
    "name:spa_x_preferred":[
        "Bella Mar\u00eda"
    ],
    "wof:name":"Bella Maria",
    "wof:placetype":"locality"
},
  "geometry": {"coordinates":[-83.59255,22.72038],"type":"Point"}
}