{
  "type": "Feature",
  "properties": {
    "gn:admin1_code":"16",
    "gn:asciiname":"San Alberto",
    "gn:country_code":"CU",
    "gn:dem":133,
    "gn:feature_class":"P",
    "gn:feature_code":"PPLL",
    "gn:name":"San Alberto",
    "gn:population":0,
    "gn:timezone":"America/Havana",
    "iso:country":"CU",
    "name:ceb_x_preferred":[
        "San Alberto"
    ],
    "name:deu_x_preferred":[
        "San Alberto"
    ],
    "name:nld_x_preferred":[
        "San Alberto"
    ],
    "name:por_x_preferred":[
        "San Alberto"
    ],
    "name:spa_x_preferred":[
        "San Alberto"
    ],
    "name:srp_x_preferred":[
        "\u0421\u0430\u043d \u0410\u043b\u0431\u0435\u0440\u0442\u043e"
    ],
    "name:swe_x_preferred":[
        "San Alberto"
    ],
    "name:vie_x_preferred":[
        "San Alberto"
    ],
    "wof:name":"San Alberto",
    "wof:placetype":"locality"
},
  "geometry": {"coordinates":[-79.59461999999998,22.4215],"type":"Point"}
}