{
  "type": "Feature",
  "properties": {
    "gn:admin1_code":"07",
    "gn:asciiname":"El Capitan",
    "gn:country_code":"CU",
    "gn:dem":37,
    "gn:feature_class":"P",
    "gn:feature_code":"PPLL",
    "gn:name":"El Capit\u00e1n",
    "gn:population":0,
    "gn:timezone":"America/Havana",
    "iso:country":"CU",
    "name:spa_x_preferred":[
        "El Capit\u00e1n"
    ],
    "wof:name":"El Capitan",
    "wof:placetype":"locality"
},
  "geometry": {"coordinates":[-78.6511,21.83952],"type":"Point"}
}