{
  "type": "Feature",
  "properties": {
    "gn:admin1_code":"07",
    "gn:asciiname":"El Capitan",
    "gn:country_code":"CU",
    "gn:dem":37,
    "gn:feature_class":"P",
    "gn:feature_code":"PPLL",
    "gn:name":"El Capit\u00e1n",
    "gn:population":0,
    "gn:timezone":"America/Havana",
    "iso:country":"CU",
    "name:ara_x_preferred":[
        "\u0625\u0644 \u0643\u0627\u0628\u064a\u062a\u0627\u0646"
    ],
    "name:bul_x_preferred":[
        "\u0415\u043b \u041a\u0430\u043f\u0438\u0442\u0430\u043d"
    ],
    "name:cat_x_preferred":[
        "El Capit\u00e1n"
    ],
    "name:ceb_x_preferred":[
        "El Capitan"
    ],
    "name:ces_x_preferred":[
        "El Capitan"
    ],
    "name:cym_x_preferred":[
        "El Capitan"
    ],
    "name:dan_x_preferred":[
        "El Capitan"
    ],
    "name:deu_x_preferred":[
        "El Capitan"
    ],
    "name:ell_x_preferred":[
        "\u0395\u03bb \u039a\u03b1\u03c0\u03b9\u03c4\u03ac\u03bd"
    ],
    "name:eus_x_preferred":[
        "El Capitan"
    ],
    "name:fas_x_preferred":[
        "\u0627\u0644 \u06a9\u0627\u067e\u06cc\u062a\u0627\u0646"
    ],
    "name:fra_x_preferred":[
        "El Capitan"
    ],
    "name:heb_x_preferred":[
        "\u05d0\u05dc \u05e7\u05e4\u05d9\u05d8\u05df"
    ],
    "name:ita_x_preferred":[
        "El Capitan"
    ],
    "name:jpn_x_preferred":[
        "\u30a8\u30eb\u30fb\u30ad\u30e3\u30d4\u30bf\u30f3"
    ],
    "name:kor_x_preferred":[
        "\uc5d8\uce74\ud53c\ud0e0"
    ],
    "name:ltz_x_preferred":[
        "El Capitan"
    ],
    "name:nld_x_preferred":[
        "El Capitan"
    ],
    "name:nno_x_preferred":[
        "El Capitan"
    ],
    "name:nor_x_preferred":[
        "El Capitan"
    ],
    "name:pnb_x_preferred":[
        "\u0627\u0644 \u06a9\u06cc\u067e\u06cc\u0679\u0627\u0646"
    ],
    "name:pol_x_preferred":[
        "El Capitan"
    ],
    "name:por_x_preferred":[
        "El Capitan"
    ],
    "name:rus_x_preferred":[
        "\u042d\u043b\u044c-\u041a\u0430\u043f\u0438\u0442\u0430\u043d"
    ],
    "name:slk_x_preferred":[
        "El Capitan"
    ],
    "name:spa_x_preferred":[
        "El Capit\u00e1n"
    ],
    "name:swe_x_preferred":[
        "El Capitan"
    ],
    "name:tur_x_preferred":[
        "El Capitan"
    ],
    "name:ukr_x_preferred":[
        "\u0421\u043a\u0435\u043b\u044f \u0415\u043b\u044c \u041a\u0430\u043f\u0456\u0442\u0430\u043d"
    ],
    "name:vie_x_preferred":[
        "El Capitan"
    ],
    "name:zho_x_preferred":[
        "\u914b\u957f\u5ca9"
    ],
    "wof:name":"El Capitan",
    "wof:placetype":"locality"
},
  "geometry": {"coordinates":[-78.6511,21.83952],"type":"Point"}
}