{
  "type": "Feature",
  "properties": {
    "gn:admin1_code":"16",
    "gn:asciiname":"Dolores",
    "gn:country_code":"CU",
    "gn:dem":99,
    "gn:feature_class":"P",
    "gn:feature_code":"PPL",
    "gn:name":"Dolores",
    "gn:population":0,
    "gn:timezone":"America/Havana",
    "iso:country":"CU",
    "name:spa_x_preferred":[
        "Dolores"
    ],
    "name:und_x_variant":[
        "Finca Dolores del Purial",
        "Dolores del Purial"
    ],
    "wof:name":"Dolores",
    "wof:placetype":"locality"
},
  "geometry": {"coordinates":[-80.01608,22.47585],"type":"Point"}
}