{
  "type": "Feature",
  "properties": {
    "gn:admin1_code":"16",
    "gn:asciiname":"Saavedra",
    "gn:country_code":"CU",
    "gn:dem":9,
    "gn:feature_class":"P",
    "gn:feature_code":"PPLL",
    "gn:name":"Saavedra",
    "gn:population":0,
    "gn:timezone":"America/Havana",
    "iso:country":"CU",
    "name:ast_x_preferred":[
        "Saavedra"
    ],
    "name:ceb_x_preferred":[
        "Saavedra"
    ],
    "name:ces_x_preferred":[
        "Saavedra"
    ],
    "name:deu_x_preferred":[
        "Saavedra"
    ],
    "name:fra_x_preferred":[
        "Saavedra"
    ],
    "name:glg_x_preferred":[
        "Saavedra"
    ],
    "name:ita_x_preferred":[
        "Saavedra"
    ],
    "name:jpn_x_preferred":[
        "\u30b5\u30a2\u30d9\u30c9\u30e9"
    ],
    "name:nds_x_preferred":[
        "Saavedra"
    ],
    "name:nld_x_preferred":[
        "Saavedra"
    ],
    "name:por_x_preferred":[
        "Saavedra"
    ],
    "name:ron_x_preferred":[
        "Saavedra"
    ],
    "name:rus_x_preferred":[
        "\u0421\u0430\u0430\u0432\u0435\u0434\u0440\u0430"
    ],
    "name:spa_x_preferred":[
        "Saavedra"
    ],
    "name:swe_x_preferred":[
        "Saavedra"
    ],
    "name:ukr_x_preferred":[
        "\u0421\u0430\u0430\u0432\u0435\u0434\u0440\u0430"
    ],
    "wof:name":"Saavedra",
    "wof:placetype":"locality"
},
  "geometry": {"coordinates":[-80.07432,22.84003],"type":"Point"}
}