{
  "type": "Feature",
  "properties": {
    "gn:admin1_code":"14",
    "gn:asciiname":"Ramon Alto",
    "gn:country_code":"CU",
    "gn:dem":84,
    "gn:feature_class":"P",
    "gn:feature_code":"PPLL",
    "gn:name":"Ram\u00f3n Alto",
    "gn:population":0,
    "gn:timezone":"America/Havana",
    "iso:country":"CU",
    "name:spa_x_preferred":[
        "Ram\u00f3n Alto"
    ],
    "wof:name":"Ramon Alto",
    "wof:placetype":"locality"
},
  "geometry": {"coordinates":[-79.30308000000002,21.87904],"type":"Point"}
}