{
  "type": "Feature",
  "properties": {
    "gn:admin1_code":"10",
    "gn:asciiname":"Las Pailas",
    "gn:country_code":"CU",
    "gn:dem":22,
    "gn:feature_class":"P",
    "gn:feature_code":"PPLL",
    "gn:name":"Las Pailas",
    "gn:population":0,
    "gn:timezone":"America/Havana",
    "iso:country":"CU",
    "wof:name":"Las Pailas",
    "wof:placetype":"locality"
},
  "geometry": {"coordinates":[-75.18889,20.00583],"type":"Point"}
}