{
  "type": "Feature",
  "properties": {
    "gn:admin1_code":"05",
    "gn:asciiname":"Nunez",
    "gn:country_code":"CU",
    "gn:dem":42,
    "gn:feature_class":"P",
    "gn:feature_code":"PPL",
    "gn:name":"N\u00fa\u00f1ez",
    "gn:population":0,
    "gn:timezone":"America/Havana",
    "iso:country":"CU",
    "name:spa_x_preferred":[
        "N\u00fa\u00f1ez"
    ],
    "wof:name":"Nunez",
    "wof:placetype":"locality"
},
  "geometry": {"coordinates":[-78.16873000000002,21.8792],"type":"Point"}
}