{
  "type": "Feature",
  "properties": {
    "gn:admin1_code":"01",
    "gn:asciiname":"Playa El Guanal",
    "gn:country_code":"CU",
    "gn:dem":5,
    "gn:feature_class":"P",
    "gn:feature_code":"PPL",
    "gn:name":"Playa El Guanal",
    "gn:population":0,
    "gn:timezone":"America/Havana",
    "iso:country":"CU",
    "name:spa_x_preferred":[
        "Playa El Guanal"
    ],
    "wof:name":"Playa El Guanal",
    "wof:placetype":"locality"
},
  "geometry": {"coordinates":[-83.38866999999998,22.22192],"type":"Point"}
}