{
  "type": "Feature",
  "properties": {
    "gn:admin1_code":"16",
    "gn:asciiname":"Maria Luisa",
    "gn:country_code":"CU",
    "gn:dem":188,
    "gn:feature_class":"P",
    "gn:feature_code":"PPL",
    "gn:name":"Mar\u00eda Luisa",
    "gn:population":0,
    "gn:timezone":"America/Havana",
    "iso:country":"CU",
    "name:und_x_variant":[
        "Central Maria Luisa",
        "Mar\u00eda Luisa"
    ],
    "wof:name":"Maria Luisa",
    "wof:placetype":"locality"
},
  "geometry": {"coordinates":[-79.61036999999997,22.39981],"type":"Point"}
}