{
  "type": "Feature",
  "properties": {
    "gn:admin1_code":"08",
    "gn:asciiname":"Charco Azul",
    "gn:country_code":"CU",
    "gn:dem":540,
    "gn:feature_class":"P",
    "gn:feature_code":"PPL",
    "gn:name":"Charco Azul",
    "gn:population":0,
    "gn:timezone":"America/Havana",
    "iso:country":"CU",
    "name:spa_x_preferred":[
        "Charco Azul"
    ],
    "name:zho_x_preferred":[
        "\u67e5\u79d1\u963f\u82cf\u5c14\u6e7e"
    ],
    "wof:name":"Charco Azul",
    "wof:placetype":"locality"
},
  "geometry": {"coordinates":[-80.06747,21.96443],"type":"Point"}
}