{
  "type": "Feature",
  "properties": {
    "gn:admin1_code":"03",
    "gn:asciiname":"Wajay",
    "gn:country_code":"CU",
    "gn:dem":74,
    "gn:feature_class":"P",
    "gn:feature_code":"PPLL",
    "gn:name":"Wajay",
    "gn:population":0,
    "gn:timezone":"America/Havana",
    "iso:country":"CU",
    "name:spa_x_preferred":[
        "Wajay"
    ],
    "wof:name":"Wajay",
    "wof:placetype":"locality"
},
  "geometry": {"coordinates":[-81.67389,22.83944],"type":"Point"}
}