{
  "type": "Feature",
  "properties": {
    "gn:admin1_code":"12",
    "gn:asciiname":"La Gejira",
    "gn:cc2":"CU",
    "gn:country_code":"CU",
    "gn:dem":68,
    "gn:feature_class":"P",
    "gn:feature_code":"PPLL",
    "gn:name":"La Gejira",
    "gn:population":0,
    "gn:timezone":"America/Havana",
    "iso:country":"CU",
    "name:und_x_variant":[
        "La Gegira",
        "La Gejira"
    ],
    "wof:name":"La Gejira",
    "wof:placetype":"locality"
},
  "geometry": {"coordinates":[-76.31528,21.11194],"type":"Point"}
}