{
  "type": "Feature",
  "properties": {
    "gn:admin1_code":"08",
    "gn:asciiname":"La Sierrita",
    "gn:country_code":"CU",
    "gn:dem":168,
    "gn:feature_class":"P",
    "gn:feature_code":"PPL",
    "gn:name":"La Sierrita",
    "gn:population":0,
    "gn:timezone":"America/Havana",
    "iso:country":"CU",
    "name:und_x_variant":[
        "Sierra",
        "La Sierra",
        "La Sierrita"
    ],
    "wof:name":"La Sierrita",
    "wof:placetype":"locality"
},
  "geometry": {"coordinates":[-80.28346999999999,21.99387],"type":"Point"}
}