{
  "type": "Feature",
  "properties": {
    "gn:admin1_code":"AR",
    "gn:asciiname":"Vivo",
    "gn:country_code":"CU",
    "gn:dem":42,
    "gn:feature_class":"P",
    "gn:feature_code":"PPLL",
    "gn:name":"Viv\u00f3",
    "gn:population":0,
    "gn:timezone":"America/Havana",
    "iso:country":"CU",
    "name:ceb_x_preferred":[
        "Vivo"
    ],
    "name:deu_x_preferred":[
        "Vivo"
    ],
    "name:epo_x_preferred":[
        "Vivo"
    ],
    "name:fin_x_preferred":[
        "Vivo"
    ],
    "name:fra_x_preferred":[
        "Vivo"
    ],
    "name:ita_x_preferred":[
        "Vivo"
    ],
    "name:jpn_x_preferred":[
        "\u30d3\u30fc\u30dc"
    ],
    "name:nld_x_preferred":[
        "Vivo"
    ],
    "name:pol_x_preferred":[
        "Vivo"
    ],
    "name:por_x_preferred":[
        "Vivo"
    ],
    "name:spa_x_preferred":[
        "Vivo"
    ],
    "name:swe_x_preferred":[
        "Vivo"
    ],
    "wof:name":"Vivo",
    "wof:placetype":"locality"
},
  "geometry": {"coordinates":[-82.93333,22.76667],"type":"Point"}
}