{
  "type": "Feature",
  "properties": {
    "gn:admin1_code":"08",
    "gn:asciiname":"Ciego Alonso",
    "gn:country_code":"CU",
    "gn:dem":66,
    "gn:feature_class":"P",
    "gn:feature_code":"PPL",
    "gn:name":"Ciego Alonso",
    "gn:population":0,
    "gn:timezone":"America/Havana",
    "iso:country":"CU",
    "name:spa_x_preferred":[
        "Ciego Alonso"
    ],
    "wof:name":"Ciego Alonso",
    "wof:placetype":"locality"
},
  "geometry": {"coordinates":[-80.36566999999999,22.23707000000001],"type":"Point"}
}