{
  "type": "Feature",
  "properties": {
    "gn:admin1_code":"13",
    "gn:asciiname":"Vedado Seis",
    "gn:country_code":"CU",
    "gn:dem":63,
    "gn:feature_class":"P",
    "gn:feature_code":"PPL",
    "gn:name":"Vedado Seis",
    "gn:population":0,
    "gn:timezone":"America/Havana",
    "iso:country":"CU",
    "name:spa_x_preferred":[
        "Vedado Seis"
    ],
    "name:und_x_variant":[
        "Vedado"
    ],
    "wof:name":"Vedado Seis",
    "wof:placetype":"locality"
},
  "geometry": {"coordinates":[-76.50825999999998,21.05506],"type":"Point"}
}