{
  "type": "Feature",
  "properties": {
    "iso:country":"CU",
    "name:fra_x_preferred":[
        "El Palmar"
    ],
    "name:lit_x_preferred":[
        "El Palmaras"
    ],
    "name:spa_x_preferred":[
        "El Palmar"
    ],
    "name:unk_x_variant":[
        "Palmar"
    ],
    "qs:gn_country":"CU",
    "qs:gn_fcode":"PPLX",
    "qs:gn_pop":0,
    "qs:name":"El Palmar",
    "qs:name_adm0":"Cuba",
    "qs:name_adm1":"Ciudad de la Habana",
    "qs:photos":369,
    "qs:photos_1k":75,
    "qs:photos_9k":2,
    "qs:photos_9r":5,
    "qs:photos_all":369,
    "qs:photos_sr":6,
    "qs:placetype":"Suburb",
    "qs:pop_sr":"0",
    "qs:woe_adm0":23424793,
    "wof:name":"El Palmar",
    "wof:placetype":"neighbourhood"
},
  "geometry": {"coordinates":[-82.42778,23.0625],"type":"Point"}
}