{
  "type": "Feature",
  "properties": {
    "gn:admin1_code":"05",
    "gn:asciiname":"Santa Elia",
    "gn:country_code":"CU",
    "gn:dem":86,
    "gn:feature_class":"P",
    "gn:feature_code":"PPLL",
    "gn:name":"Santa Elia",
    "gn:population":0,
    "gn:timezone":"America/Havana",
    "iso:country":"CU",
    "name:spa_x_preferred":[
        "Santa Elia"
    ],
    "wof:name":"Santa Elia",
    "wof:placetype":"locality"
},
  "geometry": {"coordinates":[-77.98427,21.18867],"type":"Point"}
}