{
  "type": "Feature",
  "properties": {
    "gn:admin1_code":"10",
    "gn:asciiname":"Mandinga",
    "gn:country_code":"CU",
    "gn:dem":252,
    "gn:feature_class":"P",
    "gn:feature_code":"PPL",
    "gn:name":"Mandinga",
    "gn:population":0,
    "gn:timezone":"America/Havana",
    "iso:country":"CU",
    "name:ceb_x_preferred":[
        "Mandinga"
    ],
    "name:ita_x_preferred":[
        "Mandinga"
    ],
    "name:por_x_preferred":[
        "Mandinga"
    ],
    "name:spa_x_preferred":[
        "Mandinga"
    ],
    "name:swe_x_preferred":[
        "Mandinga"
    ],
    "wof:name":"Mandinga",
    "wof:placetype":"locality"
},
  "geometry": {"coordinates":[-74.32042,20.27865],"type":"Point"}
}