{
  "type": "Feature",
  "properties": {
    "gn:admin1_code":"08",
    "gn:asciiname":"Lagunas Los Hoyos",
    "gn:country_code":"CU",
    "gn:dem":29,
    "gn:feature_class":"P",
    "gn:feature_code":"PPLL",
    "gn:name":"Lagunas Los Hoyos",
    "gn:population":0,
    "gn:timezone":"America/Havana",
    "iso:country":"CU",
    "wof:name":"Lagunas Los Hoyos",
    "wof:placetype":"locality"
},
  "geometry": {"coordinates":[-80.62860999999999,22.21472],"type":"Point"}
}