{
  "type": "Feature",
  "properties": {
    "gn:admin1_code":"13",
    "gn:asciiname":"Las Peloncitas",
    "gn:country_code":"CU",
    "gn:dem":56,
    "gn:feature_class":"P",
    "gn:feature_code":"PPLL",
    "gn:name":"Las Peloncitas",
    "gn:population":0,
    "gn:timezone":"America/Havana",
    "iso:country":"CU",
    "name:spa_x_preferred":[
        "Las Peloncitas"
    ],
    "name:und_x_variant":[
        "Peloncitas"
    ],
    "wof:name":"Las Peloncitas",
    "wof:placetype":"locality"
},
  "geometry": {"coordinates":[-77.00794999999999,20.86089],"type":"Point"}
}