{
  "type": "Feature",
  "properties": {
    "gn:admin1_code":"08",
    "gn:asciiname":"Manacas",
    "gn:country_code":"CU",
    "gn:dem":35,
    "gn:feature_class":"P",
    "gn:feature_code":"PPL",
    "gn:name":"Manacas",
    "gn:population":0,
    "gn:timezone":"America/Havana",
    "iso:country":"CU",
    "name:spa_x_preferred":[
        "Manacas"
    ],
    "wof:name":"Manacas",
    "wof:placetype":"locality"
},
  "geometry": {"coordinates":[-80.38280999999998,22.43149],"type":"Point"}
}