{
  "type": "Feature",
  "properties": {
    "gn:admin1_code":"AR",
    "gn:asciiname":"Florencio Morejon",
    "gn:country_code":"CU",
    "gn:dem":82,
    "gn:feature_class":"P",
    "gn:feature_code":"PPL",
    "gn:name":"Florencio Morej\u00f3n",
    "gn:population":0,
    "gn:timezone":"America/Havana",
    "iso:country":"CU",
    "name:spa_x_preferred":[
        "Florencio Morej\u00f3n"
    ],
    "wof:name":"Florencio Morejon",
    "wof:placetype":"locality"
},
  "geometry": {"coordinates":[-83.20067,22.67867],"type":"Point"}
}