{
  "type": "Feature",
  "properties": {
    "gn:admin1_code":"08",
    "gn:asciiname":"El Guabairo",
    "gn:country_code":"CU",
    "gn:dem":84,
    "gn:feature_class":"P",
    "gn:feature_code":"PPLL",
    "gn:name":"El Guabairo",
    "gn:population":0,
    "gn:timezone":"America/Havana",
    "iso:country":"CU",
    "name:spa_x_preferred":[
        "El Guabairo"
    ],
    "wof:name":"El Guabairo",
    "wof:placetype":"locality"
},
  "geometry": {"coordinates":[-80.29461999999999,22.17757000000001],"type":"Point"}
}