{
  "type": "Feature",
  "properties": {
    "gn:admin1_code":"MA",
    "gn:asciiname":"Juan Borrel",
    "gn:country_code":"CU",
    "gn:dem":10,
    "gn:feature_class":"P",
    "gn:feature_code":"PPL",
    "gn:name":"Juan Borrel",
    "gn:population":0,
    "gn:timezone":"America/Havana",
    "iso:country":"CU",
    "name:spa_x_preferred":[
        "Juan Borrel"
    ],
    "wof:name":"Juan Borrel",
    "wof:placetype":"locality"
},
  "geometry": {"coordinates":[-82.05454,22.71219],"type":"Point"}
}