{
  "type": "Feature",
  "properties": {
    "gn:admin1_code":"15",
    "gn:asciiname":"Los Jibaros",
    "gn:country_code":"CU",
    "gn:dem":22,
    "gn:feature_class":"P",
    "gn:feature_code":"PPL",
    "gn:name":"Los Jibaros",
    "gn:population":0,
    "gn:timezone":"America/Havana",
    "iso:country":"CU",
    "name:spa_x_preferred":[
        "Los Jibaros"
    ],
    "wof:name":"Los Jibaros",
    "wof:placetype":"locality"
},
  "geometry": {"coordinates":[-76.34132,19.98574],"type":"Point"}
}