{
  "type": "Feature",
  "properties": {
    "gn:admin1_code":"12",
    "gn:asciiname":"Casa Colorada",
    "gn:country_code":"CU",
    "gn:dem":122,
    "gn:feature_class":"P",
    "gn:feature_code":"PPL",
    "gn:name":"Casa Colorada",
    "gn:population":0,
    "gn:timezone":"America/Havana",
    "iso:country":"CU",
    "name:spa_x_preferred":[
        "Casa Colorada"
    ],
    "wof:name":"Casa Colorada",
    "wof:placetype":"locality"
},
  "geometry": {"coordinates":[-76.41498,20.98698],"type":"Point"}
}