{
  "type": "Feature",
  "properties": {
    "gn:admin1_code":"15",
    "gn:asciiname":"Gran Piedra",
    "gn:country_code":"CU",
    "gn:dem":1112,
    "gn:feature_class":"P",
    "gn:feature_code":"PPL",
    "gn:name":"Gran Piedra",
    "gn:population":0,
    "gn:timezone":"America/Havana",
    "iso:country":"CU",
    "name:spa_x_preferred":[
        "Gran Piedra"
    ],
    "wof:name":"Gran Piedra",
    "wof:placetype":"locality"
},
  "geometry": {"coordinates":[-75.62272,20.01044],"type":"Point"}
}