{
  "type": "Feature",
  "properties": {
    "gn:admin1_code":"03",
    "gn:asciiname":"Limonar",
    "gn:country_code":"CU",
    "gn:dem":71,
    "gn:feature_class":"P",
    "gn:feature_code":"PPLA2",
    "gn:name":"Limonar",
    "gn:population":25421,
    "gn:timezone":"America/Havana",
    "iso:country":"CU",
    "name:und_x_variant":[
        "Guamacaro",
        "Limonar"
    ],
    "wof:name":"Limonar",
    "wof:placetype":"locality",
    "wof:population":25421
},
  "geometry": {"coordinates":[-81.41059,22.95035],"type":"Point"}
}