{
  "type": "Feature",
  "properties": {
    "gn:admin1_code":"03",
    "gn:asciiname":"Limonar",
    "gn:country_code":"CU",
    "gn:dem":71,
    "gn:feature_class":"P",
    "gn:feature_code":"PPLA2",
    "gn:name":"Limonar",
    "gn:population":25421,
    "gn:timezone":"America/Havana",
    "iso:country":"CU",
    "name:fra_x_preferred":[
        "Limonar"
    ],
    "name:hat_x_preferred":[
        "Limonar"
    ],
    "name:ita_x_preferred":[
        "Limonar"
    ],
    "name:kat_x_preferred":[
        "\u10da\u10d8\u10db\u10dd\u10dc\u10d0\u10e0\u10d8"
    ],
    "name:por_x_preferred":[
        "Limonar"
    ],
    "name:sco_x_preferred":[
        "Limonar"
    ],
    "name:spa_x_preferred":[
        "Limonar"
    ],
    "name:und_x_variant":[
        "Guamacaro",
        "Limonar"
    ],
    "name:vie_x_preferred":[
        "Limonar"
    ],
    "name:zho_x_preferred":[
        "\u5229\u83ab\u7d0d\u723e"
    ],
    "wof:name":"Limonar",
    "wof:placetype":"locality",
    "wof:population":25421
},
  "geometry": {"coordinates":[-81.41059,22.95035],"type":"Point"}
}