{
  "type": "Feature",
  "properties": {
    "gn:admin1_code":"09",
    "gn:asciiname":"Fajardo",
    "gn:cc2":"CU",
    "gn:country_code":"CU",
    "gn:dem":23,
    "gn:feature_class":"P",
    "gn:feature_code":"PPLL",
    "gn:name":"Fajardo",
    "gn:population":0,
    "gn:timezone":"America/Havana",
    "iso:country":"CU",
    "name:und_x_variant":[
        "Graniche",
        "Fajardo"
    ],
    "wof:name":"Fajardo",
    "wof:placetype":"locality"
},
  "geometry": {"coordinates":[-76.71528000000001,20.55139],"type":"Point"}
}