{
  "type": "Feature",
  "properties": {
    "gn:admin1_code":"09",
    "gn:asciiname":"El Jardin",
    "gn:country_code":"CU",
    "gn:dem":96,
    "gn:feature_class":"P",
    "gn:feature_code":"PPLL",
    "gn:name":"El Jard\u00edn",
    "gn:population":0,
    "gn:timezone":"America/Havana",
    "iso:country":"CU",
    "wof:name":"El Jardin",
    "wof:placetype":"locality"
},
  "geometry": {"coordinates":[-76.45,20.46667],"type":"Point"}
}