{
  "type": "Feature",
  "properties": {
    "gn:admin1_code":"07",
    "gn:asciiname":"La Nenita",
    "gn:country_code":"CU",
    "gn:dem":58,
    "gn:feature_class":"P",
    "gn:feature_code":"PPL",
    "gn:name":"La Nenita",
    "gn:population":0,
    "gn:timezone":"America/Havana",
    "iso:country":"CU",
    "name:spa_x_preferred":[
        "La Nenita"
    ],
    "wof:name":"La Nenita",
    "wof:placetype":"locality"
},
  "geometry": {"coordinates":[-79.00194999999999,22.20705],"type":"Point"}
}