{
  "type": "Feature",
  "properties": {
    "gn:admin1_code":"12",
    "gn:asciiname":"Camarones",
    "gn:country_code":"CU",
    "gn:dem":192,
    "gn:feature_class":"P",
    "gn:feature_code":"PPL",
    "gn:name":"Camarones",
    "gn:population":0,
    "gn:timezone":"America/Havana",
    "iso:country":"CU",
    "name:ceb_x_preferred":[
        "Camarones"
    ],
    "name:ces_x_preferred":[
        "Camarones"
    ],
    "name:deu_x_preferred":[
        "Camarones"
    ],
    "name:fra_x_preferred":[
        "Camarones"
    ],
    "name:kat_x_preferred":[
        "\u10d9\u10d0\u10db\u10d0\u10e0\u10dd\u10dc\u10d4\u10e1\u10d8"
    ],
    "name:nld_x_preferred":[
        "Camarones"
    ],
    "name:rus_x_preferred":[
        "\u041a\u0430\u043c\u0430\u0440\u043e\u043d\u0435\u0441"
    ],
    "name:sco_x_preferred":[
        "Camarones"
    ],
    "name:spa_x_preferred":[
        "Camarones"
    ],
    "name:swe_x_preferred":[
        "Camarones"
    ],
    "wof:name":"Camarones",
    "wof:placetype":"locality"
},
  "geometry": {"coordinates":[-75.61214,20.51291],"type":"Point"}
}