{
  "type": "Feature",
  "properties": {
    "gn:admin1_code":"12",
    "gn:asciiname":"Camarones",
    "gn:country_code":"CU",
    "gn:dem":192,
    "gn:feature_class":"P",
    "gn:feature_code":"PPL",
    "gn:name":"Camarones",
    "gn:population":0,
    "gn:timezone":"America/Havana",
    "iso:country":"CU",
    "name:spa_x_preferred":[
        "Camarones"
    ],
    "wof:name":"Camarones",
    "wof:placetype":"locality"
},
  "geometry": {"coordinates":[-75.61214,20.51291],"type":"Point"}
}