{
  "type": "Feature",
  "properties": {
    "gn:admin1_code":"05",
    "gn:asciiname":"La Habana",
    "gn:country_code":"CU",
    "gn:dem":91,
    "gn:feature_class":"P",
    "gn:feature_code":"PPLL",
    "gn:name":"La Habana",
    "gn:population":0,
    "gn:timezone":"America/Havana",
    "iso:country":"CU",
    "name:spa_x_preferred":[
        "La Habana"
    ],
    "wof:name":"La Habana",
    "wof:placetype":"locality"
},
  "geometry": {"coordinates":[-77.67073000000001,21.48412],"type":"Point"}
}