{
  "type": "Feature",
  "properties": {
    "gn:admin1_code":"16",
    "gn:asciiname":"Hatillo",
    "gn:country_code":"CU",
    "gn:dem":116,
    "gn:feature_class":"P",
    "gn:feature_code":"PPL",
    "gn:name":"Hatillo",
    "gn:population":0,
    "gn:timezone":"America/Havana",
    "iso:country":"CU",
    "name:spa_x_preferred":[
        "Hatillo"
    ],
    "wof:name":"Hatillo",
    "wof:placetype":"locality"
},
  "geometry": {"coordinates":[-80.00351999999999,22.51058],"type":"Point"}
}