{
  "type": "Feature",
  "properties": {
    "gn:admin1_code":"AR",
    "gn:asciiname":"Cataluna",
    "gn:country_code":"CU",
    "gn:dem":5,
    "gn:feature_class":"P",
    "gn:feature_code":"PPLL",
    "gn:name":"Catalu\u00f1a",
    "gn:population":0,
    "gn:timezone":"America/Havana",
    "iso:country":"CU",
    "name:spa_x_preferred":[
        "Catalu\u00f1a"
    ],
    "wof:name":"Cataluna",
    "wof:placetype":"locality"
},
  "geometry": {"coordinates":[-82.61203,22.72629],"type":"Point"}
}