{
  "type": "Feature",
  "properties": {
    "gn:admin1_code":"01",
    "gn:asciiname":"Saludes",
    "gn:cc2":"CU",
    "gn:country_code":"CU",
    "gn:dem":49,
    "gn:feature_class":"P",
    "gn:feature_code":"PPLL",
    "gn:name":"Saludes",
    "gn:population":0,
    "gn:timezone":"America/Havana",
    "iso:country":"CU",
    "name:und_x_variant":[
        "Salude",
        "Saludes"
    ],
    "wof:name":"Saludes",
    "wof:placetype":"locality"
},
  "geometry": {"coordinates":[-83.78333000000001,22.35],"type":"Point"}
}