{
  "type": "Feature",
  "properties": {
    "gn:admin1_code":"01",
    "gn:asciiname":"La Jocuma",
    "gn:country_code":"CU",
    "gn:dem":15,
    "gn:feature_class":"P",
    "gn:feature_code":"PPLL",
    "gn:name":"La Jocuma",
    "gn:population":0,
    "gn:timezone":"America/Havana",
    "iso:country":"CU",
    "wof:name":"La Jocuma",
    "wof:placetype":"locality"
},
  "geometry": {"coordinates":[-83.45,22.35],"type":"Point"}
}