{
  "type": "Feature",
  "properties": {
    "gn:admin1_code":"15",
    "gn:asciiname":"El Pozo Dos",
    "gn:country_code":"CU",
    "gn:dem":148,
    "gn:feature_class":"P",
    "gn:feature_code":"PPL",
    "gn:name":"El Pozo Dos",
    "gn:population":0,
    "gn:timezone":"America/Havana",
    "iso:country":"CU",
    "name:und_x_variant":[
        "El Pozo",
        "El Pozo Dos"
    ],
    "wof:name":"El Pozo Dos",
    "wof:placetype":"locality"
},
  "geometry": {"coordinates":[-75.89619999999999,20.24325],"type":"Point"}
}