{
  "type": "Feature",
  "properties": {
    "gn:admin1_code":"13",
    "gn:asciiname":"Santa Amalia",
    "gn:country_code":"CU",
    "gn:dem":14,
    "gn:feature_class":"P",
    "gn:feature_code":"PPL",
    "gn:name":"Santa Amalia",
    "gn:population":0,
    "gn:timezone":"America/Havana",
    "iso:country":"CU",
    "name:spa_x_preferred":[
        "Santa Amalia"
    ],
    "wof:name":"Santa Amalia",
    "wof:placetype":"locality"
},
  "geometry": {"coordinates":[-77.67411,20.765],"type":"Point"}
}