{
  "type": "Feature",
  "properties": {
    "gn:admin1_code":"07",
    "gn:asciiname":"Vista Alegre",
    "gn:country_code":"CU",
    "gn:dem":12,
    "gn:feature_class":"P",
    "gn:feature_code":"PPL",
    "gn:name":"Vista Alegre",
    "gn:population":0,
    "gn:timezone":"America/Havana",
    "iso:country":"CU",
    "wof:name":"Vista Alegre",
    "wof:placetype":"locality"
},
  "geometry": {"coordinates":[-78.73194000000002,22.14389],"type":"Point"}
}