{
  "type": "Feature",
  "properties": {
    "gn:admin1_code":"09",
    "gn:asciiname":"Casimiro",
    "gn:country_code":"CU",
    "gn:dem":27,
    "gn:feature_class":"P",
    "gn:feature_code":"PPL",
    "gn:name":"Casimiro",
    "gn:population":0,
    "gn:timezone":"America/Havana",
    "iso:country":"CU",
    "name:ceb_x_preferred":[
        "Casimiro"
    ],
    "name:deu_x_preferred":[
        "Casimiro"
    ],
    "name:por_x_preferred":[
        "Casimiro"
    ],
    "name:spa_x_preferred":[
        "Casimiro"
    ],
    "name:swe_x_preferred":[
        "Casimiro"
    ],
    "wof:name":"Casimiro",
    "wof:placetype":"locality"
},
  "geometry": {"coordinates":[-76.76300000000001,20.49284],"type":"Point"}
}