{
  "type": "Feature",
  "properties": {
    "gn:admin1_code":"05",
    "gn:asciiname":"San Felipe",
    "gn:country_code":"CU",
    "gn:dem":60,
    "gn:feature_class":"P",
    "gn:feature_code":"PPLL",
    "gn:name":"San Felipe",
    "gn:population":0,
    "gn:timezone":"America/Havana",
    "iso:country":"CU",
    "wof:name":"San Felipe",
    "wof:placetype":"locality"
},
  "geometry": {"coordinates":[-77.76666999999998,20.86667000000001],"type":"Point"}
}