{
  "type": "Feature",
  "properties": {
    "gn:admin1_code":"05",
    "gn:asciiname":"San Felipe",
    "gn:country_code":"CU",
    "gn:dem":60,
    "gn:feature_class":"P",
    "gn:feature_code":"PPLL",
    "gn:name":"San Felipe",
    "gn:population":0,
    "gn:timezone":"America/Havana",
    "iso:country":"CU",
    "name:deu_x_preferred":[
        "San Felipe"
    ],
    "name:fas_x_preferred":[
        "\u0633\u0627\u0646 \u0641\u06cc\u0644\u06cc\u067e\u0647"
    ],
    "name:heb_x_preferred":[
        "\u05e1\u05df \u05e4\u05dc\u05d9\u05e4\u05d4"
    ],
    "name:hun_x_preferred":[
        "San Felipe"
    ],
    "wof:name":"San Felipe",
    "wof:placetype":"locality"
},
  "geometry": {"coordinates":[-77.76667,20.86667],"type":"Point"}
}