{
  "type": "Feature",
  "properties": {
    "gn:admin1_code":"05",
    "gn:asciiname":"Los Guiros",
    "gn:country_code":"CU",
    "gn:dem":52,
    "gn:feature_class":"P",
    "gn:feature_code":"PPLL",
    "gn:name":"Los G\u00fciros",
    "gn:population":0,
    "gn:timezone":"America/Havana",
    "iso:country":"CU",
    "name:spa_x_preferred":[
        "Los G\u00fciros"
    ],
    "wof:name":"Los Guiros",
    "wof:placetype":"locality"
},
  "geometry": {"coordinates":[-78.18638,21.27866],"type":"Point"}
}