{
  "type": "Feature",
  "properties": {
    "gn:admin1_code":"03",
    "gn:asciiname":"Santa Rosa",
    "gn:country_code":"CU",
    "gn:dem":16,
    "gn:feature_class":"P",
    "gn:feature_code":"PPLL",
    "gn:name":"Santa Rosa",
    "gn:population":0,
    "gn:timezone":"America/Havana",
    "iso:country":"CU",
    "wof:name":"Santa Rosa",
    "wof:placetype":"locality"
},
  "geometry": {"coordinates":[-81.01666999999998,22.48333],"type":"Point"}
}