{
  "type": "Feature",
  "properties": {
    "gn:admin1_code":"09",
    "gn:asciiname":"El Horno",
    "gn:country_code":"CU",
    "gn:dem":121,
    "gn:feature_class":"P",
    "gn:feature_code":"PPL",
    "gn:name":"El Horno",
    "gn:population":0,
    "gn:timezone":"America/Havana",
    "iso:country":"CU",
    "name:und_x_variant":[
        "Horno",
        "El Hornos",
        "Hornos",
        "El Horno"
    ],
    "wof:name":"El Horno",
    "wof:placetype":"locality"
},
  "geometry": {"coordinates":[-76.56493,20.30747],"type":"Point"}
}