{
  "type": "Feature",
  "properties": {
    "gn:admin1_code":"15",
    "gn:asciiname":"Mayo",
    "gn:country_code":"CU",
    "gn:dem":108,
    "gn:feature_class":"P",
    "gn:feature_code":"PPL",
    "gn:name":"Mayo",
    "gn:population":0,
    "gn:timezone":"America/Havana",
    "iso:country":"CU",
    "wof:name":"Mayo",
    "wof:placetype":"locality"
},
  "geometry": {"coordinates":[-75.96666999999999,20.48333],"type":"Point"}
}