{
  "type": "Feature",
  "properties": {
    "gn:admin1_code":"15",
    "gn:asciiname":"Mayo",
    "gn:country_code":"CU",
    "gn:dem":108,
    "gn:feature_class":"P",
    "gn:feature_code":"PPL",
    "gn:name":"Mayo",
    "gn:population":0,
    "gn:timezone":"America/Havana",
    "iso:country":"CU",
    "name:bre_x_preferred":[
        "Mayo"
    ],
    "name:cat_x_preferred":[
        "Mayo"
    ],
    "name:ceb_x_preferred":[
        "Mayo"
    ],
    "name:ces_x_preferred":[
        "Mayo"
    ],
    "name:cym_x_preferred":[
        "Mayo"
    ],
    "name:deu_x_preferred":[
        "Mayo"
    ],
    "name:fas_x_preferred":[
        "\u0645\u0627\u06cc\u0648"
    ],
    "name:fin_x_preferred":[
        "Mayo"
    ],
    "name:fra_x_preferred":[
        "Mayo"
    ],
    "name:heb_x_preferred":[
        "\u05de\u05d0\u05d9\u05d5"
    ],
    "name:ita_x_preferred":[
        "Mayo"
    ],
    "name:jpn_x_preferred":[
        "\u30e1\u30a4\u30e8\u30fc"
    ],
    "name:nld_x_preferred":[
        "Mayo"
    ],
    "name:pol_x_preferred":[
        "Mayo"
    ],
    "name:por_x_preferred":[
        "Mayo"
    ],
    "name:rus_x_preferred":[
        "\u041c\u0430\u0439\u043e"
    ],
    "name:spa_x_preferred":[
        "Mayo"
    ],
    "name:srp_x_preferred":[
        "\u041c\u0435\u0458\u043e"
    ],
    "name:swe_x_preferred":[
        "Mayo"
    ],
    "name:vol_x_preferred":[
        "Mayo"
    ],
    "wof:name":"Mayo",
    "wof:placetype":"locality"
},
  "geometry": {"coordinates":[-75.96666999999999,20.48333],"type":"Point"}
}