{
  "type": "Feature",
  "properties": {
    "gn:admin1_code":"03",
    "gn:asciiname":"Perseverancia",
    "gn:country_code":"CU",
    "gn:dem":28,
    "gn:feature_class":"P",
    "gn:feature_code":"PPL",
    "gn:name":"Perseverancia",
    "gn:population":0,
    "gn:timezone":"America/Havana",
    "iso:country":"CU",
    "wof:name":"Perseverancia",
    "wof:placetype":"locality"
},
  "geometry": {"coordinates":[-81.61667,22.76667],"type":"Point"}
}