{
  "type": "Feature",
  "properties": {
    "gn:admin1_code":"03",
    "gn:asciiname":"San Armando",
    "gn:country_code":"CU",
    "gn:dem":107,
    "gn:feature_class":"P",
    "gn:feature_code":"PPLL",
    "gn:name":"San Armando",
    "gn:population":0,
    "gn:timezone":"America/Havana",
    "iso:country":"CU",
    "wof:name":"San Armando",
    "wof:placetype":"locality"
},
  "geometry": {"coordinates":[-81.49361,22.96472],"type":"Point"}
}