{
  "type": "Feature",
  "properties": {
    "gn:admin1_code":"16",
    "gn:asciiname":"Estancia Vieja",
    "gn:country_code":"CU",
    "gn:dem":90,
    "gn:feature_class":"P",
    "gn:feature_code":"PPL",
    "gn:name":"Estancia Vieja",
    "gn:population":0,
    "gn:timezone":"America/Havana",
    "iso:country":"CU",
    "name:spa_x_preferred":[
        "Estancia Vieja"
    ],
    "wof:name":"Estancia Vieja",
    "wof:placetype":"locality"
},
  "geometry": {"coordinates":[-79.90316,22.52708],"type":"Point"}
}