{
  "type": "Feature",
  "properties": {
    "gn:admin1_code":"MA",
    "gn:asciiname":"Anita",
    "gn:country_code":"CU",
    "gn:dem":87,
    "gn:feature_class":"P",
    "gn:feature_code":"PPLL",
    "gn:name":"Anita",
    "gn:population":0,
    "gn:timezone":"America/Havana",
    "iso:country":"CU",
    "name:ceb_x_preferred":[
        "Anita"
    ],
    "name:dan_x_preferred":[
        "Anita"
    ],
    "name:deu_x_preferred":[
        "Anita"
    ],
    "name:fin_x_preferred":[
        "Anita"
    ],
    "name:fra_x_preferred":[
        "Anita"
    ],
    "name:ita_x_preferred":[
        "Anita"
    ],
    "name:jpn_x_preferred":[
        "\u30a2\u30cb\u30bf"
    ],
    "name:nld_x_preferred":[
        "Anita"
    ],
    "name:por_x_preferred":[
        "Anita"
    ],
    "name:rus_x_preferred":[
        "\u0410\u043d\u0438\u0442\u0430"
    ],
    "name:swe_x_preferred":[
        "Anita"
    ],
    "wof:name":"Anita",
    "wof:placetype":"locality"
},
  "geometry": {"coordinates":[-82.43333,22.93333],"type":"Point"}
}