{
  "type": "Feature",
  "properties": {
    "gn:admin1_code":"05",
    "gn:asciiname":"Alberto Becerra",
    "gn:country_code":"CU",
    "gn:dem":68,
    "gn:feature_class":"P",
    "gn:feature_code":"PPL",
    "gn:name":"Alberto Becerra",
    "gn:population":0,
    "gn:timezone":"America/Havana",
    "iso:country":"CU",
    "name:spa_x_preferred":[
        "Alberto Becerra"
    ],
    "wof:name":"Alberto Becerra",
    "wof:placetype":"locality"
},
  "geometry": {"coordinates":[-78.14974000000002,21.44761],"type":"Point"}
}