{
  "type": "Feature",
  "properties": {
    "gn:admin1_code":"03",
    "gn:asciiname":"San Juan Nepomuceno",
    "gn:country_code":"CU",
    "gn:dem":17,
    "gn:feature_class":"P",
    "gn:feature_code":"PPLL",
    "gn:name":"San Juan Nepomuceno",
    "gn:population":0,
    "gn:timezone":"America/Havana",
    "iso:country":"CU",
    "name:ceb_x_preferred":[
        "San Juan Nepomuceno"
    ],
    "name:deu_x_preferred":[
        "San Juan Nepomuceno"
    ],
    "name:ita_x_preferred":[
        "San Juan Nepomuceno"
    ],
    "name:spa_x_preferred":[
        "Juan Nepomuceno"
    ],
    "name:swe_x_preferred":[
        "San Juan Nepomuceno"
    ],
    "name:vie_x_preferred":[
        "San Juan Nepomuceno"
    ],
    "wof:name":"San Juan Nepomuceno",
    "wof:placetype":"locality"
},
  "geometry": {"coordinates":[-80.81667,22.95],"type":"Point"}
}