{
  "type": "Feature",
  "properties": {
    "gn:admin1_code":"12",
    "gn:asciiname":"Paincerias",
    "gn:country_code":"CU",
    "gn:dem":21,
    "gn:feature_class":"P",
    "gn:feature_code":"PPL",
    "gn:name":"Paincerias",
    "gn:population":0,
    "gn:timezone":"America/Havana",
    "iso:country":"CU",
    "name:spa_x_preferred":[
        "Paincerias"
    ],
    "name:und_x_variant":[
        "Painseira",
        "Painsera"
    ],
    "wof:name":"Paincerias",
    "wof:placetype":"locality"
},
  "geometry": {"coordinates":[-75.59884,21.01978],"type":"Point"}
}