{
  "type": "Feature",
  "properties": {
    "gn:admin1_code":"10",
    "gn:asciiname":"Arroyo del Perro",
    "gn:country_code":"CU",
    "gn:dem":395,
    "gn:feature_class":"P",
    "gn:feature_code":"PPL",
    "gn:name":"Arroyo del Perro",
    "gn:population":0,
    "gn:timezone":"America/Havana",
    "iso:country":"CU",
    "name:spa_x_preferred":[
        "Arroyo del Perro"
    ],
    "wof:name":"Arroyo del Perro",
    "wof:placetype":"locality"
},
  "geometry": {"coordinates":[-74.55821999999998,20.30519],"type":"Point"}
}