{
  "type": "Feature",
  "properties": {
    "gn:admin1_code":"10",
    "gn:asciiname":"La Amelia",
    "gn:country_code":"CU",
    "gn:dem":537,
    "gn:feature_class":"P",
    "gn:feature_code":"PPLL",
    "gn:name":"La Amelia",
    "gn:population":0,
    "gn:timezone":"America/Havana",
    "iso:country":"CU",
    "name:ceb_x_preferred":[
        "La Amelia"
    ],
    "name:ita_x_preferred":[
        "La Amelia"
    ],
    "name:spa_x_preferred":[
        "La Amelia"
    ],
    "name:swe_x_preferred":[
        "La Amelia"
    ],
    "wof:name":"La Amelia",
    "wof:placetype":"locality"
},
  "geometry": {"coordinates":[-75.24733000000001,20.35043],"type":"Point"}
}