{
  "type": "Feature",
  "properties": {
    "gn:admin1_code":"16",
    "gn:asciiname":"El Roque",
    "gn:country_code":"CU",
    "gn:dem":72,
    "gn:feature_class":"P",
    "gn:feature_code":"PPL",
    "gn:name":"El Roque",
    "gn:population":0,
    "gn:timezone":"America/Havana",
    "iso:country":"CU",
    "name:spa_x_preferred":[
        "El Roque"
    ],
    "wof:name":"El Roque",
    "wof:placetype":"locality"
},
  "geometry": {"coordinates":[-80.39986,22.62418],"type":"Point"}
}