{
  "type": "Feature",
  "properties": {
    "gn:admin1_code":"12",
    "gn:asciiname":"Algaroba",
    "gn:country_code":"CU",
    "gn:dem":99,
    "gn:feature_class":"P",
    "gn:feature_code":"PPL",
    "gn:name":"Algaroba",
    "gn:population":0,
    "gn:timezone":"America/Havana",
    "iso:country":"CU",
    "name:spa_x_preferred":[
        "Algaroba"
    ],
    "wof:name":"Algaroba",
    "wof:placetype":"locality"
},
  "geometry": {"coordinates":[-76.1849,20.94235],"type":"Point"}
}