{
  "type": "Feature",
  "properties": {
    "gn:gn_country":"CU",
    "gn:gn_fcode":"PPLX",
    "gn:gn_pop":0,
    "iso:country":"CU",
    "name:spa_x_preferred":[
        "Reparto Fomento"
    ],
    "name:unk_x_variant":[
        "Reparto Fomento"
    ],
    "qs:gn_fcode":"PPLX",
    "qs:gn_local":0,
    "qs:gn_namadm1":"15",
    "qs:gn_name":"Reparto Fomento",
    "qs:local_max":2139,
    "qs:local_sum":5427,
    "qs:localhoods":10,
    "qs:name":"Reparto Fomento",
    "qs:name_adm0":"Cuba",
    "qs:name_adm1":"Santiago de Cuba",
    "qs:name_local":"Santiago de Cuba",
    "qs:photo_max":130,
    "qs:photo_sum":785,
    "qs:placetype":"Suburb",
    "qs:quad_count":27,
    "qs:woe_adm0":23424793,
    "qs:woe_adm1":2345119,
    "qs:woe_adm2":0,
    "qs:woe_lau":0,
    "qs:woe_local":68043,
    "qs:woe_ver":"7.10.0",
    "qs_pg:aaroncc":"CU",
    "qs_pg:gn_country":"CU",
    "qs_pg:gn_fcode":"PPLX",
    "qs_pg:gn_pop":0,
    "qs_pg:name":"Reparto Fomento",
    "qs_pg:name_adm0":"Cuba",
    "qs_pg:name_adm1":"Santiago de Cuba",
    "qs_pg:photos":401,
    "qs_pg:photos_1k":81,
    "qs_pg:photos_9k":2,
    "qs_pg:photos_9r":5,
    "qs_pg:photos_all":401,
    "qs_pg:photos_sr":6,
    "qs_pg:pop_sr":0,
    "qs_pg:qs_pg_placetype":"neighbourhood",
    "qs_pg:qs_pg_placetype_gp":"Suburb",
    "qs_pg:woe_adm0":23424793,
    "wof:lang":[
        "spa"
    ],
    "wof:name":"Reparto Fomento",
    "wof:placetype":"neighbourhood"
},
  "geometry": {"coordinates":[-75.822177,20.027811],"type":"Point"}
}