{
  "type": "Feature",
  "properties": {
    "gn:admin1_code":"12",
    "gn:asciiname":"Brinquin",
    "gn:country_code":"CU",
    "gn:dem":14,
    "gn:feature_class":"P",
    "gn:feature_code":"PPLL",
    "gn:name":"Brinquin",
    "gn:population":0,
    "gn:timezone":"America/Havana",
    "iso:country":"CU",
    "wof:name":"Brinquin",
    "wof:placetype":"locality"
},
  "geometry": {"coordinates":[-74.75,20.61667000000001],"type":"Point"}
}