{
  "type": "Feature",
  "properties": {
    "gn:admin1_code":"05",
    "gn:asciiname":"Las Piedras de Zayas",
    "gn:country_code":"CU",
    "gn:dem":52,
    "gn:feature_class":"P",
    "gn:feature_code":"PPLL",
    "gn:name":"Las Piedras de Zayas",
    "gn:population":0,
    "gn:timezone":"America/Havana",
    "iso:country":"CU",
    "name:und_x_variant":[
        "Las Piedras",
        "Las Piedras de Zayas"
    ],
    "wof:name":"Las Piedras de Zayas",
    "wof:placetype":"locality"
},
  "geometry": {"coordinates":[-78.35058000000002,21.54007],"type":"Point"}
}