{
  "type": "Feature",
  "properties": {
    "gn:admin1_code":"01",
    "gn:asciiname":"Puerto del Guardiero",
    "gn:country_code":"CU",
    "gn:dem":20,
    "gn:feature_class":"P",
    "gn:feature_code":"PPLL",
    "gn:name":"Puerto del Guardiero",
    "gn:population":0,
    "gn:timezone":"America/Havana",
    "iso:country":"CU",
    "wof:name":"Puerto del Guardiero",
    "wof:placetype":"locality"
},
  "geometry": {"coordinates":[-83.28333000000001,22.46667],"type":"Point"}
}