{
  "type": "Feature",
  "properties": {
    "gn:admin1_code":"05",
    "gn:asciiname":"Banao",
    "gn:country_code":"CU",
    "gn:dem":79,
    "gn:feature_class":"P",
    "gn:feature_code":"PPL",
    "gn:name":"Banao",
    "gn:population":0,
    "gn:timezone":"America/Havana",
    "iso:country":"CU",
    "name:spa_x_preferred":[
        "Banao"
    ],
    "wof:name":"Banao",
    "wof:placetype":"locality"
},
  "geometry": {"coordinates":[-77.88609,21.6411],"type":"Point"}
}