{
  "type": "Feature",
  "properties": {
    "gn:admin1_code":"03",
    "gn:asciiname":"Admiracion",
    "gn:country_code":"CU",
    "gn:dem":19,
    "gn:feature_class":"P",
    "gn:feature_code":"PPL",
    "gn:name":"Admiraci\u00f3n",
    "gn:population":0,
    "gn:timezone":"America/Havana",
    "iso:country":"CU",
    "name:spa_x_preferred":[
        "Admiraci\u00f3n"
    ],
    "wof:name":"Admiracion",
    "wof:placetype":"locality"
},
  "geometry": {"coordinates":[-81.06213000000002,22.90573],"type":"Point"}
}