{
  "type": "Feature",
  "properties": {
    "gn:admin1_code":"14",
    "gn:asciiname":"Sipiabo",
    "gn:country_code":"CU",
    "gn:dem":146,
    "gn:feature_class":"P",
    "gn:feature_code":"PPL",
    "gn:name":"Sipiabo",
    "gn:population":0,
    "gn:timezone":"America/Havana",
    "iso:country":"CU",
    "name:spa_x_preferred":[
        "Sipiabo"
    ],
    "wof:name":"Sipiabo",
    "wof:placetype":"locality"
},
  "geometry": {"coordinates":[-79.68406,22.00996],"type":"Point"}
}