{
  "type": "Feature",
  "properties": {
    "gn:admin1_code":"12",
    "gn:asciiname":"Cayo Bariay",
    "gn:country_code":"CU",
    "gn:dem":14,
    "gn:feature_class":"P",
    "gn:feature_code":"PPL",
    "gn:name":"Cayo Bariay",
    "gn:population":0,
    "gn:timezone":"America/Havana",
    "iso:country":"CU",
    "name:spa_x_preferred":[
        "Cayo Bariay"
    ],
    "wof:name":"Cayo Bariay",
    "wof:placetype":"locality"
},
  "geometry": {"coordinates":[-76.02373,21.0773],"type":"Point"}
}