{
  "type": "Feature",
  "properties": {
    "gn:admin1_code":"12",
    "gn:asciiname":"Anoncillo",
    "gn:country_code":"CU",
    "gn:dem":55,
    "gn:feature_class":"P",
    "gn:feature_code":"PPLL",
    "gn:name":"Anoncillo",
    "gn:population":0,
    "gn:timezone":"America/Havana",
    "iso:country":"CU",
    "wof:name":"Anoncillo",
    "wof:placetype":"locality"
},
  "geometry": {"coordinates":[-76.33750000000001,21.08056],"type":"Point"}
}