{
  "type": "Feature",
  "properties": {
    "gn:admin1_code":"05",
    "gn:asciiname":"La Alina",
    "gn:country_code":"CU",
    "gn:dem":12,
    "gn:feature_class":"P",
    "gn:feature_code":"PPL",
    "gn:name":"La Alina",
    "gn:population":0,
    "gn:timezone":"America/Havana",
    "iso:country":"CU",
    "name:spa_x_preferred":[
        "La Alina"
    ],
    "wof:name":"La Alina",
    "wof:placetype":"locality"
},
  "geometry": {"coordinates":[-78.54080999999999,21.52635],"type":"Point"}
}