{
  "type": "Feature",
  "properties": {
    "gn:admin1_code":"13",
    "gn:asciiname":"Pernas",
    "gn:country_code":"CU",
    "gn:dem":47,
    "gn:feature_class":"P",
    "gn:feature_code":"PPLL",
    "gn:name":"Pernas",
    "gn:population":0,
    "gn:timezone":"America/Havana",
    "iso:country":"CU",
    "wof:name":"Pernas",
    "wof:placetype":"locality"
},
  "geometry": {"coordinates":[-77.05611,21.20278],"type":"Point"}
}