{
  "type": "Feature",
  "properties": {
    "gn:admin1_code":"16",
    "gn:asciiname":"Josefita",
    "gn:country_code":"CU",
    "gn:dem":82,
    "gn:feature_class":"P",
    "gn:feature_code":"PPLL",
    "gn:name":"Josefita",
    "gn:population":0,
    "gn:timezone":"America/Havana",
    "iso:country":"CU",
    "wof:name":"Josefita",
    "wof:placetype":"locality"
},
  "geometry": {"coordinates":[-80.40000000000001,22.78333],"type":"Point"}
}