{
  "type": "Feature",
  "properties": {
    "gn:admin1_code":"03",
    "gn:asciiname":"Prendes",
    "gn:country_code":"CU",
    "gn:dem":70,
    "gn:feature_class":"P",
    "gn:feature_code":"PPLL",
    "gn:name":"Prendes",
    "gn:population":0,
    "gn:timezone":"America/Havana",
    "iso:country":"CU",
    "name:spa_x_preferred":[
        "Prendes"
    ],
    "wof:name":"Prendes",
    "wof:placetype":"locality"
},
  "geometry": {"coordinates":[-80.71639999999999,22.74185],"type":"Point"}
}