{
  "type": "Feature",
  "properties": {
    "gn:admin1_code":"07",
    "gn:asciiname":"Angelica",
    "gn:cc2":"CU",
    "gn:country_code":"CU",
    "gn:dem":98,
    "gn:feature_class":"P",
    "gn:feature_code":"PPLL",
    "gn:name":"Ang\u00e9lica",
    "gn:population":0,
    "gn:timezone":"America/Havana",
    "iso:country":"CU",
    "name:und_x_variant":[
        "Angelida",
        "Ang\u00e9lica"
    ],
    "wof:name":"Angelica",
    "wof:placetype":"locality"
},
  "geometry": {"coordinates":[-78.92416999999998,21.90611],"type":"Point"}
}