{
  "type": "Feature",
  "properties": {
    "gn:admin1_code":"07",
    "gn:asciiname":"Angelica",
    "gn:cc2":"CU",
    "gn:country_code":"CU",
    "gn:dem":98,
    "gn:feature_class":"P",
    "gn:feature_code":"PPLL",
    "gn:name":"Ang\u00e9lica",
    "gn:population":0,
    "gn:timezone":"America/Havana",
    "iso:country":"CU",
    "name:ara_x_preferred":[
        "\u062d\u0634\u064a\u0634\u0629 \u0627\u0644\u0645\u0644\u0627\u0643"
    ],
    "name:aze_x_preferred":[
        "T\u00fct\u0259kotu"
    ],
    "name:bak_x_preferred":[
        "\u0428\u044b\u043c\u0430 \u043a\u04e9\u043f\u0448\u04d9"
    ],
    "name:bel_x_preferred":[
        "\u0414\u0443\u0434\u043d\u0456\u043a"
    ],
    "name:cat_x_preferred":[
        "Angelica"
    ],
    "name:cym_x_preferred":[
        "Llysiau'r angel"
    ],
    "name:dan_x_preferred":[
        "Angelik"
    ],
    "name:deu_x_preferred":[
        "Engelwurzen"
    ],
    "name:epo_x_preferred":[
        "Angelikoj"
    ],
    "name:est_x_preferred":[
        "Heinputk"
    ],
    "name:fas_x_preferred":[
        "\u0633\u0646\u0628\u0644 \u062e\u062a\u0627\u06cc\u06cc"
    ],
    "name:fin_x_preferred":[
        "Karhunputket"
    ],
    "name:fra_x_preferred":[
        "Angelica"
    ],
    "name:gle_x_preferred":[
        "Ainglice"
    ],
    "name:glg_x_preferred":[
        "Angelica"
    ],
    "name:hrv_x_preferred":[
        "An\u0111elika"
    ],
    "name:hun_x_preferred":[
        "Angyalgy\u00f6k\u00e9r"
    ],
    "name:hye_x_preferred":[
        "\u0532\u0578\u056d\u0576\u056b"
    ],
    "name:ido_x_preferred":[
        "Angeliko"
    ],
    "name:isl_x_preferred":[
        "Hvannir"
    ],
    "name:ita_x_preferred":[
        "Angelica"
    ],
    "name:jpn_x_preferred":[
        "\u30b7\u30b7\u30a6\u30c9\u5c5e"
    ],
    "name:kaz_x_preferred":[
        "\u0410\u044e\u0431\u0430\u043b\u0434\u044b\u0440\u0493\u0430\u043d"
    ],
    "name:kir_x_preferred":[
        "\u041a\u0435\u0440\u0435\u0447"
    ],
    "name:kor_x_preferred":[
        "\ub2f9\uadc0\uc18d"
    ],
    "name:lit_x_preferred":[
        "\u0160ventagar\u0161v\u0117"
    ],
    "name:mrj_x_preferred":[
        "\u041c\u04e7\u0441\u043a\u04d3\u0432\u044b\u0447"
    ],
    "name:nld_x_preferred":[
        "Angelica"
    ],
    "name:nor_x_preferred":[
        "Kvannslekta"
    ],
    "name:pol_x_preferred":[
        "Dzi\u0119giel"
    ],
    "name:por_x_preferred":[
        "Angelica"
    ],
    "name:ron_x_preferred":[
        "Angelica"
    ],
    "name:rus_x_preferred":[
        "\u0414\u0443\u0434\u043d\u0438\u043a"
    ],
    "name:sco_x_preferred":[
        "Angelica"
    ],
    "name:spa_x_preferred":[
        "Angelica"
    ],
    "name:sqi_x_preferred":[
        "Angjelika"
    ],
    "name:srp_x_preferred":[
        "Angelica"
    ],
    "name:swe_x_preferred":[
        "Kvannesl\u00e4ktet"
    ],
    "name:tgl_x_preferred":[
        "Anghelika"
    ],
    "name:ukr_x_preferred":[
        "\u0414\u044f\u0433\u0435\u043b\u044c"
    ],
    "name:und_x_variant":[
        "Angelida",
        "Ang\u00e9lica"
    ],
    "name:zho_x_preferred":[
        "\u7576\u6b78\u5c6c"
    ],
    "wof:name":"Angelica",
    "wof:placetype":"locality"
},
  "geometry": {"coordinates":[-78.92416999999998,21.90611],"type":"Point"}
}