{
  "type": "Feature",
  "properties": {
    "gn:admin1_code":"03",
    "gn:asciiname":"El Penon",
    "gn:country_code":"CU",
    "gn:dem":49,
    "gn:feature_class":"P",
    "gn:feature_code":"PPLL",
    "gn:name":"El Pe\u00f1\u00f3n",
    "gn:population":0,
    "gn:timezone":"America/Havana",
    "iso:country":"CU",
    "name:spa_x_preferred":[
        "El Pe\u00f1\u00f3n"
    ],
    "wof:name":"El Penon",
    "wof:placetype":"locality"
},
  "geometry": {"coordinates":[-80.9216,22.88939],"type":"Point"}
}