{
  "type": "Feature",
  "properties": {
    "gn:admin1_code":"16",
    "gn:asciiname":"Salamanca",
    "gn:country_code":"CU",
    "gn:dem":131,
    "gn:feature_class":"P",
    "gn:feature_code":"PPLL",
    "gn:name":"Salamanca",
    "gn:population":0,
    "gn:timezone":"America/Havana",
    "iso:country":"CU",
    "wof:name":"Salamanca",
    "wof:placetype":"locality"
},
  "geometry": {"coordinates":[-79.66667,22.45],"type":"Point"}
}