{
  "type": "Feature",
  "properties": {
    "gn:admin1_code":"01",
    "gn:asciiname":"La Fe",
    "gn:country_code":"CU",
    "gn:dem":7,
    "gn:feature_class":"P",
    "gn:feature_code":"PPL",
    "gn:name":"La Fe",
    "gn:population":0,
    "gn:timezone":"America/Havana",
    "iso:country":"CU",
    "name:spa_x_preferred":[
        "La Fe"
    ],
    "wof:name":"La Fe",
    "wof:placetype":"locality"
},
  "geometry": {"coordinates":[-84.27056,22.04083],"type":"Point"}
}