{
  "type": "Feature",
  "properties": {
    "gn:admin1_code":"01",
    "gn:asciiname":"Paso Real de San Diego",
    "gn:cc2":"CU",
    "gn:country_code":"CU",
    "gn:dem":37,
    "gn:feature_class":"P",
    "gn:feature_code":"PPL",
    "gn:name":"Paso Real de San Diego",
    "gn:population":0,
    "gn:timezone":"America/Havana",
    "iso:country":"CU",
    "name:und_x_variant":[
        "Paso Real San Diego",
        "Paso Real",
        "Paso Real de San Diego"
    ],
    "wof:name":"Paso Real de San Diego",
    "wof:placetype":"locality"
},
  "geometry": {"coordinates":[-83.30906999999998,22.55584],"type":"Point"}
}