{
  "type": "Feature",
  "properties": {
    "gn:admin1_code":"14",
    "gn:asciiname":"Las Marias",
    "gn:country_code":"CU",
    "gn:dem":227,
    "gn:feature_class":"P",
    "gn:feature_code":"PPLL",
    "gn:name":"Las Mar\u00edas",
    "gn:population":0,
    "gn:timezone":"America/Havana",
    "iso:country":"CU",
    "name:spa_x_preferred":[
        "Las Mar\u00edas"
    ],
    "name:und_x_variant":[
        "La Mar\u00eda"
    ],
    "wof:name":"Las Marias",
    "wof:placetype":"locality"
},
  "geometry": {"coordinates":[-79.31929000000002,22.27882],"type":"Point"}
}