{
  "type": "Feature",
  "properties": {
    "gn:admin1_code":"15",
    "gn:asciiname":"Los Coquitos",
    "gn:country_code":"CU",
    "gn:dem":81,
    "gn:feature_class":"P",
    "gn:feature_code":"PPL",
    "gn:name":"Los Coquitos",
    "gn:population":0,
    "gn:timezone":"America/Havana",
    "iso:country":"CU",
    "name:spa_x_preferred":[
        "Los Coquitos"
    ],
    "wof:name":"Los Coquitos",
    "wof:placetype":"locality"
},
  "geometry": {"coordinates":[-75.77301999999997,19.98874],"type":"Point"}
}