{
  "type": "Feature",
  "properties": {
    "gn:admin1_code":"15",
    "gn:asciiname":"Municiones",
    "gn:country_code":"CU",
    "gn:dem":94,
    "gn:feature_class":"P",
    "gn:feature_code":"PPL",
    "gn:name":"Municiones",
    "gn:population":0,
    "gn:timezone":"America/Havana",
    "iso:country":"CU",
    "name:spa_x_preferred":[
        "Municiones"
    ],
    "wof:name":"Municiones",
    "wof:placetype":"locality"
},
  "geometry": {"coordinates":[-75.93822,20.49949],"type":"Point"}
}