{
  "type": "Feature",
  "properties": {
    "gn:admin1_code":"15",
    "gn:asciiname":"Barbara",
    "gn:country_code":"CU",
    "gn:dem":415,
    "gn:feature_class":"P",
    "gn:feature_code":"PPLL",
    "gn:name":"B\u00e1rbara",
    "gn:population":0,
    "gn:timezone":"America/Havana",
    "iso:country":"CU",
    "wof:name":"Barbara",
    "wof:placetype":"locality"
},
  "geometry": {"coordinates":[-75.53333000000001,20.03333],"type":"Point"}
}