{
  "type": "Feature",
  "properties": {
    "gn:admin1_code":"16",
    "gn:asciiname":"Alto Ubero",
    "gn:country_code":"CU",
    "gn:dem":6,
    "gn:feature_class":"P",
    "gn:feature_code":"PPLL",
    "gn:name":"Alto Ubero",
    "gn:population":0,
    "gn:timezone":"America/Havana",
    "iso:country":"CU",
    "wof:name":"Alto Ubero",
    "wof:placetype":"locality"
},
  "geometry": {"coordinates":[-79.93333,22.81667],"type":"Point"}
}