{
  "type": "Feature",
  "properties": {
    "gn:admin1_code":"12",
    "gn:asciiname":"Playa Mejias",
    "gn:country_code":"CU",
    "gn:dem":6,
    "gn:feature_class":"P",
    "gn:feature_code":"PPL",
    "gn:name":"Playa Mejias",
    "gn:population":0,
    "gn:timezone":"America/Havana",
    "iso:country":"CU",
    "name:spa_x_preferred":[
        "Playa Mejias"
    ],
    "wof:name":"Playa Mejias",
    "wof:placetype":"locality"
},
  "geometry": {"coordinates":[-75.23498000000002,20.71714],"type":"Point"}
}