{
  "type": "Feature",
  "properties": {
    "gn:admin1_code":"12",
    "gn:asciiname":"El Quemado",
    "gn:country_code":"CU",
    "gn:dem":185,
    "gn:feature_class":"P",
    "gn:feature_code":"PPL",
    "gn:name":"El Quemado",
    "gn:population":0,
    "gn:timezone":"America/Havana",
    "iso:country":"CU",
    "name:spa_x_preferred":[
        "El Quemado"
    ],
    "wof:name":"El Quemado",
    "wof:placetype":"locality"
},
  "geometry": {"coordinates":[-75.27273000000002,20.43307],"type":"Point"}
}