{
  "type": "Feature",
  "properties": {
    "gn:admin1_code":"16",
    "gn:asciiname":"Platanico",
    "gn:country_code":"CU",
    "gn:dem":123,
    "gn:feature_class":"P",
    "gn:feature_code":"PPL",
    "gn:name":"Platanico",
    "gn:population":0,
    "gn:timezone":"America/Havana",
    "iso:country":"CU",
    "name:spa_x_preferred":[
        "Platanico"
    ],
    "wof:name":"Platanico",
    "wof:placetype":"locality"
},
  "geometry": {"coordinates":[-79.76843000000002,22.07652],"type":"Point"}
}