{
  "type": "Feature",
  "properties": {
    "gn:admin1_code":"15",
    "gn:asciiname":"Aguacate",
    "gn:country_code":"CU",
    "gn:dem":312,
    "gn:feature_class":"P",
    "gn:feature_code":"PPL",
    "gn:name":"Aguacate",
    "gn:population":0,
    "gn:timezone":"America/Havana",
    "iso:country":"CU",
    "name:spa_x_preferred":[
        "Aguacate"
    ],
    "wof:name":"Aguacate",
    "wof:placetype":"locality"
},
  "geometry": {"coordinates":[-76.11117,20.22322],"type":"Point"}
}