{
  "type": "Feature",
  "properties": {
    "gn:admin1_code":"14",
    "gn:asciiname":"Guasimal",
    "gn:country_code":"CU",
    "gn:dem":29,
    "gn:feature_class":"P",
    "gn:feature_code":"PPL",
    "gn:name":"Guasimal",
    "gn:population":0,
    "gn:timezone":"America/Havana",
    "iso:country":"CU",
    "name:und_x_variant":[
        "Las Guasimas",
        "Guasimal"
    ],
    "wof:name":"Guasimal",
    "wof:placetype":"locality"
},
  "geometry": {"coordinates":[-79.46419,21.74052],"type":"Point"}
}