{
  "type": "Feature",
  "properties": {
    "gn:admin1_code":"12",
    "gn:asciiname":"Yareniquen",
    "gn:country_code":"CU",
    "gn:dem":94,
    "gn:feature_class":"P",
    "gn:feature_code":"PPL",
    "gn:name":"Yareniqu\u00e9n",
    "gn:population":0,
    "gn:timezone":"America/Havana",
    "iso:country":"CU",
    "wof:name":"Yareniquen",
    "wof:placetype":"locality"
},
  "geometry": {"coordinates":[-76.28166999999998,20.9925],"type":"Point"}
}