{
  "type": "Feature",
  "properties": {
    "gn:admin1_code":"10",
    "gn:asciiname":"Oquendo",
    "gn:country_code":"CU",
    "gn:dem":24,
    "gn:feature_class":"P",
    "gn:feature_code":"PPL",
    "gn:name":"Oquendo",
    "gn:population":0,
    "gn:timezone":"America/Havana",
    "iso:country":"CU",
    "name:spa_x_preferred":[
        "Oquendo"
    ],
    "wof:name":"Oquendo",
    "wof:placetype":"locality"
},
  "geometry": {"coordinates":[-74.80464000000001,20.06761],"type":"Point"}
}