{
  "type": "Feature",
  "properties": {
    "gn:admin1_code":"01",
    "gn:asciiname":"Naranjal",
    "gn:country_code":"CU",
    "gn:dem":132,
    "gn:feature_class":"P",
    "gn:feature_code":"PPLL",
    "gn:name":"Naranjal",
    "gn:population":0,
    "gn:timezone":"America/Havana",
    "iso:country":"CU",
    "wof:name":"Naranjal",
    "wof:placetype":"locality"
},
  "geometry": {"coordinates":[-83.41667,22.63333],"type":"Point"}
}