{
  "type": "Feature",
  "properties": {
    "gn:admin1_code":"12",
    "gn:asciiname":"El Mijial",
    "gn:country_code":"CU",
    "gn:dem":108,
    "gn:feature_class":"P",
    "gn:feature_code":"PPL",
    "gn:name":"El Mijial",
    "gn:population":0,
    "gn:timezone":"America/Havana",
    "iso:country":"CU",
    "name:spa_x_preferred":[
        "El Mijial"
    ],
    "name:und_x_variant":[
        "Mijial"
    ],
    "wof:name":"El Mijial",
    "wof:placetype":"locality"
},
  "geometry": {"coordinates":[-75.24460000000001,20.49521],"type":"Point"}
}