{
  "type": "Feature",
  "properties": {
    "gn:admin1_code":"16",
    "gn:asciiname":"Sitio Grande",
    "gn:country_code":"CU",
    "gn:dem":64,
    "gn:feature_class":"P",
    "gn:feature_code":"PPL",
    "gn:name":"Sitio Grande",
    "gn:population":0,
    "gn:timezone":"America/Havana",
    "iso:country":"CU",
    "name:und_x_variant":[
        "Poblado Sitio Grande",
        "Sitio Grande"
    ],
    "wof:name":"Sitio Grande",
    "wof:placetype":"locality"
},
  "geometry": {"coordinates":[-80.06169,22.69361],"type":"Point"}
}