{
  "type": "Feature",
  "properties": {
    "gn:admin1_code":"01",
    "gn:asciiname":"Portales",
    "gn:country_code":"CU",
    "gn:dem":58,
    "gn:feature_class":"P",
    "gn:feature_code":"PPL",
    "gn:name":"Portales",
    "gn:population":0,
    "gn:timezone":"America/Havana",
    "iso:country":"CU",
    "name:fas_x_preferred":[
        "\u067e\u0648\u0631\u062a\u0627\u0644\u0633"
    ],
    "name:spa_x_preferred":[
        "Portales"
    ],
    "wof:name":"Portales",
    "wof:placetype":"locality"
},
  "geometry": {"coordinates":[-84.03220999999998,22.23101],"type":"Point"}
}