{
  "type": "Feature",
  "properties": {
    "gn:admin1_code":"15",
    "gn:asciiname":"La Guadalupe",
    "gn:cc2":"CU",
    "gn:country_code":"CU",
    "gn:dem":278,
    "gn:feature_class":"P",
    "gn:feature_code":"PPLL",
    "gn:name":"La Guadalupe",
    "gn:population":0,
    "gn:timezone":"America/Havana",
    "iso:country":"CU",
    "name:und_x_variant":[
        "Guadalupe",
        "La Guadalupe"
    ],
    "wof:name":"La Guadalupe",
    "wof:placetype":"locality"
},
  "geometry": {"coordinates":[-75.88361,20.14083],"type":"Point"}
}