{
  "type": "Feature",
  "properties": {
    "gn:admin1_code":"12",
    "gn:asciiname":"Guaramanao",
    "gn:country_code":"CU",
    "gn:dem":123,
    "gn:feature_class":"P",
    "gn:feature_code":"PPL",
    "gn:name":"Guaramanao",
    "gn:population":0,
    "gn:timezone":"America/Havana",
    "iso:country":"CU",
    "name:spa_x_preferred":[
        "Guaramanao"
    ],
    "wof:name":"Guaramanao",
    "wof:placetype":"locality"
},
  "geometry": {"coordinates":[-76.48886,20.89244],"type":"Point"}
}