{
  "type": "Feature",
  "properties": {
    "gn:admin1_code":"14",
    "gn:asciiname":"El Purial",
    "gn:country_code":"CU",
    "gn:dem":245,
    "gn:feature_class":"P",
    "gn:feature_code":"PPL",
    "gn:name":"El Purial",
    "gn:population":0,
    "gn:timezone":"America/Havana",
    "iso:country":"CU",
    "name:spa_x_preferred":[
        "El Purial"
    ],
    "wof:name":"El Purial",
    "wof:placetype":"locality"
},
  "geometry": {"coordinates":[-79.31270000000001,22.27135],"type":"Point"}
}