{
  "type": "Feature",
  "properties": {
    "gn:admin1_code":"12",
    "gn:asciiname":"Punta Gorda",
    "gn:country_code":"CU",
    "gn:dem":6,
    "gn:feature_class":"P",
    "gn:feature_code":"PPL",
    "gn:name":"Punta Gorda",
    "gn:population":0,
    "gn:timezone":"America/Havana",
    "iso:country":"CU",
    "name:ast_x_preferred":[
        "Punta Gorda"
    ],
    "name:ben_x_preferred":[
        "\u09aa\u09c1\u09a8\u09cd\u09a4\u09be \u0997\u09cb\u09b0\u09a6\u09be"
    ],
    "name:ceb_x_preferred":[
        "Punta Gorda"
    ],
    "name:deu_x_preferred":[
        "Punta Gorda"
    ],
    "name:ell_x_preferred":[
        "\u03a0\u03bf\u03cd\u03bd\u03c4\u03b1 \u0393\u03cc\u03c1\u03b4\u03b1"
    ],
    "name:fas_x_preferred":[
        "\u067e\u0648\u0646\u062a\u0627 \u06af\u0648\u0631\u062f\u0627"
    ],
    "name:fra_x_preferred":[
        "Punta Gorda"
    ],
    "name:hin_x_preferred":[
        "\u092a\u0941\u0902\u091f\u093e \u0917\u094b\u0930\u094d\u0921\u093e"
    ],
    "name:hun_x_preferred":[
        "Punta Gorda"
    ],
    "name:ind_x_preferred":[
        "Punta Gorda"
    ],
    "name:ita_x_preferred":[
        "Punta Gorda"
    ],
    "name:kor_x_preferred":[
        "\ud47c\ud0c0 \uace0\ub974\ub2e4"
    ],
    "name:nds_x_preferred":[
        "Punta Gorda"
    ],
    "name:nld_x_preferred":[
        "Punta Gorda"
    ],
    "name:pol_x_preferred":[
        "Punta Gorda"
    ],
    "name:por_x_preferred":[
        "Punta Gorda"
    ],
    "name:rus_x_preferred":[
        "\u041f\u0443\u043d\u0442\u0430-\u0413\u043e\u0440\u0434\u0430"
    ],
    "name:sco_x_preferred":[
        "Punta Gorda"
    ],
    "name:spa_x_preferred":[
        "Punta Gorda"
    ],
    "name:srp_x_preferred":[
        "\u041f\u0443\u043d\u0442\u0430 \u0413\u043e\u0440\u0434\u0430"
    ],
    "name:swe_x_preferred":[
        "Punta Gorda"
    ],
    "name:tur_x_preferred":[
        "Punta Gorda"
    ],
    "name:vie_x_preferred":[
        "Punta Gorda"
    ],
    "wof:name":"Punta Gorda",
    "wof:placetype":"locality"
},
  "geometry": {"coordinates":[-75.33681,20.67817],"type":"Point"}
}