{
  "type": "Feature",
  "properties": {
    "gn:admin1_code":"14",
    "gn:asciiname":"Tayabacoa",
    "gn:country_code":"CU",
    "gn:dem":7,
    "gn:feature_class":"P",
    "gn:feature_code":"PPL",
    "gn:name":"Tayabacoa",
    "gn:population":0,
    "gn:timezone":"America/Havana",
    "iso:country":"CU",
    "name:spa_x_preferred":[
        "Tayabacoa"
    ],
    "wof:name":"Tayabacoa",
    "wof:placetype":"locality"
},
  "geometry": {"coordinates":[-79.51120999999998,21.70082],"type":"Point"}
}