{
  "type": "Feature",
  "properties": {
    "gn:admin1_code":"12",
    "gn:asciiname":"Rio Grande",
    "gn:country_code":"CU",
    "gn:dem":14,
    "gn:feature_class":"P",
    "gn:feature_code":"PPL",
    "gn:name":"R\u00edo Grande",
    "gn:population":0,
    "gn:timezone":"America/Havana",
    "iso:country":"CU",
    "name:spa_x_preferred":[
        "R\u00edo Grande"
    ],
    "wof:name":"Rio Grande",
    "wof:placetype":"locality"
},
  "geometry": {"coordinates":[-75.31245,20.63729],"type":"Point"}
}