{
  "type": "Feature",
  "properties": {
    "gn:admin1_code":"14",
    "gn:asciiname":"Aridanes Viejo",
    "gn:country_code":"CU",
    "gn:dem":13,
    "gn:feature_class":"P",
    "gn:feature_code":"PPL",
    "gn:name":"Aridanes Viejo",
    "gn:population":0,
    "gn:timezone":"America/Havana",
    "iso:country":"CU",
    "name:spa_x_preferred":[
        "Aridanes Viejo"
    ],
    "name:und_x_variant":[
        "Arroyo Prieto"
    ],
    "wof:name":"Aridanes Viejo",
    "wof:placetype":"locality"
},
  "geometry": {"coordinates":[-79.00279999999999,22.30855],"type":"Point"}
}