{
  "type": "Feature",
  "properties": {
    "iso:country":"CU",
    "name:unk_x_variant":[
        "Aimanitas"
    ],
    "qs:gn_country":"CU",
    "qs:gn_fcode":"PPL",
    "qs:gn_pop":0,
    "qs:name":"Jaimanitas",
    "qs:name_adm0":"Cuba",
    "qs:name_adm1":"Ciudad de la Habana",
    "qs:photos":10,
    "qs:photos_1k":2,
    "qs:photos_9k":1,
    "qs:photos_9r":1,
    "qs:photos_all":10,
    "qs:photos_sr":1,
    "qs:placetype":"Town",
    "qs:pop_sr":"0",
    "qs:woe_adm0":23424793,
    "wof:name":"Jaimanitas",
    "wof:placetype":"locality"
},
  "geometry": {"coordinates":[-82.48278000000001,23.09],"type":"Point"}
}