{
  "type": "Feature",
  "properties": {
    "gn:admin1_code":"05",
    "gn:asciiname":"San Bonifacio",
    "gn:country_code":"CU",
    "gn:dem":38,
    "gn:feature_class":"P",
    "gn:feature_code":"PPLL",
    "gn:name":"San Bonifacio",
    "gn:population":0,
    "gn:timezone":"America/Havana",
    "iso:country":"CU",
    "name:azb_x_preferred":[
        "\u0633\u0646 \u0628\u0648\u0646\u06cc\u0641\u0627\u0686\u0648"
    ],
    "name:bul_x_preferred":[
        "\u0421\u0430\u043d \u0411\u043e\u043d\u0438\u0444\u0430\u0447\u043e"
    ],
    "name:ceb_x_preferred":[
        "San Bonifacio"
    ],
    "name:deu_x_preferred":[
        "San Bonifacio"
    ],
    "name:epo_x_preferred":[
        "San Bonifacio"
    ],
    "name:eus_x_preferred":[
        "San Bonifacio"
    ],
    "name:fas_x_preferred":[
        "\u0633\u0646 \u0628\u0648\u0646\u06cc\u0641\u0627\u0686\u0648"
    ],
    "name:fra_x_preferred":[
        "San Bonifacio"
    ],
    "name:hun_x_preferred":[
        "San Bonifacio"
    ],
    "name:hye_x_preferred":[
        "\u054d\u0561\u0576 \u0532\u0578\u0576\u056b\u0586\u0561\u0579\u0578"
    ],
    "name:ita_x_preferred":[
        "San Bonifacio"
    ],
    "name:jpn_x_preferred":[
        "\u30b5\u30f3\u30fb\u30dc\u30cb\u30d5\u30a1\u30fc\u30c1\u30e7"
    ],
    "name:kaz_x_preferred":[
        "\u0421\u0430\u043d-\u0411\u043e\u043d\u0438\u0444\u0430\u0447\u043e"
    ],
    "name:lat_x_preferred":[
        "Fanum Sancti Bonifatii"
    ],
    "name:lmo_x_preferred":[
        "San Bonifacio"
    ],
    "name:msa_x_preferred":[
        "San Bonifacio"
    ],
    "name:nap_x_preferred":[
        "San Bonifacio"
    ],
    "name:nld_x_preferred":[
        "San Bonifacio"
    ],
    "name:pms_x_preferred":[
        "San Bonifacio"
    ],
    "name:pol_x_preferred":[
        "San Bonifacio"
    ],
    "name:por_x_preferred":[
        "San Bonifacio"
    ],
    "name:ron_x_preferred":[
        "San Bonifacio"
    ],
    "name:rus_x_preferred":[
        "\u0421\u0430\u043d-\u0411\u043e\u043d\u0438\u0444\u0430\u0447\u043e"
    ],
    "name:scn_x_preferred":[
        "San Bonifacio"
    ],
    "name:spa_x_preferred":[
        "San Bonifacio"
    ],
    "name:srp_x_preferred":[
        "\u0421\u0430\u043d \u0411\u043e\u043d\u0438\u0444\u0430\u0447\u0438\u043e"
    ],
    "name:tur_x_preferred":[
        "San Bonifacio"
    ],
    "name:ukr_x_preferred":[
        "\u0421\u0430\u043d-\u0411\u043e\u043d\u0456\u0444\u0430\u0447\u043e"
    ],
    "name:uzb_x_preferred":[
        "San Bonifacio"
    ],
    "name:vec_x_preferred":[
        "San Bonifacio"
    ],
    "name:vie_x_preferred":[
        "San Bonifacio"
    ],
    "name:vol_x_preferred":[
        "San Bonifacio"
    ],
    "name:war_x_preferred":[
        "San Bonifacio"
    ],
    "name:zho_x_preferred":[
        "\u5723\u535a\u5c3c\u6cd5\u4e54"
    ],
    "wof:name":"San Bonifacio",
    "wof:placetype":"locality"
},
  "geometry": {"coordinates":[-78.03491,20.98129],"type":"Point"}
}