{
  "type": "Feature",
  "properties": {
    "gn:admin1_code":"05",
    "gn:asciiname":"San Bonifacio",
    "gn:country_code":"CU",
    "gn:dem":38,
    "gn:feature_class":"P",
    "gn:feature_code":"PPLL",
    "gn:name":"San Bonifacio",
    "gn:population":0,
    "gn:timezone":"America/Havana",
    "iso:country":"CU",
    "name:spa_x_preferred":[
        "San Bonifacio"
    ],
    "wof:name":"San Bonifacio",
    "wof:placetype":"locality"
},
  "geometry": {"coordinates":[-78.03491,20.98129],"type":"Point"}
}