{
  "type": "Feature",
  "properties": {
    "gn:admin1_code":"12",
    "gn:asciiname":"El Jobo",
    "gn:country_code":"CU",
    "gn:dem":150,
    "gn:feature_class":"P",
    "gn:feature_code":"PPL",
    "gn:name":"El Jobo",
    "gn:population":0,
    "gn:timezone":"America/Havana",
    "iso:country":"CU",
    "name:spa_x_preferred":[
        "El Jobo"
    ],
    "name:und_x_variant":[
        "Jobo"
    ],
    "wof:name":"El Jobo",
    "wof:placetype":"locality"
},
  "geometry": {"coordinates":[-75.44022,20.64179],"type":"Point"}
}