{
  "type": "Feature",
  "properties": {
    "gn:admin1_code":"03",
    "gn:asciiname":"El Toro",
    "gn:country_code":"CU",
    "gn:dem":78,
    "gn:feature_class":"P",
    "gn:feature_code":"PPLL",
    "gn:name":"El Toro",
    "gn:population":0,
    "gn:timezone":"America/Havana",
    "iso:country":"CU",
    "name:ceb_x_preferred":[
        "El Toro"
    ],
    "name:deu_x_preferred":[
        "El Toro"
    ],
    "name:fra_x_preferred":[
        "El Toro"
    ],
    "name:ita_x_preferred":[
        "El Toro"
    ],
    "name:nld_x_preferred":[
        "El Toro"
    ],
    "name:pol_x_preferred":[
        "El Toro"
    ],
    "name:spa_x_preferred":[
        "El Toro"
    ],
    "name:srp_x_preferred":[
        "\u0415\u043b \u0422\u043e\u0440\u043e"
    ],
    "name:swe_x_preferred":[
        "El Toro"
    ],
    "wof:name":"El Toro",
    "wof:placetype":"locality"
},
  "geometry": {"coordinates":[-81.27604000000002,22.87672],"type":"Point"}
}