{
  "type": "Feature",
  "properties": {
    "gn:admin1_code":"07",
    "gn:asciiname":"El Mameyal",
    "gn:country_code":"CU",
    "gn:dem":94,
    "gn:feature_class":"P",
    "gn:feature_code":"PPLL",
    "gn:name":"El Mameyal",
    "gn:population":0,
    "gn:timezone":"America/Havana",
    "iso:country":"CU",
    "name:spa_x_preferred":[
        "El Mameyal"
    ],
    "name:spa_x_variant":[
        "Mameyal",
        "El Mamey"
    ],
    "wof:name":"El Mameyal",
    "wof:placetype":"locality"
},
  "geometry": {"coordinates":[-78.91986999999997,21.90419],"type":"Point"}
}