{
  "type": "Feature",
  "properties": {
    "gn:admin1_code":"05",
    "gn:asciiname":"El Triangulo",
    "gn:country_code":"CU",
    "gn:dem":80,
    "gn:feature_class":"P",
    "gn:feature_code":"PPLL",
    "gn:name":"El Tri\u00e1ngulo",
    "gn:population":0,
    "gn:timezone":"America/Havana",
    "iso:country":"CU",
    "name:spa_x_preferred":[
        "El Tri\u00e1ngulo"
    ],
    "wof:name":"El Triangulo",
    "wof:placetype":"locality"
},
  "geometry": {"coordinates":[-78.27278000000003,21.67346],"type":"Point"}
}