{
  "type": "Feature",
  "properties": {
    "gn:admin1_code":"MA",
    "gn:asciiname":"San Antonio de las Vegas",
    "gn:country_code":"CU",
    "gn:dem":84,
    "gn:feature_class":"P",
    "gn:feature_code":"PPL",
    "gn:name":"San Antonio de las Vegas",
    "gn:population":0,
    "gn:timezone":"America/Havana",
    "iso:country":"CU",
    "name:spa_x_preferred":[
        "San Antonio de las Vegas"
    ],
    "wof:name":"San Antonio de las Vegas",
    "wof:placetype":"locality"
},
  "geometry": {"coordinates":[-82.25915999999999,22.85283],"type":"Point"}
}