{
  "type": "Feature",
  "properties": {
    "gn:admin1_code":"09",
    "gn:asciiname":"San Antonio",
    "gn:country_code":"CU",
    "gn:dem":67,
    "gn:feature_class":"P",
    "gn:feature_code":"PPL",
    "gn:name":"San Antonio",
    "gn:population":0,
    "gn:timezone":"America/Havana",
    "iso:country":"CU",
    "wof:name":"San Antonio",
    "wof:placetype":"locality"
},
  "geometry": {"coordinates":[-76.66667,20.31667],"type":"Point"}
}