{
  "type": "Feature",
  "properties": {
    "gn:admin1_code":"03",
    "gn:asciiname":"Dolores",
    "gn:country_code":"CU",
    "gn:dem":45,
    "gn:feature_class":"P",
    "gn:feature_code":"PPLL",
    "gn:name":"Dolores",
    "gn:population":0,
    "gn:timezone":"America/Havana",
    "iso:country":"CU",
    "wof:name":"Dolores",
    "wof:placetype":"locality"
},
  "geometry": {"coordinates":[-81.31667,23.06667],"type":"Point"}
}