{
  "type": "Feature",
  "properties": {
    "gn:admin1_code":"03",
    "gn:asciiname":"Gispert",
    "gn:country_code":"CU",
    "gn:dem":43,
    "gn:feature_class":"P",
    "gn:feature_code":"PPL",
    "gn:name":"Gispert",
    "gn:population":0,
    "gn:timezone":"America/Havana",
    "iso:country":"CU",
    "name:und_x_variant":[
        "Gisper",
        "Gispert"
    ],
    "wof:name":"Gispert",
    "wof:placetype":"locality"
},
  "geometry": {"coordinates":[-80.93814999999999,22.6793],"type":"Point"}
}