{
  "type": "Feature",
  "properties": {
    "gn:admin1_code":"16",
    "gn:asciiname":"La Veguita",
    "gn:country_code":"CU",
    "gn:dem":96,
    "gn:feature_class":"P",
    "gn:feature_code":"PPLL",
    "gn:name":"La Veguita",
    "gn:population":0,
    "gn:timezone":"America/Havana",
    "iso:country":"CU",
    "wof:name":"La Veguita",
    "wof:placetype":"locality"
},
  "geometry": {"coordinates":[-79.81667,22.38333],"type":"Point"}
}