{
  "type": "Feature",
  "properties": {
    "gn:admin1_code":"12",
    "gn:asciiname":"Dumois",
    "gn:country_code":"CU",
    "gn:dem":69,
    "gn:feature_class":"P",
    "gn:feature_code":"PPL",
    "gn:name":"Dumois",
    "gn:population":0,
    "gn:timezone":"America/Havana",
    "iso:country":"CU",
    "name:spa_x_preferred":[
        "Dumois"
    ],
    "wof:name":"Dumois",
    "wof:placetype":"locality"
},
  "geometry": {"coordinates":[-75.66580999999999,21.04084],"type":"Point"}
}