{
  "type": "Feature",
  "properties": {
    "gn:admin1_code":"09",
    "gn:asciiname":"La Escondida",
    "gn:cc2":"CU",
    "gn:country_code":"CU",
    "gn:dem":276,
    "gn:feature_class":"P",
    "gn:feature_code":"PPLL",
    "gn:name":"La Escondida",
    "gn:population":0,
    "gn:timezone":"America/Havana",
    "iso:country":"CU",
    "name:und_x_variant":[
        "Estancia Escondita",
        "La Escondida"
    ],
    "wof:name":"La Escondida",
    "wof:placetype":"locality"
},
  "geometry": {"coordinates":[-76.53333000000001,20.23333],"type":"Point"}
}