{
  "type": "Feature",
  "properties": {
    "gn:admin1_code":"15",
    "gn:asciiname":"La Silviana",
    "gn:country_code":"CU",
    "gn:dem":193,
    "gn:feature_class":"P",
    "gn:feature_code":"PPLL",
    "gn:name":"La Silviana",
    "gn:population":0,
    "gn:timezone":"America/Havana",
    "iso:country":"CU",
    "name:spa_x_preferred":[
        "La Silviana"
    ],
    "wof:name":"La Silviana",
    "wof:placetype":"locality"
},
  "geometry": {"coordinates":[-75.8344,20.29102],"type":"Point"}
}