{
  "type": "Feature",
  "properties": {
    "gn:admin1_code":"15",
    "gn:asciiname":"Calderon",
    "gn:country_code":"CU",
    "gn:dem":138,
    "gn:feature_class":"P",
    "gn:feature_code":"PPL",
    "gn:name":"Calder\u00f3n",
    "gn:population":0,
    "gn:timezone":"America/Havana",
    "iso:country":"CU",
    "name:und_x_variant":[
        "Maranjos",
        "Calder\u00f3n"
    ],
    "wof:name":"Calderon",
    "wof:placetype":"locality"
},
  "geometry": {"coordinates":[-76.02951,20.26378],"type":"Point"}
}