{
  "type": "Feature",
  "properties": {
    "gn:admin1_code":"15",
    "gn:asciiname":"Armonia",
    "gn:country_code":"CU",
    "gn:dem":219,
    "gn:feature_class":"P",
    "gn:feature_code":"PPL",
    "gn:name":"Armon\u00eda",
    "gn:population":0,
    "gn:timezone":"America/Havana",
    "iso:country":"CU",
    "name:spa_x_preferred":[
        "Armon\u00eda"
    ],
    "wof:name":"Armonia",
    "wof:placetype":"locality"
},
  "geometry": {"coordinates":[-76.12899,20.34589],"type":"Point"}
}