{
  "type": "Feature",
  "properties": {
    "gn:admin1_code":"09",
    "gn:asciiname":"Punta de Piedra",
    "gn:country_code":"CU",
    "gn:dem":20,
    "gn:feature_class":"P",
    "gn:feature_code":"PPL",
    "gn:name":"Punta de Piedra",
    "gn:population":0,
    "gn:timezone":"America/Havana",
    "iso:country":"CU",
    "name:spa_x_preferred":[
        "Punta de Piedra"
    ],
    "wof:name":"Punta de Piedra",
    "wof:placetype":"locality"
},
  "geometry": {"coordinates":[-77.24417,19.91057],"type":"Point"}
}