{
  "type": "Feature",
  "properties": {
    "gn:admin1_code":"12",
    "gn:asciiname":"Melones",
    "gn:country_code":"CU",
    "gn:dem":85,
    "gn:feature_class":"P",
    "gn:feature_code":"PPL",
    "gn:name":"Melones",
    "gn:population":0,
    "gn:timezone":"America/Havana",
    "iso:country":"CU",
    "name:spa_x_preferred":[
        "Melones"
    ],
    "wof:name":"Melones",
    "wof:placetype":"locality"
},
  "geometry": {"coordinates":[-76.04208,20.96176],"type":"Point"}
}