{
  "type": "Feature",
  "properties": {
    "gn:admin1_code":"10",
    "gn:asciiname":"Los Planitos",
    "gn:country_code":"CU",
    "gn:dem":474,
    "gn:feature_class":"P",
    "gn:feature_code":"PPL",
    "gn:name":"Los Planitos",
    "gn:population":0,
    "gn:timezone":"America/Havana",
    "iso:country":"CU",
    "name:spa_x_preferred":[
        "Los Planitos"
    ],
    "wof:name":"Los Planitos",
    "wof:placetype":"locality"
},
  "geometry": {"coordinates":[-74.27215,20.14092],"type":"Point"}
}