{
  "type": "Feature",
  "properties": {
    "gn:admin1_code":"AR",
    "gn:asciiname":"Llovera",
    "gn:country_code":"CU",
    "gn:dem":30,
    "gn:feature_class":"P",
    "gn:feature_code":"PPLL",
    "gn:name":"Llovera",
    "gn:population":0,
    "gn:timezone":"America/Havana",
    "iso:country":"CU",
    "name:spa_x_preferred":[
        "Llovera"
    ],
    "wof:name":"Llovera",
    "wof:placetype":"locality"
},
  "geometry": {"coordinates":[-82.99930000000001,22.67137],"type":"Point"}
}