{
  "type": "Feature",
  "properties": {
    "gn:admin1_code":"AR",
    "gn:asciiname":"El Chalet",
    "gn:country_code":"CU",
    "gn:dem":40,
    "gn:feature_class":"P",
    "gn:feature_code":"PPLL",
    "gn:name":"El Chalet",
    "gn:population":0,
    "gn:timezone":"America/Havana",
    "iso:country":"CU",
    "wof:name":"El Chalet",
    "wof:placetype":"locality"
},
  "geometry": {"coordinates":[-82.78333000000001,22.81667],"type":"Point"}
}