{
  "type": "Feature",
  "properties": {
    "gn:admin1_code":"03",
    "gn:asciiname":"San Carlos",
    "gn:country_code":"CU",
    "gn:dem":8,
    "gn:feature_class":"P",
    "gn:feature_code":"PPL",
    "gn:name":"San Carlos",
    "gn:population":0,
    "gn:timezone":"America/Havana",
    "iso:country":"CU",
    "name:spa_x_preferred":[
        "San Carlos"
    ],
    "wof:name":"San Carlos",
    "wof:placetype":"locality"
},
  "geometry": {"coordinates":[-81.30226,22.62142],"type":"Point"}
}