{
  "type": "Feature",
  "properties": {
    "gn:admin1_code":"16",
    "gn:asciiname":"Obispo",
    "gn:country_code":"CU",
    "gn:dem":135,
    "gn:feature_class":"P",
    "gn:feature_code":"PPL",
    "gn:name":"Obispo",
    "gn:population":0,
    "gn:timezone":"America/Havana",
    "iso:country":"CU",
    "wof:name":"Obispo",
    "wof:placetype":"locality"
},
  "geometry": {"coordinates":[-79.83194,22.18583],"type":"Point"}
}