{
  "type": "Feature",
  "properties": {
    "gn:admin1_code":"07",
    "gn:asciiname":"Juan Weiss",
    "gn:country_code":"CU",
    "gn:dem":38,
    "gn:feature_class":"P",
    "gn:feature_code":"PPLL",
    "gn:name":"Juan Weiss",
    "gn:population":0,
    "gn:timezone":"America/Havana",
    "iso:country":"CU",
    "wof:name":"Juan Weiss",
    "wof:placetype":"locality"
},
  "geometry": {"coordinates":[-79.05833,21.775],"type":"Point"}
}