{
  "type": "Feature",
  "properties": {
    "gn:admin1_code":"08",
    "gn:asciiname":"Cirilo Figueredo",
    "gn:country_code":"CU",
    "gn:dem":51,
    "gn:feature_class":"P",
    "gn:feature_code":"PPLL",
    "gn:name":"Cirilo Figueredo",
    "gn:population":0,
    "gn:timezone":"America/Havana",
    "iso:country":"CU",
    "name:und_x_variant":[
        "Cirilo Figueroa",
        "Cirilo Figueredo"
    ],
    "wof:name":"Cirilo Figueredo",
    "wof:placetype":"locality"
},
  "geometry": {"coordinates":[-80.34999999999999,22.23333],"type":"Point"}
}