{
  "type": "Feature",
  "properties": {
    "gn:admin1_code":"07",
    "gn:asciiname":"Marroqui",
    "gn:country_code":"CU",
    "gn:dem":174,
    "gn:feature_class":"P",
    "gn:feature_code":"PPL",
    "gn:name":"Marroqu\u00ed",
    "gn:population":0,
    "gn:timezone":"America/Havana",
    "iso:country":"CU",
    "name:und_x_variant":[
        "Palmarito",
        "Marroqu\u00ed"
    ],
    "wof:name":"Marroqui",
    "wof:placetype":"locality"
},
  "geometry": {"coordinates":[-78.91670000000001,22.04303],"type":"Point"}
}