{
  "type": "Feature",
  "properties": {
    "gn:admin1_code":"09",
    "gn:asciiname":"Boca del Toro",
    "gn:country_code":"CU",
    "gn:dem":17,
    "gn:feature_class":"P",
    "gn:feature_code":"PPL",
    "gn:name":"Boca del Toro",
    "gn:population":0,
    "gn:timezone":"America/Havana",
    "iso:country":"CU",
    "name:spa_x_preferred":[
        "Boca del Toro"
    ],
    "wof:name":"Boca del Toro",
    "wof:placetype":"locality"
},
  "geometry": {"coordinates":[-77.44279,19.86632],"type":"Point"}
}