{
  "type": "Feature",
  "properties": {
    "iso:country":"CU",
    "qs:gn_country":"CU",
    "qs:gn_fcode":"PPLX",
    "qs:gn_pop":0,
    "qs:name":"Habana Nueva",
    "qs:name_adm0":"Cuba",
    "qs:name_adm1":"Ciudad de la Habana",
    "qs:photos":1,
    "qs:photos_1k":1,
    "qs:photos_9k":1,
    "qs:photos_9r":1,
    "qs:photos_all":1,
    "qs:photos_sr":1,
    "qs:placetype":"Suburb",
    "qs:pop_sr":"0",
    "qs:woe_adm0":23424793,
    "wof:name":"Habana Nueva",
    "wof:placetype":"neighbourhood"
},
  "geometry": {"coordinates":[-82.31972,23.11861],"type":"Point"}
}