{
  "type": "Feature",
  "properties": {
    "gn:admin1_code":"AR",
    "gn:asciiname":"La Faustina",
    "gn:country_code":"CU",
    "gn:dem":66,
    "gn:feature_class":"P",
    "gn:feature_code":"PPL",
    "gn:name":"La Faustina",
    "gn:population":0,
    "gn:timezone":"America/Havana",
    "iso:country":"CU",
    "name:spa_x_preferred":[
        "La Faustina"
    ],
    "wof:name":"La Faustina",
    "wof:placetype":"locality"
},
  "geometry": {"coordinates":[-82.52194,22.95472],"type":"Point"}
}