{
  "type": "Feature",
  "properties": {
    "gn:admin1_code":"03",
    "gn:asciiname":"Arrieta",
    "gn:country_code":"CU",
    "gn:dem":67,
    "gn:feature_class":"P",
    "gn:feature_code":"PPL",
    "gn:name":"Arrieta",
    "gn:population":0,
    "gn:timezone":"America/Havana",
    "iso:country":"CU",
    "name:ara_x_preferred":[
        "\u0623\u0631\u0627\u064a\u062a\u0627"
    ],
    "name:arg_x_preferred":[
        "Arrieta"
    ],
    "name:bre_x_preferred":[
        "Arrieta"
    ],
    "name:cat_x_preferred":[
        "Arrieta"
    ],
    "name:ceb_x_preferred":[
        "Arrieta"
    ],
    "name:dan_x_preferred":[
        "Arrieta"
    ],
    "name:deu_x_preferred":[
        "Arrieta"
    ],
    "name:eus_x_preferred":[
        "Arrieta"
    ],
    "name:fra_x_preferred":[
        "Arrieta"
    ],
    "name:glg_x_preferred":[
        "Arrieta"
    ],
    "name:hun_x_preferred":[
        "Arrieta"
    ],
    "name:ind_x_preferred":[
        "Arrieta"
    ],
    "name:ita_x_preferred":[
        "Arrieta"
    ],
    "name:lat_x_preferred":[
        "Arrieta"
    ],
    "name:msa_x_preferred":[
        "Arrieta"
    ],
    "name:nld_x_preferred":[
        "Arrieta"
    ],
    "name:oci_x_preferred":[
        "Arrieta"
    ],
    "name:pol_x_preferred":[
        "Arrieta"
    ],
    "name:por_x_preferred":[
        "Arrieta"
    ],
    "name:rus_x_preferred":[
        "\u0410\u0440\u0440\u044c\u0435\u0442\u0430"
    ],
    "name:spa_x_preferred":[
        "Arrieta"
    ],
    "name:swe_x_preferred":[
        "Arrieta"
    ],
    "name:ukr_x_preferred":[
        "\u0410\u0440\u0440\u0456\u0454\u0442\u0430"
    ],
    "name:uzb_x_preferred":[
        "Arrieta"
    ],
    "name:war_x_preferred":[
        "Arrieta"
    ],
    "name:zho_x_preferred":[
        "\u963f\u5217\u5854"
    ],
    "wof:name":"Arrieta",
    "wof:placetype":"locality"
},
  "geometry": {"coordinates":[-80.90000000000001,22.76667],"type":"Point"}
}