{
  "type": "Feature",
  "properties": {
    "gn:admin1_code":"03",
    "gn:asciiname":"Ponce",
    "gn:country_code":"CU",
    "gn:dem":65,
    "gn:feature_class":"P",
    "gn:feature_code":"PPLL",
    "gn:name":"Ponce",
    "gn:population":0,
    "gn:timezone":"America/Havana",
    "iso:country":"CU",
    "name:ceb_x_preferred":[
        "Ponce"
    ],
    "name:deu_x_preferred":[
        "Ponce"
    ],
    "name:fin_x_preferred":[
        "Ponce"
    ],
    "name:fra_x_preferred":[
        "Ponce"
    ],
    "name:ita_x_preferred":[
        "Ponce"
    ],
    "name:jpn_x_preferred":[
        "\u30dd\u30f3\u30bb"
    ],
    "name:nld_x_preferred":[
        "Ponce"
    ],
    "name:pol_x_preferred":[
        "Ponce"
    ],
    "name:rus_x_preferred":[
        "\u041f\u043e\u043d\u0441\u0435"
    ],
    "name:spa_x_preferred":[
        "Ponce"
    ],
    "name:ukr_x_preferred":[
        "\u041f\u043e\u043d\u0441\u0435"
    ],
    "wof:name":"Ponce",
    "wof:placetype":"locality"
},
  "geometry": {"coordinates":[-81.28083000000002,22.98167],"type":"Point"}
}