{
  "type": "Feature",
  "properties": {
    "gn:admin1_code":"09",
    "gn:asciiname":"Palmas Altas",
    "gn:country_code":"CU",
    "gn:dem":17,
    "gn:feature_class":"P",
    "gn:feature_code":"PPL",
    "gn:name":"Palmas Altas",
    "gn:population":0,
    "gn:timezone":"America/Havana",
    "iso:country":"CU",
    "wof:name":"Palmas Altas",
    "wof:placetype":"locality"
},
  "geometry": {"coordinates":[-77.05,20.31667],"type":"Point"}
}