{
  "type": "Feature",
  "properties": {
    "gn:admin1_code":"07",
    "gn:asciiname":"Fabal",
    "gn:country_code":"CU",
    "gn:dem":15,
    "gn:feature_class":"P",
    "gn:feature_code":"PPL",
    "gn:name":"Fabal",
    "gn:population":0,
    "gn:timezone":"America/Havana",
    "iso:country":"CU",
    "name:spa_x_preferred":[
        "Fabal"
    ],
    "wof:name":"Fabal",
    "wof:placetype":"locality"
},
  "geometry": {"coordinates":[-78.39686,22.08816],"type":"Point"}
}