{
  "type": "Feature",
  "properties": {
    "gn:admin1_code":"14",
    "gn:asciiname":"Caguasal",
    "gn:country_code":"CU",
    "gn:dem":120,
    "gn:feature_class":"P",
    "gn:feature_code":"PPL",
    "gn:name":"Caguasal",
    "gn:population":0,
    "gn:timezone":"America/Havana",
    "iso:country":"CU",
    "name:spa_x_preferred":[
        "Caguasal"
    ],
    "wof:name":"Caguasal",
    "wof:placetype":"locality"
},
  "geometry": {"coordinates":[-79.76259,22.15985],"type":"Point"}
}