{
  "type": "Feature",
  "properties": {
    "gn:admin1_code":"12",
    "gn:asciiname":"Tres Palmas",
    "gn:country_code":"CU",
    "gn:dem":205,
    "gn:feature_class":"P",
    "gn:feature_code":"PPL",
    "gn:name":"Tres Palmas",
    "gn:population":0,
    "gn:timezone":"America/Havana",
    "iso:country":"CU",
    "name:spa_x_preferred":[
        "Tres Palmas"
    ],
    "wof:name":"Tres Palmas",
    "wof:placetype":"locality"
},
  "geometry": {"coordinates":[-75.27478000000001,20.51001],"type":"Point"}
}