{
  "type": "Feature",
  "properties": {
    "gn:admin1_code":"09",
    "gn:asciiname":"La Punta",
    "gn:country_code":"CU",
    "gn:dem":6,
    "gn:feature_class":"P",
    "gn:feature_code":"PPLL",
    "gn:name":"La Punta",
    "gn:population":0,
    "gn:timezone":"America/Havana",
    "iso:country":"CU",
    "name:spa_x_preferred":[
        "La Punta"
    ],
    "wof:name":"La Punta",
    "wof:placetype":"locality"
},
  "geometry": {"coordinates":[-77.03506999999998,20.6308],"type":"Point"}
}