{
  "type": "Feature",
  "properties": {
    "gn:admin1_code":"05",
    "gn:asciiname":"La Tumba",
    "gn:cc2":"CU",
    "gn:country_code":"CU",
    "gn:dem":79,
    "gn:feature_class":"P",
    "gn:feature_code":"PPLL",
    "gn:name":"La Tumba",
    "gn:population":0,
    "gn:timezone":"America/Havana",
    "iso:country":"CU",
    "name:spa_x_preferred":[
        "La tumba"
    ],
    "name:und_x_variant":[
        "Salsipuedes",
        "La Tumba"
    ],
    "wof:name":"La Tumba",
    "wof:placetype":"locality"
},
  "geometry": {"coordinates":[-78.27583,21.69111],"type":"Point"}
}