{
  "type": "Feature",
  "properties": {
    "gn:admin1_code":"15",
    "gn:asciiname":"La Carolina",
    "gn:country_code":"CU",
    "gn:dem":599,
    "gn:feature_class":"P",
    "gn:feature_code":"PPLL",
    "gn:name":"La Carolina",
    "gn:population":0,
    "gn:timezone":"America/Havana",
    "iso:country":"CU",
    "name:spa_x_preferred":[
        "La Carolina"
    ],
    "name:spa_x_variant":[
        "Carolina"
    ],
    "wof:name":"La Carolina",
    "wof:placetype":"locality"
},
  "geometry": {"coordinates":[-75.55970000000001,19.9977],"type":"Point"}
}