{
  "type": "Feature",
  "properties": {
    "gn:admin1_code":"16",
    "gn:asciiname":"Fortuna",
    "gn:country_code":"CU",
    "gn:dem":4,
    "gn:feature_class":"P",
    "gn:feature_code":"PPLL",
    "gn:name":"Fortuna",
    "gn:population":0,
    "gn:timezone":"America/Havana",
    "iso:country":"CU",
    "wof:name":"Fortuna",
    "wof:placetype":"locality"
},
  "geometry": {"coordinates":[-80.03333000000001,22.91667],"type":"Point"}
}