{
  "type": "Feature",
  "properties": {
    "gn:admin1_code":"10",
    "gn:asciiname":"Manglito",
    "gn:country_code":"CU",
    "gn:dem":14,
    "gn:feature_class":"P",
    "gn:feature_code":"PPL",
    "gn:name":"Manglito",
    "gn:population":0,
    "gn:timezone":"America/Havana",
    "iso:country":"CU",
    "name:spa_x_preferred":[
        "Manglito"
    ],
    "wof:name":"Manglito",
    "wof:placetype":"locality"
},
  "geometry": {"coordinates":[-74.34666999999997,20.29341],"type":"Point"}
}