{
  "type": "Feature",
  "properties": {
    "gn:admin1_code":"AR",
    "gn:asciiname":"La Aurora",
    "gn:country_code":"CU",
    "gn:dem":22,
    "gn:feature_class":"P",
    "gn:feature_code":"PPL",
    "gn:name":"La Aurora",
    "gn:population":0,
    "gn:timezone":"America/Havana",
    "iso:country":"CU",
    "name:ceb_x_preferred":[
        "La Aurora"
    ],
    "name:deu_x_preferred":[
        "La Aurora"
    ],
    "name:glg_x_preferred":[
        "La Aurora"
    ],
    "name:rus_x_preferred":[
        "\u041b\u0430-\u0410\u0443\u0440\u043e\u0440\u0430"
    ],
    "name:spa_x_preferred":[
        "La Aurora"
    ],
    "name:srp_x_preferred":[
        "\u041b\u0430 \u0410\u0443\u0440\u043e\u0440\u0430"
    ],
    "name:swe_x_preferred":[
        "La Aurora"
    ],
    "name:und_x_variant":[
        "Aurora"
    ],
    "wof:name":"La Aurora",
    "wof:placetype":"locality"
},
  "geometry": {"coordinates":[-82.55136,23.03828],"type":"Point"}
}