{
  "type": "Feature",
  "properties": {
    "gn:admin1_code":"07",
    "gn:asciiname":"San Agustin del Zapote",
    "gn:country_code":"CU",
    "gn:dem":41,
    "gn:feature_class":"P",
    "gn:feature_code":"PPLL",
    "gn:name":"San Agust\u00edn del Zapote",
    "gn:population":0,
    "gn:timezone":"America/Havana",
    "iso:country":"CU",
    "wof:name":"San Agustin del Zapote",
    "wof:placetype":"locality"
},
  "geometry": {"coordinates":[-78.90000000000001,22.18333],"type":"Point"}
}