{
  "type": "Feature",
  "properties": {
    "gn:admin1_code":"03",
    "gn:asciiname":"Anguila",
    "gn:country_code":"CU",
    "gn:dem":28,
    "gn:feature_class":"P",
    "gn:feature_code":"PPL",
    "gn:name":"Anguila",
    "gn:population":0,
    "gn:timezone":"America/Havana",
    "iso:country":"CU",
    "name:spa_x_preferred":[
        "Anguila"
    ],
    "wof:name":"Anguila",
    "wof:placetype":"locality"
},
  "geometry": {"coordinates":[-80.96661999999998,22.91168],"type":"Point"}
}