{
  "type": "Feature",
  "properties": {
    "gn:admin1_code":"MA",
    "gn:asciiname":"Guanaja",
    "gn:country_code":"CU",
    "gn:dem":89,
    "gn:feature_class":"P",
    "gn:feature_code":"PPLL",
    "gn:name":"Guanaja",
    "gn:population":0,
    "gn:timezone":"America/Havana",
    "iso:country":"CU",
    "name:bre_x_preferred":[
        "Guanaja"
    ],
    "name:cat_x_preferred":[
        "Guanaja"
    ],
    "name:ceb_x_preferred":[
        "Guanaja"
    ],
    "name:deu_x_preferred":[
        "Guanaja"
    ],
    "name:ell_x_preferred":[
        "\u0393\u03bf\u03c5\u03b1\u03bd\u03ac\u03c7\u03b1"
    ],
    "name:fin_x_preferred":[
        "Guanaja"
    ],
    "name:fra_x_preferred":[
        "Guanaja"
    ],
    "name:ita_x_preferred":[
        "Guanaja"
    ],
    "name:kor_x_preferred":[
        "\uad6c\uc544\ub098\uc57c\uc12c"
    ],
    "name:lit_x_preferred":[
        "Guanacha"
    ],
    "name:mar_x_preferred":[
        "\u0917\u094d\u0935\u093e\u0928\u093e\u0939\u093e"
    ],
    "name:nld_x_preferred":[
        "Guanaja"
    ],
    "name:pol_x_preferred":[
        "Guanaja"
    ],
    "name:por_x_preferred":[
        "Guanaja"
    ],
    "name:spa_x_preferred":[
        "Guanaja"
    ],
    "name:swe_x_preferred":[
        "Guanaja"
    ],
    "name:zho_x_preferred":[
        "\u74dc\u7d0d\u54c8\u5cf6"
    ],
    "wof:name":"Guanaja",
    "wof:placetype":"locality"
},
  "geometry": {"coordinates":[-82.06944,23.07833],"type":"Point"}
}