{
  "type": "Feature",
  "properties": {
    "gn:admin1_code":"MA",
    "gn:asciiname":"Guanaja",
    "gn:country_code":"CU",
    "gn:dem":89,
    "gn:feature_class":"P",
    "gn:feature_code":"PPLL",
    "gn:name":"Guanaja",
    "gn:population":0,
    "gn:timezone":"America/Havana",
    "iso:country":"CU",
    "name:spa_x_preferred":[
        "Guanaja"
    ],
    "wof:name":"Guanaja",
    "wof:placetype":"locality"
},
  "geometry": {"coordinates":[-82.06944,23.07833],"type":"Point"}
}