{
  "type": "Feature",
  "properties": {
    "gn:admin1_code":"15",
    "gn:asciiname":"El Descanso",
    "gn:cc2":"CU",
    "gn:country_code":"CU",
    "gn:dem":132,
    "gn:feature_class":"P",
    "gn:feature_code":"PPLL",
    "gn:name":"El Descanso",
    "gn:population":0,
    "gn:timezone":"America/Havana",
    "iso:country":"CU",
    "name:und_x_variant":[
        "Descanso",
        "El Descanso"
    ],
    "wof:name":"El Descanso",
    "wof:placetype":"locality"
},
  "geometry": {"coordinates":[-76.25,20.35],"type":"Point"}
}