{
  "type": "Feature",
  "properties": {
    "gn:admin1_code":"AR",
    "gn:asciiname":"Andres",
    "gn:country_code":"CU",
    "gn:dem":36,
    "gn:feature_class":"P",
    "gn:feature_code":"PPLL",
    "gn:name":"Andr\u00e9s",
    "gn:population":0,
    "gn:timezone":"America/Havana",
    "iso:country":"CU",
    "name:ceb_x_preferred":[
        "Andres"
    ],
    "name:ces_x_preferred":[
        "Andres"
    ],
    "name:fra_x_preferred":[
        "Andres"
    ],
    "name:ita_x_preferred":[
        "Andres"
    ],
    "name:jpn_x_preferred":[
        "\u30a2\u30f3\u30c9\u30ec\u30b9"
    ],
    "name:kor_x_preferred":[
        "\uc548\ub4dc\ub808\uc2a4"
    ],
    "name:nld_x_preferred":[
        "Andres"
    ],
    "name:tgl_x_preferred":[
        "Andres"
    ],
    "wof:name":"Andres",
    "wof:placetype":"locality"
},
  "geometry": {"coordinates":[-82.53333000000001,22.83333],"type":"Point"}
}