{
  "type": "Feature",
  "properties": {
    "gn:admin1_code":"MA",
    "gn:asciiname":"La Ruda",
    "gn:country_code":"CU",
    "gn:dem":92,
    "gn:feature_class":"P",
    "gn:feature_code":"PPLL",
    "gn:name":"La Ruda",
    "gn:population":0,
    "gn:timezone":"America/Havana",
    "iso:country":"CU",
    "wof:name":"La Ruda",
    "wof:placetype":"locality"
},
  "geometry": {"coordinates":[-82.21666999999999,22.85],"type":"Point"}
}