{
  "type": "Feature",
  "properties": {
    "gn:admin1_code":"07",
    "gn:asciiname":"Mina Dos",
    "gn:country_code":"CU",
    "gn:dem":81,
    "gn:feature_class":"P",
    "gn:feature_code":"PPLL",
    "gn:name":"Mina Dos",
    "gn:population":0,
    "gn:timezone":"America/Havana",
    "iso:country":"CU",
    "name:spa_x_preferred":[
        "Mina Dos"
    ],
    "name:spa_x_variant":[
        "La Mina"
    ],
    "wof:name":"Mina Dos",
    "wof:placetype":"locality"
},
  "geometry": {"coordinates":[-78.79889,21.93694],"type":"Point"}
}