{
  "type": "Feature",
  "properties": {
    "gn:admin1_code":"02",
    "gn:asciiname":"Minas",
    "gn:country_code":"CU",
    "gn:dem":51,
    "gn:feature_class":"P",
    "gn:feature_code":"PPL",
    "gn:name":"Minas",
    "gn:population":0,
    "gn:timezone":"America/Havana",
    "iso:country":"CU",
    "name:spa_x_preferred":[
        "Minas"
    ],
    "wof:name":"Minas",
    "wof:placetype":"locality"
},
  "geometry": {"coordinates":[-82.19537,23.12395],"type":"Point"}
}