{
  "type": "Feature",
  "properties": {
    "gn:admin1_code":"10",
    "gn:asciiname":"Ribera",
    "gn:country_code":"CU",
    "gn:dem":30,
    "gn:feature_class":"P",
    "gn:feature_code":"PPL",
    "gn:name":"Ribera",
    "gn:population":0,
    "gn:timezone":"America/Havana",
    "iso:country":"CU",
    "name:spa_x_preferred":[
        "Ribera"
    ],
    "wof:name":"Ribera",
    "wof:placetype":"locality"
},
  "geometry": {"coordinates":[-74.53338000000002,20.35898],"type":"Point"}
}