{
  "type": "Feature",
  "properties": {
    "gn:admin1_code":"09",
    "gn:asciiname":"Santa Barbara",
    "gn:country_code":"CU",
    "gn:dem":297,
    "gn:feature_class":"P",
    "gn:feature_code":"PPLL",
    "gn:name":"Santa B\u00e1rbara",
    "gn:population":0,
    "gn:timezone":"America/Havana",
    "iso:country":"CU",
    "wof:name":"Santa Barbara",
    "wof:placetype":"locality"
},
  "geometry": {"coordinates":[-76.56667,20.21667],"type":"Point"}
}