{
  "type": "Feature",
  "properties": {
    "gn:admin1_code":"05",
    "gn:asciiname":"La Hortensia",
    "gn:country_code":"CU",
    "gn:dem":51,
    "gn:feature_class":"P",
    "gn:feature_code":"PPLL",
    "gn:name":"La Hortensia",
    "gn:population":0,
    "gn:timezone":"America/Havana",
    "iso:country":"CU",
    "name:spa_x_preferred":[
        "La Hortensia"
    ],
    "wof:name":"La Hortensia",
    "wof:placetype":"locality"
},
  "geometry": {"coordinates":[-78.33043000000001,21.53654],"type":"Point"}
}