{
  "type": "Feature",
  "properties": {
    "gn:admin1_code":"08",
    "gn:asciiname":"Junco",
    "gn:country_code":"CU",
    "gn:dem":36,
    "gn:feature_class":"P",
    "gn:feature_code":"PPLL",
    "gn:name":"Junco",
    "gn:population":0,
    "gn:timezone":"America/Havana",
    "iso:country":"CU",
    "name:ara_x_preferred":[
        "\u062c\u0646\u0643"
    ],
    "name:aze_x_preferred":[
        "Yunko"
    ],
    "name:bre_x_preferred":[
        "Junko"
    ],
    "name:cat_x_preferred":[
        "Junco"
    ],
    "name:ceb_x_preferred":[
        "Junco"
    ],
    "name:ces_x_preferred":[
        "Junco"
    ],
    "name:epo_x_preferred":[
        "Junkuloj"
    ],
    "name:fas_x_preferred":[
        "\u0633\u0627\u0632\u0648\u0646\u0634\u06cc\u0646"
    ],
    "name:fin_x_preferred":[
        "Junkot"
    ],
    "name:fra_x_preferred":[
        "Junco"
    ],
    "name:gle_x_preferred":[
        "Luachair\u00edn"
    ],
    "name:hun_x_preferred":[
        "Junco"
    ],
    "name:nav_x_preferred":[
        "Dilch\u02bc\u00f3shii"
    ],
    "name:nld_x_preferred":[
        "Junco"
    ],
    "name:nno_x_preferred":[
        "Junco"
    ],
    "name:nor_x_preferred":[
        "Junco"
    ],
    "name:pol_x_preferred":[
        "Junco"
    ],
    "name:por_x_preferred":[
        "Junco"
    ],
    "name:rus_x_preferred":[
        "\u042e\u043d\u043a\u043e"
    ],
    "name:spa_x_preferred":[
        "Junco"
    ],
    "name:swe_x_preferred":[
        "Juncor"
    ],
    "name:tur_x_preferred":[
        "Junko"
    ],
    "name:ukr_x_preferred":[
        "\u042e\u043d\u043a\u043e"
    ],
    "name:vie_x_preferred":[
        "Junco"
    ],
    "name:war_x_preferred":[
        "Junco"
    ],
    "wof:name":"Junco",
    "wof:placetype":"locality"
},
  "geometry": {"coordinates":[-80.38333,22.13333],"type":"Point"}
}