{
  "type": "Feature",
  "properties": {
    "gn:admin1_code":"16",
    "gn:asciiname":"Batey Colorado",
    "gn:country_code":"CU",
    "gn:dem":220,
    "gn:feature_class":"P",
    "gn:feature_code":"PPL",
    "gn:name":"Batey Colorado",
    "gn:population":0,
    "gn:timezone":"America/Havana",
    "iso:country":"CU",
    "name:spa_x_preferred":[
        "Batey Colorado"
    ],
    "wof:name":"Batey Colorado",
    "wof:placetype":"locality"
},
  "geometry": {"coordinates":[-79.38594000000001,22.29783],"type":"Point"}
}