{
  "type": "Feature",
  "properties": {
    "gn:admin1_code":"16",
    "gn:asciiname":"La Derecha",
    "gn:country_code":"CU",
    "gn:dem":160,
    "gn:feature_class":"P",
    "gn:feature_code":"PPLL",
    "gn:name":"La Derecha",
    "gn:population":0,
    "gn:timezone":"America/Havana",
    "iso:country":"CU",
    "name:spa_x_preferred":[
        "La Derecha"
    ],
    "wof:name":"La Derecha",
    "wof:placetype":"locality"
},
  "geometry": {"coordinates":[-80.04619,22.28257],"type":"Point"}
}