{
  "type": "Feature",
  "properties": {
    "gn:admin1_code":"09",
    "gn:asciiname":"El Mate",
    "gn:country_code":"CU",
    "gn:dem":180,
    "gn:feature_class":"P",
    "gn:feature_code":"PPLL",
    "gn:name":"El Mate",
    "gn:population":0,
    "gn:timezone":"America/Havana",
    "iso:country":"CU",
    "name:spa_x_preferred":[
        "El Mate"
    ],
    "wof:name":"El Mate",
    "wof:placetype":"locality"
},
  "geometry": {"coordinates":[-77.17191,20.0587],"type":"Point"}
}