{
  "type": "Feature",
  "properties": {
    "gn:admin1_code":"03",
    "gn:asciiname":"Guasimal",
    "gn:country_code":"CU",
    "gn:dem":54,
    "gn:feature_class":"P",
    "gn:feature_code":"PPLL",
    "gn:name":"Guasimal",
    "gn:population":0,
    "gn:timezone":"America/Havana",
    "iso:country":"CU",
    "name:ceb_x_preferred":[
        "Guasimal"
    ],
    "name:deu_x_preferred":[
        "Guasimal"
    ],
    "name:hat_x_preferred":[
        "Guasimal"
    ],
    "name:nld_x_preferred":[
        "Guasimal"
    ],
    "wof:name":"Guasimal",
    "wof:placetype":"locality"
},
  "geometry": {"coordinates":[-80.78333000000001,22.81667],"type":"Point"}
}