{
  "type": "Feature",
  "properties": {
    "gn:admin1_code":"07",
    "gn:asciiname":"Laguna Larga",
    "gn:country_code":"CU",
    "gn:dem":23,
    "gn:feature_class":"P",
    "gn:feature_code":"PPL",
    "gn:name":"Laguna Larga",
    "gn:population":0,
    "gn:timezone":"America/Havana",
    "iso:country":"CU",
    "name:spa_x_preferred":[
        "Laguna Larga"
    ],
    "name:und_x_variant":[
        "Manga Larga",
        "Languna Larga",
        "Marga Larga"
    ],
    "wof:name":"Laguna Larga",
    "wof:placetype":"locality"
},
  "geometry": {"coordinates":[-78.30194,21.9475],"type":"Point"}
}