{
  "type": "Feature",
  "properties": {
    "gn:admin1_code":"01",
    "gn:asciiname":"Conico",
    "gn:country_code":"CU",
    "gn:dem":20,
    "gn:feature_class":"P",
    "gn:feature_code":"PPL",
    "gn:name":"Con\u00edco",
    "gn:population":0,
    "gn:timezone":"America/Havana",
    "iso:country":"CU",
    "wof:name":"Conico",
    "wof:placetype":"locality"
},
  "geometry": {"coordinates":[-84.29333000000003,22.25306],"type":"Point"}
}