{
  "type": "Feature",
  "properties": {
    "gn:admin1_code":"MA",
    "gn:asciiname":"San Esteban",
    "gn:country_code":"CU",
    "gn:dem":43,
    "gn:feature_class":"P",
    "gn:feature_code":"PPLL",
    "gn:name":"San Esteban",
    "gn:population":0,
    "gn:timezone":"America/Havana",
    "iso:country":"CU",
    "name:ast_x_preferred":[
        "San Esteban"
    ],
    "name:ceb_x_preferred":[
        "San Esteban"
    ],
    "name:deu_x_preferred":[
        "San Esteban"
    ],
    "name:eus_x_preferred":[
        "San Esteban"
    ],
    "name:fra_x_preferred":[
        "San Esteban"
    ],
    "name:ita_x_preferred":[
        "San Esteban"
    ],
    "name:nld_x_preferred":[
        "San Esteban"
    ],
    "name:por_x_preferred":[
        "San Esteban"
    ],
    "name:spa_x_preferred":[
        "San Esteban"
    ],
    "name:srp_x_preferred":[
        "\u0421\u0430\u043d \u0415\u0441\u0442\u0435\u0431\u0430\u043d"
    ],
    "name:swe_x_preferred":[
        "San Esteban"
    ],
    "name:war_x_preferred":[
        "San Esteban"
    ],
    "wof:name":"San Esteban",
    "wof:placetype":"locality"
},
  "geometry": {"coordinates":[-81.71665,23.09118],"type":"Point"}
}