{
  "type": "Feature",
  "properties": {
    "gn:admin1_code":"MA",
    "gn:asciiname":"San Esteban",
    "gn:country_code":"CU",
    "gn:dem":43,
    "gn:feature_class":"P",
    "gn:feature_code":"PPLL",
    "gn:name":"San Esteban",
    "gn:population":0,
    "gn:timezone":"America/Havana",
    "iso:country":"CU",
    "name:spa_x_preferred":[
        "San Esteban"
    ],
    "wof:name":"San Esteban",
    "wof:placetype":"locality"
},
  "geometry": {"coordinates":[-81.71665,23.09118],"type":"Point"}
}