{
  "type": "Feature",
  "properties": {
    "gn:admin1_code":"03",
    "gn:asciiname":"Aguedita",
    "gn:country_code":"CU",
    "gn:dem":73,
    "gn:feature_class":"P",
    "gn:feature_code":"PPL",
    "gn:name":"Aguedita",
    "gn:population":0,
    "gn:timezone":"America/Havana",
    "iso:country":"CU",
    "name:spa_x_preferred":[
        "Aguedita"
    ],
    "wof:name":"Aguedita",
    "wof:placetype":"locality"
},
  "geometry": {"coordinates":[-80.75395999999998,22.68697],"type":"Point"}
}