{
  "type": "Feature",
  "properties": {
    "gn:admin1_code":"16",
    "gn:asciiname":"El Barro",
    "gn:country_code":"CU",
    "gn:dem":69,
    "gn:feature_class":"P",
    "gn:feature_code":"PPL",
    "gn:name":"El Barro",
    "gn:population":0,
    "gn:timezone":"America/Havana",
    "iso:country":"CU",
    "name:spa_x_preferred":[
        "El Berro"
    ],
    "name:spa_x_variant":[
        "El Barro"
    ],
    "wof:name":"El Barro",
    "wof:placetype":"locality"
},
  "geometry": {"coordinates":[-79.81686999999999,22.45234],"type":"Point"}
}