{
  "type": "Feature",
  "properties": {
    "gn:admin1_code":"07",
    "gn:asciiname":"El Milagro",
    "gn:country_code":"CU",
    "gn:dem":81,
    "gn:feature_class":"P",
    "gn:feature_code":"PPL",
    "gn:name":"El Milagro",
    "gn:population":0,
    "gn:timezone":"America/Havana",
    "iso:country":"CU",
    "name:spa_x_preferred":[
        "El Milagro"
    ],
    "wof:name":"El Milagro",
    "wof:placetype":"locality"
},
  "geometry": {"coordinates":[-78.98568,21.87875],"type":"Point"}
}