{
  "type": "Feature",
  "properties": {
    "gn:admin1_code":"01",
    "gn:asciiname":"La Maria",
    "gn:country_code":"CU",
    "gn:dem":58,
    "gn:feature_class":"P",
    "gn:feature_code":"PPLL",
    "gn:name":"La Mar\u00eda",
    "gn:population":0,
    "gn:timezone":"America/Havana",
    "iso:country":"CU",
    "wof:name":"La Maria",
    "wof:placetype":"locality"
},
  "geometry": {"coordinates":[-83.48333000000002,22.53333],"type":"Point"}
}