{
  "type": "Feature",
  "properties": {
    "gn:admin1_code":"15",
    "gn:asciiname":"San Juan",
    "gn:country_code":"CU",
    "gn:dem":495,
    "gn:feature_class":"P",
    "gn:feature_code":"PPLL",
    "gn:name":"San Juan",
    "gn:population":0,
    "gn:timezone":"America/Havana",
    "iso:country":"CU",
    "wof:name":"San Juan",
    "wof:placetype":"locality"
},
  "geometry": {"coordinates":[-75.68333,20.05],"type":"Point"}
}