{
  "type": "Feature",
  "properties": {
    "gn:admin1_code":"05",
    "gn:asciiname":"El Jardin",
    "gn:cc2":"CU",
    "gn:country_code":"CU",
    "gn:dem":43,
    "gn:feature_class":"P",
    "gn:feature_code":"PPL",
    "gn:name":"El Jard\u00edn",
    "gn:population":0,
    "gn:timezone":"America/Havana",
    "iso:country":"CU",
    "name:spa_x_preferred":[
        "Casa El Jard\u00edn"
    ],
    "name:und_x_variant":[
        "Jard\u00edn",
        "El Jard\u00edn"
    ],
    "wof:name":"El Jardin",
    "wof:placetype":"locality"
},
  "geometry": {"coordinates":[-78.05,21.76667],"type":"Point"}
}