{
  "type": "Feature",
  "properties": {
    "gn:admin1_code":"13",
    "gn:asciiname":"Los Apostoles",
    "gn:country_code":"CU",
    "gn:dem":4,
    "gn:feature_class":"P",
    "gn:feature_code":"PPLL",
    "gn:name":"Los Ap\u00f3stoles",
    "gn:population":0,
    "gn:timezone":"America/Havana",
    "iso:country":"CU",
    "name:spa_x_preferred":[
        "Los Ap\u00f3stoles"
    ],
    "name:und_x_variant":[
        "Los Doce Ap\u00f3stoles",
        "Doce Ap\u00f3stoles"
    ],
    "wof:name":"Los Apostoles",
    "wof:placetype":"locality"
},
  "geometry": {"coordinates":[-76.81421,21.36233],"type":"Point"}
}