{
  "type": "Feature",
  "properties": {
    "gn:admin1_code":"13",
    "gn:asciiname":"El Canal",
    "gn:country_code":"CU",
    "gn:dem":20,
    "gn:feature_class":"P",
    "gn:feature_code":"PPL",
    "gn:name":"El Canal",
    "gn:population":0,
    "gn:timezone":"America/Havana",
    "iso:country":"CU",
    "name:und_x_variant":[
        "Canal",
        "El Canal"
    ],
    "wof:name":"El Canal",
    "wof:placetype":"locality"
},
  "geometry": {"coordinates":[-76.45684,21.1585],"type":"Point"}
}