{
  "type": "Feature",
  "properties": {
    "gn:admin1_code":"07",
    "gn:asciiname":"Villa Maria",
    "gn:cc2":"CU",
    "gn:country_code":"CU",
    "gn:dem":33,
    "gn:feature_class":"P",
    "gn:feature_code":"PPLL",
    "gn:name":"Villa Mar\u00eda",
    "gn:population":0,
    "gn:timezone":"America/Havana",
    "iso:country":"CU",
    "name:cat_x_preferred":[
        "Villa Maria"
    ],
    "name:deu_x_preferred":[
        "Villa Maria"
    ],
    "name:fra_x_preferred":[
        "Villa-Maria"
    ],
    "name:ita_x_preferred":[
        "Villa Maria"
    ],
    "name:nld_x_preferred":[
        "Villa Maria"
    ],
    "name:por_x_preferred":[
        "Villa Mar\u00eda"
    ],
    "name:spa_x_preferred":[
        "Villa Mar\u00eda"
    ],
    "name:srp_x_preferred":[
        "Vila Marija"
    ],
    "name:und_x_variant":[
        "Villa Marla",
        "Villa Mar\u00eda"
    ],
    "wof:name":"Villa Maria",
    "wof:placetype":"locality"
},
  "geometry": {"coordinates":[-78.66778000000002,22.0175],"type":"Point"}
}