{
  "type": "Feature",
  "properties": {
    "gn:admin1_code":"12",
    "gn:asciiname":"El Nispero",
    "gn:country_code":"CU",
    "gn:dem":90,
    "gn:feature_class":"P",
    "gn:feature_code":"PPL",
    "gn:name":"El N\u00edspero",
    "gn:population":0,
    "gn:timezone":"America/Havana",
    "iso:country":"CU",
    "name:ceb_x_preferred":[
        "El N\u00edspero"
    ],
    "name:fra_x_preferred":[
        "El Nispero"
    ],
    "name:ita_x_preferred":[
        "El N\u00edspero"
    ],
    "name:nld_x_preferred":[
        "El N\u00edspero"
    ],
    "name:por_x_preferred":[
        "El Nispero"
    ],
    "name:spa_x_preferred":[
        "El N\u00edspero"
    ],
    "name:swe_x_preferred":[
        "El N\u00edspero"
    ],
    "name:zho_x_preferred":[
        "\u57c3\u723e\u5c3c\u65af\u4f69\u7f85"
    ],
    "wof:name":"El Nispero",
    "wof:placetype":"locality"
},
  "geometry": {"coordinates":[-76.02733000000001,20.65586],"type":"Point"}
}