{
  "type": "Feature",
  "properties": {
    "gn:admin1_code":"02",
    "gn:asciiname":"El Cano",
    "gn:cc2":"CU",
    "gn:country_code":"CU",
    "gn:dem":62,
    "gn:feature_class":"P",
    "gn:feature_code":"PPL",
    "gn:name":"El Cano",
    "gn:population":0,
    "gn:timezone":"America/Havana",
    "iso:country":"CU",
    "name:und_x_variant":[
        "Cano",
        "El Cano"
    ],
    "wof:name":"El Cano",
    "wof:placetype":"locality"
},
  "geometry": {"coordinates":[-82.45917,23.03306],"type":"Point"}
}