{
  "type": "Feature",
  "properties": {
    "gn:admin1_code":"16",
    "gn:asciiname":"Platanical",
    "gn:country_code":"CU",
    "gn:dem":82,
    "gn:feature_class":"P",
    "gn:feature_code":"PPL",
    "gn:name":"Platanical",
    "gn:population":0,
    "gn:timezone":"America/Havana",
    "iso:country":"CU",
    "name:spa_x_preferred":[
        "Platanical"
    ],
    "wof:name":"Platanical",
    "wof:placetype":"locality"
},
  "geometry": {"coordinates":[-80.1591,22.53197],"type":"Point"}
}