{
  "type": "Feature",
  "properties": {
    "gn:admin1_code":"05",
    "gn:asciiname":"La Yagruma",
    "gn:country_code":"CU",
    "gn:dem":16,
    "gn:feature_class":"P",
    "gn:feature_code":"PPL",
    "gn:name":"La Yagruma",
    "gn:population":0,
    "gn:timezone":"America/Havana",
    "iso:country":"CU",
    "name:spa_x_preferred":[
        "La Yagruma"
    ],
    "wof:name":"La Yagruma",
    "wof:placetype":"locality"
},
  "geometry": {"coordinates":[-78.11258000000002,21.95461],"type":"Point"}
}