{
  "type": "Feature",
  "properties": {
    "gn:admin1_code":"15",
    "gn:asciiname":"La Emilia",
    "gn:country_code":"CU",
    "gn:dem":349,
    "gn:feature_class":"P",
    "gn:feature_code":"PPL",
    "gn:name":"La Emilia",
    "gn:population":0,
    "gn:timezone":"America/Havana",
    "iso:country":"CU",
    "name:spa_x_preferred":[
        "La Emilia"
    ],
    "wof:name":"La Emilia",
    "wof:placetype":"locality"
},
  "geometry": {"coordinates":[-76.09433,20.05252],"type":"Point"}
}