{
  "type": "Feature",
  "properties": {
    "gn:admin1_code":"05",
    "gn:asciiname":"La Eternidad",
    "gn:country_code":"CU",
    "gn:dem":9,
    "gn:feature_class":"P",
    "gn:feature_code":"PPLL",
    "gn:name":"La Eternidad",
    "gn:population":0,
    "gn:timezone":"America/Havana",
    "iso:country":"CU",
    "name:spa_x_preferred":[
        "La Eternidad"
    ],
    "wof:name":"La Eternidad",
    "wof:placetype":"locality"
},
  "geometry": {"coordinates":[-77.83333,21.78333],"type":"Point"}
}