{
  "type": "Feature",
  "properties": {
    "gn:admin1_code":"07",
    "gn:asciiname":"Los Mangos",
    "gn:country_code":"CU",
    "gn:dem":27,
    "gn:feature_class":"P",
    "gn:feature_code":"PPLL",
    "gn:name":"Los Mangos",
    "gn:population":0,
    "gn:timezone":"America/Havana",
    "iso:country":"CU",
    "wof:name":"Los Mangos",
    "wof:placetype":"locality"
},
  "geometry": {"coordinates":[-78.46583000000003,21.84556],"type":"Point"}
}