{
  "type": "Feature",
  "properties": {
    "gn:admin1_code":"16",
    "gn:asciiname":"Jibacoa",
    "gn:country_code":"CU",
    "gn:dem":342,
    "gn:feature_class":"P",
    "gn:feature_code":"PPL",
    "gn:name":"Jibacoa",
    "gn:population":0,
    "gn:timezone":"America/Havana",
    "iso:country":"CU",
    "name:spa_x_preferred":[
        "Jibacoa"
    ],
    "wof:name":"Jibacoa",
    "wof:placetype":"locality"
},
  "geometry": {"coordinates":[-79.98879000000002,22.01802],"type":"Point"}
}