{
  "type": "Feature",
  "properties": {
    "gn:admin1_code":"10",
    "gn:asciiname":"Cardonal",
    "gn:country_code":"CU",
    "gn:dem":30,
    "gn:feature_class":"P",
    "gn:feature_code":"PPL",
    "gn:name":"Cardonal",
    "gn:population":0,
    "gn:timezone":"America/Havana",
    "iso:country":"CU",
    "name:spa_x_preferred":[
        "Cardonal"
    ],
    "wof:name":"Cardonal",
    "wof:placetype":"locality"
},
  "geometry": {"coordinates":[-74.78628,20.0655],"type":"Point"}
}