{
  "type": "Feature",
  "properties": {
    "gn:admin1_code":"AR",
    "gn:asciiname":"Quiebra Hacha",
    "gn:country_code":"CU",
    "gn:dem":56,
    "gn:feature_class":"P",
    "gn:feature_code":"PPL",
    "gn:name":"Quiebra Hacha",
    "gn:population":0,
    "gn:timezone":"America/Havana",
    "iso:country":"CU",
    "name:und_x_variant":[
        "Poblado Quiebra Hacha",
        "Quiebra Hacha"
    ],
    "wof:name":"Quiebra Hacha",
    "wof:placetype":"locality"
},
  "geometry": {"coordinates":[-82.81833,22.97056],"type":"Point"}
}