{
  "type": "Feature",
  "properties": {
    "gn:admin1_code":"03",
    "gn:asciiname":"Siguagua",
    "gn:cc2":"CU",
    "gn:country_code":"CU",
    "gn:dem":9,
    "gn:feature_class":"P",
    "gn:feature_code":"PPL",
    "gn:name":"Siguagua",
    "gn:population":0,
    "gn:timezone":"America/Havana",
    "iso:country":"CU",
    "name:und_x_variant":[
        "Siguaguas",
        "Siguagua"
    ],
    "wof:name":"Siguagua",
    "wof:placetype":"locality"
},
  "geometry": {"coordinates":[-81.16056,23.00194],"type":"Point"}
}