{
  "type": "Feature",
  "properties": {
    "gn:admin1_code":"09",
    "gn:asciiname":"El Guaimaro",
    "gn:country_code":"CU",
    "gn:dem":207,
    "gn:feature_class":"P",
    "gn:feature_code":"PPL",
    "gn:name":"El Gu\u00e1imaro",
    "gn:population":0,
    "gn:timezone":"America/Havana",
    "iso:country":"CU",
    "name:spa_x_preferred":[
        "El Gu\u00e1imaro"
    ],
    "wof:name":"El Guaimaro",
    "wof:placetype":"locality"
},
  "geometry": {"coordinates":[-77.40810999999999,19.96384],"type":"Point"}
}