{
  "type": "Feature",
  "properties": {
    "gn:admin1_code":"07",
    "gn:asciiname":"La Pedrera",
    "gn:country_code":"CU",
    "gn:dem":33,
    "gn:feature_class":"P",
    "gn:feature_code":"PPL",
    "gn:name":"La Pedrera",
    "gn:population":0,
    "gn:timezone":"America/Havana",
    "iso:country":"CU",
    "name:spa_x_preferred":[
        "La Pedrera"
    ],
    "wof:name":"La Pedrera",
    "wof:placetype":"locality"
},
  "geometry": {"coordinates":[-78.79549,22.15468],"type":"Point"}
}