{
  "type": "Feature",
  "properties": {
    "gn:admin1_code":"12",
    "gn:asciiname":"Arroyo de Oro",
    "gn:country_code":"CU",
    "gn:dem":32,
    "gn:feature_class":"P",
    "gn:feature_code":"PPL",
    "gn:name":"Arroyo de Oro",
    "gn:population":0,
    "gn:timezone":"America/Havana",
    "iso:country":"CU",
    "name:spa_x_preferred":[
        "Arroyo de Oro"
    ],
    "wof:name":"Arroyo de Oro",
    "wof:placetype":"locality"
},
  "geometry": {"coordinates":[-75.87918000000001,21.06021],"type":"Point"}
}