{
  "type": "Feature",
  "properties": {
    "gn:admin1_code":"09",
    "gn:asciiname":"Horno de Cal",
    "gn:country_code":"CU",
    "gn:dem":53,
    "gn:feature_class":"P",
    "gn:feature_code":"PPLL",
    "gn:name":"Horno de Cal",
    "gn:population":0,
    "gn:timezone":"America/Havana",
    "iso:country":"CU",
    "name:spa_x_preferred":[
        "Horno de Cal"
    ],
    "wof:name":"Horno de Cal",
    "wof:placetype":"locality"
},
  "geometry": {"coordinates":[-76.54217,20.497],"type":"Point"}
}