{
  "type": "Feature",
  "properties": {
    "gn:admin1_code":"16",
    "gn:asciiname":"Julian Grimau",
    "gn:country_code":"CU",
    "gn:dem":110,
    "gn:feature_class":"P",
    "gn:feature_code":"PPL",
    "gn:name":"Juli\u00e1n Grimau",
    "gn:population":0,
    "gn:timezone":"America/Havana",
    "iso:country":"CU",
    "name:spa_x_preferred":[
        "Julian Grimau"
    ],
    "name:spa_x_variant":[
        "Juli\u00e1n Grimau"
    ],
    "wof:name":"Julian Grimau",
    "wof:placetype":"locality"
},
  "geometry": {"coordinates":[-80.00973,22.45661],"type":"Point"}
}