{
  "type": "Feature",
  "properties": {
    "gn:admin1_code":"15",
    "gn:asciiname":"El Aji",
    "gn:country_code":"CU",
    "gn:dem":203,
    "gn:feature_class":"P",
    "gn:feature_code":"PPL",
    "gn:name":"El Aj\u00ed",
    "gn:population":0,
    "gn:timezone":"America/Havana",
    "iso:country":"CU",
    "wof:name":"El Aji",
    "wof:placetype":"locality"
},
  "geometry": {"coordinates":[-76.31667,20.28333],"type":"Point"}
}