{
  "type": "Feature",
  "properties": {
    "gn:admin1_code":"16",
    "gn:asciiname":"Mata Viejo",
    "gn:country_code":"CU",
    "gn:dem":107,
    "gn:feature_class":"P",
    "gn:feature_code":"PPL",
    "gn:name":"Mata Viejo",
    "gn:population":0,
    "gn:timezone":"America/Havana",
    "iso:country":"CU",
    "wof:name":"Mata Viejo",
    "wof:placetype":"locality"
},
  "geometry": {"coordinates":[-79.96361,22.61611],"type":"Point"}
}