{
  "type": "Feature",
  "properties": {
    "gn:admin1_code":"12",
    "gn:asciiname":"Veinte y Cinco de Tomi",
    "gn:country_code":"CU",
    "gn:dem":90,
    "gn:feature_class":"P",
    "gn:feature_code":"PPL",
    "gn:name":"Veinte y Cinco de Tomi",
    "gn:population":0,
    "gn:timezone":"America/Havana",
    "iso:country":"CU",
    "name:spa_x_preferred":[
        "Veinte y Cinco de Tomi"
    ],
    "wof:name":"Veinte y Cinco de Tomi",
    "wof:placetype":"locality"
},
  "geometry": {"coordinates":[-76.38013000000002,20.79657000000001],"type":"Point"}
}