{
  "type": "Feature",
  "properties": {
    "gn:admin1_code":"09",
    "gn:asciiname":"Vivian",
    "gn:country_code":"CU",
    "gn:dem":42,
    "gn:feature_class":"P",
    "gn:feature_code":"PPLL",
    "gn:name":"Vivian",
    "gn:population":0,
    "gn:timezone":"America/Havana",
    "iso:country":"CU",
    "name:bre_x_preferred":[
        "Vivian"
    ],
    "name:bul_x_preferred":[
        "\u0412\u0438\u0432\u0438\u0430\u043d"
    ],
    "name:ceb_x_preferred":[
        "Vivian"
    ],
    "name:deu_x_preferred":[
        "Vivian"
    ],
    "name:est_x_preferred":[
        "Vivian"
    ],
    "name:fra_x_preferred":[
        "Vivian"
    ],
    "name:ita_x_preferred":[
        "Vivian"
    ],
    "name:jpn_x_preferred":[
        "\u30f4\u30a3\u30f4\u30a3\u30a2\u30f3"
    ],
    "name:kor_x_preferred":[
        "\ube44\ube44\uc5b8"
    ],
    "name:nld_x_preferred":[
        "Vivian"
    ],
    "name:pol_x_preferred":[
        "Vivian"
    ],
    "name:por_x_preferred":[
        "Vivian"
    ],
    "name:rus_x_preferred":[
        "\u0412\u0438\u0432\u0438\u0430\u043d"
    ],
    "name:spa_x_preferred":[
        "Vivian"
    ],
    "name:srp_x_preferred":[
        "\u0412\u0438\u0432\u0438\u0458\u0430\u043d"
    ],
    "name:swe_x_preferred":[
        "Vivian"
    ],
    "name:vol_x_preferred":[
        "Vivian"
    ],
    "name:zho_x_preferred":[
        "\u8587\u8587\u5b89"
    ],
    "wof:name":"Vivian",
    "wof:placetype":"locality"
},
  "geometry": {"coordinates":[-76.55972,20.65306],"type":"Point"}
}