{
  "type": "Feature",
  "properties": {
    "gn:admin1_code":"03",
    "gn:asciiname":"La Josefa",
    "gn:country_code":"CU",
    "gn:dem":65,
    "gn:feature_class":"P",
    "gn:feature_code":"PPL",
    "gn:name":"La Josefa",
    "gn:population":0,
    "gn:timezone":"America/Havana",
    "iso:country":"CU",
    "name:spa_x_preferred":[
        "La Josefa"
    ],
    "wof:name":"La Josefa",
    "wof:placetype":"locality"
},
  "geometry": {"coordinates":[-81.46394000000002,22.78255],"type":"Point"}
}